Workbook

Sheet Main
B1: Financials are presented in euros | D1: =C3*62526.632 -> 1328690.9 | F1: Reinach (Kanton Aargau, Schweiz)
B2: #VALUE! | D2: #VALUE! | E2: #VALUE! | F2: Engineering services/ Highly demanding aerostructures
B3: Price | C3: {=_FV(B2,"Price")} -> 21.25 | D3: {=_FV(D2,"Price")} -> 1.2575 | E3: {=_FV(E2,"Price")} -> 1.0858 | F3: Recycling & cast house (where recyclables ar emelted)
B4: Market cap CHF | C4: =C3*C5 -> 1328690.9 | F4: Extrusion (shaping metals through a shaped die)
B5: Shares outstanding | C5: =Model!AF137 -> 62526.632 | D5: =C6*D3 -> 1814186 | E5: #VALUE! | F5: Machining
B6: Market cap | C6: =C4*E3 -> 1442692.6 | E6: {=_FV(E5,"Price")} -> 1.1572 | F6: Surface Finishing (SF) Treatment & painting
B7: (-) Cash | C7: =-Model!AF169 -> -112759 | F7: Subassembly
B8: (+) Debt | C8: =Model!AF179+Model!AF187+Model!AF180+Model!AF188 -> 240879
B9: (+) Noncontrolling | C9: =Model!AF177 -> 15598
B10: (+) Pension liability | C10: =+Model!AF201+Model!AF202 -> 8625 | D10: =C12*E6 -> 1845775.2 | E10: =2300000/C12-1 -> 0.44197407
B11: Net debt | C11: =SUM(C7:C10) -> 152343 | D11: =C3*C5 -> 1328690.9
B12: TEV | C12: =C6+C11 -> 1595035.6 | F12: Alpine Metal Tech GmbH - bought 47% interest in 2022. Bought rest of the shares in 8/19/2024. Has full ownership.
B13: 2025 EBITDA | C13: =+Model!AF104 -> 161339
B14: TEV/2025EBITDA | C14: =C12/C13 -> 9.8862371 | D14: 11.6 | E14: =C13*D14 -> 1871532.4 | F14: Majority Shareholder - Dr. Michael Tojner
B15: P/E | C15: {=_FV(B2,"P/E",TRUE)} -> 708.3333 | E15: =+E14-C11 -> 1719189.4
B16: Alt P/E | C16: =C3/Model!V138 -> 25.893056 | E16: =E15/C5 -> 27.495314
B17: BV | C17: =Model!AF178 -> 997834 | D17: 29
B18: BVPS | C18: =C17/C5 -> 15.958544 | D18: =D17*C5/1000 -> 1813.2723 | F18: Investees
B19: P/BV | C19: =(C3*E3)/C18 -> 1.4458243 | F19: Alpine Metal Tech GmbH (wholly owned sub)
F20: Belairbus NV (129,000 Eur. BV on balance sheet)
B21: FCF (FY2025) | C21: =Model!AF248 -> 92752.885 | F21: Flabel Corporation NV
B22: FCFPS (FY2024) | C22: =C21/C5 -> 1.4834141 | F22: BeLighting NV
B23: P/FCF | C23: =C3/C22 -> 14.325063
B24: PPE | C24: =Model!P151 -> 650763 | F24: Seeking to divest energy segment at favorable point in market cycle
F25: 35 offers on the table - 39:00 on Q2 2025 call
F27: Aerostructures Product line: Aluminum, titanium, Composites
B28: LTM Net Sales | C28: =SUM(Model!P86:P86) -> 411868 | F28: Fuselage Floor Grid
B29: Sales ps | C29: =C28/C5 -> 6.5870812 | F29: Fuselage Stringers
C30: =C3/C29 -> 3.2260116 | F30: Seat Track
C31: FY2025 | D31: FY2026 | E31: FY2027 | F31: Engine Rings
B32: Revenue | C32: =Model!AF86 -> 979331 | D32: =Model!AL86 -> 1050000 | E32: =Model!AM86 -> 1119000 | F32: Wing Structures
B33: Y/Y Growth | D33: =D32/C32-1 -> 0.072160485 | E33: =E32/D32-1 -> 0.065714286 | F33: False Rail
B34: EBITDA | C34: =Model!AF99 -> 160592 | D34: =Model!AL104 -> 181050 | E34: =Model!AM104 -> 214669 | F34: Landing Gear (737), Engine parts (737), High Lift Mechanisms
B35: Margin | C35: =C34/C32 -> 0.16398133 | D35: =D34/D32 -> 0.17242857 | E35: =E34/E32 -> 0.19184004 | F35: Aerostructure Revenue target (FY2025): 850 Eur.
B36: Y/Y Growth | D36: =D34/C34-1 -> 0.12739115 | E36: =E34/D34-1 -> 0.18568904
B37: prsent EV/EBITDA | C37: =$C$12/C34 -> 9.9322233 | D37: =$C$12/D34 -> 8.8099178 | E37: =$C$12/E34 -> 7.4302094
B38: Implied TTM multiple | C38: 11.3 | D38: 12 | E38: 11
B39: Implied TEV | C39: =C34*C38 -> 1814689.6 | D39: =D34*D38 -> 2172600 | E39: =E34*E38 -> 2361359
B40: Discount (premium) | C40: =1-(C12/C39) -> 0.12104218
B41: Net Debt | E41: =C11 -> 152343
B42: Intrinsic EV | E42: =E39-E41 -> 2209016
B43: Intrinsic EV PS - Currency adjusted | E43: =(E42/C5)/E3 -> 32.537486
B44: MOM | E44: =E43/C3 -> 1.5311758
B45: Implied IRR | E45: =(E43/C3)^(1/(2027-2025-0.25))-1 -> 0.27564139
F72: 45909
F73: Montana Aerospace AG: love hate relationship
F74: Love
F75: High growth
F76: Superb leader with Airbus experience and connections.
F77: Continued growth/runway in air travel demand drive more orders and airplanes
F80: Hate
F81: Free cash flow
F82: Low/unpredictable profitability
F83: Supplier squeezed by much more powerful buyers
F84: Increasing no. shares
F86: Research Questions
F87: Who are the primary customers?
... F94: Regulatory moats? What designations does MTASF have with US FAA and EASA?

Sheet Model
O1: Un-restated. Old data. | S1: Restated | Z1: P.243 of 320 (prospectus) | AF1: P.133 of 124 | AH1: CAGR Analysis
C2: Q1'2022 | D2: Q2'2022 | E2: Q3'2022 | F2: Q4'2022 | G2: Q1'2023 | H2: Q2'2023 | I2: Q3'2023 | J2: Q4'2023 | K2: Q1'2024 | L2: Q2'2024 | M2: Q3'2024 | N2: Q4'2024 | O2: Q1'2025 | P2: Q2'2025 | Q2: Q3'2025 | S2: Q1'2025 | U2: Q1'2026 | V2: TTM Figures | X2: FY2018 | Y2: FY2019 | Z2: FY2020 | AA2: FY2021 | AB2: FY2022 | AC2: FY2023 | AD2: FY2024 | AE2: FY2024-restated | AF2: FY2025 | AH2: 22-25 | AI2: 21-25 | AJ2: 18-25 | AL2: 2026 | AM2: =AL2+1 -> 2027 | AN2: =AM2+1 -> 2028 | AO2: =AN2+1 -> 2029 | AP2: =AO2+1 -> 2030 | AQ2: =AP2+1 -> 2031 | AR2: =AQ2+1 -> 2032 | AS2: =AR2+1 -> 2033 | AT2: =AS2+1 -> 2034 | ... BM2: =BL2+1 -> 2053
B3: Stock price at 12/31 | AA3: 34 | AB3: 14.34 | AC3: 17.66 | AD3: 14.32 | AF3: 28.3 | AH3: =IFERROR(((AF3/AB3))^(1/(2025-2022))-1,"") -> 0.25433179 | AI3: =((AF3/AA3)^(1/(2025-2021)))-1 -> -0.044838344 | AJ3: =IFERROR((AF3/X3)^(1/(2025-2018))-1,"")
B4: Market cap | AA4: =+AA3*AA137 -> 1420135.2 | AB4: =+AB3*AB137 -> 871985.06 | AC4: =+AC3*AC137 -> 1094665.6 | AD4: =+AD3*AD137 -> 887929.56 | AF4: =+AF3*AF137 -> 1769503.7 | AH4: =IFERROR(((AF4/AB4))^(1/(2025-2022))-1,"") -> 0.26604014 | AJ4: =IFERROR((AF4/X4)^(1/(2025-2018))-1,"")
B5: (+) net debt | AA5: =+AA204 -> 81050 | AB5: =+AB204 -> 277963 | AC5: =+AC204 -> 273987 | AD5: =+AD204 -> 217998 | AF5: =+AF204 -> 152343 | AH5: =IFERROR(((AF5/AB5))^(1/(2025-2022))-1,"") -> -0.18163854 | AJ5: =IFERROR((AF5/X5)^(1/(2025-2018))-1,"")
B6: TEV | AA6: =+AA4+AA5 -> 1501185.2 | AB6: =+AB4+AB5 -> 1149948.1 | AC6: =+AC4+AC5 -> 1368652.6 | AD6: =+AD4+AD5 -> 1105927.6 | AF6: =+AF4+AF5 -> 1921846.7 | AH6: =IFERROR(((AF6/AB6))^(1/(2025-2022))-1,"") -> 0.18671611 | AJ6: =IFERROR((AF6/X6)^(1/(2025-2018))-1,"")
B7: TEV/EBITDA | AA7: =AA6/AA99 -> 32.596904 | AB7: =AB6/AB99 -> 9.0601309 | AC7: =AC6/AC99 -> 14.124091 | AD7: =AD6/AD99 -> 6.8918885 | AF7: =AF6/AF99 -> 11.967263 | AH7: =IFERROR(((AF7/AB7))^(1/(2025-2022))-1,"") -> 0.097202495 | AJ7: =IFERROR((AF7/X7)^(1/(2025-2018))-1,"")
A8: X | B8: SEGMENT | AH8: =IFERROR(((AF8/AB8))^(1/(2025-2022))-1,"") | AJ8: =IFERROR((AF8/X8)^(1/(2025-2018))-1,"")
B9: Aerostructures
B10: Net Sales | C10: 89358 | D10: =256935-C10 -> 167577 | E10: =433174-D10-C10 -> 176239 | F10: =AB10-E10-D10-C10 -> 202349 | G10: 166389 | H10: =332024-G10 -> 165635 | I10: =496727-H10-G10 -> 164703 | J10: =AC10-I10-H10-G10 -> 206340 | K10: 207384 | L10: =407878-K10 -> 200494 | M10: =610539-L10-K10 -> 202661 | N10: =AD10-M10-L10-K10 -> 203526 | O10: 221323 | P10: =429903-O10 -> 208580 | Q10: =649100-P10-O10 -> 219197 | S10: 221323 | U10: 233528 | V10: =Q10+P10+O10+N10 -> 852626 | AA10: 284587 | AB10: 635523 | AC10: 703067 | AD10: 814065 | AF10: 881272 | AH10: =IFERROR(((AF10/AB10))^(1/(2025-2022))-1,"") -> 0.11513188 | AI10: =((AF10/AA10)^(1/(2025-2021)))-1 -> 0.32655032 | AL10: 950000
B11: Intersegment | C11: 519 | D11: =572-C11 -> 53 | E11: =648-D11-C11 -> 76 | F11: =AB11-E11-D11-C11 -> 256 | G11: 371 | H11: =695-G11 -> 324 | I11: =1010-H11-G11 -> 315 | J11: =AC11-I11-H11-G11 -> 452 | K11: 389 | L11: =1102-K11 -> 713 | M11: =1462-L11-K11 -> 360 | N11: =AD11-M11-L11-K11 -> 92 | O11: 0 | P11: 0 | Q11: 0 | S11: 0 | U11: 0 | V11: =Q11+P11+O11+N11 -> 92 | AA11: 378 | AB11: 904 | AC11: 1462 | AD11: 1554 | AF11: 0 | AH11: =IFERROR(((AF11/AB11))^(1/(2025-2022))-1,"") -> -1 | AI11: =((AF11/AA11)^(1/(2025-2021)))-1 -> -1 | AL11: 0
B12: Sales | C12: =C11+C10 -> 89877 | D12: =D11+D10 -> 167630 | E12: =E11+E10 -> 176315 | F12: =F11+F10 -> 202605 | G12: =G11+G10 -> 166760 | H12: =H11+H10 -> 165959 | I12: =I11+I10 -> 165018 | J12: =J11+J10 -> 206792 | ... Q12: =Q11+Q10 -> 219197 | S12: =S11+S10 -> 221323 | U12: =U11+U10 -> 233528 | V12: =V11+V10 -> 852718 | AA12: =AA11+AA10 -> 284965 | AB12: =AB11+AB10 -> 636427 | AC12: =AC11+AC10 -> 704529 | AD12: =AD11+AD10 -> 815619 | AF12: =AF11+AF10 -> 881272 | AH12: =IFERROR(((AF12/AB12))^(1/(2025-2022))-1,"") -> 0.11460364 | AI12: =((AF12/AA12)^(1/(2025-2021)))-1 -> 0.32611019 | AL12: =AL11+AL10 -> 950000 | AM12: =AL12*(1+AM13) -> 1016500 | AN12: =AM12*(1+AN13) -> 1077490 | AO12: =AN12*(1+AO13) -> 1131364.5 | AP12: =AO12*(1+AP13) -> 1176619.1 | AQ12: =AP12*(1+AQ13) -> 1217800.7 | AR12: =AQ12*(1+AR13) -> 1254334.8 | AS12: =AR12*(1+AS13) -> 1279421.5 | AT12: =AS12*(1+AT13) -> 1305009.9 | AU12: =AT12*(1+AU13) -> 1331110.1
B13: Net Sales Growth Y/Y | U13: =U12/S12-1 -> 0.055145647 | V13: =V12/AD12-1 -> 0.045485699 | AB13: =AB10/AA10-1 -> 1.2331414 | AC13: =AC10/AB10-1 -> 0.10628097 | AD13: =AD10/AC10-1 -> 0.15787685 | AF13: =AF10/AD10-1 -> 0.08255729 | AH13: =IFERROR(((AF13/AB13))^(1/(2025-2022))-1,"") -> -0.59394875 | AL13: =AL12/AF12-1 -> 0.077987273 | AM13: 0.07 | AN13: 0.06 | AO13: 0.05 | AP13: 0.04 | AQ13: 0.035 | AR13: 0.03 | AS13: 0.02 | AT13: 0.02 | AU13: 0.02
B14: EBITDA | C14: 11678 | D14: =24586-C14 -> 12908 | E14: =32702-D14-C14 -> 8116 | F14: =AB14-E14-D14-C14 -> 33006 | G14: 13452 | H14: =35171-G14 -> 21719 | I14: =52695-H14-G14 -> 17524 | J14: =AC14-I14-H14-G14 -> 20874 | K14: 29287 | L14: =60097-K14 -> 30810 | M14: =90888-L14-K14 -> 30791 | N14: =AD14-M14-L14-K14 -> 36147 | O14: 39812 | P14: =76421-O14 -> 36609 | Q14: =111200-P14-O14 -> 34779 | S14: 39812 | U14: 42468 | V14: =Q14+P14+O14+N14 -> 147347 | AA14: 35127 | AB14: 65708 | AC14: 73569 | AD14: 127035 | AF14: 159811 | AH14: =IFERROR(((AF14/AB14))^(1/(2025-2022))-1,"") -> 0.34481581 | AI14: =((AF14/AA14)^(1/(2025-2021)))-1 -> 0.46046584 | AL14: =AL15*AL12 -> 171000 | AM14: =AM15*AM12 -> 203300 | AN14: =AN15*AN12 -> 210110.55 | AO14: =AO15*AO12 -> 220616.08 | AP14: =AP15*AP12 -> 229440.72 | AQ14: =AQ15*AQ12 -> 237471.15 | AR14: =AR15*AR12 -> 244595.28 | AS14: =AS15*AS12 -> 249487.19 | ... AU14: =AU15*AU12 -> 259566.47
B15: Margin% | C15: =C14/C$12 -> 0.12993313 | D15: =D14/D$12 -> 0.077002923 | E15: =E14/E$12 -> 0.046031251 | F15: =F14/F$12 -> 0.16290812 | G15: =G14/G$12 -> 0.080666827 | H15: =H14/H$12 -> 0.13086967 | I15: =I14/I$12 -> 0.10619448 | J15: =J14/J$12 -> 0.10094201 | ... Q15: =Q14/Q$12 -> 0.15866549 | S15: =S14/S$12 -> 0.17988189 | U15: =U14/U$12 -> 0.181854 | V15: =V14/V$12 -> 0.17279687 | AA15: =AA14/AA$12 -> 0.12326777 | AB15: =AB14/AB$12 -> 0.10324515 | AC15: =AC14/AC$12 -> 0.10442295 | AD15: =AD14/AD$12 -> 0.15575287 | AF15: =AF14/AF$12 -> 0.18134129 | AH15: =IFERROR(((AF15/AB15))^(1/(2025-2022))-1,"") -> 0.20654173 | AI15: =((AF15/AA15)^(1/(2025-2021)))-1 -> 0.1013156 | AL15: 0.18 | AM15: 0.2 | AN15: 0.195 | AO15: 0.195 | AP15: 0.195 | AQ15: 0.195 | AR15: 0.195 | AS15: 0.195 | AT15: 0.195 | AU15: 0.195
B16: D&A | C16: -14970 | D16: =-37801-C16 -> -22831 | E16: =-62307-D16-C16 -> -24506 | F16: =AB16-E16-D16-C16 -> -27111 | G16: -22983 | H16: =-42109-G16 -> -19126 | I16: =-64593-H16-G16 -> -22484 | J16: =AC16-I16-H16-G16 -> -17934 | K16: -20244 | L16: =-41789-K16 -> -21545 | M16: =-62487-L16-K16 -> -20698 | N16: =AD16-M16-L16-K16 -> -20512 | O16: -21520 | P16: =-42525-O16 -> -21005 | S16: -21520 | U16: -22541 | AA16: -54104 | AB16: -89418 | AC16: -82527 | AD16: -82999 | AF16: -87106 | AH16: =IFERROR(((AF16/AB16))^(1/(2025-2022))-1,"") -> -0.0086940649 | AI16: =((AF16/AA16)^(1/(2025-2021)))-1 -> 0.12643121 | AL16: =-AL17*AL12 -> -90250 | AM16: =-AM17*AM12 -> -91485 | AN16: =-AN17*AN12 -> -91586.65 | AO16: =-AO17*AO12 -> -90509.16 | AP16: =-AP17*AP12 -> -88246.431 | AQ16: =-AQ17*AQ12 -> -85246.052 | AR16: =-AR17*AR12 -> -81531.76 | AS16: =-AS17*AS12 -> -76765.288 | ... AU16: =-AU17*AU12 -> -79866.606
B17: % of revenue | C17: =-C16/C$12 -> 0.16656097 | D17: =-D16/D$12 -> 0.13619877 | E17: =-E16/E$12 -> 0.13898988 | F17: =-F16/F$12 -> 0.1338121 | G17: =-G16/G$12 -> 0.13782082 | H17: =-H16/H$12 -> 0.11524533 | I17: =-I16/I$12 -> 0.1362518 | J17: =-J16/J$12 -> 0.086724825 | ... P17: =-P16/P$12 -> 0.10070477 | S17: =-S16/S$12 -> 0.097233455 | U17: =-U16/U$12 -> 0.096523757 | AA17: =-AA16/AA$12 -> 0.18986191 | AB17: =-AB16/AB$12 -> 0.14050001 | AC17: =-AC16/AC$12 -> 0.11713783 | AD17: =-AD16/AD$12 -> 0.10176197 | AF17: =-AF16/AF$12 -> 0.09884122 | AH17: =IFERROR(((AF17/AB17))^(1/(2025-2022))-1,"") -> -0.11062023 | AI17: =((AF17/AA17)^(1/(2025-2021)))-1 -> -0.15057496 | AL17: 0.095 | AM17: 0.09 | AN17: 0.085 | AO17: 0.08 | AP17: 0.075 | AQ17: 0.07 | AR17: 0.065 | AS17: 0.06 | AT17: 0.06 | AU17: 0.06
B18: Segment EBIT | S18: =S14+S16 -> 18292 | U18: =U14+U16 -> 19927 | AA18: =AA14+AA16 -> -18977 | AB18: =AB14+AB16 -> -23710 | AC18: =AC14+AC16 -> -8958 | AD18: =AD14+AD16 -> 44036 | AF18: =AF14+AF16 -> 72705 | AH18: =IFERROR(((AF18/AB18))^(1/(2025-2022))-1,"") -> -2.452817 | AL18: =AL14+AL16 -> 80750 | AM18: =AM14+AM16 -> 111815 | AN18: =AN14+AN16 -> 118523.9 | AO18: =AO14+AO16 -> 130106.92 | AP18: =AP14+AP16 -> 141194.29 | AQ18: =AQ14+AQ16 -> 152225.09 | AR18: =AR14+AR16 -> 163063.52 | AS18: =AS14+AS16 -> 172721.9 | ... AU18: =AU14+AU16 -> 179699.86
B19: Margin% | S19: =S18/S$12 -> 0.082648437 | U19: =U18/U$12 -> 0.085330239 | AA19: =AA18/AA$12 -> -0.066594143 | AB19: =AB18/AB$12 -> -0.037254862 | AC19: =AC18/AC$12 -> -0.012714878 | AD19: =AD18/AD$12 -> 0.053990895 | AF19: =AF18/AF$12 -> 0.082500068 | AH19: =IFERROR(((AF19/AB19))^(1/(2025-2022))-1,"") -> -2.3034382 | AL19: =AL18/AL$12 -> 0.085 | AM19: =AM18/AM$12 -> 0.11 | AN19: =AN18/AN$12 -> 0.11 | AO19: =AO18/AO$12 -> 0.115 | AP19: =AP18/AP$12 -> 0.12 | AQ19: =AQ18/AQ$12 -> 0.125 | AR19: =AR18/AR$12 -> 0.13 | AS19: =AS18/AS$12 -> 0.135 | ... AU19: =AU18/AU$12 -> 0.135
B20: Investments | C20: 16369 | D20: =30538-C20 -> 14169 | E20: =49043-D20-C20 -> 18505 | F20: =AB20-E20-D20-C20 -> 28179 | G20: 12492 | H20: =24312-G20 -> 11820 | I20: =34871-H20-G20 -> 10559 | J20: =AC20-I20-H20-G20 -> 19149 | K20: 11805 | L20: =25517-K20 -> 13712 | M20: =39783-L20-K20 -> 14266 | N20: =AD20-M20-L20-K20 -> 33499 | O20: 23138 | P20: =36460-O20 -> 13322 | S20: 23138 | U20: 8121 | AA20: 100787 | AB20: 77222 | AC20: 54020 | AD20: 73282 | AF20: 68161 | AH20: =IFERROR(((AF20/AB20))^(1/(2025-2022))-1,"") -> -0.04075038 | AI20: =((AF20/AA20)^(1/(2025-2021)))-1 -> -0.093155426 | AL20: =AL21*AL12 -> 66500 | AM20: =AM21*AM12 -> 71155 | AN20: =AN21*AN12 -> 75424.3 | AO20: =AO21*AO12 -> 79195.515 | AP20: =AP21*AP12 -> 82363.336 | AQ20: =AQ21*AQ12 -> 85246.052 | AR20: =AR21*AR12 -> 87803.434 | AS20: =AS21*AS12 -> 89559.503 | ... AU20: =AU21*AU12 -> 93177.706
B21: % of revenue | C21: =C20/C$12 -> 0.18212668 | D21: =D20/D$12 -> 0.084525443 | E21: =E20/E$12 -> 0.1049542 | F21: =F20/F$12 -> 0.13908344 | G21: =G20/G$12 -> 0.07491005 | H21: =H20/H$12 -> 0.07122241 | I21: =I20/I$12 -> 0.063986959 | J21: =J20/J$12 -> 0.092600294 | ... P21: =P20/P$12 -> 0.063869978 | S21: =S20/S$12 -> 0.10454404 | U21: =U20/U$12 -> 0.034775273 | AA21: =AA20/AA$12 -> 0.35368203 | AB21: =AB20/AB$12 -> 0.12133678 | AC21: =AC20/AC$12 -> 0.076675339 | AD21: =AD20/AD$12 -> 0.089848324 | AF21: =AF20/AF$12 -> 0.077343885 | AH21: =IFERROR(((AF21/AB21))^(1/(2025-2022))-1,"") -> -0.13938051 | AI21: =((AF21/AA21)^(1/(2025-2021)))-1 -> -0.31616197 | AL21: 0.07 | AM21: 0.07 | AN21: 0.07 | AO21: 0.07 | AP21: 0.07 | AQ21: 0.07 | AR21: 0.07 | AS21: 0.07 | AT21: 0.07 | AU21: 0.07
B22: Valuation Multiple | AF22: 10 | AH22: =IFERROR(((AF22/AB22))^(1/(2025-2022))-1,"")
B23: Segment Value | AF23: =AF14*AF22 -> 1598110 | AH23: =IFERROR(((AF23/AB23))^(1/(2025-2022))-1,"")
B24: Cumul. Segemnet capex | AA24: =+V20+W20+X20+Y20+AA20 -> 100787 | AB24: =+W20+X20+Y20+AA20+AB20 -> 178009 | AC24: =+X20+Y20+AA20+AB20+AC20 -> 232029 | AD24: =+Y20+AC20+AA20+AB20+AD20 -> 305311 | AF24: =+AA20+AB20+AC20+AD20+AF20 -> 373472
B25: "Cash return on segment investment" | AA25: =AA14/AA24 -> 0.34852709 | AB25: =AB14/AB24 -> 0.3691274 | AC25: =AC14/AC24 -> 0.31706813 | AD25: =AD14/AD24 -> 0.41608393 | AF25: =AF14/AF24 -> 0.42790624 | AM25: =AF10-AB10 -> 245749
B26: Δ EBIT | AB26: =AB18-AA18 -> -4733 | AC26: =AC18-AB18 -> 14752 | AD26: =AD18-AC18 -> 52994 | AF26: =AF18-AD18 -> 28669 | AL26: =AF18-AA18 -> 91682 | AM26: =AF18-AB18 -> 96415
B27: Δ Invested Capital | AB27: =AB20 -> 77222 | AC27: =AC20 -> 54020 | AD27: =AD20 -> 73282 | AF27: =AF20 -> 68161 | AL27: =AF348-AA348 -> 139349
B28: Δ EBIT/Δ Invested Capital | AB28: =AB26/AB27 -> -0.061290824 | AC28: =AC26/AC27 -> 0.27308404 | AD28: =AD26/AD27 -> 0.72315166 | AF28: =AF26/AF27 -> 0.42060709 | AL28: =AL26/AL27 -> 0.65793081
B30: Alpine Metal Tech
B31: Net Sales | O31: 17068 | S31: 17068 | U31: 14664 | AD31: 36959 | AF31: 98060 | AH31: =IFERROR(((AF31/AB31))^(1/(2025-2022))-1,"") | AL31: 100000 | AM31: =AL31 -> 100000 | AN31: =AM31 -> 100000 | AO31: =AN31 -> 100000 | AP31: =AO31 -> 100000 | AQ31: =AP31 -> 100000 | AR31: =AQ31 -> 100000 | AS31: =AR31 -> 100000 | AT31: =AS31 -> 100000 | AU31: =AT31 -> 100000
B32: Intersegment | O32: 0 | S32: 0 | U32: 0 | AD32: 0 | AF32: 10 | AH32: =IFERROR(((AF32/AB32))^(1/(2025-2022))-1,"") | AL32: 0 | AM32: 0 | AN32: 0 | AO32: 0 | AP32: 0 | AQ32: 0 | AR32: 0 | AS32: 0 | AT32: 0 | AU32: 0
B33: Sales | O33: =+O31+O32 -> 17068 | S33: =+S31+S32 -> 17068 | U33: =+U31+U32 -> 14664 | AD33: =AD32+AD31 -> 36959 | AF33: =AF32+AF31 -> 98070 | AH33: =IFERROR(((AF33/AB33))^(1/(2025-2022))-1,"") | AL33: 100000 | AM33: =AL33*(1+AM34) -> 102500 | AN33: =AM33*(1+AN34) -> 105062.5 | AO33: =AN33*(1+AO34) -> 107689.06 | AP33: =AO33*(1+AP34) -> 110381.29 | AQ33: =AP33*(1+AQ34) -> 113140.82 | AR33: =AQ33*(1+AR34) -> 115969.34 | AS33: =AR33*(1+AS34) -> 118288.73 | AT33: =AS33*(1+AT34) -> 120654.5 | AU33: =AT33*(1+AU34) -> 123067.59
B34: Net Sales Growth Y/Y | U34: =U33/S33-1 -> -0.14084837 | AD34: =AD31/AC31-1 -> #DIV/0! | AF34: N/A | AH34: =IFERROR(((AF34/AB34))^(1/(2025-2022))-1,"") | AL34: =AL33/AF33-1 -> 0.019679821 | AM34: 0.025 | AN34: 0.025 | AO34: 0.025 | AP34: 0.025 | AQ34: 0.025 | AR34: 0.025 | AS34: 0.02 | AT34: 0.02 | AU34: 0.02
B35: EBITDA | O35: 617 | S35: 617 | U35: -558 | AD35: 4042 | AF35: 9139 | AH35: =IFERROR(((AF35/AB35))^(1/(2025-2022))-1,"") | AL35: =AL33*AL36 -> 9000 | AM35: =AM33*AM36 -> 10250 | AN35: =AN33*AN36 -> 10506.25 | AO35: =AO33*AO36 -> 10768.906 | AP35: =AP33*AP36 -> 11038.129 | AQ35: =AQ33*AQ36 -> 11314.082 | AR35: =AR33*AR36 -> 11596.934 | AS35: =AS33*AS36 -> 11828.873 | ... AU35: =AU33*AU36 -> 12306.759
B36: % of revenue | O36: =O35/O33 -> 0.03614952 | S36: =S35/S33 -> 0.03614952 | U36: =U35/U33 -> -0.038052373 | AD36: =AD35/AD$33 -> 0.10936443 | AF36: =AF35/AF$33 -> 0.093188539 | AH36: =IFERROR(((AF36/AB36))^(1/(2025-2022))-1,"") | AL36: 0.09 | AM36: 0.1 | AN36: 0.1 | AO36: 0.1 | AP36: 0.1 | AQ36: 0.1 | AR36: 0.1 | AS36: 0.1 | AT36: 0.1 | AU36: 0.1
B37: D&A | O37: -1197 | S37: -1197 | U37: -1049 | AD37: -1538 | AF37: -4054 | AH37: =IFERROR(((AF37/AB37))^(1/(2025-2022))-1,"") | AL37: =-AL38*AL33 -> -4000 | AM37: =-AM38*AM33 -> -4100 | AN37: =-AN38*AN33 -> -4202.5 | AO37: =-AO38*AO33 -> -4307.5625 | AP37: =-AP38*AP33 -> -4415.2516 | AQ37: =-AQ38*AQ33 -> -4525.6329 | AR37: =-AR38*AR33 -> -4638.7737 | AS37: =-AS38*AS33 -> -4731.5491 | ... AU37: =-AU38*AU33 -> -4922.7037
B38: % of revenue | O38: =-O37/O33 -> 0.07013124 | S38: =-S37/S33 -> 0.07013124 | U38: =-U37/U33 -> 0.071535734 | AD38: =-AD37/AD$33 -> 0.04161368 | AF38: =-AF37/AF$33 -> 0.04133782 | AH38: =IFERROR(((AF38/AB38))^(1/(2025-2022))-1,"") | AL38: 0.04 | AM38: 0.04 | AN38: 0.04 | AO38: 0.04 | AP38: 0.04 | AQ38: 0.04 | AR38: 0.04 | AS38: 0.04 | AT38: 0.04 | AU38: 0.04
B39: Segment EBIT | AF39: =AF35-AF37 -> 13193
B40: Margin% | AF40: =AF39/AF33 -> 0.13452636
B41: Investments | O41: 637 | S41: 637 | U41: 553 | AD41: 1580 | AF41: 1226 | AH41: =IFERROR(((AF41/AB41))^(1/(2025-2022))-1,"") | AL41: =AL42*AL33 -> 500 | AM41: =AM42*AM33 -> 512.5 | AN41: =AN42*AN33 -> 525.3125 | AO41: =AO42*AO33 -> 538.44531 | AP41: =AP42*AP33 -> 551.90645 | AQ41: =AQ42*AQ33 -> 565.70411 | AR41: =AR42*AR33 -> 579.84671 | AS41: =AS42*AS33 -> 591.44364 | ... AU41: =AU42*AU33 -> 615.33797
B42: % of revenue | O42: =O41/O33 -> 0.037321303 | S42: =S41/S33 -> 0.037321303 | U42: =U41/U33 -> 0.037711402 | AD42: =AD41/AD$12 -> 0.001937179 | AF42: =AF41/AF$12 -> 0.0013911709 | AH42: =IFERROR(((AF42/AB42))^(1/(2025-2022))-1,"") | AL42: 0.005 | AM42: 0.005 | AN42: 0.005 | AO42: 0.005 | AP42: 0.005 | AQ42: 0.005 | AR42: 0.005 | AS42: 0.005 | AT42: 0.005 | AU42: 0.005
B43: Valuation Multiple | AF43: 7.5 | AH43: =IFERROR(((AF43/AB43))^(1/(2025-2022))-1,"")
B44: Segment Value | AF44: =AF35*AF43 -> 68542.5 | AH44: =IFERROR(((AF44/AB44))^(1/(2025-2022))-1,"")
B45: E-Mobility
B46: Net Sales | C46: 45307 | D46: =94443-C46 -> 49136 | E46: =140817-D46-C46 -> 46374 | F46: =AB46-E46-D46-C46 -> 50201 | G46: 46930 | H46: =89997-G46 -> 43067 | I46: =127413-H46-G46 -> 37416 | J46: =AC46-I46-H46-G46 -> 38623 | K46: 40651 | AA46: 122493 | AB46: 191018 | AC46: 166036 | AH46: =IFERROR(((AF46/AB46))^(1/(2025-2022))-1,"") -> -1
B47: Intersegment | C47: 85 | D47: =163-C47 -> 78 | E47: =0-D47-C47 -> -163 | F47: =AB47-E47-D47-C47 -> 204 | G47: 224 | H47: =310-G47 -> 86 | I47: =513-H47-G47 -> 203 | J47: =AC47-I47-H47-G47 -> 323 | K47: 49 | AA47: 1 | AB47: 204 | AC47: 836 | AH47: =IFERROR(((AF47/AB47))^(1/(2025-2022))-1,"") -> -1
B48: Sales | C48: =C47+C46 -> 45392 | D48: =D47+D46 -> 49214 | E48: =E47+E46 -> 46211 | F48: =F47+F46 -> 50405 | G48: =G47+G46 -> 47154 | H48: =H47+H46 -> 43153 | I48: =I47+I46 -> 37619 | J48: =J47+J46 -> 38946 | K48: =K47+K46 -> 40700 | AA48: =AA47+AA46 -> 122494 | AB48: =AB47+AB46 -> 191222 | AC48: =AC47+AC46 -> 166872 | AH48: =IFERROR(((AF48/AB48))^(1/(2025-2022))-1,"") -> -1
B49: Net Sales Growth Y/Y | U49: =U48/S48-1 -> #DIV/0! | V49: =V48/AD48-1 -> #DIV/0! | AB49: =AB46/AA46-1 -> 0.55941972 | AC49: =AC46/AB46-1 -> -0.13078349 | AH49: =IFERROR(((AF49/AB49))^(1/(2025-2022))-1,"") -> -1 | AL49: =AL48/AF48-1 -> #DIV/0! | AM49: 0.07 | AN49: 0.06 | AO49: 0.05 | AP49: 0.04 | AQ49: 0.035 | AR49: 0.03 | AS49: 0.025 | AT49: 0.025 | AU49: 0.025
B50: EBITDA | C50: 4163 | D50: =8040-C50 -> 3877 | E50: =12675-D50-C50 -> 4635 | F50: =AB50-E50-D50-C50 -> 11722 | G50: 3296 | H50: =7191-G50 -> 3895 | I50: =18280-H50-G50 -> 11089 | J50: =AC50-I50-H50-G50 -> 7101 | K50: 1900 | AA50: 8582 | AB50: 24397 | AC50: 25381 | AH50: =IFERROR(((AF50/AB50))^(1/(2025-2022))-1,"") -> -1
B51: Margin% | C51: =C50/C$12 -> 0.046318858 | D51: =D50/D$48 -> 0.078778396 | E51: =E50/E$12 -> 0.026288177 | F51: =F50/F$12 -> 0.05785642 | G51: =G50/G$12 -> 0.019764932 | H51: =H50/H$48 -> 0.090260237 | I51: =I50/I$12 -> 0.06719873 | J51: =J50/J$12 -> 0.034338853 | K51: =K50/K$48 -> 0.046683047 | AA51: =AA50/AA$12 -> 0.030115979 | AB51: =AB50/AB$12 -> 0.038334326 | AC51: =AC50/AC$12 -> 0.036025487 | AH51: =IFERROR(((AF51/AB51))^(1/(2025-2022))-1,"") -> -1
B52: D&A | C52: -2444 | D52: =-4926-C52 -> -2482 | E52: =-7489-D52-C52 -> -2563 | F52: =AB52-E52-D52-C52 -> -3025 | G52: -2535 | H52: =-5089-G52 -> -2554 | I52: =-7258-H52-G52 -> -2169 | J52: =AC52-I52-H52-G52 -> -2853 | K52: -2418 | AA52: -9731 | AB52: -10514 | AC52: -10111 | AH52: =IFERROR(((AF52/AB52))^(1/(2025-2022))-1,"") -> -1
B53: Margin% | C53: =-C52/C$12 -> 0.027192719 | D53: =-D52/D$48 -> 0.050432804 | E53: =-E52/E$12 -> 0.014536483 | F53: =-F52/F$12 -> 0.01493053 | G53: =-G52/G$12 -> 0.015201487 | H53: =-H52/H$48 -> 0.059184761 | I53: =-I52/I$12 -> 0.013144021 | J53: =-J52/J$12 -> 0.013796472 | K53: =-K52/K$48 -> 0.059410319 | AA53: =-AA52/AA$12 -> 0.034148053 | AB53: =-AB52/AB$12 -> 0.016520355 | AC53: =-AC52/AC$12 -> 0.014351432 | AH53: =IFERROR(((AF53/AB53))^(1/(2025-2022))-1,"") -> -1
B54: Investments | C54: 2105 | D54: =4622-C54 -> 2517 | E54: =5174-D54-C54 -> 552 | F54: =AB54-E54-D54-C54 -> 1473 | G54: 2105 | H54: =4622-G54 -> 2517 | I54: =4429-H54-G54 -> -193 | J54: =AC54-I54-H54-G54 -> 1691 | K54: 11805 | AA54: 5444 | AB54: 6647 | AC54: 6120 | AH54: =IFERROR(((AF54/AB54))^(1/(2025-2022))-1,"") -> -1
B55: Share of % | C55: =C54/C$12 -> 0.023420897 | D55: =D54/D$48 -> 0.051143983 | E55: =E54/E$12 -> 0.0031307603 | F55: =F54/F$12 -> 0.0072703043 | G55: =G54/G$12 -> 0.012622931 | H55: =H54/H$48 -> 0.058327347 | I55: =I54/I$12 -> -0.0011695694 | J55: =J54/J$12 -> 0.0081772989 | K55: =K54/K$48 -> 0.29004914 | AA55: =AA54/AA$12 -> 0.019104101 | AB55: =AB54/AB$12 -> 0.010444246 | AC55: =AC54/AC$12 -> 0.0086866545 | AH55: =IFERROR(((AF55/AB55))^(1/(2025-2022))-1,"") -> -1
B56: Energy (*discontinued in Q3 2025*)
B57: Net Sales | C57: 108622 | D57: =227434-C57 -> 118812 | E57: =348609-D57-C57 -> 121175 | F57: =AB57-E57-D57-C57 -> 130985 | G57: 139764 | H57: =281986-G57 -> 142222 | I57: =418024-H57-G57 -> 136038 | J57: =AC57-I57-H57-G57 -> 149257 | K57: 147649 | L57: =311671-K57 -> 164022 | M57: =469420-L57-K57 -> 157749 | N57: =AD57-M57-L57-K57 -> 173228 | O57: 170377 | P57: =356661-O57 -> 186284 | AA57: 382972 | AB57: 479594 | AC57: 567281 | AD57: 642648 | AF57: 525650 | AH57: =IFERROR(((AF57/AB57))^(1/(2025-2022))-1,"") -> 0.031037139
B58: Intersegment | C58: 0 | D58: 0 | E58: 0 | F58: =AB58-E58-D58-C58 -> 0 | G58: 0 | H58: 0 | I58: 0 | J58: =AC58-I58-H58-G58 -> 0 | K58: 0 | L58: 0 | M58: 0 | N58: =AD58-M58-L58-K58 -> 0 | O58: 0 | P58: 0 | AA58: 0 | AB58: 0 | AC58: 0 | AD58: 0 | AH58: =IFERROR(((AF58/AB58))^(1/(2025-2022))-1,"")
B59: Sales | C59: =C58+C57 -> 108622 | D59: =D58+D57 -> 118812 | E59: =E58+E57 -> 121175 | F59: =F58+F57 -> 130985 | G59: =G58+G57 -> 139764 | H59: =H58+H57 -> 142222 | I59: =I58+I57 -> 136038 | J59: =J58+J57 -> 149257 | ... P59: =P58+P57 -> 186284 | AA59: =AA58+AA57 -> 382972 | AB59: =AB58+AB57 -> 479594 | AC59: =AC58+AC57 -> 567281 | AD59: =AD58+AD57 -> 642648 | AF59: =AF58+AF57 -> 525650 | AH59: =IFERROR(((AF59/AB59))^(1/(2025-2022))-1,"") -> 0.031037139
B60: Net Sales Growth Y/Y | U60: =U59/S59-1 -> #DIV/0! | V60: =V59/AD59-1 -> -1 | AB60: =AB57/AA57-1 -> 0.25229521 | AC60: =AC57/AB57-1 -> 0.1828359 | AD60: =AD57/AC57-1 -> 0.13285656 | AF60: =AF57/AD57-1 -> -0.18205612 | AH60: =IFERROR(((AF60/AB60))^(1/(2025-2022))-1,"") -> -1.8969442 | AL60: =AL59/AF59-1 -> -1 | AM60: 0.07 | AN60: 0.06 | AO60: 0.05 | AP60: 0.04 | AQ60: 0.035 | AR60: 0.03 | AS60: 0.025 | AT60: 0.025 | AU60: 0.025
B61: EBITDA | C61: 1435 | D61: =3149-C61 -> 1714 | E61: =9829-D61-C61 -> 6680 | F61: =AB61-E61-D61-C61 -> 23461 | G61: 7175 | H61: =13465-G61 -> 6290 | I61: =18692-H61-G61 -> 5227 | J61: =AC61-I61-H61-G61 -> 6375 | K61: 8183 | L61: =18189-K61 -> 10006 | M61: =25450-L61-K61 -> 7261 | N61: =AD61-M61-L61-K61 -> 10046 | O61: 10205 | P61: =24033-O61 -> 13828 | AA61: 8564 | AB61: 33290 | AC61: 25067 | AD61: 35496 | AF61: 36398 | AH61: =IFERROR(((AF61/AB61))^(1/(2025-2022))-1,"") -> 0.03019928
B62: Margin% | C62: =C61/C$12 -> 0.015966265 | D62: =D61/D$59 -> 0.014426152 | E62: =E61/E$12 -> 0.037886737 | F62: =F61/F$12 -> 0.11579675 | G62: =G61/G$12 -> 0.043025905 | H62: =H61/H$59 -> 0.044226632 | I62: =I61/I$12 -> 0.031675332 | J62: =J61/J$12 -> 0.030828078 | K62: =K61/K$59 -> 0.055421981 | L62: =L61/L$59 -> 0.061004012 | M62: =M61/M$12 -> 0.035764773 | N62: =N61/N$12 -> 0.049337485 | O62: =O61/O$59 -> 0.059896582 | P62: =P61/P$59 -> 0.074230744 | AA62: =AA61/AA$12 -> 0.030052814 | AB62: =AB61/AB$12 -> 0.052307649 | AC62: =AC61/AC$12 -> 0.035579799 | AD62: =AD61/AD$12 -> 0.04352032 | AF62: =AF61/AF$12 -> 0.041301664 | AH62: =IFERROR(((AF62/AB62))^(1/(2025-2022))-1,"") -> -0.0757259
B63: D&A | C63: -1841 | D63: =-3827-C63 -> -1986 | E63: =-5893-D63-C63 -> -2066 | F63: =AB63-E63-D63-C63 -> -3186 | G63: -2384 | H63: =-4869-G63 -> -2485 | I63: =-7458-H63-G63 -> -2589 | J63: =AC63-I63-H63-G63 -> -2716 | K63: -2380 | L63: =-4740-K63 -> -2360 | M63: =-7168-L63-K63 -> -2428 | N63: =AD63-M63-L63-K63 -> -2812 | O63: -2231 | P63: =-4475-O63 -> -2244 | AA63: -7644 | AB63: -9079 | AC63: -10174 | AD63: -9980 | AF63: -7029 | AH63: =IFERROR(((AF63/AB63))^(1/(2025-2022))-1,"") -> -0.081769229
B64: Margin% | C64: =-C63/C$12 -> 0.02048355 | D64: =-D63/D$59 -> 0.016715483 | E64: =-E63/E$12 -> 0.011717664 | F64: =-F63/F$12 -> 0.01572518 | G64: =-G63/G$12 -> 0.014295994 | H64: =-H63/H$59 -> 0.017472684 | I64: =-I63/I$12 -> 0.015689198 | J64: =-J63/J$12 -> 0.01313397 | K64: =-K63/K$59 -> 0.01611931 | L64: =-L63/L$59 -> 0.014388314 | M64: =-M63/M$12 -> 0.011959354 | N64: =-N63/N$12 -> 0.013810174 | O64: =-O63/O$59 -> 0.01309449 | P64: =-P63/P$59 -> 0.012046123 | AA64: =-AA63/AA$12 -> 0.026824347 | AB64: =-AB63/AB$12 -> 0.01426558 | AC64: =-AC63/AC$12 -> 0.014440853 | AD64: =-AD63/AD$12 -> 0.012236105 | AF64: =-AF63/AF$12 -> 0.0079759711 | AH64: =IFERROR(((AF64/AB64))^(1/(2025-2022))-1,"") -> -0.1761818
B65: Investments | C65: 1128 | D65: =3101-C65 -> 1973 | E65: =6080-D65-C65 -> 2979 | F65: =AB65-E65-D65-C65 -> 2131 | G65: 2227 | H65: =4559-G65 -> 2332 | I65: =4559-H65-G65 -> 0 | J65: =AC65-I65-H65-G65 -> 9148 | K65: 3876 | L65: =8735-K65 -> 4859 | M65: =15512-L65-K65 -> 6777 | N65: =AD65-M65-L65-K65 -> 12800 | O65: 6278 | P65: =12568-O65 -> 6290 | AA65: 6454 | AB65: 8211 | AC65: 13707 | AD65: 28312 | AF65: 22207 | AH65: =IFERROR(((AF65/AB65))^(1/(2025-2022))-1,"") -> 0.39325715
B66: Share of % | C66: =C65/C$12 -> 0.012550486 | D66: =D65/D$59 -> 0.016606067 | E66: =E65/E$12 -> 0.016895897 | F66: =F65/F$12 -> 0.010518003 | G66: =G65/G$12 -> 0.013354521 | H66: =H65/H$59 -> 0.016396901 | I66: =I65/I$12 -> 0 | J66: =J65/J$12 -> 0.044237688 | K66: =K65/K$59 -> 0.026251448 | L66: =L65/L$59 -> 0.029624075 | M66: =M65/M$12 -> 0.033380783 | N66: =N65/N$12 -> 0.062862812 | O66: =O65/O$59 -> 0.036847697 | P66: =P65/P$59 -> 0.033765648 | AA66: =AA65/AA$12 -> 0.022648395 | AB66: =AB65/AB$12 -> 0.012901715 | AC66: =AC65/AC$12 -> 0.019455551 | AD66: =AD65/AD$12 -> 0.034712286 | AF66: =AF65/AF$12 -> 0.025198804 | AH66: =IFERROR(((AF66/AB66))^(1/(2025-2022))-1,"") -> 0.25000233
B67: Reconciliation | AH67: =IFERROR(((AF67/AB67))^(1/(2025-2022))-1,"")
B68: Net Sales | C68: -504 | D68: =-736-C68 -> -232 | E68: =-648-D68-C68 -> 88 | F68: =AB68-E68-D68-C68 -> -460 | G68: -595 | H68: =-1005-G68 -> -410 | I68: =4899-H68-G68 -> 5904 | K68: -438 | L68: =-1102-K68 -> -664 | M68: =4899-L68-K68 -> 6001 | O68: 17068 | P68: =34072-O68 -> 17004 | AA68: -379 | AB68: -1108 | AC68: -1462 | AD68: 35406 | AH68: =IFERROR(((AF68/AB68))^(1/(2025-2022))-1,"") -> -1
AE69: Implied EV | AF69: =AF44+AF23 -> 1666652.5 | AH69: =IFERROR(((AF69/AB69))^(1/(2025-2022))-1,"")
B70: Growth Rates | AH70: =IFERROR(((AF70/AB70))^(1/(2025-2022))-1,"")
B71: Aerostructures | D71: 1.199 | E71: =E12/AD12-1 -> -0.78382676 | F71: =F12/W12-1 -> #DIV/0! | G71: =G12/C12-1 -> 0.85542464 | H71: =H12/D12-1 -> -0.0099683827 | I71: =I12/E12-1 -> -0.064072824 | J71: =J12/F12-1 -> 0.020665828 | K71: =K12/G12-1 -> 0.24594027 | L71: =L12/H12-1 -> 0.21238981 | M71: =M12/I12-1 -> 0.23029609 | N71: =N12/J12-1 -> -0.015348756 | ... P71: =P12/L12-1 -> 0.036643854 | AA71: =AA12/AI12-1 -> 873829.41 | AB71: =AB12/AA12-1 -> 1.2333515 | AC71: =AC12/AB12-1 -> 0.10700677 | AD71: =AD12/AC12-1 -> 0.15767981 | AH71: =IFERROR(((AF71/AB71))^(1/(2025-2022))-1,"") -> -1
B72: Energy | D72: 0.213 | E72: =E59/AD59-1 -> -0.81144421 | F72: =F59/W59-1 -> #DIV/0! | G72: =G59/C59-1 -> 0.28670067 | H72: =H59/D59-1 -> 0.19703397 | I72: =I59/E59-1 -> 0.12265731 | J72: =J59/F59-1 -> 0.13949689 | K72: =K59/G59-1 -> 0.056416531 | L72: =L59/H59-1 -> 0.15328149 | M72: =M59/I59-1 -> 0.15959511 | N72: =N59/J59-1 -> 0.16060218 | ... P72: =P59/L59-1 -> 0.1357257 | AB72: =AB59/AA59-1 -> 0.25229521 | AC72: =AC59/AB59-1 -> 0.1828359 | AD72: =AD59/AC59-1 -> 0.13285656 | AH72: =IFERROR(((AF72/AB72))^(1/(2025-2022))-1,"") -> -1
B73: E-mobility | D73: 0.717 | E73: =E46/AD46-1 -> #DIV/0! | F73: =F46/W46-1 -> #DIV/0! | G73: =G46/C46-1 -> 0.035822279 | H73: =H46/D46-1 -> -0.12351433 | I73: =I46/E46-1 -> -0.19316859 | J73: =J46/F46-1 -> -0.23063286 | K73: =K46/G46-1 -> -0.13379501 | L73: =L46/H46-1 -> -1 | M73: =M46/I46-1 -> -1 | N73: =N46/J46-1 -> -1 | ... P73: =P46/L46-1 -> #DIV/0! | AB73: =AB46/AA46-1 -> 0.55941972 | AC73: =AC46/AB46-1 -> -0.13078349 | AD73: =AD46/AC46-1 -> -1 | AH73: =IFERROR(((AF73/AB73))^(1/(2025-2022))-1,"") -> -1
B74: Company Revenue | D74: 0.611 | E74: =E86/AD86-1 -> -0.7698365 | F74: =F86/W86-1 -> #DIV/0! | G74: =G86/C86-1 -> 0.45130648 | H74: =H86/D86-1 -> -0.082462059 | I74: =I86/E86-1 -> -0.12521634 | J74: =J86/F86-1 -> -0.19520303 | K74: =K86/G86-1 -> 0.0055227651 | L74: =L86/H86-1 -> 0.18404384 | M74: =M86/I86-1 -> -0.30497671 | N74: =N86/J86-1 -> 0.83078204 | ... P74: =P86/L86-1 -> 0.12990686 | AA74: =AA86/AI86-1 -> 14322828 | AB74: =AB86/AA86-1 -> 0.65322536 | AC74: =AC86/AB86-1 -> -0.027398414 | AD74: =AD86/AC86-1 -> 0.17579829 | AH74: =IFERROR(((AF74/AB74))^(1/(2025-2022))-1,"") -> -1
B75: Company OpEx | J75: =J98/F98-1 -> -0.21432054 | K75: =K98/G98-1 -> -0.02470238 | L75: =L98/H98-1 -> 0.21730759 | M75: =M98/I98-1 -> -0.34492148 | N75: =N98/J98-1 -> 0.81920175 | O75: =O98/K98-1 -> 0.11680986 | P75: =P98/L98-1 -> 0.098916025 | AB75: =AB98/AA98-1 -> 0.58940004 | AC75: =AC98/AB98-1 -> -0.081911388 | AD75: =AD98/AC98-1 -> 0.15251384 | AH75: =IFERROR(((AF75/AB75))^(1/(2025-2022))-1,"") -> -1
B76: Share of Total Revenue | AH76: =IFERROR(((AF76/AB76))^(1/(2025-2022))-1,"")
B77: Aerostructures | C77: =C12/C$86 -> 0.36942788 | D77: =D12/D$86 -> 0.49960659 | E77: =E12/E$86 -> 0.51285818 | F77: =F12/F$86 -> 0.52825825 | G77: =G12/G$86 -> 0.47229554 | H77: =H12/H$86 -> 0.53907996 | I77: =I12/I$86 -> 0.5487047 | J77: =J12/J$86 -> 0.66995176 | ... P77: =P12/P$86 -> 0.50642439 | AA77: =AA12/AA$86 -> 0.36069145 | AB77: =AB12/AB$86 -> 0.48726011 | AC77: =AC12/AC$86 -> 0.55459528 | AD77: =AD12/AD$86 -> 0.54604924 | AF77: =AF12/AF$86 -> 0.89987144 | AH77: =IFERROR(((AF77/AB77))^(1/(2025-2022))-1,"") -> 0.22689257
B78: Energy | C78: =C59/C$86 -> 0.44647679 | D78: =D59/D$86 -> 0.3541088 | E78: =E59/E$86 -> 0.3524691 | F78: =F59/F$86 -> 0.34152122 | G78: =G59/G$86 -> 0.39583782 | H78: =H59/H$86 -> 0.46197573 | I78: =I59/I$86 -> 0.45234271 | J78: =J59/J$86 -> 0.48355347 | ... P78: =P59/P$86 -> 0.45229054 | AA78: =AA59/AA$86 -> 0.48474278 | AB78: =AB59/AB$86 -> 0.36718591 | AC78: =AC59/AC$86 -> 0.44655559 | AD78: =AD59/AD$86 -> 0.43024678 | AF78: 0 | AH78: =IFERROR(((AF78/AB78))^(1/(2025-2022))-1,"") -> -1
B79: E-mobility | C79: =C48/C$86 -> 0.18657799 | D79: =D48/D$86 -> 0.14667803 | E79: =E48/E$86 -> 0.13441675 | F79: =F48/F$86 -> 0.13142251 | G79: =G48/G$86 -> 0.13354896 | H79: =H48/H$86 -> 0.14017268 | I79: =I48/I$86 -> 0.1250877 | J79: =J48/J$86 -> 0.12617481 | ... P79: =P48/P$86 -> 0 | AA79: =AA48/AA$86 -> 0.15504549 | AB79: =AB48/AB$86 -> 0.14640305 | AC79: =AC48/AC$86 -> 0.13135928 | AD79: =AD48/AD$86 -> 0 | AF79: =AF48/AF$86 -> 0 | AH79: =IFERROR(((AF79/AB79))^(1/(2025-2022))-1,"") -> -1
B80: Intersegment | C80: =C68/C$86 -> -0.0020716273 | D80: =D68/D$86 -> -0.00069145575 | E80: =E68/E$86 -> 0.00025597096 | F80: =F68/F$86 -> -0.0011993722 | G80: =G68/G$86 -> -0.0016851514 | H80: =H68/H$86 -> -0.0013317915 | I80: =I68/I$86 -> 0.01963151 | J80: =J68/J$86 -> 0 | ... P80: =P68/P$86 -> 0.041285072 | AA80: =AA68/AA$86 -> -0.00047971526 | AB80: =AB68/AB$86 -> -0.000848305 | AC80: =AC68/AC$86 -> -0.0011508657 | AD80: =AD68/AD$86 -> 0.023703983 | AF80: =AF68/AF$86 -> 0 | AH80: =IFERROR(((AF80/AB80))^(1/(2025-2022))-1,"") -> -1
C81: =C77+C78+C79+C80 -> 1.000411 | D81: =D77+D78+D79+D80 -> 0.99970196 | E81: =E77+E78+E79+E80 -> 1 | F81: =F77+F78+F79+F80 -> 1.0000026 | G81: =G77+G78+G79+G80 -> 0.99999717 | H81: =H77+H78+H79+H80 -> 1.1398966 | I81: =I77+I78+I79+I80 -> 1.1457666 | J81: =J77+J78+J79+J80 -> 1.27968 | ... P81: =P77+P78+P79+P80 -> 1 | AA81: =AA77+AA78+AA79+AA80 -> 1 | AB81: =AB77+AB78+AB79+AB80 -> 1.0000008 | AC81: =AC77+AC78+AC79+AC80 -> 1.1313593 | AD81: =AD77+AD78+AD79+AD80 -> 1 | AF81: =AF77+AF78+AF79+AF80 -> 0.89987144 | AH81: =IFERROR(((AF81/AB81))^(1/(2025-2022))-1,"") -> -0.034556835 | AI81: Discount to TEV
B82: Valuation | AD82: =AD44+AD23 -> 0 | AF82: =AF44+AF23 -> 1666652.5 | AH82: =IFERROR(((AF82/AB82))^(1/(2025-2022))-1,"") | AI82: =AF82/Main!C12-1 -> 0.044899868
B83: PPS | AF83: =(AF82/AF137)/Main!E3 -> 24.548795 | AH83: =IFERROR(((AF83/AB83))^(1/(2025-2022))-1,"")
B84: Consolidated IS | M84: Adjusted:
C85: =C59+C48+C12+C68 -> 243387 | D85: =D59+D48+D12+D68 -> 335424 | E85: =E59+E48+E12+E68 -> 343789 | F85: =F59+F48+F12+F68 -> 383535 | G85: =G59+G48+G12+G68 -> 353083 | K85: =K59+K48+K12+K68 -> 395684 | L85: =L59+L48+L12+L68 -> 364565 | O85: =O59+O48+O12+O68 -> 408768 | P85: =P59+P48+P12+P68 -> 411868 | AA85: =AA59+AA48+AA12+AA68 -> 790052 | AB85: =AB59+AB48+AB12+AB68 -> 1306135 | AC85: =AC59+AC48+AC12+AC68 -> 1437220 | AD85: =AD59+AD48+AD12+AD68 -> 1493673 | AF85: =AF59+AF48+AF12+AF33 -> 1504992 | AH85: =IFERROR(((AF85/AB85))^(1/(2025-2022))-1,"") -> 0.048371907 | AI85: =((AF85/AA85)^(1/(2025-2021)))-1 -> 0.17481539 | AL85: =AL59+AL48+AL12+AL33 -> 1050000 | AM85: =AM59+AM48+AM12+AM33 -> 1119000 | AN85: =AN59+AN48+AN12+AN33 -> 1182552.5 | AO85: =AO59+AO48+AO12+AO33 -> 1239053.6 | AP85: =AP59+AP48+AP12+AP33 -> 1287000.4 | AQ85: =AQ59+AQ48+AQ12+AQ33 -> 1330941.6 | AR85: =AR59+AR48+AR12+AR33 -> 1370304.1 | AS85: =AS59+AS48+AS12+AS33 -> 1397710.2 | ... AU85: =AU59+AU48+AU12+AU33 -> 1454177.7
B86: Net Sales | C86: 243287 | D86: =578811-C86 -> 335524 | E86: 343789 | F86: =AB86-E86-D86-C86 -> 383534 | G86: 353084 | H86: 307856 | I86: 300741 | J86: =AC86-I86-H86-G86 -> 308667 | K86: 355034 | L86: 364515 | M86: 209022 | N86: =AD86-M86-L86-K86 -> 565102 | O86: 408768 | P86: 411868 | Q86: 248355 | S86: 238391 | U86: 248192 | V86: =Q86+P86+O86+N86 -> 1634093 | X86: 766038 | Y86: 783262 | Z86: 614185 | AA86: 790052 | AB86: 1306134 | AC86: 1270348 | AD86: 1493673 | AE86: 851025 | AF86: 979331 | AH86: =IFERROR(((AF86/AB86))^(1/(2025-2022))-1,"") -> -0.09152303 | AI86: =((AF86/AA86)^(1/(2025-2021)))-1 -> 0.055160333 | AJ86: =IFERROR((AF86/X86)^(1/(2025-2018))-1,"") -> 0.035714089 | AL86: =AL85 -> 1050000 | AM86: =AM85 -> 1119000 | AN86: =AN85 -> 1182552.5 | AO86: =AO85 -> 1239053.6 | AP86: =AP85 -> 1287000.4 | AQ86: =AP86*(1+AQ87) -> 1336273 | AR86: =AQ86*(1+AR87) -> 1387432.1 | AS86: =AR86*(1+AS87) -> 1440549.8 | AT86: =AS86*(1+AT87) -> 1495701.1 | AU86: =AT86*(1+AU87) -> 1552963.9 | AV86: =AU86*(1+AV87) -> 1599552.8 | AW86: =AV86*(1+AW87) -> 1647539.4 | AX86: =AW86*(1+AX87) -> 1696965.6 | ... BM86: =BL86*(1+BM87) -> 2643817
B87: Growth Y/Y | J87: =J86/F86-1 -> -0.19520303 | K87: =K86/G86-1 -> 0.0055227651 | L87: =L86/H86-1 -> 0.18404384 | M87: =M86/I86-1 -> -0.30497671 | N87: =N86/J86-1 -> 0.83078204 | O87: =O86/K86-1 -> 0.15134888 | P87: =P86/L86-1 -> 0.12990686 | Q87: =Q86/M86-1 -> 0.18817636 | U87: =U86/S86-1 -> 0.041113129 | V87: =V86/AD86-1 -> 0.094009867 | Y87: =Y86/X86-1 -> 0.022484524 | Z87: =Z86/Y86-1 -> -0.21586264 | AA87: =AA86/Z86-1 -> 0.28634206 | AB87: =AB86/AA86-1 -> 0.65322536 | AC87: =AC86/AB86-1 -> -0.027398414 | AD87: =AD86/AC86-1 -> 0.17579829 | AE87: NM | AF87: =AF86/AE86-1 -> 0.15076643 | AH87: =IFERROR(((AF87/AB87))^(1/(2025-2022))-1,"") -> -0.38659515 | AI87: =((AF87/AA87)^(1/(2025-2021)))-1 -> -0.14816619 | AJ87: =IFERROR((AF87/X87)^(1/(2025-2018))-1,"") | AL87: =AL86/AF86-1 -> 0.072160485 | AM87: =AM86/AL86-1 -> 0.065714286 | AN87: =AN86/AM86-1 -> 0.056794013 | AO87: =AO86/AN86-1 -> 0.047778904 | AP87: =AP86/AO86-1 -> 0.038696315 | AQ87: =AQ86/AP86-1 -> 0.038284896 | AR87: =AR86/AQ86-1 -> 0.038284896 | AS87: =AS86/AR86-1 -> 0.038284896 | AT87: =AT86/AS86-1 -> 0.038284896 | AU87: =AU86/AT86-1 -> 0.038284896 | AV87: 0.03 | AW87: 0.03 | AX87: 0.03 | AY87: 0.03 | AZ87: 0.03 | BA87: 0.03 | BB87: 0.03 | BC87: 0.03 | BD87: 0.03 | BE87: 0.03 | BF87: 0.03 | BG87: 0.03 | BH87: 0.03 | BI87: 0.03 | BJ87: 0.03 | BK87: 0.03 | BL87: 0.03 | BM87: 0.03
B88: Change in finished/unfinished goods | C88: 17034 | D88: =27170-C88 -> 10136 | E88: 1997 | F88: =AB88-E88-D88-C88 -> -16734 | G88: 11082 | H88: -5484 | I88: 6491 | J88: =AC88-I88-H88-G88 -> -15781 | K88: 17546 | L88: 13057 | M88: 1159 | N88: =AD88-M88-L88-K88 -> -9672 | O88: 10938 | P88: 5779 | Q88: -11360 | S88: 4751 | U88: 11380 | V88: =Q88+P88+O88+N88 -> -4315 | X88: -5835 | Y88: 13313 | Z88: -9396 | AA88: 21830 | AB88: 12433 | AC88: -3692 | AD88: 22090 | AE88: 17818 | AF88: -9653 | AH88: =IFERROR(((AF88/AB88))^(1/(2025-2022))-1,"") -> -1.9190986 | AI88: =((AF88/AA88)^(1/(2025-2021)))-1 -> #NUM! | AJ88: =IFERROR((AF88/X88)^(1/(2025-2018))-1,"") -> 0.074562388
B89: Own work capitalized | C89: 6676 | D89: =10806-C89 -> 4130 | E89: 6586 | F89: =AB89-E89-D89-C89 -> 12347 | G89: 3450 | H89: 2737 | I89: 2052 | J89: =AC89-I89-H89-G89 -> 5535 | K89: 2128 | L89: 2430 | M89: 2740 | N89: =AD89-M89-L89-K89 -> 6685 | O89: 2089 | P89: 2621 | Q89: 1753 | S89: 2089 | U89: 1144 | V89: =Q89+P89+O89+N89 -> 13148 | X89: 1463 | Y89: 29112 | Z89: 42140 | AA89: 34584 | AB89: 29739 | AC89: 13774 | AD89: 13983 | AE89: 13848 | AF89: 8316 | AH89: =IFERROR(((AF89/AB89))^(1/(2025-2022))-1,"") -> -0.34607284 | AI89: =((AF89/AA89)^(1/(2025-2021)))-1 -> -0.2997392 | AJ89: =IFERROR((AF89/X89)^(1/(2025-2018))-1,"") -> 0.28176976
B90: as a % of revenue | X90: =X89/X$86 -> 0.0019098269 | Y90: =Y89/Y$86 -> 0.03716764 | Z90: =Z89/Z$86 -> 0.068611249 | AA90: =AA89/AA$86 -> 0.043774334 | AB90: =AB89/AB$86 -> 0.022768721 | AC90: =AC89/AC$86 -> 0.010842698 | AD90: =AD89/AD$86 -> 0.0093614868 | AE90: =AE89/AE$86 -> 0.016272142 | AF90: =AF89/AF$86 -> 0.008491511
B91: Other operating income | C91: 4705 | D91: =12073-C91 -> 7368 | E91: 26667 | F91: =AB91-E91-D91-C91 -> 66092 | G91: 5450 | H91: 9434 | I91: 5804 | J91: =AC91-I91-H91-G91 -> 13366 | K91: 4993 | L91: 2864 | M91: 11895 | N91: =AD91-M91-L91-K91 -> 14250 | O91: 9831 | P91: 11284 | Q91: 6077 | S91: 9662 | U91: 3675 | V91: =Q91+P91+O91+N91 -> 41442 | X91: 24184 | Y91: 25420 | Z91: 37934 | AA91: 33999 | AB91: 104832 | AC91: 34054 | AD91: 34002 | AE91: 33484 | AF91: 36714 | AH91: =IFERROR(((AF91/AB91))^(1/(2025-2022))-1,"") -> -0.29512418 | AI91: =((AF91/AA91)^(1/(2025-2021)))-1 -> 0.019392397 | AJ91: =IFERROR((AF91/X91)^(1/(2025-2018))-1,"") -> 0.061452367
B92: Cost of materials, supplies and services | C92: -173683 | D92: =-393255-C92 -> -219572 | E92: -227588 | F92: =AB92-E92-D92-C92 -> -236307 | G92: -234434 | H92: -183964 | I92: -197315 | J92: =AC92-I92-H92-G92 -> -187707 | K92: -235753 | L92: -228317 | M92: -101042 | N92: =AD92-M92-L92-K92 -> -362785 | O92: -256973 | P92: -253224 | Q92: -108290 | S92: -114590 | U92: -122222 | V92: =Q92+P92+O92+N92 -> -981272 | X92: -460023 | Y92: -469028 | Z92: -400948 | AA92: -558334 | AB92: -857150 | AC92: -803420 | AD92: -927897 | AE92: -410617 | AF92: -445879 | AH92: =IFERROR(((AF92/AB92))^(1/(2025-2022))-1,"") -> -0.19575804 | AI92: =((AF92/AA92)^(1/(2025-2021)))-1 -> -0.054675887 | AJ92: =IFERROR((AF92/X92)^(1/(2025-2018))-1,"") -> -0.004451331
B93: as a % of revenue | X93: =-X92/X$86 -> 0.60052243 | Y93: =-Y92/Y$86 -> 0.59881368 | Z93: =-Z92/Z$86 -> 0.65281308 | AA93: =-AA92/AA$86 -> 0.70670538 | AB93: =-AB92/AB$86 -> 0.65624967 | AC93: =-AC92/AC$86 -> 0.63244087 | AD93: =-AD92/AD$86 -> 0.6212183 | AE93: =-AE92/AE$86 -> 0.48249699 | AF93: =-AF92/AF$86 -> 0.45528938
B94: Personnel expenses | C94: -50052 | D94: =-121957-C94 -> -71905 | E94: -73155 | F94: =AB94-E94-D94-C94 -> -73153 | G94: -70301 | H94: -61085 | I94: -61564 | J94: =AC94-I94-H94-G94 -> -55547 | K94: -68186 | L94: -70973 | M94: -60011 | N94: =AD94-M94-L94-K94 -> -95390 | O94: -82925 | P94: -83068 | Q94: -65123 | S94: -69303 | U94: -70369 | V94: =Q94+P94+O94+N94 -> -326506 | X94: -160037 | Y94: -180960 | Z94: -156954 | AA94: -173645 | AB94: -268265 | AC94: -248497 | AD94: -294560 | AE94: -242556 | AF94: -276864 | AH94: =IFERROR(((AF94/AB94))^(1/(2025-2022))-1,"") -> 0.010572536 | AI94: =((AF94/AA94)^(1/(2025-2021)))-1 -> 0.12370174 | AJ94: =IFERROR((AF94/X94)^(1/(2025-2018))-1,"") -> 0.081450346
B95: Capitalized R&D | AE95: -380 | AF95: -446
B96: % of revenue | AE96: =-AE95/AE86 -> 0.00044652037 | AF96: =-AF95/AF86 -> 0.00045541293
B97: Other operating expenses | C97: -33563 | D97: =-85015-C97 -> -51452 | E97: -60174 | F97: =AB97-E97-D97-C97 -> -55610 | G97: -46972 | H97: -38006 | I97: -37113 | J97: =AC97-I97-H97-G97 -> -43574 | K97: -39080 | L97: -45275 | M97: -32845 | N97: =AD97-M97-L97-K97 -> -63623 | O97: -43189 | P97: -42356 | Q97: -35368 | S97: -32821 | U97: -31212 | V97: =Q97+P97+O97+N97 -> -184536 | X97: -100306 | Y97: -112268 | Z97: -93670 | AA97: -102433 | AB97: -200799 | AC97: -165665 | AD97: -180823 | AE97: -138318 | AF97: -131373 | AH97: =IFERROR(((AF97/AB97))^(1/(2025-2022))-1,"") -> -0.13187648 | AI97: =((AF97/AA97)^(1/(2025-2021)))-1 -> 0.064183587 | AJ97: =IFERROR((AF97/X97)^(1/(2025-2018))-1,"") -> 0.039297509
B98: Operating Costs | C98: =SUM(C92:C97) -> -257298 | D98: =SUM(D92:D97) -> -342929 | E98: =SUM(E92:E97) -> -360917 | F98: =SUM(F92:F97) -> -365070 | G98: =SUM(G92:G97) -> -351707 | H98: =SUM(H92:H97) -> -283055 | I98: =SUM(I92:I97) -> -295992 | J98: =SUM(J92:J97) -> -286828 | ... Q98: =SUM(Q92:Q97) -> -208781 | S98: =SUM(S92:S97) -> -216714 | U98: =SUM(U92:U97) -> -223803 | V98: =SUM(V92:V97) -> -1492314 | X98: =SUM(X92:X97) -> -720365.4 | Y98: =SUM(Y92:Y97) -> -762255.4 | Z98: =SUM(Z92:Z97) -> -651571.35 | AA98: =SUM(AA92:AA97) -> -834411.29 | AB98: =SUM(AB92:AB97) -> -1326213.3 | AC98: =SUM(AC92:AC97) -> -1217581.4 | AD98: =SUM(AD92:AD97) -> -1403279.4 | AE98: =+AE92+AE94+AE97 -> -791491 | AF98: =+AF92+AF94+AF97 -> -854116 | AH98: =IFERROR(((AF98/AB98))^(1/(2025-2022))-1,"") -> -0.13642283 | AI98: =((AF98/AA98)^(1/(2025-2021)))-1 -> 0.005852202 | AJ98: =IFERROR((AF98/X98)^(1/(2025-2018))-1,"") -> 0.02462816
B99: EBITDA as reported | C99: =C86+C88+C89+C91+C92+C94+C97 -> 14404 | D99: =D86+D88+D89+D91+D92+D94+D97 -> 14229 | E99: =E86+E88+E89+E91+E92+E94+E97 -> 18122 | F99: =F86+F88+F89+F91+F92+F94+F97 -> 80169 | G99: =G86+G88+G89+G91+G92+G94+G97 -> 21359 | H99: =H86+H88+H89+H91+H92+H94+H97 -> 31488 | I99: =I86+I88+I89+I91+I92+I94+I97 -> 19096 | J99: =J86+J88+J89+J91+J92+J94+J97 -> 24959 | ... Q99: =Q86+Q88+Q89+Q91+Q92+Q94+Q97 -> 36044 | S99: =S86+S88+S89+S91+S92+S94+S97 -> 38179 | U99: =U86+U88+U89+U91+U92+U94+U97 -> 40588 | V99: =V86+V88+V89+V91+V92+V94+V97 -> 192054 | X99: =+X86+X88+X89+X91+X92+X94+X97 -> 65484 | Y99: =+Y86+Y88+Y89+Y91+Y92+Y94+Y97 -> 88851 | Z99: =+Z86+Z88+Z89+Z91+Z92+Z94+Z97 -> 33291 | AA99: =+AA86+AA88+AA89+AA91+AA92+AA94+AA97 -> 46053 | AB99: =+AB86+AB88+AB89+AB91+AB92+AB94+AB97 -> 126924 | AC99: =+AC86+AC88+AC89+AC91+AC92+AC94+AC97 -> 96902 | AD99: =+AD86+AD88+AD89+AD91+AD92+AD94+AD97 -> 160468 | AE99: =+AE86+AE88+AE89+AE91+AE92+AE94+AE97 -> 124684 | AF99: =+AF86+AF88+AF89+AF91+AF92+AF94+AF97 -> 160592 | AH99: =IFERROR(((AF99/AB99))^(1/(2025-2022))-1,"") -> 0.081583497 | AI99: =((AF99/AA99)^(1/(2025-2021)))-1 -> 0.36652158 | AJ99: =IFERROR((AF99/X99)^(1/(2025-2018))-1,"") -> 0.13672531 | AL99: =AL14+AL35 -> 180000 | AM99: =AM14+AM35 -> 213550 | AN99: =AN14+AN35 -> 220616.8 | AO99: =AO14+AO35 -> 231384.98 | AP99: =AP14+AP35 -> 240478.85 | AQ99: =AQ14+AQ35 -> 248785.23 | AR99: =AR14+AR35 -> 256192.21 | AS99: =AS14+AS35 -> 261316.06 | ... AU99: =AU14+AU35 -> 271873.23 | AV99: =AV86*AV106 -> 287919.5 | AW99: =AW86*AW106 -> 329507.87 | AX99: =AX86*AX106 -> 339393.11 | AY99: =AY86*AY106 -> 349574.9 | AZ99: =AZ86*AZ106 -> 360062.15 | BA99: =BA86*BA106 -> 370864.02 | BB99: =BB86*BB106 -> 381989.94 | BC99: =BC86*BC106 -> 393449.63 | ... BM99: =BM86*BM106 -> 528763.41
B100: margin% | G100: =G99/G$86 -> 0.060492687 | H100: =H99/H$86 -> 0.10228159 | I100: =I99/I$86 -> 0.063496497 | J100: =J99/J$86 -> 0.080860604 | K100: =K99/K$86 -> 0.10331968 | L100: =L99/L$86 -> 0.10507387 | M100: =M99/M$86 -> 0.14791744 | N100: =N99/N$86 -> 0.096561329 | ... Q100: =Q99/Q$86 -> 0.14513096 | S100: =S99/S$86 -> 0.16015286 | U100: =U99/U$86 -> 0.16353468 | X100: =X99/X$86 -> 0.08548401 | Y100: =Y99/Y$86 -> 0.11343714 | Z100: =Z99/Z$86 -> 0.054203538 | AA100: =AA99/AA$86 -> 0.0582911 | AB100: =AB99/AB$86 -> 0.097175328 | AC100: =AC99/AC$86 -> 0.076279886 | AD100: =AD99/AD$86 -> 0.10743181 | AE100: =AE99/AE$86 -> 0.14651038 | AF100: =AF99/AF$86 -> 0.16398133 | AH100: =IFERROR(((AF100/AB100))^(1/(2025-2022))-1,"") -> 0.19054586 | AI100: =((AF100/AB100)^(1/(2025-2022)))-1 -> 0.19054586 | AJ100: =IFERROR((AF100/X100)^(1/(2025-2018))-1,"") -> 0.097528093 | AL100: =AL99/AL$86 -> 0.17142857 | AM100: =AM99/AM$86 -> 0.19084004 | AN100: =AN99/AN$86 -> 0.18655984 | AO100: =AO99/AO$86 -> 0.18674333 | AP100: =AP99/AP$86 -> 0.1868522 | AQ100: =AQ99/AQ$86 -> 0.18617844 | AR100: =AR99/AR$86 -> 0.18465207 | AS100: =AS99/AS$86 -> 0.18140022 | ... BM100: =BM99/BM$86 -> 0.2
B101: (+) Legal costs | X101: =3638+5753+1439 -> 10830 | Y101: =3188+8370+1519 -> 13077 | Z101: =4867+5203+1488 -> 11558 | AB101: 2568 | AC101: 14657 | AE101: 3432 | AF101: 0 | AH101: =IFERROR(((AF101/AB101))^(1/(2025-2022))-1,"") -> -1 | AJ101: =IFERROR((AF101/X101)^(1/(2025-2018))-1,"") -> -1
...

Sheet Comps
B2: All figures are TTM and in Millions | D2: Montana Aerospace AG | F2: FACC AG | H2: FIGEAC AÉRO | J2: Ducommun (DCO) | L2: Standard Aero | M2: Senior Plc | N2: Senior PLC | P2: Montana Products | Q2: FACC AG Products
B3: Revenue | D3: =Model!AF86/1000 -> 979.331 | F3: =[1]Model!$P$82 -> 984.405 | H3: =[2]Model!$W$144 -> 486.8 | J3: =[3]Model!$C$95 -> 824.658 | L3: =[4]Model!$G$16/1000 -> 6062.513 | P3: A350 F Floor Section | Q3: Wing elements | S3: Montana & DCO
B4: EBITDA margin | D4: =Model!AF100 -> 0.16398133 | F4: =[1]Model!$P$96 -> 0.082044484 | H4: =[2]Model!$V$159 -> 0.15561305 | J4: =[3]Model!$C$108 -> 0.13183041 | L4: =[4]Model!$G$27 -> 0.12554579 | Q4: Spoilers | S4: Montana | Z4: DCO | AF4: 1/1/2022=100% | AH4: 1/1/2023=100%
B5: EBIT margin | D5: =Model!AF111 -> 0.070267356 | F5: =[1]Model!$P$93 -> 0.042995515 | H5: =[2]Model!$V$157 -> 0.051205495 | J5: =[3]Model!$C$106 -> 0.091017125 | P5: Fuselage systems | Q5: Winglets | R5: A320 | S5: Date | T5: Open | U5: High | V5: Low | W5: Close | X5: Adj Close | Y5: Volume | Z5: Open | AA5: High | AB5: Low | AC5: Close | AD5: Adj Close | AE5: Volume | AF5: AERO | AG5: DCO | AH5: AERO | AI5: DCO
B6: Unlevered Free Cash Flow | D6: =+Model!AF356/1000 -> 65.96945 | F6: =[1]Model!$P$220 -> 13.53425 | H6: =[2]Model!$V$276 -> 32.643 | J6: =[3]Model!$C$190 -> -58.396 | L6: =[4]Model!$G$131/1000 -> 234.297 | S6: 44562 | T6: 34 | U6: 36.15 | V6: 33.5 | W6: 34.9 | X6: 34.9 | Y6: 205085 | Z6: 47.44 | AA6: 49.4 | AB6: 46.9 | AC6: 46.99 | AD6: 46.99 | AE6: 113200 | AF6: =X6/$X$6 -> 1 | AG6: =AD6/$AD$6 -> 1
B7: Net Debt | D7: =Main!C11/1000 -> 152.343 | F7: =[1]Main!$C$10 -> 145.431 | H7: =[2]Main!$C$13 -> 346.833 | J7: =[3]Main!$C$10 -> 303.591 | L7: =[4]Model!$G$93 -> 0.83027626 | P7: Landing gear | Q7: Ailerons | S7: 44569 | T7: 35 | U7: 35.9 | V7: 33.55 | W7: 35.15 | X7: 35.15 | Y7: 122046 | Z7: 46.49 | AA7: 46.63 | AB7: 44.84 | AC7: 45.55 | AD7: 45.55 | AE7: 99700 | AF7: =X7/$X$6 -> 1.0071633 | AG7: =AD7/$AD$6 -> 0.96935518
B8: Net Debt to EBITDA | D8: =Model!AF206 -> 0.9486338 | F8: =[1]Model!$P$171 -> 1.8006686 | H8: =[2]Model!V221 -> 7.034764 | J8: =[3]Model!$C$154 -> 2.764108 | L8: =[4]Sheet1!$C$7/1000 -> 8163.3488 | N8: =[5]Sheet2!$C$76 -> 1.5115979 | P8: Enigne rings/nacelles | Q8: Empennage | S8: 44576 | T8: 35.05 | U8: 36.5 | V8: 33.65 | W8: 34.1 | X8: 34.1 | Y8: 96143 | Z8: 44.92 | AA8: 45.1 | AB8: 42.51 | AC8: 43.25 | AD8: 43.25 | AE8: 100000 | AF8: =X8/$X$6 -> 0.97707736 | AG8: =AD8/$AD$6 -> 0.9204086
B9: Market Cap | D9: =Main!C6/1000 -> 1442.6926 | F9: =[1]Main!$D$7 -> 739.0506 | H9: =[2]Main!$C$7 -> 509.6525 | J9: =[3]Main!$C$6 -> 2482.178 | P9: High lift mechanisms | Q9: Vertical stabilizer & rudder | S9: 44583 | T9: 34 | U9: 35.05 | V9: 31.2 | W9: 33.9 | X9: 33.9 | Y9: 153638 | Z9: 42.25 | AA9: 45.21 | AB9: 40.82 | AC9: 42.39 | AD9: 42.39 | AE9: 136000 | AF9: =X9/$X$6 -> 0.9713467 | AG9: =AD9/$AD$6 -> 0.90210683
B10: EV to 2025 EBITDA | D10: =Main!C14 -> 9.8862371 | F10: =[1]Main!$D$13 -> 10.945962 | H10: =[2]Main!$D$18 -> 11.354476 | J10: =[3]Main!$C$14 -> 22.831974 | L10: =[4]Sheet1!$C$15 -> 13.254411 | Q10: Fairings | S10: 44590 | T10: 34.1 | U10: 35.5 | V10: 33.4 | W10: 35.15 | X10: 35.15 | Y10: 84309 | Z10: 42.63 | AA10: 44.09 | AB10: 41.81 | AC10: 43.56 | AD10: 43.56 | AE10: 217100 | AF10: =X10/$X$6 -> 1.0071633 | AG10: =AD10/$AD$6 -> 0.92700575
P11: Aluminum | Q11: Radomes | S11: 44597 | T11: 35.35 | U11: 36.75 | V11: 33.1 | W11: 34.8 | X11: 34.8 | Y11: 107167 | Z11: 43.24 | AA11: 45.01 | AB11: 42.74 | AC11: 43.96 | AD11: 43.96 | AE11: 203500 | AF11: =X11/$X$6 -> 0.99713467 | AG11: =AD11/$AD$6 -> 0.9355182
S12: 44604 | T12: 34.3 | U12: 34.45 | V12: 31.5 | W12: 32 | X12: 32 | Y12: 166091 | Z12: 44.12 | AA12: 46.96 | AB12: 44.12 | AC12: 46.07 | AD12: 46.07 | AE12: 209400 | AF12: =X12/$X$6 -> 0.91690544 | AG12: =AD12/$AD$6 -> 0.98042137
B13: No. Employees | D13: 6346 | F13: 3907 | H13: 3362 | J13: 2000 | P13: Titanium | Q13: Wing to body fairings | S13: 44611 | T13: 32.15 | U13: 33.75 | V13: 24.55 | W13: 25.15 | X13: 25.15 | Y13: 303046 | Z13: 45.65 | AA13: 49.21 | AB13: 43.09 | AC13: 49.07 | AD13: 49.07 | AE13: 123900 | AF13: =X13/$X$6 -> 0.72063037 | AG13: =AD13/$AD$6 -> 1.0442647
P14: Composite | Q14: Flap track fairings | S14: 44618 | T14: 25.5 | U14: 26.1 | V14: 18.54 | W14: 18.54 | X14: 18.54 | Y14: 1211845 | Z14: 49.13 | AA14: 51.58 | AB14: 49.13 | AC14: 50.2 | AD14: 50.2 | AE14: 203900 | AF14: =X14/$X$6 -> 0.53123209 | AG14: =AD14/$AD$6 -> 1.0683124
B15: (1) defined as operating cash flow minus PPE acquisitions | J15: 1.8 | S15: 44625 | T15: 17.82 | U15: 18 | V15: 15.28 | W15: 15.9 | X15: 15.9 | Y15: 609677 | Z15: 50.57 | AA15: 52.94 | AB15: 50.22 | AC15: 50.65 | AD15: 50.65 | AE15: 168500 | AF15: =X15/$X$6 -> 0.45558739 | AG15: =AD15/$AD$6 -> 1.0778889
B16: (2) from EBITDA | S16: 44632 | T16: 15.94 | U16: 17.36 | V16: 14.84 | W16: 16.8 | X16: 16.8 | Y16: 583264 | Z16: 51.09 | AA16: 52.29 | AB16: 50.08 | AC16: 50.82 | AD16: 50.82 | AE16: 330500 | AF16: =X16/$X$6 -> 0.48137536 | AG16: =AD16/$AD$6 -> 1.0815067
S17: 44639 | T17: 17.2 | U17: 17.82 | V17: 16 | W17: 16.44 | X17: 16.44 | Y17: 262995 | Z17: 51.5 | AA17: 54.61 | AB17: 51.3 | AC17: 53.52 | AD17: 53.52 | AE17: 139800 | AF17: =X17/$X$6 -> 0.47106017 | AG17: =AD17/$AD$6 -> 1.1389657
S18: 44646 | T18: 16.34 | U18: 16.92 | V18: 15.1 | W18: 15.22 | X18: 15.22 | Y18: 525974 | Z18: 53.52 | AA18: 53.66 | AB18: 52.08 | AC18: 53.31 | AD18: 53.31 | AE18: 145600 | AF18: =X18/$X$6 -> 0.43610315 | AG18: =AD18/$AD$6 -> 1.1344967
S19: 44653 | T19: 15.52 | U19: 18.62 | V19: 15.48 | W19: 17.56 | X19: 17.56 | Y19: 646027 | Z19: 53.54 | AA19: 54.02 | AB19: 51.38 | AC19: 52.08 | AD19: 52.08 | AE19: 150900 | AF19: =X19/$X$6 -> 0.50315186 | AG19: =AD19/$AD$6 -> 1.1083209
S20: 44660 | T20: 17.66 | U20: 18.78 | V20: 17.24 | W20: 18.26 | X20: 18.26 | Y20: 302366 | Z20: 52.09 | AA20: 55.93 | AB20: 51.83 | AC20: 55.42 | AD20: 55.42 | AE20: 129700 | AF20: =X20/$X$6 -> 0.52320917 | AG20: =AD20/$AD$6 -> 1.1793999
S21: 44667 | T21: 18.26 | U21: 18.64 | V21: 17.24 | W21: 17.84 | X21: 17.84 | Y21: 522545 | Z21: 55.45 | AA21: 58.18 | AB21: 55.3 | AC21: 55.53 | AD21: 55.53 | AE21: 181300 | AF21: =X21/$X$6 -> 0.51117479 | AG21: =AD21/$AD$6 -> 1.1817408
S22: 44674 | T22: 17.5 | U22: 17.7 | V22: 14.2 | W22: 14.92 | X22: 14.92 | Y22: 658409 | Z22: 55.45 | AA22: 55.45 | AB22: 50.81 | AC22: 51.07 | AD22: 51.07 | AE22: 223100 | AF22: =X22/$X$6 -> 0.42750716 | AG22: =AD22/$AD$6 -> 1.086827
S23: 44681 | T23: 15 | U23: 16.3 | V23: 14.06 | W23: 15.6 | X23: 15.6 | Y23: 390389 | Z23: 51.3 | AA23: 55.31 | AB23: 49.14 | AC23: 50.15 | AD23: 50.15 | AE23: 265100 | AF23: =X23/$X$6 -> 0.4469914 | AG23: =AD23/$AD$6 -> 1.0672484
S24: 44688 | T24: 15.74 | U24: 16.16 | V24: 14.7 | W24: 15.58 | X24: 15.58 | Y24: 475268 | Z24: 49.34 | AA24: 49.34 | AB24: 45.03 | AC24: 46.11 | AD24: 46.11 | AE24: 229200 | AF24: =X24/$X$6 -> 0.44641834 | AG24: =AD24/$AD$6 -> 0.98127261
S25: 44695 | T25: 15.46 | U25: 16.78 | V25: 15.34 | W25: 15.5 | X25: 15.5 | Y25: 144205 | Z25: 46 | AA25: 46.31 | AB25: 40 | AC25: 40.88 | AD25: 40.88 | AE25: 241200 | AF25: =X25/$X$6 -> 0.44412607 | AG25: =AD25/$AD$6 -> 0.86997233
S26: 44702 | T26: 15.62 | U26: 15.9 | V26: 13.66 | W26: 14.94 | X26: 14.94 | Y26: 181348 | Z26: 41.66 | AA26: 44.56 | AB26: 40.69 | AC26: 44.14 | AD26: 44.14 | AE26: 144200 | AF26: =X26/$X$6 -> 0.42808023 | AG26: =AD26/$AD$6 -> 0.9393488
S27: 44709 | T27: 14.84 | U27: 17.86 | V27: 14.84 | W27: 16.84 | X27: 16.84 | Y27: 308488 | Z27: 44.11 | AA27: 46.72 | AB27: 43.78 | AC27: 45.82 | AD27: 45.82 | AE27: 207800 | AF27: =X27/$X$6 -> 0.48252149 | AG27: =AD27/$AD$6 -> 0.97510109
S28: 44716 | T28: 16.84 | U28: 17.88 | V28: 16.08 | W28: 16.3 | X28: 16.3 | Y28: 106233 | Z28: 45.95 | AA28: 47.43 | AB28: 44.64 | AC28: 46.87 | AD28: 46.87 | AE28: 212200 | AF28: =X28/$X$6 -> 0.46704871 | AG28: =AD28/$AD$6 -> 0.99744627
... S58: 44926 | T58: 14.34 | U58: 16.38 | V58: 14.34 | W58: 16.26 | X58: 16.26 | Y58: 103167 | Z58: 50.02 | AA58: 52.6 | AB58: 48.68 | AC58: 52.27 | AD58: 52.27 | AE58: 164100 | AF58: =X58/$X$6 -> 0.46590258 | AG58: =AD58/$AD$6 -> 1.1123643
S59: 44933 | T59: 16.52 | U59: 17.42 | V59: 15.8 | W59: 17.14 | X59: 17.14 | Y59: 318404 | Z59: 53.07 | AA59: 57.46 | AB59: 51.97 | AC59: 57.4 | AD59: 57.4 | AE59: 225200 | AF59: =X59/$X$6 -> 0.49111748 | AG59: =AD59/$AD$6 -> 1.2215365 | AH59: =X59/$X$59 -> 1 | AI59: =AD59/$AD$59 -> 1
S60: 44940 | T60: 17.14 | U60: 18.16 | V60: 16.52 | W60: 17.3 | X60: 17.3 | Y60: 282279 | Z60: 57.82 | AA60: 57.82 | AB60: 53.5 | AC60: 54.12 | AD60: 54.12 | AE60: 230300 | AF60: =X60/$X$6 -> 0.49570201 | AG60: =AD60/$AD$6 -> 1.1517344 | AH60: =X60/$X$59 -> 1.0093349 | AI60: =AD60/$AD$59 -> 0.94285714
S61: 44947 | T61: 17.38 | U61: 18.34 | V61: 17.04 | W61: 17.84 | X61: 17.84 | Y61: 240520 | Z61: 54.35 | AA61: 56.81 | AB61: 53.51 | AC61: 56.19 | AD61: 56.19 | AE61: 218800 | AF61: =X61/$X$6 -> 0.51117479 | AG61: =AD61/$AD$6 -> 1.1957863 | AH61: =X61/$X$59 -> 1.0408401 | AI61: =AD61/$AD$59 -> 0.97891986
S62: 44954 | T62: 17.32 | U62: 17.54 | V62: 15.84 | W62: 16.84 | X62: 16.84 | Y62: 219882 | Z62: 56.24 | AA62: 57.9 | AB62: 55.38 | AC62: 56.34 | AD62: 56.34 | AE62: 225000 | AF62: =X62/$X$6 -> 0.48252149 | AG62: =AD62/$AD$6 -> 1.1989785 | AH62: =X62/$X$59 -> 0.98249708 | AI62: =AD62/$AD$59 -> 0.9815331
S63: 44961 | T63: 16.78 | U63: 16.78 | V63: 15.4 | W63: 15.56 | X63: 15.56 | Y63: 162939 | Z63: 56.23 | AA63: 57.27 | AB63: 55.28 | AC63: 56.14 | AD63: 56.14 | AE63: 213300 | AF63: =X63/$X$6 -> 0.44584527 | AG63: =AD63/$AD$6 -> 1.1947223 | AH63: =X63/$X$59 -> 0.90781797 | AI63: =AD63/$AD$59 -> 0.97804878
S64: 44968 | T64: 15.48 | U64: 17.34 | V64: 15.42 | W64: 16.26 | X64: 16.26 | Y64: 123504 | Z64: 56.48 | AA64: 58.28 | AB64: 53.25 | AC64: 53.6 | AD64: 53.6 | AE64: 346700 | AF64: =X64/$X$6 -> 0.46590258 | AG64: =AD64/$AD$6 -> 1.1406682 | AH64: =X64/$X$59 -> 0.94865811 | AI64: =AD64/$AD$59 -> 0.93379791
S65: 44975 | T65: 16.2 | U65: 17.4 | V65: 16.12 | W65: 17 | X65: 17 | Y65: 190839 | Z65: 53.41 | AA65: 55.67 | AB65: 52.75 | AC65: 55.49 | AD65: 55.49 | AE65: 199200 | AF65: =X65/$X$6 -> 0.48710602 | AG65: =AD65/$AD$6 -> 1.1808896 | AH65: =X65/$X$59 -> 0.99183197 | AI65: =AD65/$AD$59 -> 0.96672474
S66: 44982 | T66: 17.04 | U66: 17.92 | V66: 16.94 | W66: 17.38 | X66: 17.38 | Y66: 106931 | Z66: 55.71 | AA66: 56.5 | AB66: 53.58 | AC66: 55.83 | AD66: 55.83 | AE66: 245800 | AF66: =X66/$X$6 -> 0.49799427 | AG66: =AD66/$AD$6 -> 1.1881251 | AH66: =X66/$X$59 -> 1.0140023 | AI66: =AD66/$AD$59 -> 0.97264808
S67: 44989 | T67: 17.34 | U67: 17.74 | V67: 16.24 | W67: 16.6 | X67: 16.6 | Y67: 160162 | Z67: 55.83 | AA67: 56.37 | AB67: 52.4 | AC67: 53.32 | AD67: 53.32 | AE67: 285200 | AF67: =X67/$X$6 -> 0.4756447 | AG67: =AD67/$AD$6 -> 1.1347095 | AH67: =X67/$X$59 -> 0.96849475 | AI67: =AD67/$AD$59 -> 0.92891986
S68: 44996 | T68: 16.7 | U68: 16.74 | V68: 13.92 | W68: 14.46 | X68: 14.46 | Y68: 316415 | Z68: 52.39 | AA68: 54.21 | AB68: 49.93 | AC68: 50.15 | AD68: 50.15 | AE68: 413300 | AF68: =X68/$X$6 -> 0.41432665 | AG68: =AD68/$AD$6 -> 1.0672484 | AH68: =X68/$X$59 -> 0.84364061 | AI68: =AD68/$AD$59 -> 0.87369338
S69: 45003 | T69: 14.28 | U69: 14.76 | V69: 13.26 | W69: 13.74 | X69: 13.74 | Y69: 263543 | Z69: 50.49 | AA69: 53.91 | AB69: 50.27 | AC69: 52.64 | AD69: 52.64 | AE69: 268600 | AF69: =X69/$X$6 -> 0.39369628 | AG69: =AD69/$AD$6 -> 1.1202383 | AH69: =X69/$X$59 -> 0.80163361 | AI69: =AD69/$AD$59 -> 0.91707317
S70: 45010 | T70: 13.74 | U70: 14.94 | V70: 13.38 | W70: 14.94 | X70: 14.94 | Y70: 465449 | Z70: 53.13 | AA70: 54.88 | AB70: 52.77 | AC70: 54.71 | AD70: 54.71 | AE70: 232000 | AF70: =X70/$X$6 -> 0.42808023 | AG70: =AD70/$AD$6 -> 1.1642903 | AH70: =X70/$X$59 -> 0.87164527 | AI70: =AD70/$AD$59 -> 0.95313589
... S214: 46018 | T214: 27.5 | U214: 28.45 | V214: 27.5 | W214: 28.3 | X214: 28.3 | Y214: 248605 | Z214: 96.3 | AA214: 96.8 | AB214: 94 | AC214: 95.13 | AD214: 95.13 | AE214: 191200 | AF214: =X214/$X$6 -> 0.81088825 | AG214: =AD214/$AD$6 -> 2.0244733 | AH214: =X214/$X$59 -> 1.6511085 | AI214: =AD214/$AD$59 -> 1.6573171

Sheet Figure 1
B3: FACC AG
C4: FY2021 | D4: FY2022 | E4: FY2023 | F4: FY2024 | G4: FY2025 | H4: FY2026E | I4: FY2027E
B5: Aerostructures + Nacelles Segments
B6: Revenues | C6: 271.204 | D6: 332.418 | E6: 402.109 | F6: 507.733 | G6: 525.317
B7: EBITDA | C7: 7.306 | D7: -12.385 | E7: 32.507 | F7: 47.411 | G7: 53.107
B8: Margin | C8: 0.026939131 | D8: -0.037257309 | E8: 0.080841264 | F8: 0.093377819 | G8: 0.10109515
B10: Cabin Interiors Segment
B11: Revenues | C11: 497.554 | D11: 606.976 | E11: 736.202 | F11: 884.522 | G11: 984.405
B12: EBITDA | C12: 1.52 | D12: 8.824 | E12: -1.114 | F12: 2.021 | G12: 22.548
B13: Margin | C13: 0.0030549448 | D13: 0.014537642 | E13: -0.0015131717 | F13: 0.0022848499 | G13: 0.022905207
C15: 12/21 | D15: 12/22 | E15: 12/23 | F15: 12/24 | G15: 12/25 | H15: 12/26E | I15: 12/27E
B16: Montana Aerostructures Segment only
B17: Revenues | C17: 284.965 | D17: 636.427 | E17: 704.529 | F17: 815.619 | G17: 881.272 | H17: =Model!AL12/1000 -> 950 | I17: =Model!AM12/1000 -> 1016.5
B18: EBITDA | C18: 35.127 | D18: 65.708 | E18: 73.569 | F18: 127.035 | G18: 159.811 | H18: =Model!AL14/1000 -> 171 | I18: =Model!AM14/1000 -> 203.3
B19: Margin | C19: 0.12326777 | D19: 0.10324515 | E19: 0.10442295 | F19: 0.15575287 | G19: 0.18134129 | H19: =H18/H17 -> 0.18 | I19: =I18/I17 -> 0.2
B20: Group (incl. E-mobility and Energy Segments) | J20: 0.001
B21: Revenues | C21: =Model!AA86/1000 -> 790.052 | D21: =Model!AB86/1000 -> 1306.134 | E21: =Model!AC86/1000 -> 1270.348 | F21: =Model!AD86/1000 -> 1493.673 | G21: =Model!AF86/1000 -> 979.331 | H21: =(Model!AL86)*0.001 -> 1050 | I21: =(Model!AM86)*0.001 -> 1119
B22: EBITDA | C22: =Model!AA99/1000 -> 46.053 | D22: =Model!AB99/1000 -> 126.924 | E22: =Model!AC99/1000 -> 96.902 | F22: =Model!AD99/1000 -> 160.468 | G22: =Model!AF99/1000 -> 160.592 | H22: =(Model!AL99)*0.001 -> 180 | I22: =(Model!AM99)*0.001 -> 213.55
B23: Margin | C23: =C22/C21 -> 0.0582911 | D23: =D22/D21 -> 0.097175328 | E23: =E22/E21 -> 0.076279886 | F23: =F22/F21 -> 0.10743181 | G23: =G22/G21 -> 0.16398133 | H23: =H22/H21 -> 0.17142857 | I23: =I22/I21 -> 0.19084004
B24: Net Income | C24: =Model!AA133/1000 -> -49.38 | D24: =Model!AB133/1000 -> -36.775 | E24: =Model!AC133/1000 -> -38.408 | F24: =Model!AD133/1000 -> 35.787 | G24: =Model!AF133/1000 -> -3.033 | H24: =(Model!AL130)*0.001 -> 21 | I24: =(Model!AM130)*0.001 -> 22.38
B25: EPS | C25: =Model!AA138 -> -1.1733432 | D25: =Model!AB138 -> -0.59383747 | E25: =Model!AC138 -> -0.61225513 | F25: =Model!AD138 -> 0.58202194 | G25: =Model!AF138 -> -0.049115071 | H25: =Model!AL138 -> 0.33585689 | I25: =Model!AM138 -> 0.35792748
C27: 44561 | D27: =EOMONTH(C27,12) -> 44926 | E27: =EOMONTH(D27,12) -> 45291 | F27: =EOMONTH(E27,12) -> 45657 | G27: =EOMONTH(F27,12) -> 46022
B28: Sales | C28: 284965 | D28: 636427 | E28: 704529 | F28: 815619 | G28: 881272 | H28: =Model!AL12 -> 950000 | I28: =Model!AM12 -> 1016500
B29: EBITDA | C29: 35127 | D29: 65708 | E29: 73569 | F29: 127035 | G29: 159811
B30: D&A | C30: -54104 | D30: -89418 | E30: -82527 | F30: -82999 | G30: -87106
B31: Segment EBIT | C31: -18977 | D31: -23710 | E31: -8958 | F31: 44036 | G31: 72705
B32: Investments | C32: 100787 | D32: 77222 | E32: 54020 | F32: 73282 | G32: =Model!AF20 -> 68161 | H32: =Model!AL20 -> 66500 | I32: =Model!AM20 -> 71155
B33: Y/Y change
B34: Incremental revenue | D34: =D28-C28 -> 351462 | E34: =E28-D28 -> 68102 | F34: =F28-E28 -> 111090 | G34: =G28-F28 -> 65653
B35: Incremental EBITDA | D35: =D29-C29 -> 30581 | E35: =E29-D29 -> 7861 | F35: =F29-E29 -> 53466 | G35: =G29-F29 -> 32776
B36: Incremental D&A | D36: =D30-C30 -> -35314 | E36: =E30-D30 -> 6891 | F36: =F30-E30 -> -472 | G36: =G30-F30 -> -4107
B37: Incremental EBIT | D37: =D31-C31 -> -4733 | E37: =E31-D31 -> 14752 | F37: =F31-E31 -> 52994 | G37: =G31-F31 -> 28669
B38: Incremental EBIT margins | D38: =D37/D34 -> -0.013466605 | E38: =E37/E34 -> 0.21661625 | F38: =F37/F34 -> 0.47703664 | G38: =G37/G34 -> 0.43667464
B43: Y/Y change (%)
B44: =B28 -> Sales | D44: =D28/C28-1 -> 1.2333515 | E44: =E28/D28-1 -> 0.10700677 | F44: =F28/E28-1 -> 0.15767981 | G44: =G28/F28-1 -> 0.080494692
B45: =B29 -> EBITDA | D45: =D29/C29-1 -> 0.87058388 | E45: =E29/D29-1 -> 0.11963536 | F45: =F29/E29-1 -> 0.72674632 | G45: =G29/F29-1 -> 0.25800764
B46: =B30 -> D&A | D46: =D30/C30-1 -> 0.6527059 | E46: =E30/D30-1 -> -0.07706502 | F46: =F30/E30-1 -> 0.0057193403 | G46: =G30/F30-1 -> 0.049482524
B47: =B31 -> Segment EBIT | D47: =D31/C31-1 -> 0.24940718 | E47: =E31/D31-1 -> -0.62218473 | F47: =F31/E31-1 -> -5.9158294 | G47: =G31/F31-1 -> 0.65103552
B48: Sales | D48: =D32/C32-1 -> -0.23380992 | E48: =E32/D32-1 -> -0.30045842 | F48: =F32/E32-1 -> 0.35657164 | G48: =G32/F32-1 -> -0.069880735
B49: margins
B50: EBITDA | C50: 0.12326777 | D50: 0.10324515 | E50: 0.10442295 | F50: 0.15575287 | G50: 0.18134129
B51: Segment EBIT | C51: -0.066594143 | D51: -0.037254862 | E51: -0.012714878 | F51: 0.053990895 | G51: 0.082500068
B52: Investments | C52: 0.35368203 | D52: 0.12133678 | E52: 0.076675339 | F52: 0.089848324 | G52: 0.077343885 | H52: =H32/H28 -> 0.07 | I52: =I32/I28 -> 0.07
C56: Revenue | D56: EBITDA Margin | E56: EBIT Margin | F56: Cpex % Revenue
B57: 2021 | C57: 284.965 | D57: 0.12326777 | E57: -0.066594143 | F57: 0.35368203
B58: 2022 | C58: 636.427 | D58: 0.10324515 | E58: -0.037254862 | F58: 0.12133678
B59: 2023 | C59: 704.529 | D59: 0.10442295 | E59: -0.012714878 | F59: 0.076675339
B60: 2024 | C60: 815.619 | D60: 0.15575287 | E60: 0.053990895 | F60: 0.089848324
B61: 2025 | C61: 881.272 | D61: 0.18134129 | E61: 0.082500068 | F61: 0.077343885
B62: 2026E | C62: =H17 -> 950 | D62: =H19 -> 0.18 | E62: =Model!AL19 -> 0.085 | F62: =H52 -> 0.07
B63: 2027E | C63: =I17 -> 1016.5 | D63: =+Model!AM15 -> 0.2 | E63: =Model!AM19 -> 0.11 | F63: =I52 -> 0.07

Sheet DCF Base
V1: Critique
B2: Assumptions | F2: 2025(A) | G2: 2029E | H2: 2035E
B3: Terminal WACC | C3: 0.075 | D3: Capex/Revenue | F3: =C17/C12 -> 0.076351101 | G3: 0.076 | H3: 0.076 | U3: (a) | V3: Proof of lower risk?
B4: Terminal Growth | C4: 0.02 | D4: D&A/Revenue | F4: =-C18/C12 -> 0.093713974 | G4: 0.09 | H4: 0.07 | U4: (b) | V4: Okay with this, but please verify Boeing and Airbus numbers
B5: EUR/CHF | C5: 0.94 | D5: NWC Absorption | F5: =C20/C12 -> -0.012082738 | G5: -0.012 | H5: 0.01 | U5: (c) | V5: Proof that management can return in excess of COC?
B6: Net Debt (12/31/2025) | C6: =Main!C11/1000 -> 152.343 | D6: =C47 -> 29.120626
B7: Swiss Tax rate | C7: 0.19
B8: Terminal EBIT margin | C8: 0.12
U9: (d) | V9: Implies Montana lies in top quartile of
C10: 0 | D10: 1 | E10: 2 | F10: 3 | G10: 4 | H10: 5 | I10: 6 | J10: 7 | K10: 8 | L10: 9 | M10: 10
B11: Figures in millions | C11: 2025 | D11: 2026 | E11: =D11+1 -> 2027 | F11: =E11+1 -> 2028 | G11: =F11+1 -> 2029 | H11: =G11+1 -> 2030 | I11: =H11+1 -> 2031 | J11: =I11+1 -> 2032 | K11: =J11+1 -> 2033 | L11: =K11+1 -> 2034 | M11: =L11+1 -> 2035 | O11: Terminal | Q11: 2026-2029 | R11: 2030-2035 | S11: Aggregate | T11: CAGR
B12: Revenue | C12: =Model!$AF$86/1000 -> 979.331 | D12: =C12*(1+D13) -> 1050 | E12: =D12*(1+E13) -> 1119 | F12: =E12*(1+F13) -> 1182.5525 | G12: =F12*(1+G13) -> 1239.0536 | H12: =G12*(1+H13) -> 1287.0004 | I12: =H12*(1+I13) -> 1336.273 | J12: =I12*(1+J13) -> 1387.4321 | K12: =J12*(1+K13) -> 1440.5498 | ... M12: =L12*(1+M13) -> 1552.9639 | O12: =M12*(1+O13) -> 1584.0232 | Q12: =IFERROR(SUM(D12:G12),"") -> 4590.6061 | R12: =IFERROR(SUM(H12:M12),"") -> 8499.9203 | S12: =+SUM(D12:M12) -> 13090.526 | T12: =IFERROR(((M12/C12))^(1/(2035-2025))-1,"") -> 0.047184451
B13: Revenue growth | C13: =Model!$AF$87 -> 0.15076643 | D13: =Model!AL87 -> 0.072160485 | E13: =Model!AM87 -> 0.065714286 | F13: =Model!AN87 -> 0.056794013 | G13: =Model!AO87 -> 0.047778904 | H13: =Model!AP87 -> 0.038696315 | I13: =Model!AQ87 -> 0.038284896 | J13: =Model!AR87 -> 0.038284896 | K13: =Model!AS87 -> 0.038284896 | ... M13: =Model!AU87 -> 0.038284896 | O13: =C4 -> 0.02 | U13: (e) | V13: Must validate extended growth run rate
B14: EBIT | C14: =Model!AF110/1000 -> 68.815 | D14: =D12*D15 -> 86.8 | E14: =E12*E15 -> 119.084 | F14: =F12*F15 -> 126.0102 | G14: =G12*G15 -> 137.80731 | H14: =H12*H15 -> 149.10417 | I14: =I12*I15 -> 160.34982 | J14: =J12*J15 -> 171.40911 | K14: =K12*K15 -> 181.25977 | ... M14: =M12*M15 -> 188.63688 | O14: =O12*O15 -> 190.08278 | Q14: =IFERROR(SUM(D14:G14),"") -> 469.70152 | R14: =IFERROR(SUM(H14:M14),"") -> 1035.6711 | S14: =+SUM(D14:M14) -> 1505.3726 | T14: =IFERROR(((M14/C14))^(1/(2035-2025))-1,"") -> 0.10609989
B15: EBIT Margin | C15: =Model!$AF$111 -> 0.070267356 | D15: =Model!AL111 -> 0.082666667 | E15: =Model!AM111 -> 0.10642002 | F15: =Model!AN111 -> 0.10655781 | G15: =Model!AO111 -> 0.11121982 | H15: =Model!AP111 -> 0.11585402 | I15: =Model!AQ111 -> 0.11999779 | J15: =Model!AR111 -> 0.12354414 | K15: =Model!AS111 -> 0.1258268 | ... M15: =Model!AU111 -> 0.12146894 | O15: =C8 -> 0.12 | Q15: =Q14/Q12 -> 0.10231798 | R15: =R14/R12 -> 0.1218448 | S15: =S14/S12 -> 0.1149971 | V15: See (d)
B16: NOPAT | C16: =C14*(1-$C$7) -> 55.74015 | D16: =D14*(1-$C$7) -> 70.308 | E16: =E14*(1-$C$7) -> 96.45804 | F16: =F14*(1-$C$7) -> 102.06826 | G16: =G14*(1-$C$7) -> 111.62392 | H16: =H14*(1-$C$7) -> 120.77438 | I16: =I14*(1-$C$7) -> 129.88335 | J16: =J14*(1-$C$7) -> 138.84138 | ... M16: =M14*(1-$C$7) -> 152.79587 | O16: =O14*(1-$C$7) -> 153.96705 | Q16: =IFERROR(SUM(D16:G16),"") -> 380.45823 | R16: =IFERROR(SUM(H16:M16),"") -> 838.89356 | S16: =+SUM(D16:M16) -> 1219.3518 | T16: =IFERROR(((M16/C16))^(1/(2035-2025))-1,"") -> 0.10609989
B17: Gross Capex | C17: =Model!AF367 -> 74.773 | D17: =$C$17+($G$17-$C$17)*((D$11-$C$11)/($G$11-$C$11)) -> 79.621768 | E17: =$C$17+($G$17-$C$17)*((E$11-$C$11)/($G$11-$C$11)) -> 84.470535 | F17: =$C$17+($G$17-$C$17)*((F$11-$C$11)/($G$11-$C$11)) -> 89.319303 | G17: =G12*$G$3 -> 94.168071 | H17: =$G$17+(($M$17-$G$17)*(H$11-$G$11)/($M$11-$G$11)) -> 98.144268 | I17: =$G$17+(($M$17-$G$17)*(I$11-$G$11)/($M$11-$G$11)) -> 102.12047 | J17: =$G$17+(($M$17-$G$17)*(J$11-$G$11)/($M$11-$G$11)) -> 106.09666 | K17: =$G$17+(($M$17-$G$17)*(K$11-$G$11)/($M$11-$G$11)) -> 110.07286 | L17: =$G$17+(($M$17-$G$17)*(L$11-$G$11)/($M$11-$G$11)) -> 114.04906 | M17: =M12*$H$3 -> 118.02525 | O17: =O12*$H$3 -> 120.38576 | Q17: =IFERROR(SUM(D17:G17),"") -> 347.57968 | R17: =IFERROR(SUM(H17:M17),"") -> 648.50857 | S17: =+SUM(D17:M17) -> 996.08824 | T17: =IFERROR(((M17/C17))^(1/(2035-2025))-1,"") -> 0.046701904
B18: D&A | C18: =Model!AF368 -> -91.777 | D18: =$C$18+($G$18-$C$18)*((D$11-$C$11)/($G$11-$C$11)) -> -96.711455 | E18: =$C$18+($G$18-$C$18)*((E$11-$C$11)/($G$11-$C$11)) -> -101.64591 | F18: =$C$18+($G$18-$C$18)*((F$11-$C$11)/($G$11-$C$11)) -> -106.58037 | G18: =-G12*$G$4 -> -111.51482 | H18: =$G$18+(($M$18-$G$18)*(H$11-$G$11)/($M$11-$G$11)) -> -111.04693 | I18: =$G$18+(($M$18-$G$18)*(I$11-$G$11)/($M$11-$G$11)) -> -110.57904 | J18: =$G$18+(($M$18-$G$18)*(J$11-$G$11)/($M$11-$G$11)) -> -110.11115 | K18: =$G$18+(($M$18-$G$18)*(K$11-$G$11)/($M$11-$G$11)) -> -109.64325 | L18: =$G$18+(($M$18-$G$18)*(L$11-$G$11)/($M$11-$G$11)) -> -109.17536 | M18: =-M12*$H$4 -> -108.70747 | O18: =-O12*$H$4 -> -110.88162 | Q18: =IFERROR(SUM(D18:G18),"") -> -416.45255 | R18: =IFERROR(SUM(H18:M18),"") -> -659.2632 | S18: =+SUM(D18:M18) -> -1075.7158 | T18: =IFERROR(((M18/C18))^(1/(2035-2025))-1,"") -> 0.017074003
B19: Net Capex | C19: =C17+C18 -> -17.004 | D19: =D17+D18 -> -17.089687 | E19: =E17+E18 -> -17.175375 | F19: =F17+F18 -> -17.261062 | G19: =G17+G18 -> -17.34675 | H19: =H17+H18 -> -12.902661 | I19: =I17+I18 -> -8.4585722 | J19: =J17+J18 -> -4.0144833 | ... M19: =M17+M18 -> 9.3177832 | O19: =O17+O18 -> 9.5041389 | Q19: =IFERROR(SUM(D19:G19),"") -> -68.872875 | R19: =IFERROR(SUM(H19:M19),"") -> -10.754633 | S19: =+SUM(D19:M19) -> -79.627508 | T19: =IFERROR(((M19/C19))^(1/(2035-2025))-1,"")
B20: δ NWC | C20: =Model!AF370 -> -11.833 | D20: =$C$20+($G$20-$C$20)*((D$11-$C$11)/($G$11-$C$11)) -> -12.591911 | E20: =$C$20+($G$20-$C$20)*((E$11-$C$11)/($G$11-$C$11)) -> -13.350821 | F20: =$C$20+($G$20-$C$20)*((F$11-$C$11)/($G$11-$C$11)) -> -14.109732 | G20: =G12*$G$5 -> -14.868643 | H20: =$G$20+(($M$20-$G$20)*(H$11-$G$11)/($M$11-$G$11)) -> -9.8022625 | I20: =$G$20+(($M$20-$G$20)*(I$11-$G$11)/($M$11-$G$11)) -> -4.7358823 | J20: =$G$20+(($M$20-$G$20)*(J$11-$G$11)/($M$11-$G$11)) -> 0.330498 | K20: =$G$20+(($M$20-$G$20)*(K$11-$G$11)/($M$11-$G$11)) -> 5.3968782 | L20: =$G$20+(($M$20-$G$20)*(L$11-$G$11)/($M$11-$G$11)) -> 10.463258 | M20: =M12*$H$5 -> 15.529639 | O20: =O12*$H$5 -> 15.840232 | Q20: =IFERROR(SUM(D20:G20),"") -> -54.921107 | R20: =IFERROR(SUM(H20:M20),"") -> 17.182129 | S20: =+SUM(D20:M20) -> -37.738978 | T20: =IFERROR(((M20/C20))^(1/(2035-2025))-1,"")
B21: Reinvestment | C21: =C19+C20 -> -28.837 | D21: =D19+D20 -> -29.681598 | E21: =E19+E20 -> -30.526196 | F21: =F19+F20 -> -31.370794 | G21: =G19+G20 -> -32.215393 | H21: =H19+H20 -> -22.704924 | I21: =I19+I20 -> -13.194454 | J21: =J19+J20 -> -3.6839853 | ... M21: =M19+M20 -> 24.847422 | O21: =O19+O20 -> 25.34437 | Q21: =IFERROR(SUM(D21:G21),"") -> -123.79398 | R21: =IFERROR(SUM(H21:M21),"") -> 6.4274954 | S21: =+SUM(D21:M21) -> -117.36649 | T21: =IFERROR(((M21/C21))^(1/(2035-2025))-1,"")
B22: Reinvestment Rate | C22: =C21/C16 -> -0.51734701 | D22: =D21/D16 -> -0.4221653 | E22: =E21/E16 -> -0.31647125 | F22: =F21/F16 -> -0.30735111 | G22: =G21/G16 -> -0.28860652 | H22: =H21/H16 -> -0.18799454 | I22: =I21/I16 -> -0.10158696 | J22: =J21/J16 -> -0.02653377 | ... M22: =M21/M16 -> 0.16261841 | O22: =O21/O16 -> 0.16460905 | Q22: =Q21/Q16 -> -0.32538127 | R22: =R21/R16 -> 0.0076618724 | S22: =S21/S16 -> -0.096253179 | V22: see note (c)
B23: FCFF | C23: =C16-C21 -> 84.57715 | D23: =D16-D21 -> 99.989598 | E23: =E16-E21 -> 126.98424 | F23: =F16-F21 -> 133.43906 | G23: =G16-G21 -> 143.83932 | H23: =H16-H21 -> 143.4793 | I23: =I16-I21 -> 143.07781 | J23: =J16-J21 -> 142.52537 | ... M23: =M16-M21 -> 127.94845 | O23: =O16-O21 -> 128.62268 | Q23: =IFERROR(SUM(D23:G23),"") -> 504.25221 | R23: =IFERROR(SUM(H23:M23),"") -> 832.46606 | S23: =+SUM(D23:M23) -> 1336.7183 | T23: =IFERROR(((M23/C23))^(1/(2035-2025))-1,"") -> 0.042265108
B24: Y/Y growth | D24: =D23/C23-1 -> 0.18222946 | E24: =E23/D23-1 -> 0.26997446 | F24: =F23/E23-1 -> 0.050831681 | G24: =G23/F23-1 -> 0.077940142 | H24: =H23/G23-1 -> -0.0025029219 | I24: =I23/H23-1 -> -0.0027982701 | J24: =J23/I23-1 -> -0.0038611059 | K24: =K23/J23-1 -> -0.010745004 | ... M24: =M23/L23-1 -> -0.048294371 | O24: =O23/M23-1 -> 0.0052695245
B25: Cost of Capital | D25: 0.075 | E25: =D25 -> 0.075 | F25: =E25 -> 0.075 | G25: =F25 -> 0.075 | H25: =G25 -> 0.075 | I25: =H25-($H$25-$M$25)/5 -> 0.074 | J25: =I25-($H$25-$M$25)/5 -> 0.073 | K25: =J25-($H$25-$M$25)/5 -> 0.072 | L25: =K25-($H$25-$M$25)/5 -> 0.071 | M25: 0.07 | O25: =C3 -> 0.075
B26: Discount factor | D26: =1/((1+D25)^D10) -> 0.93023256 | E26: =1/((1+E25)^E10) -> 0.86533261 | F26: =1/((1+F25)^F10) -> 0.80496057 | G26: =1/((1+G25)^G10) -> 0.74880053 | H26: =1/((1+H25)^H10) -> 0.69655863 | I26: =1/((1+I25)^I10) -> 0.65158985 | J26: =1/((1+J25)^J10) -> 0.61066348 | K26: =1/((1+K25)^K10) -> 0.57337891 | ... M26: =1/((1+M25)^M10) -> 0.50834929
B27: PV FCFF | D27: =D23*D26 -> 93.01358 | E27: =E23*E26 -> 109.8836 | F27: =F23*F26 -> 107.41318 | G27: =G23*G26 -> 107.70696 | H27: =H23*H26 -> 99.941744 | I27: =I23*I26 -> 93.228046 | J27: =J23*J26 -> 87.035036 | K27: =K23*K26 -> 80.842947 | ... M27: =M23*M26 -> 65.042505 | O27: =O23*O26 -> 0
B28: Invested Capital | C28: =Model!AF341/1000 -> 1098.483 | D28: =C28+D21 -> 1068.8014 | E28: =D28+E21 -> 1038.2752 | F28: =E28+F21 -> 1006.9044 | G28: =F28+G21 -> 974.68902 | H28: =G28+H21 -> 951.98409 | I28: =H28+I21 -> 938.78964 | J28: =I28+J21 -> 935.10566 | K28: =J28+K21 -> 940.93214 | ... M28: =L28+M21 -> 981.11651 | O28: =M28+O21 -> 1006.4609 | Q28: =G28-D28 -> -94.112383 | R28: =M28-H28 -> 29.132419 | S28: =M28-C28 -> -117.36649 | T28: =IFERROR(((M28/C28))^(1/(2035-2025))-1,"") -> -0.011235821
B29: Incremental IC | D29: =D28-C28 -> -29.681598 | E29: =E28-D28 -> -30.526196 | F29: =F28-E28 -> -31.370794 | G29: =G28-F28 -> -32.215393 | H29: =H28-G28 -> -22.704924 | I29: =I28-H28 -> -13.194454 | J29: =J28-I28 -> -3.6839853 | K29: =K28-J28 -> 5.8264838 | ... M29: =M28-L28 -> 24.847422 | Q29: =G29-D29 -> -2.5337945 | R29: =M29-H29 -> 47.552346 | S29: =M29-D29 -> 54.52902
B30: Implied EBITDA | D30: =D14-D18 -> 183.51146 | E30: =E14-E18 -> 220.72991 | F30: =F14-F18 -> 232.59057 | G30: =G14-G18 -> 249.32214 | H30: =H14-H18 -> 260.1511 | I30: =I14-I18 -> 270.92885 | J30: =J14-J18 -> 281.52026 | K30: =K14-K18 -> 290.90303 | ... M30: =M14-M18 -> 297.34435
B31: Implied EBITDA margin | D31: =D30/D12 -> 0.17477281 | E31: =E30/E12 -> 0.1972564 | F31: =F30/F12 -> 0.19668519 | G31: =G30/G12 -> 0.20121982 | H31: =H30/H12 -> 0.20213755 | I31: =I30/I12 -> 0.20274962 | J31: =J30/J12 -> 0.20290741 | K31: =K30/K12 -> 0.20193889 | ... M31: =M30/M12 -> 0.19146894
B32: FCFF/EBITDA turnover | D32: =D23/D30 -> 0.54486843 | E32: =E23/E30 -> 0.57529238 | F32: =F23/F30 -> 0.57370795 | G32: =G23/G30 -> 0.57692157 | H32: =H23/H30 -> 0.55152295 | I32: =I23/I30 -> 0.52810103 | J32: =J23/J30 -> 0.50627037 | K32: =K23/K30 -> 0.48467674 | ... M32: =M23/M30 -> 0.43030396
B33: Sum PV (FCFF) | C33: =SUM(C27:M27) -> 916.62248
B34: Terminal cash flow | C34: =O23 -> 128.62268
B35: Terminal cost of capital | C35: =O25 -> 0.075
B36: Terminal value | C36: =C34/(C35-C4) -> 2338.5942
B37: (+) PV Terminal value | C37: =C36*M26 -> 1188.8227
B38: Sum of PV | C38: =C37+C33 -> 2105.4452
B39: Probability of failure | C39: 0.01
B40: Proceeds if firm fails | C40: =Model!$AF$178*0.5/1000 -> 498.917
B41: Value of operating assets | C41: =C38*(1-C39)+C40*C39 -> 2089.3799
B42: Net Debt | C42: =C6 -> 152.343
B43: Value of Equity | C43: =C41-C42 -> 1937.0369
B44: (-) value of options | C44: 0
B45: Value of equity in common stock | C45: =C43-C44 -> 1937.0369
B46: No. Shares | C46: =Main!$C$5/1000 -> 62.526632
B47: Implied PPS | C47: =(C45/C46)*C5 -> 29.120626
B48: Up- (down-) side from current | C48: =(C47/Main!C3)-1 -> 0.37038241
B50: Invested Capital at start of valuation | D50: =C28 -> 1098.483
B51: Invested Capital at end of valuation | D51: =M28 -> 981.11651
B52: Change in invested capital over 10 years | D52: =D51-D50 -> -117.36649
B53: Change in NOPAT over 10 years | D53: =M16-C16 -> 97.055724
B54: Marginal ROIC over 10 years | D54: =D53/D52 -> -0.82694581
B55: ROIC at end of valuation | D55: =#REF! -> #REF!
B56: Average WACC over 10 years (compounded) | D56: 0.08
C58: Base Year | D58: Years 1-5 | E58: Years 6-10 | G58: After Year 10 | H58: Narrative
B59: Revenues | C59: =C12 -> 979.331 | D59: =((H12/D12)^(1/(H10-D10))-1) -> 0.052197688 | E59: =((M12/I12)^(1/(M10-I10))-1) -> 0.038284896 | G59: =C4 -> 0.02 | H59: High signle digit growth during first five years to reflect growth and volume of narrow-bodies. Boeing anticipates to deliver 55 737's per month whereas Airbus expects to deliver 60+.
B60: Opearing Margin | C60: =C15 -> 0.070267356 | D60: =AVERAGE(D15:H15) -> 0.10454367 | E60: =AVERAGE(I15:M15) -> 0.12289324 | G60: =O15 -> 0.12 | H60: High-teens margins reflects (1) Montana's exposure to mature narrowbody programs, (2) in-house aluminum extrusion and machining capability in DACH region;.
B61: Tax Rate | C61: =$C$7 -> 0.19 | D61: =$C$7 -> 0.19 | E61: =$C$7 -> 0.19 | G61: =$C$7 -> 0.19 | H61: Applying tax rate disclosed in FY 2025 financials. MHT reflects corporate tax rate of businesses in Canton Argau.
D62: Avg. Sales-to-Capital | E62: =AVERAGE(#REF!) -> #REF!
B63: Return on Capital | C63: =#REF! -> #REF! | D63: Marginal ROIC | E63: =D54 -> -0.82694581 | H63: Low ROIC in initial year reflects carry-overs from prior business segments. Low reinvestment rates in first few years point to excess capacity being utilized
B64: Cost of Capital | D64: =AVERAGE(D25:H25) -> 0.075 | E64: =AVERAGE(I25:M25) -> 0.072 | G64: =O25 -> 0.075 | H64: Low WACC reflects long-term supply agreements with large OE coutnerparties; net debt at less than 1x EBITDA; upshot from swiss sovereign rating.
C66: Revenues | D66: Operating Margin | E66: EBIT | F66: NOPAT | G66: Reinvestment | H66: FCFF | I66: 1000
B67: 1 | C67: =D12 -> 1050 | D67: =D15 -> 0.082666667 | E67: =(D14/1000)*1000 -> 86.8 | F67: =(D16/1000)*1000 -> 70.308 | G67: =(D21/1000)*1000 -> -29.681598 | H67: =F67-G67 -> 99.989598
B68: 2 | C68: =E12 -> 1119 | D68: =E15 -> 0.10642002 | E68: =(E14/1000)*1000 -> 119.084 | F68: =(E16/1000)*1000 -> 96.45804 | G68: =(E21/1000)*1000 -> -30.526196 | H68: =F68-G68 -> 126.98424
B69: 3 | C69: =F12 -> 1182.5525 | D69: =F15 -> 0.10655781 | E69: =(F14/1000)*1000 -> 126.0102 | F69: =(F16/1000)*1000 -> 102.06826 | G69: =(F21/1000)*1000 -> -31.370794 | H69: =F69-G69 -> 133.43906
B70: 4 | C70: =G12 -> 1239.0536 | D70: =G15 -> 0.11121982 | E70: =(G14/1000)*1000 -> 137.80731 | F70: =(G16/1000)*1000 -> 111.62392 | G70: =(G21/1000)*1000 -> -32.215393 | H70: =F70-G70 -> 143.83932
B71: 5 | C71: =H12 -> 1287.0004 | D71: =H15 -> 0.11585402 | E71: =(H14/1000)*1000 -> 149.10417 | F71: =(H16/1000)*1000 -> 120.77438 | G71: =(H21/1000)*1000 -> -22.704924 | H71: =F71-G71 -> 143.4793
B72: 6 | C72: =I12 -> 1336.273 | D72: =I15 -> 0.11999779 | E72: =(I14/1000)*1000 -> 160.34982 | F72: =(I16/1000)*1000 -> 129.88335 | G72: =(I21/1000)*1000 -> -13.194454 | H72: =F72-G72 -> 143.07781
B73: 7 | C73: =J12 -> 1387.4321 | D73: =J15 -> 0.12354414 | E73: =(J14/1000)*1000 -> 171.40911 | F73: =(J16/1000)*1000 -> 138.84138 | G73: =(J21/1000)*1000 -> -3.6839853 | H73: =F73-G73 -> 142.52537
B74: 8 | C74: =K12 -> 1440.5498 | D74: =K15 -> 0.1258268 | E74: =(K14/1000)*1000 -> 181.25977 | F74: =(K16/1000)*1000 -> 146.82041 | G74: =(K21/1000)*1000 -> 5.8264838 | H74: =F74-G74 -> 140.99393
B75: 9 | C75: =L12 -> 1495.7011 | D75: =L15 -> 0.12362851 | E75: =(L14/1000)*1000 -> 184.91131 | F75: =(L16/1000)*1000 -> 149.77816 | G75: =(L21/1000)*1000 -> 15.336953 | H75: =F75-G75 -> 134.44121
B76: 10 | C76: =M12 -> 1552.9639 | D76: =M15 -> 0.12146894 | E76: =(M14/1000)*1000 -> 188.63688 | F76: =(M16/1000)*1000 -> 152.79587 | G76: =(M21/1000)*1000 -> 24.847422 | H76: =F76-G76 -> 127.94845
B77: Teminal Year | C77: =O12 -> 1584.0232 | D77: =O15 -> 0.12 | E77: =(O14/1000)*1000 -> 190.08278 | F77: =(O16/1000)*1000 -> 153.96705 | G77: =(O21/1000)*1000 -> 25.34437 | H77: =F77-G77 -> 128.62268

Sheet DCF Current
V1: Critique
B2: Assumptions | F2: 2025(A) | G2: 2029E | H2: 2035E
B3: Terminal WACC | C3: 0.09 | D3: Capex/Revenue | F3: =C17/C12 -> 0.076351101 | G3: 0.07 | H3: 0.1 | U3: (a) | V3: Proof of lower risk?
B4: Terminal Growth | C4: 0.02 | D4: D&A/Revenue | F4: =-C18/C12 -> 0.093713974 | G4: 0.09 | H4: 0.07 | U4: (b) | V4: Okay with this, but please verify Boeing and Airbus numbers
B5: EUR/CHF | C5: 0.94 | D5: NWC Absorption | F5: =C20/C12 -> -0.012082738 | G5: -0.012 | H5: 0.02 | U5: (c) | V5: Proof that management can return in excess of COC?
B6: Net Debt (12/31/2025) | C6: =Main!C11/1000 -> 152.343 | D6: =C47 -> 18.353548
B7: Swiss Tax rate | C7: 0.19
B8: Terminal EBIT margin | C8: 0.12
U9: (d) | V9: Implies Montana lies in top quartile of
C10: 0 | D10: 1 | E10: 2 | F10: 3 | G10: 4 | H10: 5 | I10: 6 | J10: 7 | K10: 8 | L10: 9 | M10: 10
B11: Figures in millions | C11: 2025 | D11: 2026 | E11: =D11+1 -> 2027 | F11: =E11+1 -> 2028 | G11: =F11+1 -> 2029 | H11: =G11+1 -> 2030 | I11: =H11+1 -> 2031 | J11: =I11+1 -> 2032 | K11: =J11+1 -> 2033 | L11: =K11+1 -> 2034 | M11: =L11+1 -> 2035 | O11: Terminal | Q11: 2026-2029 | R11: 2030-2035 | S11: Aggregate | T11: CAGR
B12: Revenue | C12: =Model!$AF$86/1000 -> 979.331 | D12: =C12*(1+D13) -> 1050 | E12: =D12*(1+E13) -> 1119 | F12: =E12*(1+F13) -> 1182.5525 | G12: =F12*(1+G13) -> 1239.0536 | H12: =G12*(1+H13) -> 1287.0004 | I12: =H12*(1+I13) -> 1336.273 | J12: =I12*(1+J13) -> 1387.4321 | K12: =J12*(1+K13) -> 1440.5498 | ... M12: =L12*(1+M13) -> 1552.9639 | O12: =M12*(1+O13) -> 1584.0232 | Q12: =IFERROR(SUM(D12:G12),"") -> 4590.6061 | R12: =IFERROR(SUM(H12:M12),"") -> 8499.9203 | S12: =+SUM(D12:M12) -> 13090.526 | T12: =IFERROR(((M12/C12))^(1/(2035-2025))-1,"") -> 0.047184451
B13: Revenue growth | C13: =Model!$AF$87 -> 0.15076643 | D13: =Model!AL87 -> 0.072160485 | E13: =Model!AM87 -> 0.065714286 | F13: =Model!AN87 -> 0.056794013 | G13: =Model!AO87 -> 0.047778904 | H13: =Model!AP87 -> 0.038696315 | I13: =Model!AQ87 -> 0.038284896 | J13: =Model!AR87 -> 0.038284896 | K13: =Model!AS87 -> 0.038284896 | ... M13: =Model!AU87 -> 0.038284896 | O13: =C4 -> 0.02 | U13: (e) | V13: Must validate extended growth run rate
B14: EBIT | C14: =Model!AF110/1000 -> 68.815 | D14: =D12*D15 -> 86.8 | E14: =E12*E15 -> 119.084 | F14: =F12*F15 -> 126.0102 | G14: =G12*G15 -> 137.80731 | H14: =H12*H15 -> 149.10417 | I14: =I12*I15 -> 160.34982 | J14: =J12*J15 -> 171.40911 | K14: =K12*K15 -> 181.25977 | ... M14: =M12*M15 -> 188.63688 | O14: =O12*O15 -> 190.08278 | Q14: =IFERROR(SUM(D14:G14),"") -> 469.70152 | R14: =IFERROR(SUM(H14:M14),"") -> 1035.6711 | S14: =+SUM(D14:M14) -> 1505.3726 | T14: =IFERROR(((M14/C14))^(1/(2035-2025))-1,"") -> 0.10609989
B15: EBIT Margin | C15: =Model!$AF$111 -> 0.070267356 | D15: =Model!AL111 -> 0.082666667 | E15: =Model!AM111 -> 0.10642002 | F15: =Model!AN111 -> 0.10655781 | G15: =Model!AO111 -> 0.11121982 | H15: =Model!AP111 -> 0.11585402 | I15: =Model!AQ111 -> 0.11999779 | J15: =Model!AR111 -> 0.12354414 | K15: =Model!AS111 -> 0.1258268 | ... M15: =Model!AU111 -> 0.12146894 | O15: =C8 -> 0.12 | Q15: =Q14/Q12 -> 0.10231798 | R15: =R14/R12 -> 0.1218448 | S15: =S14/S12 -> 0.1149971 | V15: See (d)
B16: NOPAT | C16: =C14*(1-$C$7) -> 55.74015 | D16: =D14*(1-$C$7) -> 70.308 | E16: =E14*(1-$C$7) -> 96.45804 | F16: =F14*(1-$C$7) -> 102.06826 | G16: =G14*(1-$C$7) -> 111.62392 | H16: =H14*(1-$C$7) -> 120.77438 | I16: =I14*(1-$C$7) -> 129.88335 | J16: =J14*(1-$C$7) -> 138.84138 | ... M16: =M14*(1-$C$7) -> 152.79587 | O16: =O14*(1-$C$7) -> 153.96705 | Q16: =IFERROR(SUM(D16:G16),"") -> 380.45823 | R16: =IFERROR(SUM(H16:M16),"") -> 838.89356 | S16: =+SUM(D16:M16) -> 1219.3518 | T16: =IFERROR(((M16/C16))^(1/(2035-2025))-1,"") -> 0.10609989
B17: Gross Capex | C17: =Model!AF367 -> 74.773 | D17: =$C$17+($G$17-$C$17)*((D$11-$C$11)/($G$11-$C$11)) -> 77.763187 | E17: =$C$17+($G$17-$C$17)*((E$11-$C$11)/($G$11-$C$11)) -> 80.753375 | F17: =$C$17+($G$17-$C$17)*((F$11-$C$11)/($G$11-$C$11)) -> 83.743562 | G17: =G12*$G$3 -> 86.733749 | H17: =$G$17+(($M$17-$G$17)*(H$11-$G$11)/($M$11-$G$11)) -> 98.160856 | I17: =$G$17+(($M$17-$G$17)*(I$11-$G$11)/($M$11-$G$11)) -> 109.58796 | J17: =$G$17+(($M$17-$G$17)*(J$11-$G$11)/($M$11-$G$11)) -> 121.01507 | K17: =$G$17+(($M$17-$G$17)*(K$11-$G$11)/($M$11-$G$11)) -> 132.44217 | L17: =$G$17+(($M$17-$G$17)*(L$11-$G$11)/($M$11-$G$11)) -> 143.86928 | M17: =M12*$H$3 -> 155.29639 | O17: =O12*$H$3 -> 158.40232 | Q17: =IFERROR(SUM(D17:G17),"") -> 328.99387 | R17: =IFERROR(SUM(H17:M17),"") -> 760.37173 | S17: =+SUM(D17:M17) -> 1089.3656 | T17: =IFERROR(((M17/C17))^(1/(2035-2025))-1,"") -> 0.075825056
B18: D&A | C18: =Model!AF368 -> -91.777 | D18: =$C$18+($G$18-$C$18)*((D$11-$C$11)/($G$11-$C$11)) -> -96.711455 | E18: =$C$18+($G$18-$C$18)*((E$11-$C$11)/($G$11-$C$11)) -> -101.64591 | F18: =$C$18+($G$18-$C$18)*((F$11-$C$11)/($G$11-$C$11)) -> -106.58037 | G18: =-G12*$G$4 -> -111.51482 | H18: =$G$18+(($M$18-$G$18)*(H$11-$G$11)/($M$11-$G$11)) -> -111.04693 | I18: =$G$18+(($M$18-$G$18)*(I$11-$G$11)/($M$11-$G$11)) -> -110.57904 | J18: =$G$18+(($M$18-$G$18)*(J$11-$G$11)/($M$11-$G$11)) -> -110.11115 | K18: =$G$18+(($M$18-$G$18)*(K$11-$G$11)/($M$11-$G$11)) -> -109.64325 | L18: =$G$18+(($M$18-$G$18)*(L$11-$G$11)/($M$11-$G$11)) -> -109.17536 | M18: =-M12*$H$4 -> -108.70747 | O18: =-O12*$H$4 -> -110.88162 | Q18: =IFERROR(SUM(D18:G18),"") -> -416.45255 | R18: =IFERROR(SUM(H18:M18),"") -> -659.2632 | S18: =+SUM(D18:M18) -> -1075.7158 | T18: =IFERROR(((M18/C18))^(1/(2035-2025))-1,"") -> 0.017074003
B19: Net Capex | C19: =C17+C18 -> -17.004 | D19: =D17+D18 -> -18.948268 | E19: =E17+E18 -> -20.892536 | F19: =F17+F18 -> -22.836803 | G19: =G17+G18 -> -24.781071 | H19: =H17+H18 -> -12.886073 | I19: =I17+I18 -> -0.99107542 | J19: =J17+J18 -> 10.903922 | ... M19: =M17+M18 -> 46.588916 | O19: =O17+O18 -> 47.520695 | Q19: =IFERROR(SUM(D19:G19),"") -> -87.458678 | R19: =IFERROR(SUM(H19:M19),"") -> 101.10853 | S19: =+SUM(D19:M19) -> 13.649851 | T19: =IFERROR(((M19/C19))^(1/(2035-2025))-1,"")
B20: δ NWC | C20: =Model!AF370 -> -11.833 | D20: =$C$20+($G$20-$C$20)*((D$11-$C$11)/($G$11-$C$11)) -> -12.591911 | E20: =$C$20+($G$20-$C$20)*((E$11-$C$11)/($G$11-$C$11)) -> -13.350821 | F20: =$C$20+($G$20-$C$20)*((F$11-$C$11)/($G$11-$C$11)) -> -14.109732 | G20: =G12*$G$5 -> -14.868643 | H20: =$G$20+(($M$20-$G$20)*(H$11-$G$11)/($M$11-$G$11)) -> -7.2139894 | I20: =$G$20+(($M$20-$G$20)*(I$11-$G$11)/($M$11-$G$11)) -> 0.440664 | J20: =$G$20+(($M$20-$G$20)*(J$11-$G$11)/($M$11-$G$11)) -> 8.0953174 | K20: =$G$20+(($M$20-$G$20)*(K$11-$G$11)/($M$11-$G$11)) -> 15.749971 | L20: =$G$20+(($M$20-$G$20)*(L$11-$G$11)/($M$11-$G$11)) -> 23.404624 | M20: =M12*$H$5 -> 31.059277 | O20: =O12*$H$5 -> 31.680463 | Q20: =IFERROR(SUM(D20:G20),"") -> -54.921107 | R20: =IFERROR(SUM(H20:M20),"") -> 71.535864 | S20: =+SUM(D20:M20) -> 16.614757 | T20: =IFERROR(((M20/C20))^(1/(2035-2025))-1,"")
B21: Reinvestment | C21: =C19+C20 -> -28.837 | D21: =D19+D20 -> -31.540178 | E21: =E19+E20 -> -34.243357 | F21: =F19+F20 -> -36.946535 | G21: =G19+G20 -> -39.649714 | H21: =H19+H20 -> -20.100063 | I21: =I19+I20 -> -0.55041142 | J21: =J19+J20 -> 18.99924 | ... M21: =M19+M20 -> 77.648194 | O21: =O19+O20 -> 79.201158 | Q21: =IFERROR(SUM(D21:G21),"") -> -142.37978 | R21: =IFERROR(SUM(H21:M21),"") -> 172.64439 | S21: =+SUM(D21:M21) -> 30.264608 | T21: =IFERROR(((M21/C21))^(1/(2035-2025))-1,"")
B22: Reinvestment Rate | C22: =C21/C16 -> -0.51734701 | D22: =D21/D16 -> -0.44860014 | E22: =E21/E16 -> -0.3550078 | F22: =F21/F16 -> -0.36197868 | G22: =G21/G16 -> -0.35520803 | H22: =H21/H16 -> -0.16642655 | I22: =I21/I16 -> -0.0042377366 | J22: =J21/J16 -> 0.13684133 | ... M22: =M21/M16 -> 0.50818253 | O22: =O21/O16 -> 0.51440329 | Q22: =Q21/Q16 -> -0.37423237 | R22: =R21/R16 -> 0.20580012 | S22: =S21/S16 -> 0.024820243 | V22: see note (c)
B23: FCFF | C23: =C16-C21 -> 84.57715 | D23: =D16-D21 -> 101.84818 | E23: =E16-E21 -> 130.7014 | F23: =F16-F21 -> 139.0148 | G23: =G16-G21 -> 151.27364 | H23: =H16-H21 -> 140.87444 | I23: =I16-I21 -> 130.43376 | J23: =J16-J21 -> 119.84214 | ... M23: =M16-M21 -> 75.147681 | O23: =O16-O21 -> 74.765893 | Q23: =IFERROR(SUM(D23:G23),"") -> 522.83801 | R23: =IFERROR(SUM(H23:M23),"") -> 666.24916 | S23: =+SUM(D23:M23) -> 1189.0872 | T23: =IFERROR(((M23/C23))^(1/(2035-2025))-1,"") -> -0.011751296
B24: Y/Y growth | D24: =D23/C23-1 -> 0.20420443 | E24: =E23/D23-1 -> 0.28329636 | F24: =F23/E23-1 -> 0.063606072 | G24: =G23/F23-1 -> 0.088183701 | H24: =H23/G23-1 -> -0.068744302 | I24: =I23/H23-1 -> -0.074113346 | J24: =J23/I23-1 -> -0.081203061 | K24: =K23/J23-1 -> -0.096548824 | ... M24: =M23/L23-1 -> -0.18032291 | O24: =O23/M23-1 -> -0.0050805018
B25: Cost of Capital | D25: 0.075 | E25: =D25 -> 0.075 | F25: =E25 -> 0.075 | G25: =F25 -> 0.075 | H25: =G25 -> 0.075 | I25: =H25-($H$25-$M$25)/5 -> 0.074 | J25: =I25-($H$25-$M$25)/5 -> 0.073 | K25: =J25-($H$25-$M$25)/5 -> 0.072 | L25: =K25-($H$25-$M$25)/5 -> 0.071 | M25: 0.07 | O25: =C3 -> 0.09
B26: Discount factor | D26: =1/((1+D25)^D10) -> 0.93023256 | E26: =1/((1+E25)^E10) -> 0.86533261 | F26: =1/((1+F25)^F10) -> 0.80496057 | G26: =1/((1+G25)^G10) -> 0.74880053 | H26: =1/((1+H25)^H10) -> 0.69655863 | I26: =1/((1+I25)^I10) -> 0.65158985 | J26: =1/((1+J25)^J10) -> 0.61066348 | K26: =1/((1+K25)^K10) -> 0.57337891 | ... M26: =1/((1+M25)^M10) -> 0.50834929
B27: PV FCFF | D27: =D23*D26 -> 94.742492 | E27: =E23*E26 -> 113.10018 | F27: =F23*F26 -> 111.90143 | G27: =G23*G26 -> 113.27378 | H27: =H23*H26 -> 98.127306 | I27: =I23*I26 -> 84.989316 | J27: =J23*J26 -> 73.183219 | K27: =K23*K26 -> 62.080609 | ... M27: =M23*M26 -> 38.20127 | O27: =O23*O26 -> 0
B28: Invested Capital | C28: =Model!AF341/1000 -> 1098.483 | D28: =C28+D21 -> 1066.9428 | E28: =D28+E21 -> 1032.6995 | F28: =E28+F21 -> 995.75293 | G28: =F28+G21 -> 956.10321 | H28: =G28+H21 -> 936.00315 | I28: =H28+I21 -> 935.45274 | J28: =I28+J21 -> 954.45198 | K28: =J28+K21 -> 993.00087 | ... M28: =L28+M21 -> 1128.7476 | O28: =M28+O21 -> 1207.9488 | Q28: =G28-D28 -> -110.83961 | R28: =M28-H28 -> 192.74446 | S28: =M28-C28 -> 30.264608 | T28: =IFERROR(((M28/C28))^(1/(2035-2025))-1,"") -> 0.0027215537
B29: Incremental IC | D29: =D28-C28 -> -31.540178 | E29: =E28-D28 -> -34.243357 | F29: =F28-E28 -> -36.946535 | G29: =G28-F28 -> -39.649714 | H29: =H28-G28 -> -20.100063 | I29: =I28-H28 -> -0.55041142 | J29: =J28-I28 -> 18.99924 | K29: =K28-J28 -> 38.548891 | ... M29: =M28-L28 -> 77.648194 | Q29: =G29-D29 -> -8.1095355 | R29: =M29-H29 -> 97.748256 | S29: =M29-D29 -> 109.18837
B30: Implied EBITDA | D30: =D14-D18 -> 183.51146 | E30: =E14-E18 -> 220.72991 | F30: =F14-F18 -> 232.59057 | G30: =G14-G18 -> 249.32214 | H30: =H14-H18 -> 260.1511 | I30: =I14-I18 -> 270.92885 | J30: =J14-J18 -> 281.52026 | K30: =K14-K18 -> 290.90303 | ... M30: =M14-M18 -> 297.34435
B31: Implied EBITDA margin | D31: =D30/D12 -> 0.17477281 | E31: =E30/E12 -> 0.1972564 | F31: =F30/F12 -> 0.19668519 | G31: =G30/G12 -> 0.20121982 | H31: =H30/H12 -> 0.20213755 | I31: =I30/I12 -> 0.20274962 | J31: =J30/J12 -> 0.20290741 | K31: =K30/K12 -> 0.20193889 | ... M31: =M30/M12 -> 0.19146894
B32: FCFF/EBITDA turnover | D32: =D23/D30 -> 0.5549963 | E32: =E23/E30 -> 0.5921327 | F32: =F23/F30 -> 0.5976803 | G32: =G23/G30 -> 0.60673971 | H32: =H23/H30 -> 0.54151007 | I32: =I23/I30 -> 0.48143179 | J32: =J23/J30 -> 0.42569633 | K32: =K23/K30 -> 0.37219112 | ... M32: =M23/M30 -> 0.25272947
B33: Sum PV (FCFF) | C33: =SUM(C27:M27) -> 839.04975
B34: Terminal cash flow | C34: =O23 -> 74.765893
B35: Terminal cost of capital | C35: =O25 -> 0.09
B36: Terminal value | C36: =C34/(C35-C4) -> 1068.0842
B37: (+) PV Terminal value | C37: =C36*M26 -> 542.95984
B38: Sum of PV | C38: =C37+C33 -> 1382.0096
B39: Probability of failure | C39: 0.01
B40: Proceeds if firm fails | C40: =Model!$AF$178*0.5/1000 -> 498.917
B41: Value of operating assets | C41: =C38*(1-C39)+C40*C39 -> 1373.1787
B42: Net Debt | C42: =C6 -> 152.343
B43: Value of Equity | C43: =C41-C42 -> 1220.8357
B44: (-) value of options | C44: 0
B45: Value of equity in common stock | C45: =C43-C44 -> 1220.8357
B46: No. Shares | C46: =Main!$C$5/1000 -> 62.526632
B47: Implied PPS | C47: =(C45/C46)*C5 -> 18.353548
B48: Up- (down-) side from current | C48: =(C47/Main!C3)-1 -> -0.13630364
B50: Invested Capital at start of valuation | D50: =C28 -> 1098.483
B51: Invested Capital at end of valuation | D51: =M28 -> 1128.7476
B52: Change in invested capital over 10 years | D52: =D51-D50 -> 30.264608
B53: Change in NOPAT over 10 years | D53: =M16-C16 -> 97.055724
B54: Marginal ROIC over 10 years | D54: =D53/D52 -> 3.2069051
B55: ROIC at end of valuation | D55: =#REF! -> #REF!
B56: Average WACC over 10 years (compounded) | D56: 0.08
C58: Base Year | D58: Years 1-5 | E58: Years 6-10 | G58: After Year 10 | H58: Narrative
B59: Revenues | C59: =C12 -> 979.331 | D59: =((H12/D12)^(1/(H10-D10))-1) -> 0.052197688 | E59: =((M12/I12)^(1/(M10-I10))-1) -> 0.038284896 | G59: =C4 -> 0.02
B60: Opearing Margin | C60: =C15 -> 0.070267356 | D60: =AVERAGE(D15:H15) -> 0.10454367 | E60: =AVERAGE(I15:M15) -> 0.12289324 | G60: =O15 -> 0.12
B61: Tax Rate | C61: =$C$7 -> 0.19 | D61: =$C$7 -> 0.19 | E61: =$C$7 -> 0.19 | G61: =$C$7 -> 0.19
D62: Avg. Sales-to-Capital | E62: =AVERAGE(#REF!) -> #REF!
B63: Return on Capital | C63: =#REF! -> #REF! | D63: Marginal ROIC | E63: =D54 -> 3.2069051
B64: Cost of Capital | D64: =AVERAGE(D25:H25) -> 0.075 | E64: =AVERAGE(I25:M25) -> 0.072 | G64: =O25 -> 0.09
C66: Revenues | D66: Operating Margin | E66: EBIT | F66: NOPAT | G66: Reinvestment | H66: FCFF | I66: 1000
B67: 1 | C67: =D12 -> 1050 | D67: =D15 -> 0.082666667 | E67: =(D14/1000)*1000 -> 86.8 | F67: =(D16/1000)*1000 -> 70.308 | G67: =(D21/1000)*1000 -> -31.540178 | H67: =F67-G67 -> 101.84818
B68: 2 | C68: =E12 -> 1119 | D68: =E15 -> 0.10642002 | E68: =(E14/1000)*1000 -> 119.084 | F68: =(E16/1000)*1000 -> 96.45804 | G68: =(E21/1000)*1000 -> -34.243357 | H68: =F68-G68 -> 130.7014
B69: 3 | C69: =F12 -> 1182.5525 | D69: =F15 -> 0.10655781 | E69: =(F14/1000)*1000 -> 126.0102 | F69: =(F16/1000)*1000 -> 102.06826 | G69: =(F21/1000)*1000 -> -36.946535 | H69: =F69-G69 -> 139.0148
B70: 4 | C70: =G12 -> 1239.0536 | D70: =G15 -> 0.11121982 | E70: =(G14/1000)*1000 -> 137.80731 | F70: =(G16/1000)*1000 -> 111.62392 | G70: =(G21/1000)*1000 -> -39.649714 | H70: =F70-G70 -> 151.27364
B71: 5 | C71: =H12 -> 1287.0004 | D71: =H15 -> 0.11585402 | E71: =(H14/1000)*1000 -> 149.10417 | F71: =(H16/1000)*1000 -> 120.77438 | G71: =(H21/1000)*1000 -> -20.100063 | H71: =F71-G71 -> 140.87444
B72: 6 | C72: =I12 -> 1336.273 | D72: =I15 -> 0.11999779 | E72: =(I14/1000)*1000 -> 160.34982 | F72: =(I16/1000)*1000 -> 129.88335 | G72: =(I21/1000)*1000 -> -0.55041142 | H72: =F72-G72 -> 130.43376
B73: 7 | C73: =J12 -> 1387.4321 | D73: =J15 -> 0.12354414 | E73: =(J14/1000)*1000 -> 171.40911 | F73: =(J16/1000)*1000 -> 138.84138 | G73: =(J21/1000)*1000 -> 18.99924 | H73: =F73-G73 -> 119.84214
B74: 8 | C74: =K12 -> 1440.5498 | D74: =K15 -> 0.1258268 | E74: =(K14/1000)*1000 -> 181.25977 | F74: =(K16/1000)*1000 -> 146.82041 | G74: =(K21/1000)*1000 -> 38.548891 | H74: =F74-G74 -> 108.27152
B75: 9 | C75: =L12 -> 1495.7011 | D75: =L15 -> 0.12362851 | E75: =(L14/1000)*1000 -> 184.91131 | F75: =(L16/1000)*1000 -> 149.77816 | G75: =(L21/1000)*1000 -> 58.098542 | H75: =F75-G75 -> 91.679616
B76: 10 | C76: =M12 -> 1552.9639 | D76: =M15 -> 0.12146894 | E76: =(M14/1000)*1000 -> 188.63688 | F76: =(M16/1000)*1000 -> 152.79587 | G76: =(M21/1000)*1000 -> 77.648194 | H76: =F76-G76 -> 75.147681
B77: Teminal Year | C77: =O12 -> 1584.0232 | D77: =O15 -> 0.12 | E77: =(O14/1000)*1000 -> 190.08278 | F77: =(O16/1000)*1000 -> 153.96705 | G77: =(O21/1000)*1000 -> 79.201158 | H77: =F77-G77 -> 74.765893

Sheet DCF MKT
R1: Critique
B2: Assumptions | D2: =C43 -> 19.350265
B3: WACC | C3: 0.08 | Q3: (a) | R3: Proof of lower risk?
B4: Terminal Growth | C4: 0.025 | Q4: (b) | R4: Okay with this, but please verify Boeing and Airbus numbers
B5: Implied Terminal ROIC | C5: =C4/M19 -> 0.092404488 | Q5: (c) | R5: Proof that management can return in excess of COC?
B6: EUR/CHF | C6: 0.94
B7: Net Debt (12/31/2025 | C7: =Main!C11 -> 152343
B8: Swiss Tax rate | C8: 0.174
B9: Terminal EBIT margin | C9: =H16 -> 0.1 | Q9: (d) | R9: Implies Montana lies in top quartile of
C12: 0 | D12: 1 | E12: 2 | F12: 3 | G12: 4 | H12: 5 | I12: 6 | J12: 7 | K12: 8 | L12: 9 | M12: 10
B13: Figures in thousands | C13: 2025(A) | D13: 2026 | E13: =D13+1 -> 2027 | F13: =E13+1 -> 2028 | G13: =F13+1 -> 2029 | H13: =G13+1 -> 2030 | I13: =H13+1 -> 2031 | J13: =I13+1 -> 2032 | K13: =J13+1 -> 2033 | L13: =K13+1 -> 2034 | M13: =L13+1 -> 2035
B14: Revenue growth | C14: =Model!$AF$87 -> 0.15076643 | D14: 0.1 | E14: 0.08 | F14: 0.07 | G14: 0.06 | H14: 0.06 | I14: 0.05 | J14: 0.04 | K14: =Model!AS87 -> 0.038284896 | L14: =Model!AT87 -> 0.038284896 | M14: =Model!AU87 -> 0.038284896 | Q14: (e) | R14: Must validate extended growth run rate
B15: Revenue | C15: =Model!$AF$86 -> 979331 | D15: =C15*(1+D14) -> 1077264.1 | E15: =D15*(1+E14) -> 1163445.2 | F15: =E15*(1+F14) -> 1244886.4 | G15: =F15*(1+G14) -> 1319579.6 | H15: =G15*(1+H14) -> 1398754.4 | I15: =H15*(1+I14) -> 1468692.1 | J15: =I15*(1+J14) -> 1527439.8 | K15: =J15*(1+K14) -> 1585917.6 | ... M15: =L15*(1+M14) -> 1709675.5
B16: EBIT Margin | C16: =Model!$AF$111 -> 0.070267356 | D16: =Model!AL111 -> 0.082666667 | E16: 0.1 | F16: 0.1 | G16: 0.1 | H16: 0.1 | I16: 0.11 | J16: 0.11 | K16: 0.11 | L16: 0.11 | M16: 0.11 | R16: See (d)
B17: EBIT | C17: =Model!AF110 -> 68815 | D17: =D15*D16 -> 89053.832 | E17: =E15*E16 -> 116344.52 | F17: =F15*F16 -> 124488.64 | G17: =G15*G16 -> 131957.96 | H17: =H15*H16 -> 139875.44 | I17: =I15*I16 -> 161556.13 | J17: =J15*J16 -> 168018.37 | K17: =K15*K16 -> 174450.94 | ... M17: =M15*M16 -> 188064.31
B18: NOPAT | C18: =C17*(1-$C$8) -> 56841.19 | D18: =D17*(1-$C$8) -> 73558.465 | E18: =E17*(1-$C$8) -> 96100.576 | F18: =F17*(1-$C$8) -> 102827.62 | G18: =G17*(1-$C$8) -> 108997.27 | H18: =H17*(1-$C$8) -> 115537.11 | I18: =I17*(1-$C$8) -> 133445.36 | J18: =J17*(1-$C$8) -> 138783.18 | ... M18: =M17*(1-$C$8) -> 155341.12
B19: Reinvestment Rate | C19: =C20/C18 -> -0.15574973 | D19: =D20/D18 -> 0 | E19: =E20/E18 -> 0.0030921904 | F19: =F20/F18 -> 0.79201647 | G19: =G20/G18 -> 0.62297792 | H19: =H20/H18 -> 0.57106309 | I19: =I20/I18 -> 0.41927403 | J19: =J20/J18 -> 0.32561962 | ... M19: =M20/M18 -> 0.27054963 | R19: see note (c)
B20: Reinvestment | C20: =-Model!AF357 -> -8853 | D20: 0 | E20: =(E15-D15)/E26 -> 297.16127 | F20: =(F15-E15)/F26 -> 81441.166 | G20: =(G15-F15)/G26 -> 67902.894 | H20: =(H15-G15)/H26 -> 65978.979 | I20: =(I15-H15)/I26 -> 55950.174 | J20: =(J15-I15)/J26 -> 45190.525 | K20: =(K15-J15)/K26 -> 43316.942 | L20: =(L15-K15)/L26 -> 43369.065 | M20: =(M15-L15)/M26 -> 42027.482
B21: FCFF | C21: =C18-C20 -> 65694.19 | D21: =D18-D20 -> 73558.465 | E21: =E18-E20 -> 95803.415 | F21: =F18-F20 -> 21386.45 | G21: =G18-G20 -> 41094.379 | H21: =H18-H20 -> 49558.131 | I21: =I18-I20 -> 77495.187 | J21: =J18-J20 -> 93592.651 | ... M21: =M18-M20 -> 113313.64
B22: Y/Y growth | D22: =D21/C21-1 -> 0.11971036 | E22: =E21/D21-1 -> 0.30241182 | F22: =F21/E21-1 -> -0.77676735 | G22: =G21/F21-1 -> 0.92151472 | H22: =H21/G21-1 -> 0.20595887 | I22: =I21/H21-1 -> 0.56372297 | J22: =J21/I21-1 -> 0.2077221 | K22: =K21/J21-1 -> 0.076788961 | ... M22: =M21/L21-1 -> 0.066540227
B23: Discount factor | D23: =1/((1+$C$3)^D12) -> 0.92592593 | E23: =1/((1+$C$3)^E12) -> 0.85733882 | F23: =1/((1+$C$3)^F12) -> 0.79383224 | G23: =1/((1+$C$3)^G12) -> 0.73502985 | H23: =1/((1+$C$3)^H12) -> 0.6805832 | I23: =1/((1+$C$3)^I12) -> 0.63016963 | J23: =1/((1+$C$3)^J12) -> 0.5834904 | K23: =1/((1+$C$3)^K12) -> 0.54026888 | ... M23: =1/((1+$C$3)^M12) -> 0.46319349
B24: PV FCFF | D24: =D21*D23 -> 68109.69 | E24: =E21*E23 -> 82135.986 | F24: =F21*F23 -> 16977.254 | G24: =G21*G23 -> 30205.595 | H24: =H21*H23 -> 33728.431 | I24: =I21*I23 -> 48835.113 | J24: =J21*J23 -> 54610.413 | K24: =K21*K23 -> 54448.046 | ... M24: =M21*M23 -> 52486.139
E25: =E20/E15 -> 0.00025541492 | F25: =F20/F15 -> 0.065420561 | G25: =G20/G15 -> 0.051457976 | H25: =H20/H15 -> 0.047169811 | I25: =I20/I15 -> 0.038095238 | J25: =J20/J15 -> 0.029585799 | K25: =K20/K15 -> 0.027313488 | L25: =L20/L15 -> 0.026338006 | M25: =M20/M15 -> 0.024582139
B26: Sales-to-capital ratio | D26: N/A | E26: =AVERAGE([2]Model!$V$255,[3]Model!$C$203,[1]Model!$I$244,Model!$AF$350) -> 290.01467 | F26: 1 | G26: 1.1 | H26: 1.2 | I26: 1.25 | J26: 1.3 | K26: 1.35 | L26: 1.4 | M26: 1.5
B27: Invested Capital | C27: =Model!AF341 -> 1098483 | D27: =C27+D20 -> 1098483 | E27: =D27+E20 -> 1098780.2 | F27: =E27+F20 -> 1180221.3 | G27: =F27+G20 -> 1248124.2 | H27: =G27+H20 -> 1314103.2 | I27: =H27+I20 -> 1370053.4 | J27: =I27+J20 -> 1415243.9 | K27: =J27+K20 -> 1458560.8 | ... M27: =L27+M20 -> 1543957.4
B28: ROIC | D28: =D18/D27 -> 0.066963681 | E28: =E18/E27 -> 0.087461149 | F28: =F18/F27 -> 0.087125706 | G28: =G18/G27 -> 0.087328866 | H28: =H18/H27 -> 0.08792088 | I28: =I18/I27 -> 0.097401579 | J28: =J18/J27 -> 0.09806308 | K28: =K18/K27 -> 0.098793599 | ... M28: =M18/M27 -> 0.10061231
B29: Sum PV (FCFF) | C29: =SUM(C24:M24) -> 494685.18
B30: Terminal cash flow | C30: =M21 -> 113313.64
B31: Terminal cost of capital | C31: =C3 -> 0.08 | D31: =C43 -> 19.350265 | E31: 0.075 | F31: 0.085 | G31: 0.09 | H31: 0.095
B32: Terminal value | C32: =C30/(C31-C4) -> 2060247.9 | D32: 0.015 | E32: 18.973772 | F32: 15.621365 | G32: 14.289116 | H32: 13.12856
B33: (+) PV Terminal value | C33: =C32*M23 -> 954293.43 | D33: 0.025 | E33: 21.701332 | F33: 17.397326 | G33: 15.75042 | H33: 14.343769
B34: Sum of PV | C34: =C33+C29 -> 1448978.6 | D34: 0.035 | E34: 25.792672 | F34: 19.883672 | G34: 17.743107 | H34: 15.964048
B35: Probability of failure | C35: 0.01 | D35: 0.045 | E35: 32.611572 | F35: 23.613191 | G35: 20.621433 | H35: 18.232438
B36: Proceeds if firm fails | C36: =Model!$AF$178*0.5 -> 498917 | D36: 0.055 | E36: 46.249371 | F36: 29.829056 | G36: 25.144517 | H36: 21.635023
B37: Value of operating assets | C37: =C34*(1-C35)+C36*C35 -> 1439478 | D37: 0.065 | E37: 87.16277 | F37: 42.260786 | G37: 33.286068 | H37: 27.305998
B38: Net Debt | C38: =Main!$C$11 -> 152343 | D38: 0.075 | E38: #DIV/0! | F38: 79.555975 | G38: 52.283021 | H38: 38.647949
B39: Value of Equity | C39: =C37-C38 -> 1287135
B40: (-) value of options | C40: 0
B41: Value of equity in common stock | C41: =C39-C40 -> 1287135
B42: No. Shares | C42: =Main!$C$5 -> 62526.632
B43: Implied PPS | C43: =(C41/C42)*C6 -> 19.350265
C44: =C43/Main!C3-1 -> -0.089399293

Sheet DCF 3-bear
R1: Critique
B2: Assumptions | D2: =C43 -> 17.718381
B3: WACC | C3: 0.095 | Q3: (a) | R3: Proof of lower risk?
B4: Terminal Growth | C4: 0.025 | D4: Think of this as fleet growth. DCO Growth rate: 5% CAGR in the last decade | Q4: (b) | R4: Okay with this, but please verify Boeing and Airbus numbers
B5: Implied Terminal ROIC | C5: =M14/M19 -> 0.16723655 | Q5: (c) | R5: Proof that management can return in excess of COC?
B6: EUR/CHF | C6: 0.94
B7: Net Debt (12/31/2025 | C7: =Main!C11 -> 152343
B8: Swiss Tax rate | C8: 0.174
B9: Terminal EBIT margin | C9: =H16 -> 0.12 | Q9: (d) | R9: Implies Montana lies in top quartile of
C12: 0 | D12: 1 | E12: 2 | F12: 3 | G12: 4 | H12: 5 | I12: 6 | J12: 7 | K12: 8 | L12: 9 | M12: 10
B13: Figures in thousands | C13: 2025(A) | D13: 2026 | E13: =D13+1 -> 2027 | F13: =E13+1 -> 2028 | G13: =F13+1 -> 2029 | H13: =G13+1 -> 2030 | I13: =H13+1 -> 2031 | J13: =I13+1 -> 2032 | K13: =J13+1 -> 2033 | L13: =K13+1 -> 2034 | M13: =L13+1 -> 2035
B14: Revenue growth | C14: =Model!$AF$87 -> 0.15076643 | D14: 0.08 | E14: 0.08 | F14: 0.07 | G14: 0.06 | H14: 0.06 | I14: 0.05 | J14: 0.04 | K14: =Model!AS87 -> 0.038284896 | L14: =Model!AT87 -> 0.038284896 | M14: =Model!AU87 -> 0.038284896 | Q14: (e) | R14: Must validate extended growth run rate
B15: Revenue | C15: =Model!$AF$86 -> 979331 | D15: =C15*(1+D14) -> 1057677.5 | E15: =D15*(1+E14) -> 1142291.7 | F15: =E15*(1+F14) -> 1222252.1 | G15: =F15*(1+G14) -> 1295587.2 | H15: =G15*(1+H14) -> 1373322.5 | I15: =H15*(1+I14) -> 1441988.6 | J15: =I15*(1+J14) -> 1499668.1 | K15: =J15*(1+K14) -> 1557082.8 | ... M15: =L15*(1+M14) -> 1678590.5
B16: EBIT Margin | C16: =Model!$AF$111 -> 0.070267356 | D16: =Model!AL111 -> 0.082666667 | E16: 0.1 | F16: 0.12 | G16: 0.12 | H16: 0.12 | I16: 0.12 | J16: 0.12 | K16: 0.12 | L16: 0.13 | M16: 0.13 | R16: See (d)
B17: EBIT | C17: =Model!AF110 -> 68815 | D17: =D15*D16 -> 87434.672 | E17: =E15*E16 -> 114229.17 | F17: =F15*F16 -> 146670.25 | G17: =G15*G16 -> 155470.47 | H17: =H15*H16 -> 164798.69 | I17: =I15*I16 -> 173038.63 | J17: =J15*J16 -> 179960.17 | K17: =K15*K16 -> 186849.93 | ... M17: =M15*M16 -> 218216.77
B18: NOPAT | C18: =C17*(1-$C$8) -> 56841.19 | D18: =D17*(1-$C$8) -> 72221.039 | E18: =E17*(1-$C$8) -> 94353.293 | F18: =F17*(1-$C$8) -> 121149.63 | G18: =G17*(1-$C$8) -> 128418.61 | H18: =H17*(1-$C$8) -> 136123.72 | I18: =I17*(1-$C$8) -> 142929.91 | J18: =J17*(1-$C$8) -> 148647.1 | ... M18: =M17*(1-$C$8) -> 180247.05
B19: Reinvestment Rate | C19: =C20/C18 -> -0.15574973 | D19: =D20/D18 -> 0.0037405529 | E19: =E20/E18 -> 0.0030921904 | F19: =F20/F18 -> 0.66001373 | G19: =G20/G18 -> 0.51914826 | H19: =H20/H18 -> 0.47588591 | I19: =I20/I18 -> 0.38433452 | J19: =J20/J18 -> 0.29848465 | ... M19: =M20/M18 -> 0.22892661 | R19: see note (c)
B20: Reinvestment | C20: =-Model!AF357 -> -8853 | D20: =(D15-C15)/D26 -> 270.14661 | E20: =(E15-D15)/E26 -> 291.75834 | F20: =(F15-E15)/F26 -> 79960.417 | G20: =(G15-F15)/G26 -> 66668.296 | H20: =(H15-G15)/H26 -> 64779.361 | I20: =(I15-H15)/I26 -> 54932.898 | J20: =(J15-I15)/J26 -> 44368.879 | K20: =(K15-J15)/K26 -> 42529.361 | ... M20: =(M15-L15)/M26 -> 41263.346
B21: FCFF | C21: =C18-C20 -> 65694.19 | D21: =D18-D20 -> 71950.892 | E21: =E18-E20 -> 94061.534 | F21: =F18-F20 -> 41189.21 | G21: =G18-G20 -> 61750.309 | H21: =H18-H20 -> 71344.361 | I21: =I18-I20 -> 87997.01 | J21: =J18-J20 -> 104278.22 | ... M21: =M18-M20 -> 138983.7
B22: Y/Y growth | D22: =D21/C21-1 -> 0.09523981 | E22: =E21/D21-1 -> 0.30730185 | F22: =F21/E21-1 -> -0.56210357 | G22: =G21/F21-1 -> 0.49918653 | H22: =H21/G21-1 -> 0.15536847 | I22: =I21/H21-1 -> 0.23341227 | J22: =J21/I21-1 -> 0.1850201 | K22: =K21/J21-1 -> 0.072215045 | ... M22: =M21/L21-1 -> 0.060780521
B23: Discount factor | D23: =1/((1+$C$3)^D12) -> 0.91324201 | E23: =1/((1+$C$3)^E12) -> 0.83401097 | F23: =1/((1+$C$3)^F12) -> 0.76165385 | G23: =1/((1+$C$3)^G12) -> 0.69557429 | H23: =1/((1+$C$3)^H12) -> 0.63522767 | I23: =1/((1+$C$3)^I12) -> 0.58011659 | J23: =1/((1+$C$3)^J12) -> 0.52978684 | K23: =1/((1+$C$3)^K12) -> 0.4838236 | ... M23: =1/((1+$C$3)^M12) -> 0.40351419
B24: PV FCFF | D24: =D21*D23 -> 65708.577 | E24: =E21*E23 -> 78448.351 | F24: =F21*F23 -> 31371.921 | G24: =G21*G23 -> 42951.928 | H24: =H21*H23 -> 45319.912 | I24: =I21*I23 -> 51048.525 | J24: =J21*J23 -> 55245.231 | K24: =K21*K23 -> 54095.679 | ... M24: =M21*M23 -> 56081.897
E25: =E20/E15 -> 0.00025541492 | F25: =F20/F15 -> 0.065420561 | G25: =G20/G15 -> 0.051457976 | H25: =H20/H15 -> 0.047169811 | I25: =I20/I15 -> 0.038095238 | J25: =J20/J15 -> 0.029585799 | K25: =K20/K15 -> 0.027313488 | L25: =L20/L15 -> 0.026338006 | M25: =M20/M15 -> 0.024582139
B26: Sales-to-capital ratio | D26: =AVERAGE([2]Model!$V$255,[3]Model!$C$203,[1]Model!$I$244,Model!$AF$350) -> 290.01467 | E26: =AVERAGE([2]Model!$V$255,[3]Model!$C$203,[1]Model!$I$244,Model!$AF$350) -> 290.01467 | F26: 1 | G26: 1.1 | H26: 1.2 | I26: 1.25 | J26: 1.3 | K26: 1.35 | L26: 1.4 | M26: 1.5
B27: Invested Capital | C27: =Model!AF341 -> 1098483 | D27: =C27+D20 -> 1098753.1 | E27: =D27+E20 -> 1099044.9 | F27: =E27+F20 -> 1179005.3 | G27: =F27+G20 -> 1245673.6 | H27: =G27+H20 -> 1310453 | I27: =H27+I20 -> 1365385.9 | J27: =I27+J20 -> 1409754.8 | K27: =J27+K20 -> 1452284.1 | ... M27: =L27+M20 -> 1536128
B28: ROIC | D28: =D18/D27 -> 0.065729995 | E28: =E18/E27 -> 0.085850262 | F28: =F18/F27 -> 0.10275579 | G28: =G18/G27 -> 0.1030917 | H28: =H18/H27 -> 0.10387532 | I28: =I18/I27 -> 0.10468096 | J28: =J18/J27 -> 0.10544182 | K28: =K18/K27 -> 0.10627262 | ... M28: =M18/M27 -> 0.11733856
B29: Sum PV (FCFF) | C29: =SUM(C24:M24) -> 538163.05
B30: Terminal cash flow | C30: =M21 -> 138983.7
B31: Terminal cost of capital | C31: =C3 -> 0.095 | D31: =C43 -> 17.718381 | E31: 0.075 | F31: 0.085 | G31: 0.09 | H31: 0.095
B32: Terminal value | C32: =C30/(C31-C4) -> 1985481.5 | D32: 0.015 | E32: 23.378776 | F32: 19.276516 | G32: 17.646987 | H32: 16.227879
B33: (+) PV Terminal value | C33: =C32*M23 -> 801169.95 | D33: 0.025 | E33: 26.724237 | F33: 21.454803 | G33: 19.439335 | H33: 17.718381
B34: Sum of PV | C34: =C33+C29 -> 1339333 | D34: 0.035 | E34: 31.742429 | F34: 24.504406 | G34: 21.883446 | H34: 19.705718
B35: Probability of failure | C35: 0.01 | D35: 0.045 | E35: 40.106082 | F35: 29.07881 | G35: 25.413828 | H35: 22.487989
B36: Proceeds if firm fails | C36: =Model!$AF$178*0.5 -> 498917 | D36: 0.055 | E36: 56.833388 | F36: 36.702817 | G36: 30.961571 | H36: 26.661395
B37: Value of operating assets | C37: =C34*(1-C35)+C36*C35 -> 1330928.8 | D37: 0.065 | E37: 107.01531 | F37: 51.95083 | G37: 40.947509 | H37: 33.617073
B38: Net Debt | C38: =Main!$C$11 -> 152343 | D38: 0.075 | E38: #DIV/0! | F38: 97.69487 | G38: 64.248031 | H38: 47.528429
B39: Value of Equity | C39: =C37-C38 -> 1178585.8
B40: (-) value of options | C40: 0
B41: Value of equity in common stock | C41: =C39-C40 -> 1178585.8
B42: No. Shares | C42: =Main!$C$5 -> 62526.632
B43: Implied PPS | C43: =(C41/C42)*C6 -> 17.718381
C44: =C43/Main!C3-1 -> -0.16619383

Sheet DCF- Bull
S1: Critique
B2: Assumptions | D2: =C45 -> 41.514878
B3: WACC | C3: =AVERAGE(D23:O23) -> 0.07 | R3: (a) | S3: Proof of lower risk?
B4: Terminal Growth | C4: 0.03 | R4: (b) | S4: Okay with this, but please verify Boeing and Airbus numbers
B5: Implied Terminal ROIC | C5: =C4/O19 -> 39.478188 | R5: (c) | S5: Proof that management can return in excess of COC?
B6: EUR/CHF | C6: 0.94
B7: Net Debt (12/31/2025 | C7: =Main!C11 -> 152343
B8: Swiss Tax rate | C8: 0.174
B9: Terminal EBIT margin | C9: 0.13 | R9: (d) | S9: Implies Montana lies in top quartile of
C11: Base Year:
C12: 0 | D12: 1 | E12: 2 | F12: 3 | G12: 4 | H12: 5 | I12: 6 | J12: 7 | K12: 8 | L12: 9 | M12: 10
B13: Figures in thousands | C13: 2025(A) | D13: 2026 | E13: =D13+1 -> 2027 | F13: =E13+1 -> 2028 | G13: =F13+1 -> 2029 | H13: =G13+1 -> 2030 | I13: =H13+1 -> 2031 | J13: =I13+1 -> 2032 | K13: =J13+1 -> 2033 | L13: =K13+1 -> 2034 | M13: =L13+1 -> 2035 | O13: Terminal
B14: Revenue growth | C14: =Model!$AF$87 -> 0.15076643 | D14: 0.1 | E14: 0.09 | F14: 0.08 | G14: 0.07 | H14: 0.06 | I14: 0.05 | J14: 0.05 | K14: 0.04 | L14: 0.04 | M14: 0.04 | O14: =C4 -> 0.03 | R14: (e) | S14: Must validate extended growth run rate
B15: Revenue | C15: =Model!$AF$86 -> 979331 | D15: =C15*(1+D14) -> 1077264.1 | E15: =D15*(1+E14) -> 1174217.9 | F15: =E15*(1+F14) -> 1268155.3 | G15: =F15*(1+G14) -> 1356926.2 | H15: =G15*(1+H14) -> 1438341.7 | I15: =H15*(1+I14) -> 1510258.8 | J15: =I15*(1+J14) -> 1585771.8 | K15: =J15*(1+K14) -> 1649202.6 | ... M15: =L15*(1+M14) -> 1783777.6 | O15: =M15*(1+O14) -> 1837290.9
B16: EBIT Margin | C16: =Model!$AF$111 -> 0.070267356 | D16: =Model!AL111 -> 0.082666667 | E16: =Model!AM111 -> 0.10642002 | F16: =Model!AN111 -> 0.10655781 | G16: =Model!AO111 -> 0.11121982 | H16: 0.14 | I16: 0.15 | J16: 0.16 | K16: 0.16 | L16: 0.16 | M16: 0.16 | O16: 0.16 | S16: See (d)
B17: EBIT | C17: =Model!AF110 -> 68815 | D17: =D15*D16 -> 89053.832 | E17: =E15*E16 -> 124960.29 | F17: =F15*F16 -> 135131.85 | G17: =G15*G16 -> 150917.08 | H17: =H15*H16 -> 201367.84 | I17: =I15*I16 -> 226538.82 | J17: =J15*J16 -> 253723.48 | K17: =K15*K16 -> 263872.42 | ... M17: =M15*M16 -> 285404.41 | O17: =O15*O16 -> 293966.54
B18: NOPAT | C18: =C17*(1-$C$8) -> 56841.19 | D18: =D17*(1-$C$8) -> 73558.465 | E18: =E17*(1-$C$8) -> 103217.2 | F18: =F17*(1-$C$8) -> 111618.91 | G18: =G17*(1-$C$8) -> 124657.51 | H18: =H17*(1-$C$8) -> 166329.84 | I18: =I17*(1-$C$8) -> 187121.07 | J18: =J17*(1-$C$8) -> 209575.6 | ... M18: =M17*(1-$C$8) -> 235744.04 | O18: =O17*(1-$C$8) -> 242816.37
B19: Reinvestment Rate | C19: =C20/C18 -> -0.15574973 | D19: =D20/D18 -> 1.4959147 | E19: =E20/E18 -> 0 | F19: =F20/F18 -> 0.084159066 | G19: =G20/G18 -> 0.089014763 | H19: =H20/H18 -> 0.09789653 | I19: =I20/I18 -> 0.12811151 | J19: =J20/J18 -> 0.072062723 | ... M19: =M20/M18 -> 0.30633951 | O19: =O20/O18 -> 0.00075991329 | S19: see note (c)
B20: Reinvestment | C20: =-Model!AF357 -> -8853 | D20: =(D15-C15)/D27 -> 110037.19 | E20: 0 | F20: =(F15-E15)/F27 -> 9393.743 | G20: =(G15-F15)/G27 -> 11096.359 | H20: =(H15-G15)/H27 -> 16283.114 | I20: =(I15-H15)/I27 -> 23972.362 | J20: =(J15-I15)/J27 -> 15102.588 | K20: =(K15-J15)/K27 -> 21143.624 | L20: =(L15-K15)/L27 -> 43978.737 | M20: =(M15-L15)/M27 -> 72217.716 | O20: =(O15-M15)/O27 -> 184.51938
B21: FCFF | C21: =C18-C20 -> 65694.19 | D21: =D18-D20 -> -36478.726 | E21: =E18-E20 -> 103217.2 | F21: =F18-F20 -> 102225.16 | G21: =G18-G20 -> 113561.15 | H21: =H18-H20 -> 150046.72 | I21: =I18-I20 -> 163148.71 | J21: =J18-J20 -> 194473.01 | ... M21: =M18-M20 -> 163526.33 | O21: =O18-O20 -> 242631.85
B22: Y/Y growth | D22: =D21/C21-1 -> -1.5552808 | E22: =E21/D21-1 -> -3.8295176 | F22: =F21/E21-1 -> -0.0096111149 | G22: =G21/F21-1 -> 0.11089235 | H22: =H21/G21-1 -> 0.32128567 | I22: =I21/H21-1 -> 0.087319344 | J22: =J21/I21-1 -> 0.19199847 | K22: =K21/J21-1 -> 0.012042744 | ... M22: =M21/L21-1 -> -0.10493752 | O22: =O21/M21-1 -> 0.4837479
B23: Cost of Capital | D23: 0.07 | E23: =D23 -> 0.07 | F23: =E23 -> 0.07 | G23: =F23 -> 0.07 | H23: =G23 -> 0.07 | I23: =H23-($H$23-$M$23)/5 -> 0.07 | J23: =I23-($H$23-$M$23)/5 -> 0.07 | K23: =J23-($H$23-$M$23)/5 -> 0.07 | L23: =K23-($H$23-$M$23)/5 -> 0.07 | M23: 0.07 | O23: =M23 -> 0.07
B24: Discount factor | D24: =1/((1+D23)^D12) -> 0.93457944 | E24: =1/((1+E23)^E12) -> 0.87343873 | F24: =1/((1+F23)^F12) -> 0.81629788 | G24: =1/((1+G23)^G12) -> 0.76289521 | H24: =1/((1+H23)^H12) -> 0.71298618 | I24: =1/((1+I23)^I12) -> 0.66634222 | J24: =1/((1+J23)^J12) -> 0.62274974 | K24: =1/((1+K23)^K12) -> 0.5820091 | ... M24: =1/((1+M23)^M12) -> 0.50834929 | O24: =1/((1+O23)^O12) -> 1
B25: PV FCFF | D25: =D21*D24 -> -34092.267 | E25: =E21*E24 -> 90153.897 | F25: =F21*F24 -> 83446.185 | G25: =G21*G24 -> 86635.26 | H25: =H21*H24 -> 106981.24 | I25: =I21*I24 -> 108712.87 | J25: =J21*J24 -> 121108.02 | K25: =K21*K24 -> 114548.12 | ... M25: =M21*M24 -> 83128.493 | O25: =O21*O24 -> 242631.85
E26: =E20/E15 -> 0 | F26: =F20/F15 -> 0.0074074074 | G26: =G20/G15 -> 0.0081775701 | H26: =H20/H15 -> 0.011320755 | I26: =I20/I15 -> 0.015873016 | J26: =J20/J15 -> 0.0095238095 | K26: =K20/K15 -> 0.012820513 | L26: =L20/L15 -> 0.025641026 | M26: =M20/M15 -> 0.04048583
B27: Sales-to-capital ratio | C27: =C15/C28 -> 0.89153041 | D27: 0.89 | E27: N/A | F27: 10 | G27: 8 | H27: 5 | I27: 3 | J27: 5 | K27: 3 | L27: 1.5 | M27: 0.95 | O27: =AVERAGE([2]Model!$V$255,[3]Model!$C$203,[1]Model!$I$244,Model!$AF$350) -> 290.01467
B28: Invested Capital | C28: =Model!AF341 -> 1098483 | D28: =C28+D20 -> 1208520.2 | E28: =D28+E20 -> 1208520.2 | F28: =E28+F20 -> 1217913.9 | G28: =F28+G20 -> 1229010.3 | H28: =G28+H20 -> 1245293.4 | I28: =H28+I20 -> 1269265.8 | J28: =I28+J20 -> 1284368.4 | K28: =J28+K20 -> 1305512 | ... M28: =L28+M20 -> 1421708.4 | O28: =M28+O20 -> 1421893 | P28: =M28-C28 -> 323225.43
B29: ROIC | C29: =C18/C28 -> 0.05174517 | D29: =D18/D28 -> 0.060866559 | E29: =E18/E28 -> 0.085407921 | F29: =F18/F28 -> 0.091647615 | G29: =G18/G28 -> 0.10142918 | H29: =H18/H28 -> 0.13356679 | I29: =I18/I28 -> 0.14742466 | J29: =J18/J28 -> 0.16317406 | ... M29: =M18/M28 -> 0.16581743 | O29: =O18/O28 -> 0.17076979
B31: Sum PV (FCFF) | C31: =SUM(C25:M25) -> 859997.55
B32: Terminal cash flow | C32: =M21 -> 163526.33
B33: Terminal cost of capital | C33: =O23 -> 0.07
B34: Terminal value | C34: =C32/(C33-C4) -> 4088158.2
B35: (+) PV Terminal value | C35: =C34*M24 -> 2078212.3
B36: Sum of PV | C36: =C35+C31 -> 2938209.9
B37: Probability of failure | C37: 0.01
B38: Proceeds if firm fails | C38: =Model!$AF$178*0.5 -> 498917
B39: Value of operating assets | C39: =C36*(1-C37)+C38*C37 -> 2913817
B40: Net Debt | C40: =Main!$C$11 -> 152343
B41: Value of Equity | C41: =C39-C40 -> 2761474
B42: (-) value of options | C42: 0
B43: Value of equity in common stock | C43: =C41-C42 -> 2761474
B44: No. Shares | C44: =Main!$C$5 -> 62526.632
B45: Implied PPS | C45: =(C43/C44)*C6 -> 41.514878
B46: Up- (down-) side from current | C46: =C45/Main!C3-1 -> 0.95364133
B48: Invested Capital at start of valuation | D48: =C28 -> 1098483
B49: Invested Capital at end of valuation | D49: =M28 -> 1421708.4
B50: Change in invested capital over 10 years | D50: =D49-D48 -> 323225.43
B51: Change in NOPAT over 10 years | D51: =M18-C18 -> 178902.85
B52: Marginal ROIC over 10 years | D52: =D51/D50 -> 0.5534925
B53: ROIC at end of valuation | D53: =M29 -> 0.16581743
B54: Average WACC over 10 years (compounded) | D54: 0.08
C56: Base Year | D56: Years 1-5 | E56: Years 6-10 | G56: After Year 10 | H56: Narrative
B57: Revenues | C57: =C15/1000 -> 979.331 | D57: =((H15/D15)^(1/(H12-D12))-1) -> 0.074941857 | E57: =((M15/I15)^(1/(M12-I12))-1) -> 0.042491036 | G57: =C4 -> 0.03
B58: Opearing Margin | C58: =C16 -> 0.070267356 | D58: =AVERAGE(D16:H16) -> 0.10937286 | E58: =AVERAGE(I16:M16) -> 0.158 | G58: =O16 -> 0.16
B59: Tax Rate | C59: =$C$8 -> 0.174 | D59: =$C$8 -> 0.174 | E59: =$C$8 -> 0.174 | G59: =$C$8 -> 0.174
D60: Avg. Sales-to-Capital | E60: =AVERAGE(D27:M27) -> 4.1488889
B61: Return on Capital | C61: =C29 -> 0.05174517 | D61: Marginal ROIC | E61: =D52 -> 0.5534925
B62: Cost of Capital | D62: =AVERAGE(D23:H23) -> 0.07 | E62: =AVERAGE(I23:M23) -> 0.07 | G62: =O23 -> 0.07
C64: Revenues | D64: Operating Margin | E64: EBIT | F64: NOPAT | G64: Reinvestment | H64: FCFF
B65: 1 | C65: =D15/1000 -> 1077.2641 | D65: =D16 -> 0.082666667 | E65: =D17/1000 -> 89.053832 | F65: =D18/1000 -> 73.558465 | G65: =D20/1000 -> 110.03719 | H65: =F65-G65 -> -36.478726
B66: 2 | C66: =E15/1000 -> 1174.2179 | D66: =E16 -> 0.10642002 | E66: =E17/1000 -> 124.96029 | F66: =E18/1000 -> 103.2172 | G66: =E20/1000 -> 0 | H66: =F66-G66 -> 103.2172
B67: 3 | C67: =F15/1000 -> 1268.1553 | D67: =F16 -> 0.10655781 | E67: =F17/1000 -> 135.13185 | F67: =F18/1000 -> 111.61891 | G67: =F20/1000 -> 9.393743 | H67: =F67-G67 -> 102.22516
B68: 4 | C68: =G15/1000 -> 1356.9262 | D68: =G16 -> 0.11121982 | E68: =G17/1000 -> 150.91708 | F68: =G18/1000 -> 124.65751 | G68: =G20/1000 -> 11.096359 | H68: =F68-G68 -> 113.56115
B69: 5 | C69: =H15/1000 -> 1438.3417 | D69: =H16 -> 0.14 | E69: =H17/1000 -> 201.36784 | F69: =H18/1000 -> 166.32984 | G69: =H20/1000 -> 16.283114 | H69: =F69-G69 -> 150.04672
B70: 6 | C70: =I15/1000 -> 1510.2588 | D70: =I16 -> 0.15 | E70: =I17/1000 -> 226.53882 | F70: =I18/1000 -> 187.12107 | G70: =I20/1000 -> 23.972362 | H70: =F70-G70 -> 163.14871
B71: 7 | C71: =J15/1000 -> 1585.7718 | D71: =J16 -> 0.16 | E71: =J17/1000 -> 253.72348 | F71: =J18/1000 -> 209.5756 | G71: =J20/1000 -> 15.102588 | H71: =F71-G71 -> 194.47301
B72: 8 | C72: =K15/1000 -> 1649.2026 | D72: =K16 -> 0.16 | E72: =K17/1000 -> 263.87242 | F72: =K18/1000 -> 217.95862 | G72: =K20/1000 -> 21.143624 | H72: =F72-G72 -> 196.815
B73: 9 | C73: =L15/1000 -> 1715.1707 | D73: =L16 -> 0.16 | E73: =L17/1000 -> 274.42732 | F73: =L18/1000 -> 226.67697 | G73: =L20/1000 -> 43.978737 | H73: =F73-G73 -> 182.69823
B74: 10 | C74: =M15/1000 -> 1783.7776 | D74: =M16 -> 0.16 | E74: =M18/1000 -> 235.74404 | F74: =M18/1000 -> 235.74404 | G74: =M20/1000 -> 72.217716 | H74: =F74-G74 -> 163.52633
B75: Teminal Year | C75: =O15/1000 -> 1837.2909 | D75: =O16 -> 0.16 | E75: =O18/1000 -> 242.81637 | F75: =O18/1000 -> 242.81637 | G75: =O20/1000 -> 0.18451938 | H75: =F75-G75 -> 242.63185

Sheet SOTP
B2: In EUR thousands | C2: EBITDA margin | E2: EBITDA | F2: Multiple | G2: EV | H2: Value per share
C3: FY 2025A | D3: FY 2027E | E3: FY 2027E | H3: € | I3: CHF
B4: Aerostructures | C4: =Model!AF15 -> 0.18134129 | D4: =Model!AM15 -> 0.2 | E4: =Model!AM14 -> 203300 | F4: 10 | G4: =E4*F4 -> 2033000 | H4: =G4/$C$11 -> 32.514145 | I4: =H4*$C$10 -> 30.563297
B5: Alpine Metal Tech | C5: =Model!AF36 -> 0.093188539 | D5: =Model!AM36 -> 0.1 | E5: =Model!AM35 -> 10250 | F5: 9.25 | G5: =E5*F5 -> 94812.5 | H5: =G5/$C$11 -> 1.5163539 | I5: =H5*$C$10 -> 1.4253726
E6: =+E4+E5 -> 213550 | G6: =G4+G5 -> 2127812.5 | H6: =+H4+H5 -> 34.030499 | I6: =+I4+I5 -> 31.988669
B7: (-) 2027 net debt | G7: 0 | H7: =G7/$C$11 -> 0 | I7: =H7*$C$10 -> 0
B8: Intrinsic Equity Vlaue | G8: =+G6+G7 -> 2127812.5 | H8: =H6+H7 -> 34.030499 | I8: =I6+I7 -> 31.988669
I9: =I8/Main!C3-1 -> 0.50534914
B10: EUR/CHF | C10: 0.94
B11: Shares outstanding | C11: =Model!$AF$137 -> 62526.632
C13: Market Cap | E13: TEV/EBITDA
E14: 25A | F14: 26E | G14: 27E
B15: #VALUE! | C15: {=_FV(B15,"Market cap",TRUE)/1000} -> 2489117.4 | E15: 20 | F15: 15.1 | G15: 14
B16: #VALUE! | C16: {=_FV(B16,"Market cap",TRUE)/1000} -> 523837.6 | E16: =[1]Main!$D$13 -> 10.945962 | F16: 13.36 | G16: 12
B17: #VALUE! | C17: {=_FV(B17,"Market cap",TRUE)/1000} -> 509652.5 | E17: =[2]Main!$C$18 -> 11.602665 | F17: 10.55 | G17: 9.5
B18: #VALUE! | C18: {=_FV(B18,"Market cap",TRUE)/1000} -> 962564.5 | E18: =[5]Main!$D$13 -> 13.91578 | F18: 14 | G18: 12.5
B19: Median | C19: =MEDIAN(C15,C16,C17,C18) -> 743201.05 | E19: =MEDIAN(E15,E16,E17,E18) -> 12.759222 | F19: =MEDIAN(F15,F16,F17,F18) -> 13.68 | G19: =MEDIAN(G15,G16,G17,G18) -> 12.25
B20: #VALUE! | C20: =Main!C4 -> 1328690.9 | E20: =Main!C14 -> 9.8862371
B22: Not Included in the Median calculation:
B23: #VALUE! | C23: 7276082.9 | E23: 27.897973 | F23: 19 | G23: 17.5
B24: #VALUE! | C24: {=_FV(B24,"Market cap",TRUE)/1000} -> 8118258 | E24: 12.4 | F24: 11 | G24: 9

Sheet WACC 
C3: Carrying Amount | D3: % of capitalization | E3: Maturity | F3: Effective interest rate
B4: Cash & Equivalents | C4: =Model!$AF$169 -> 112759
B5: Loan I | C5: 98233 | E5: 2030 | F5: 0.0447 | G5: =C5*F5 -> 4391.0151
B6: Loan II | C6: 90069 | E6: 2030 | F6: 0.0438 | G6: =C6*F6 -> 3945.0222
B7: Loan III | C7: 417 | E7: 2026 | F7: n/a
B8: Loans and borrwoings | C8: =+C5+C6+C7 -> 188719
B9: Lease liabilities | C9: =31134+5760 -> 36894 | F9: 0.054 | G9: =C9*F9 -> 1992.276
B10: Other | C10: =14318+949 -> 15267
B11: Total Debt | C11: =+C8+C9+C10 -> 240880 | D11: =C11/$C$14 -> 0.56125373 | G11: =G5+G6+G9 -> 10328.313
B13: Shareholders' Equity | C13: =Model!$AF$179 -> 188302 | D13: =C13/$C$14 -> 0.43874627
B14: Total Capitalization | C14: =C11+C13 -> 429182 | D14: =+D11+D13 -> 1
B15: Net Debt | C15: =C11-C4 -> 128121
B17: Equity Risk Premium (rm-rf) | C17: 0.0423 | D17: Source: Damodoran ERP dataset as of 1/6/2026
B18: Rf | C18: 0.0299 | D18: Source: 10 year German Bund as of 5/7/2026. All cash flows are denomenated in Euros
B19: Unlevered Beta | C19: 0.87
B20: Relevered Beta
B21: Target debt/equity | C21: =(C11/C14)/(C13/C14) -> 1.2792217
B22: Target marginal tax rate | C22: 0.19
B23: Relevered Beta | C23: =C19*((1+C21)*(1-C22)) -> 1.6061675
B24: Size premium | C24: 0.01
B25: Cost of Equity (Ke) | C25: =C18+(C23*C17)+C24 -> 0.10784089
B27: Cost of debt | C27: =G11/C8 -> 0.054728529
B28: After-tax cost of debt (Kd) | C28: =C27*(1-C22) -> 0.044330109
B30: WACC | C30: =(C28*D11)+(C25*D13) -> 0.072195225

Sheet Analysts
B3: Analyst(s) | C3: Bank/Institution | D3: Email | E3: Recommendation | F3: Worth reaching out to
B4: George McWhirter | C4: Berenberg | D4: george.mcwhirter@berenberg.com | E4: BUY
B5: Josh Sullivan | C5: Jones Trading | D5: jsullivan@jonestrading.com | E5: BUY | F5: YES
B6: Aymeric Poulain | C6: Kepler Cheuvreux | D6: apoulain@keplercheuvreux.com | E6: Hold | F6: YES
B7: Olfa Taamallah | C7: Oddo BHF | D7: Olfa.taamallah@oddo-bhf.com | E7: BUY | G7: Tunisia
B8: Christian Bader | C8: Zürcher Kantonalbank | D8: christian.bader@zkb.ch | E8: BUY

Sheet Fixed assets and subs
B1: Wholly Owned | C1: p.176 of 208 in 2024 annual
B2: Company | C2: Countries | D2: Acquisition Price | E2: Multiple | F2: Description
B3: Alpine Metal Tech | C3: CN|BR|DK|DE|AT|US|UK | F3: Special purpose machinery for steel, auto, aerospace, "lifecycle business." Product line incl. NUMTEC (aluminum wheel industry deburring); GEGA (autogenous touch cutting and scarfing) KNORR (optoelectronic measuring & image processingsystems - rails); MAKRA (clamping devices & testing aluminium wheels. AMAKON (conveyors); MAGNEMAG (paints and inkjets for plate pipe and long products); SIMULATION (fire training); INTERMATO (vertical lathes - machines for machining workpieces with diameters from 100mm to 6m).
B4: Asco Aerospace | C4: CA|US|DE|BE | F4: April 2022 Acquisition. Manufacture high-lift mechanisms and critical structure sub-assemblies. Portfolio: large complex fuselage, wing and landing gear components. Partnership with Lockheed Martin (F-35)
B5: ASTA Group | C5: BA|US|CN|AT|IN
B6: GeGa GmbH
B7: Immobiliere Asco NV
B8: IMT Intermato SRL
B9: Industrie Captial Alpha GmbH
B10: Insulated Conductors and Enameled Wires NV | C10: NL
B11: MAKRA GmbH
B12: MTC Aerosystems | C12: HU| US
B13: PPE Fios Esmaitados S.A
B14: S.R.I.F. NV | C14: BE
B15: Simulation live Fire Training Solution Inc. | C15: US (Pittsburgh)
B16: Universal Alloy Corp | C16: SG|RO|VN|US (Georgia) | F16: <= gloabal manufacturer of structural components and assemblies; 4,300 headcount. Acquired by Montana Tech components
B19: Subsidiary
B20: Cefival S.A. (90% ownership; Persan FR)
B21: PT IMT Intermo Asia | C21: ID
B23: Affiliated
B24: BeLighting
B25: Belairbus NV
B26: Flabel Corporation Nv
C29: M2
B30: Annaheim, GA | C30: 17800
B31: Ball Ground, GA | C31: 9900
B32: Canton, GA | C32: 18700
B33: Pittsburgh, PA | C33: 1900
B34: Clearwater, KS | C34: 5500
B35: Brazil
B36: Nova Lima | C36: 800
B37: Chequilho | C37: 36000
B38: Austria
B39: Ranshofen | C39: 22700
B40: Oed | C40: 22000
B41: Regau | C41: 13000
B42: Switzerland
B43: Menziken | C43: 3500
B44: Reinach | C44: 64000
B45: Germany
B46: Bonfield | C46: 2701
B47: Forst | C47: 11800
B48: Dilingen | C48: 18900
B49: Burton upon trent (UK) | C49: 1900
B50: Stenlose (DN) | C50: 300
B51: Montblanc (Es) | C51: 600
B52: Romania
B53: Dumbravita | C53: 42000
B54: Satu Mare | C54: 20500
B55: Baia Mare | C55: 80000
B56: China
B57: Baoying | C57: 32000
B58: Taicang | C58: 700
B59: Vietnam
B60: DaNang | C60: 40000
B61: India
B62: Banglore
B63: vadodara | C63: 11000
B64: Crosio della Valle | C64: 18800
B65: Cazin (Bosina) | C65: 20000
C66: =SUM(C30:C65) -> 517001
C68: 23000
C69: 8500
C70: 1500
C71: 5000
C72: 5500
C73: 11333
C74: 15361
C75: 500
C76: 900
C77: 44950
C78: 1559
C79: 4256
... C93: 25000
C94: =SUM(C68:C93) -> 251282

Sheet Capex
B34: Source: Figeac aero FY2018/2019 slide presentation
C35: Présentation PowerPoint
C36: *Using this information to extrapolate onto Montana
B38: Figeac Capex | D38: 81774

Sheet Labor costs
B2: Avg. earnings of employees in PPP$ by reference area
B3: ource: Wages and Working Time Statistics (COND) database, ILOSTAT (https://ilostat.ilo.org/topics/wages/)
B4: Area | C4: Year | D4: Total | E4: Discount
B5: Switzerland | C5: 2025 | D5: 5808 | E5: =D5/$D$5-1 -> 0
B6: Romania | C6: 2024 | D6: 2919 | E6: =D6/$D$5-1 -> -0.49741736
B7: Vietnam | C7: 2024 | D7: 1198 | E7: =D7/$D$5-1 -> -0.79373278
