Workbook

Sheet Dashboard
C2: =Main!B2 -> #VALUE!
B3: Operating margin | C3: =SUM(Model!M84:P84)/SUM(Model!M69:P69) -> 0.056094961
B4: Return on Assets
B5: Return on Equity | C5: =Model!W101/Model!W132 -> 0.038737897
B6: Revenue | C6: =Model!W69 -> 1493673
B7: 4-year Revenue CAGR | C7: =Model!Z68 -> 0.2365166
B8: Gross Profit | C8: =Model!W69+Model!W74 -> 565776
B9: Total Debt/Equity | C9: =(Model!O143+Model!O135)/Model!O134 -> 0.2743066
B10: Book Value Per Share
B11: 52 Week Change
B12: Market Cap
B13: Trailing P/E
B14: Price/Sales
B15: Price/Book | C15: =Main!C16 -> 1.6663525

Sheet Main
B1: Financials are presented in euros | D1: =C3*62526.632 -> 1535028.8 | F1: Reinach (Kanton Aargau, Schweiz)
B2: #VALUE! | D2: #VALUE! | E2: #VALUE! | F2: Engineering services/ Highly demanding aerostructures | H2: Revenue | I2: EBITDA | J2: Rev Growth | K2: EBITDA margin | L2: 2025 EV/EBITDA
B3: Price | C3: {=_FV(B2,"Price")} -> 24.55 | D3: {=_FV(D2,"Price")} -> 1.2639 | E3: {=_FV(E2,"Price")} -> 1.0832 | F3: Recycling & cast house (where recyclables ar emelted) | G3: 2020 | H3: 265 | I3: 43.3 | K3: =I3/H3 -> 0.16339623
B4: Market cap CHF | C4: =C3*C11 -> 1535028.8 | F4: Extrusion (shaping metals through a shaped die) | G4: 2021 | H4: 285 | I4: 42.9 | J4: =H4/H3-1 -> 0.075471698 | K4: =I4/H4 -> 0.15052632
B5: Market cap | C5: =C4*E3 -> 1662743.2 | D5: =C5*D3 -> 2101541.1 | E5: #VALUE! | F5: Machining | G5: 2022 | H5: 637 | I5: 69.4 | J5: =H5/H4-1 -> 1.2350877 | K5: =I5/H5 -> 0.10894819
B6: Debt | C6: =Model!Y135+Model!Y143+Model!Y136+Model!Y144 -> 240879 | E6: {=_FV(E5,"Price")} -> 1.1665 | F6: Surface Finishing (SF) Treatment & painting | G6: 2023 | H6: 705 | I6: 89.2 | J6: =H6/H5-1 -> 0.10675039 | K6: =I6/H6 -> 0.12652482
B7: Cash | C7: =-Model!Y125 -> -112759 | F7: Subassembly | G7: 2024 | H7: 816 | I7: 130.5 | J7: =H7/H6-1 -> 0.15744681 | K7: =I7/H7 -> 0.15992647
B8: (+) Net Debt | C8: =C6+C7 -> 128120 | G8: 2025 | H8: 971 | I8: 161 | J8: =H8/H7-1 -> 0.18995098 | K8: =I8/H8 -> 0.16580844
B9: (+) Noncontrolling | C9: =Model!Y133 -> 15598
B10: EV (Takeover value) | C10: =C5+C8+C9 -> 1806461.2 | D10: =C10*E6 -> 2107237 | E10: =2300000/C10-1 -> 0.27320752 | G10: 2026e | H10: =H8*(1+J10) -> 1116.65 | I10: =H10*K10 -> 200.997 | J10: 0.15 | K10: =Model!AA80 -> 0.18 | L10: =($C$10/1000)/I10 -> 8.9875034
B11: Shares outstanding | C11: =Model!Y104 -> 62526.632 | D11: =C3*C11 -> 1535028.8 | G11: 2027e | H11: =H10*(1+J11) -> 1228.315 | I11: =H11*K11 -> 184.24725 | J11: 0.1 | K11: =Model!AB80 -> 0.15 | L11: =($C$10/1000)/I11 -> 9.8045491
B12: P/E | C12: {=_FV(B2,"P/E",TRUE)} -> 30.6875 | F12: Alpine Metal Tech GmbH - bought 47% interest in 2022. Bought rest of the shares in 8/19/2024. Has full ownership. | G12: 2028e | H12: =H11*(1+J12) -> 1351.1465 | I12: =H12*K12 -> 216.18344 | J12: 0.1 | K12: =Model!AC80 -> 0.16 | L12: =($C$10/1000)/I12 -> 8.3561498
B13: Alt P/E | C13: =C3/Model!R105 -> 29.914096 | G13: 2029e | H13: =H12*(1+J13) -> 1486.2612 | I13: =H13*K13 -> 252.6644 | J13: 0.1 | K13: =Model!AD80 -> 0.17 | L13: =($C$10/1000)/I13 -> 7.1496469
B14: BV | C14: =Model!Y134 -> 997834 | F14: Majority Shareholder - Dr. Michael Tojner | G14: 2030e | H14: =H13*(1+J14) -> 1634.8873 | I14: =H14*K14 -> 326.97745 | J14: 0.1 | K14: =Model!AE80 -> 0.2 | L14: =($C$10/1000)/I14 -> 5.5247272
B15: BVPS | C15: =C14/C11 -> 15.958544
B16: P/BV | C16: =(C3*E3)/C15 -> 1.6663525 | G16: 2027 analysis
I17: Market pricing in
B18: FCF (FY2025) | C18: =Model!Y184 -> 92753 | F18: Investees | G18: EBITDA forecast) | I18: =I11 -> 184.24725
B19: FCFPS (FY2024) | C19: =C18/C11 -> 1.4834159 | F19: Alpine Metal Tech GmbH (wholly owned sub) | G19: Multiple | I19: 10
B20: P/FCF | C20: =C3/C19 -> 16.549641 | F20: Belairbus NV (129,000 Eur. BV on balance sheet) | G20: Implied EV | I20: =I19*$I$18 -> 1842.4725
B21: PPE | C21: =Model!P109 -> 650763 | F21: Flabel Corporation NV | G21: Net debt | I21: 100
B22: FY2025 EBITDA | C22: =Model!Y78 -> 160592.15 | F22: BeLighting NV | G22: Implied market cap | I22: =I20-I21 -> 1742.4725
B23: EV/EBITDA | C23: =C10/Model!R78 -> 9.4060067 | G23: PPS | I23: =I22/($C$11/1000) -> 27.867685
B24: Backlog: | C24: Unknown | F24: Seeking to divest energy segment at favorable point in market cycle | G24: MOM | I24: =I23/$C$3 -> 1.1351399
F25: 35 offers on the table - 39:00 on Q2 2025 call | I25: =I23/1.6 -> 17.417303
I26: =I25/$C$3 -> 0.70946246
F27: Aerostructures Product line: Aluminum, titanium, Composites
F28: Fuselage Floor Grid | H28: Revenue | I28: EBITDA | J28: Rev Growth | K28: EBITDA margin | L28: 2025 EV/EBITDA
F29: Fuselage Stringers | G29: 2020 | H29: 265 | I29: 43.3 | K29: =I29/H29 -> 0.16339623
F30: Seat Track | G30: 2021 | H30: 285 | I30: 42.9 | J30: =H30/H29-1 -> 0.075471698 | K30: =I30/H30 -> 0.15052632
F31: Engine Rings | G31: 2022 | H31: 637 | I31: 69.4 | J31: =H31/H30-1 -> 1.2350877 | K31: =I31/H31 -> 0.10894819
F32: Wing Structures | G32: 2023 | H32: 705 | I32: 89.2 | J32: =H32/H31-1 -> 0.10675039 | K32: =I32/H32 -> 0.12652482
F33: False Rail | G33: 2024 | H33: 816 | I33: 130.5 | J33: =H33/H32-1 -> 0.15744681 | K33: =I33/H33 -> 0.15992647
F34: Landing Gear (737), Engine parts (737), High Lift Mechanisms | G34: 2025 | H34: 971 | I34: 161 | J34: =H34/H33-1 -> 0.18995098 | K34: =I34/H34 -> 0.16580844
F35: Aerostructure Revenue target (FY2025): 850 Eur. | G35: 2026e | H35: =H34*(1+J35) -> 1116.65 | I35: =H35*K35 -> 223.33 | J35: 0.15 | K35: 0.2 | L35: =($C$10/1000)/I35 -> 8.088753
C36: 35 | G36: 2027e | H36: =H35*(1+J36) -> 1250.648 | I36: =H36*K36 -> 250.1296 | J36: 0.12 | K36: 0.2 | L36: =($C$10/1000)/I36 -> 7.2221009
C37: =C3/C36-1 -> -0.29857143 | G37: 2028e | H37: =H36*(1+J37) -> 1375.7128 | I37: =H37*K37 -> 275.14256 | J37: 0.1 | K37: 0.2 | L37: =($C$10/1000)/I37 -> 6.5655463
G38: 2029e | H38: =H37*(1+J38) -> 1513.2841 | I38: =H38*K38 -> 302.65682 | J38: 0.1 | K38: 0.2 | L38: =($C$10/1000)/I38 -> 5.9686784
G39: 2030e | H39: =H38*(1+J39) -> 1664.6125 | I39: =H39*K39 -> 332.9225 | J39: 0.1 | K39: 0.2 | L39: =($C$10/1000)/I39 -> 5.4260713
G41: 2027 analysis
I42: Base Case
G43: EBITDA forecast) | I43: =I36 -> 250.1296
G44: Multiple | I44: 12
G45: Implied EV | I45: =I44*$I$43 -> 3001.5552
G46: Net debt | I46: 0
G47: Implied market cap | I47: =I45-I46 -> 3001.5552
G48: PPS | I48: =I47/($C$11/1000) -> 48.004428
G49: MOM | I49: =I48/$C$3 -> 1.9553738
I50: =I48/1.6 -> 30.002767
I51: =I50/$C$3 -> 1.2221087
H53: Revenue | I53: EBITDA | J53: Rev Growth | K53: EBITDA margin | L53: 2025 EV/EBITDA
G54: 2020 | H54: 265 | I54: 43.3 | K54: =I54/H54 -> 0.16339623
G55: 2021 | H55: 285 | I55: 42.9 | J55: =H55/H54-1 -> 0.075471698 | K55: =I55/H55 -> 0.15052632
G56: 2022 | H56: 637 | I56: 69.4 | J56: =H56/H55-1 -> 1.2350877 | K56: =I56/H56 -> 0.10894819
G57: 2023 | H57: 705 | I57: 89.2 | J57: =H57/H56-1 -> 0.10675039 | K57: =I57/H57 -> 0.12652482
G58: 2024 | H58: 816 | I58: 130.5 | J58: =H58/H57-1 -> 0.15744681 | K58: =I58/H58 -> 0.15992647
G59: 2025 | H59: 971 | I59: 161 | J59: =H59/H58-1 -> 0.18995098 | K59: =Model!#REF! -> #REF!
G60: 2026e | H60: =H59*(1+J60) -> 1048.68 | I60: =H60*K60 -> 125.8416 | J60: 0.08 | K60: 0.12 | L60: =($C$10/1000)/I60 -> 14.35504
G61: 2027e | H61: =H60*(1+J61) -> 1101.114 | I61: =H61*K61 -> 132.13368 | J61: 0.05 | K61: 0.12 | L61: =($C$10/1000)/I61 -> 13.671467
G62: 2028e | H62: =H61*(1+J62) -> 1156.1697 | I62: =H62*K62 -> 138.74036 | J62: 0.05 | K62: 0.12 | L62: =($C$10/1000)/I62 -> 13.020445
G63: 2029e | H63: =H62*(1+J63) -> 1213.9782 | I63: =H63*K63 -> 145.67738 | J63: 0.05 | K63: 0.12 | L63: =($C$10/1000)/I63 -> 12.400423
G64: 2030e | H64: =H63*(1+J64) -> 1274.6771 | I64: =H64*K64 -> 152.96125 | J64: 0.05 | K64: 0.12 | L64: =($C$10/1000)/I64 -> 11.809927
G65: 2027 analysis
I66: Bear Case
G67: EBITDA forecast) | I67: =I61 -> 132.13368
G68: Multiple | I68: 8
G69: Implied EV | I69: =I68*$I$67 -> 1057.0694
G70: Net debt | I70: 150
G71: Implied market cap | I71: =I69-I70 -> 907.06944
G72: PPS | I72: =I71/($C$11/1000) -> 14.506929
G73: MOM | I73: =I72/$C$3 -> 0.59091362
I74: =I72/1.6 -> 9.0668309
I75: =I74/$C$3 -> 0.36932101
H76: Revenue | I76: EBITDA | J76: Rev Growth | K76: EBITDA margin | L76: 2025 EV/EBITDA
G77: 2020 | H77: 265 | I77: 43.3 | K77: =I77/H77 -> 0.16339623
G78: 2021 | H78: 285 | I78: 42.9 | J78: =H78/H77-1 -> 0.075471698 | K78: =I78/H78 -> 0.15052632
G79: 2022 | H79: 637 | I79: 69.4 | J79: =H79/H78-1 -> 1.2350877 | K79: =I79/H79 -> 0.10894819
G80: 2023 | H80: 705 | I80: 89.2 | J80: =H80/H79-1 -> 0.10675039 | K80: =I80/H80 -> 0.12652482
G81: 2024 | H81: 816 | I81: 130.5 | J81: =H81/H80-1 -> 0.15744681 | K81: =I81/H81 -> 0.15992647
G82: 2025 | H82: 971 | I82: 161 | J82: =H82/H81-1 -> 0.18995098 | K82: =Model!#REF! -> #REF!
G83: 2026e | H83: =H82*(1+J83) -> 1165.2 | I83: =H83*K83 -> 233.04 | J83: 0.2 | K83: 0.2 | L83: =($C$10/1000)/I83 -> 7.7517216
G84: 2027e | H84: =H83*(1+J84) -> 1339.98 | I84: =H84*K84 -> 294.7956 | J84: 0.15 | K84: 0.22 | L84: =($C$10/1000)/I84 -> 6.1278432
G85: 2028e | H85: =H84*(1+J85) -> 1540.977 | I85: =H85*K85 -> 339.01494 | J85: 0.15 | K85: 0.22 | L85: =($C$10/1000)/I85 -> 5.3285593
G86: 2029e | H86: =H85*(1+J86) -> 1772.1235 | I86: =H86*K86 -> 389.86718 | J86: 0.15 | K86: 0.22 | L86: =($C$10/1000)/I86 -> 4.6335298
G87: 2030e | H87: =H86*(1+J87) -> 2037.9421 | I87: =H87*K87 -> 448.34726 | J87: 0.15 | K87: 0.22 | L87: =($C$10/1000)/I87 -> 4.0291564
G88: 2027 analysis
I89: Bull
G90: EBITDA forecast) | I90: =I84 -> 294.7956
G91: Multiple | I91: 15
G92: Implied EV | I92: =I91*$I$90 -> 4421.934
G93: Net debt | I93: 150
G94: Implied market cap | I94: =I92-I93 -> 4271.934
G95: PPS | I95: =I94/($C$11/1000) -> 68.321831
G96: MOM | I96: =I95/$C$3 -> 2.7829666
I97: =I95/1.6 -> 42.701145
I98: =I97/$C$3 -> 1.7393542

Sheet Model
C2: Q1'2022 | D2: Q2'2022 | E2: Q3'2022 | F2: Q4'2022 | G2: Q1'2023 | H2: Q2'2023 | I2: Q3'2023 | J2: Q4'2023 | K2: Q1'2024 | L2: Q2'2024 | M2: Q3'2024 | N2: Q4'2024 | O2: Q1'2025 | P2: Q2'2025 | Q2: Q3'2025 | R2: TTM Figures | T2: FY2021 | U2: FY2022 | V2: FY2023 | W2: FY2024 | X2: FY2024-restated | Y2: FY2025 | Z2: CAGR: | AA2: FY2026 | AB2: FY2027 | AC2: FY2028 | AD2: FY2029 | AE2: FY2030
A3: X | B3: SEGMENT
B4: Aerostructures
B5: Net Sales | C5: 89358 | D5: =256935-C5 -> 167577 | E5: =433174-D5-C5 -> 176239 | F5: =U5-E5-D5-C5 -> 202349 | G5: 166389 | H5: =332024-G5 -> 165635 | I5: =496727-H5-G5 -> 164703 | J5: =V5-I5-H5-G5 -> 206340 | K5: 207384 | L5: =407878-K5 -> 200494 | M5: =610539-L5-K5 -> 202661 | N5: =W5-M5-L5-K5 -> 203526 | O5: 221323 | P5: =429903-O5 -> 208580 | Q5: =649100-P5-O5 -> 219197 | R5: =Q5+P5+O5+N5 -> 852626 | T5: 284587 | U5: 635523 | V5: 703067 | W5: 814065 | Y5: 881272 | Z5: =((W5/T5)^(1/(2024-2021)))-1 -> 0.41954122 | AA5: 1000000
B6: Intersegment | C6: 519 | D6: =572-C6 -> 53 | E6: =648-D6-C6 -> 76 | F6: =U6-E6-D6-C6 -> 256 | G6: 371 | H6: =695-G6 -> 324 | I6: =1010-H6-G6 -> 315 | J6: =V6-I6-H6-G6 -> 452 | K6: 389 | L6: =1102-K6 -> 713 | M6: =1462-L6-K6 -> 360 | N6: =W6-M6-L6-K6 -> 92 | O6: 0 | P6: 0 | Q6: 0 | R6: =Q6+P6+O6+N6 -> 92 | T6: 378 | U6: 904 | V6: 1462 | W6: 1554 | Y6: 0 | AA6: 0
B7: Sales | C7: =C6+C5 -> 89877 | D7: =D6+D5 -> 167630 | E7: =E6+E5 -> 176315 | F7: =F6+F5 -> 202605 | G7: =G6+G5 -> 166760 | H7: =H6+H5 -> 165959 | I7: =I6+I5 -> 165018 | J7: =J6+J5 -> 206792 | ... R7: =R6+R5 -> 852718 | T7: =T6+T5 -> 284965 | U7: =U6+U5 -> 636427 | V7: =V6+V5 -> 704529 | W7: =W6+W5 -> 815619 | Y7: =Y6+Y5 -> 881272 | AA7: =AA6+AA5 -> 1000000 | AB7: =AA7*(1+AB8) -> 1100000 | AC7: =AB7*(1+AC8) -> 1265000 | AD7: =AC7*(1+AD8) -> 1429450 | AE7: =AD7*(1+AE8) -> 1572395
B8: Net Sales Growth Y/Y | R8: =R7/W7-1 -> 0.045485699 | U8: =U5/T5-1 -> 1.2331414 | V8: =V5/U5-1 -> 0.10628097 | W8: =W5/V5-1 -> 0.15787685 | Y8: =Y5/W5-1 -> 0.08255729 | AA8: =AA7/Y7-1 -> 0.13472345 | AB8: 0.1 | AC8: 0.15 | AD8: 0.13 | AE8: 0.1
B9: EBITDA | C9: 11678 | D9: =24586-C9 -> 12908 | E9: =32702-D9-C9 -> 8116 | F9: =U9-E9-D9-C9 -> 33006 | G9: 13452 | H9: =35171-G9 -> 21719 | I9: =52695-H9-G9 -> 17524 | J9: =V9-I9-H9-G9 -> 20874 | K9: 29287 | L9: =60097-K9 -> 30810 | M9: =90888-L9-K9 -> 30791 | N9: =W9-M9-L9-K9 -> 36147 | O9: 39812 | P9: =76421-O9 -> 36609 | Q9: =111200-P9-O9 -> 34779 | R9: =Q9+P9+O9+N9 -> 147347 | T9: 35127 | U9: 65708 | V9: 73569 | W9: 127035 | Y9: 159811 | Z9: =((W9/T9)^(1/(2024-2021)))-1 -> 0.53494957 | AA9: 185000
B10: Margin% | C10: =C9/C$7 -> 0.12993313 | D10: =D9/D$7 -> 0.077002923 | E10: =E9/E$7 -> 0.046031251 | F10: =F9/F$7 -> 0.16290812 | G10: =G9/G$7 -> 0.080666827 | H10: =H9/H$7 -> 0.13086967 | I10: =I9/I$7 -> 0.10619448 | J10: =J9/J$7 -> 0.10094201 | ... R10: =R9/R$7 -> 0.17279687 | T10: =T9/T$7 -> 0.12326777 | U10: =U9/U$7 -> 0.10324515 | V10: =V9/V$7 -> 0.10442295 | W10: =W9/W$7 -> 0.15575287 | Y10: =Y9/Y$7 -> 0.18134129 | AA10: =AA9/AA$7 -> 0.185
B11: D&A | C11: -14970 | D11: =-37801-C11 -> -22831 | E11: =-62307-D11-C11 -> -24506 | F11: =U11-E11-D11-C11 -> -27111 | G11: -22983 | H11: =-42109-G11 -> -19126 | I11: =-64593-H11-G11 -> -22484 | J11: =V11-I11-H11-G11 -> -17934 | K11: -20244 | L11: =-41789-K11 -> -21545 | M11: =-62487-L11-K11 -> -20698 | N11: =W11-M11-L11-K11 -> -20512 | O11: -21520 | P11: =-42525-O11 -> -21005 | T11: -54104 | U11: -89418 | V11: -82527 | W11: -82999 | Y11: -87106
B12: Margin% | C12: =-C11/C$7 -> 0.16656097 | D12: =-D11/D$7 -> 0.13619877 | E12: =-E11/E$7 -> 0.13898988 | F12: =-F11/F$7 -> 0.1338121 | G12: =-G11/G$7 -> 0.13782082 | H12: =-H11/H$7 -> 0.11524533 | I12: =-I11/I$7 -> 0.1362518 | J12: =-J11/J$7 -> 0.086724825 | ... P12: =-P11/P$7 -> 0.10070477 | T12: =-T11/T$7 -> 0.18986191 | U12: =-U11/U$7 -> 0.14050001 | V12: =-V11/V$7 -> 0.11713783 | W12: =-W11/W$7 -> 0.10176197 | Y12: =-Y11/Y$7 -> 0.09884122
B13: Investments | C13: 16369 | D13: =30538-C13 -> 14169 | E13: =49043-D13-C13 -> 18505 | F13: =U13-E13-D13-C13 -> 28179 | G13: 12492 | H13: =24312-G13 -> 11820 | I13: =34871-H13-G13 -> 10559 | J13: =V13-I13-H13-G13 -> 19149 | K13: 11805 | L13: =25517-K13 -> 13712 | M13: =39783-L13-K13 -> 14266 | N13: =W13-M13-L13-K13 -> 33499 | O13: 23138 | P13: =36460-O13 -> 13322 | T13: 100787 | U13: 77222 | V13: 54020 | W13: 73282 | Y13: 68161
B14: Share of rev% | C14: =C13/C$7 -> 0.18212668 | D14: =D13/D$7 -> 0.084525443 | E14: =E13/E$7 -> 0.1049542 | F14: =F13/F$7 -> 0.13908344 | G14: =G13/G$7 -> 0.07491005 | H14: =H13/H$7 -> 0.07122241 | I14: =I13/I$7 -> 0.063986959 | J14: =J13/J$7 -> 0.092600294 | ... P14: =P13/P$7 -> 0.063869978 | T14: =T13/T$7 -> 0.35368203 | U14: =U13/U$7 -> 0.12133678 | V14: =V13/V$7 -> 0.076675339 | W14: =W13/W$7 -> 0.089848324 | Y14: =Y13/Y$7 -> 0.077343885
B15: Valuation Multiple | Y15: 10
B16: Segment Value | Y16: =Y9*Y15 -> 1598110
B17: Alpine Metal Tech
B18: Net Sales | W18: 36959 | Y18: 98060 | AA18: =Y18 -> 98060 | AB18: =AA18 -> 98060 | AC18: =AB18 -> 98060 | AD18: =AC18 -> 98060 | AE18: =AD18 -> 98060
B19: Intersegment | W19: 0 | Y19: 10 | AA19: 0 | AB19: 0 | AC19: 0 | AD19: 0 | AE19: 0
B20: Sales | W20: =W19+W18 -> 36959 | Y20: =Y19+Y18 -> 98070 | AA20: =AA19+AA18 -> 98060 | AB20: =AB19+AB18 -> 98060 | AC20: =AC19+AC18 -> 98060 | AD20: =AD19+AD18 -> 98060 | AE20: =AE19+AE18 -> 98060
B21: Net Sales Growth Y/Y | W21: =W18/V18-1 -> #DIV/0! | Y21: =Y18/W18-1 -> 1.6532103
B22: EBITDA | W22: 4042 | Y22: 9139
B23: Margin% | W23: =W22/W$20 -> 0.10936443 | Y23: =Y22/Y$20 -> 0.093188539
B24: D&A | W24: -1538 | Y24: -4054
B25: Margin% | W25: =-W24/W$7 -> 0.0018856844 | Y25: =-Y24/Y$7 -> 0.0046001688
B26: Investments | W26: 1580 | Y26: 1226
B27: Share of rev% | W27: =W26/W$7 -> 0.001937179 | Y27: =Y26/Y$7 -> 0.0013911709
B28: Valuation Multiple | Y28: 7.5
B29: Segment Value | Y29: =Y22*Y28 -> 68542.5
B30: E-Mobility
B31: Net Sales | C31: 45307 | D31: =94443-C31 -> 49136 | E31: =140817-D31-C31 -> 46374 | F31: =U31-E31-D31-C31 -> 50201 | G31: 46930 | H31: =89997-G31 -> 43067 | I31: =127413-H31-G31 -> 37416 | J31: =V31-I31-H31-G31 -> 38623 | K31: 40651 | T31: 122493 | U31: 191018 | V31: 166036
B32: Intersegment | C32: 85 | D32: =163-C32 -> 78 | E32: =0-D32-C32 -> -163 | F32: =U32-E32-D32-C32 -> 204 | G32: 224 | H32: =310-G32 -> 86 | I32: =513-H32-G32 -> 203 | J32: =V32-I32-H32-G32 -> 323 | K32: 49 | T32: 1 | U32: 204 | V32: 836
B33: Sales | C33: =C32+C31 -> 45392 | D33: =D32+D31 -> 49214 | E33: =E32+E31 -> 46211 | F33: =F32+F31 -> 50405 | G33: =G32+G31 -> 47154 | H33: =H32+H31 -> 43153 | I33: =I32+I31 -> 37619 | J33: =J32+J31 -> 38946 | K33: =K32+K31 -> 40700 | T33: =T32+T31 -> 122494 | U33: =U32+U31 -> 191222 | V33: =V32+V31 -> 166872
B34: EBITDA | C34: 4163 | D34: =8040-C34 -> 3877 | E34: =12675-D34-C34 -> 4635 | F34: =U34-E34-D34-C34 -> 11722 | G34: 3296 | H34: =7191-G34 -> 3895 | I34: =18280-H34-G34 -> 11089 | J34: =V34-I34-H34-G34 -> 7101 | K34: 1900 | T34: 8582 | U34: 24397 | V34: 25381
B35: Margin% | C35: =C34/C$7 -> 0.046318858 | D35: =D34/D$33 -> 0.078778396 | E35: =E34/E$7 -> 0.026288177 | F35: =F34/F$7 -> 0.05785642 | G35: =G34/G$7 -> 0.019764932 | H35: =H34/H$33 -> 0.090260237 | I35: =I34/I$7 -> 0.06719873 | J35: =J34/J$7 -> 0.034338853 | K35: =K34/K$33 -> 0.046683047 | T35: =T34/T$7 -> 0.030115979 | U35: =U34/U$7 -> 0.038334326 | V35: =V34/V$7 -> 0.036025487
B36: D&A | C36: -2444 | D36: =-4926-C36 -> -2482 | E36: =-7489-D36-C36 -> -2563 | F36: =U36-E36-D36-C36 -> -3025 | G36: -2535 | H36: =-5089-G36 -> -2554 | I36: =-7258-H36-G36 -> -2169 | J36: =V36-I36-H36-G36 -> -2853 | K36: -2418 | T36: -9731 | U36: -10514 | V36: -10111
B37: Margin% | C37: =-C36/C$7 -> 0.027192719 | D37: =-D36/D$33 -> 0.050432804 | E37: =-E36/E$7 -> 0.014536483 | F37: =-F36/F$7 -> 0.01493053 | G37: =-G36/G$7 -> 0.015201487 | H37: =-H36/H$33 -> 0.059184761 | I37: =-I36/I$7 -> 0.013144021 | J37: =-J36/J$7 -> 0.013796472 | K37: =-K36/K$33 -> 0.059410319 | T37: =-T36/T$7 -> 0.034148053 | U37: =-U36/U$7 -> 0.016520355 | V37: =-V36/V$7 -> 0.014351432
B38: Investments | C38: 2105 | D38: =4622-C38 -> 2517 | E38: =5174-D38-C38 -> 552 | F38: =U38-E38-D38-C38 -> 1473 | G38: 2105 | H38: =4622-G38 -> 2517 | I38: =4429-H38-G38 -> -193 | J38: =V38-I38-H38-G38 -> 1691 | K38: 11805 | T38: 5444 | U38: 6647 | V38: 6120
B39: Share of % | C39: =C38/C$7 -> 0.023420897 | D39: =D38/D$33 -> 0.051143983 | E39: =E38/E$7 -> 0.0031307603 | F39: =F38/F$7 -> 0.0072703043 | G39: =G38/G$7 -> 0.012622931 | H39: =H38/H$33 -> 0.058327347 | I39: =I38/I$7 -> -0.0011695694 | J39: =J38/J$7 -> 0.0081772989 | K39: =K38/K$33 -> 0.29004914 | T39: =T38/T$7 -> 0.019104101 | U39: =U38/U$7 -> 0.010444246 | V39: =V38/V$7 -> 0.0086866545
B40: Energy (*discontinued in Q3 2025*)
B41: Net Sales | C41: 108622 | D41: =227434-C41 -> 118812 | E41: =348609-D41-C41 -> 121175 | F41: =U41-E41-D41-C41 -> 130985 | G41: 139764 | H41: =281986-G41 -> 142222 | I41: =418024-H41-G41 -> 136038 | J41: =V41-I41-H41-G41 -> 149257 | K41: 147649 | L41: =311671-K41 -> 164022 | M41: =469420-L41-K41 -> 157749 | N41: =W41-M41-L41-K41 -> 173228 | O41: 170377 | P41: =356661-O41 -> 186284 | T41: 382972 | U41: 479594 | V41: 567281 | W41: 642648 | Y41: 525650
B42: Intersegment | C42: 0 | D42: 0 | E42: 0 | F42: =U42-E42-D42-C42 -> 0 | G42: 0 | H42: 0 | I42: 0 | J42: =V42-I42-H42-G42 -> 0 | K42: 0 | L42: 0 | M42: 0 | N42: =W42-M42-L42-K42 -> 0 | O42: 0 | P42: 0 | T42: 0 | U42: 0 | V42: 0 | W42: 0
B43: Sales | C43: =C42+C41 -> 108622 | D43: =D42+D41 -> 118812 | E43: =E42+E41 -> 121175 | F43: =F42+F41 -> 130985 | G43: =G42+G41 -> 139764 | H43: =H42+H41 -> 142222 | I43: =I42+I41 -> 136038 | J43: =J42+J41 -> 149257 | ... P43: =P42+P41 -> 186284 | T43: =T42+T41 -> 382972 | U43: =U42+U41 -> 479594 | V43: =V42+V41 -> 567281 | W43: =W42+W41 -> 642648 | Y43: =Y42+Y41 -> 525650
B44: EBITDA | C44: 1435 | D44: =3149-C44 -> 1714 | E44: =9829-D44-C44 -> 6680 | F44: =U44-E44-D44-C44 -> 23461 | G44: 7175 | H44: =13465-G44 -> 6290 | I44: =18692-H44-G44 -> 5227 | J44: =V44-I44-H44-G44 -> 6375 | K44: 8183 | L44: =18189-K44 -> 10006 | M44: =25450-L44-K44 -> 7261 | N44: =W44-M44-L44-K44 -> 10046 | O44: 10205 | P44: =24033-O44 -> 13828 | T44: 8564 | U44: 33290 | V44: 25067 | W44: 35496 | Y44: 36398
B45: Margin% | C45: =C44/C$7 -> 0.015966265 | D45: =D44/D$43 -> 0.014426152 | E45: =E44/E$7 -> 0.037886737 | F45: =F44/F$7 -> 0.11579675 | G45: =G44/G$7 -> 0.043025905 | H45: =H44/H$43 -> 0.044226632 | I45: =I44/I$7 -> 0.031675332 | J45: =J44/J$7 -> 0.030828078 | K45: =K44/K$43 -> 0.055421981 | L45: =L44/L$43 -> 0.061004012 | M45: =M44/M$7 -> 0.035764773 | N45: =N44/N$7 -> 0.049337485 | O45: =O44/O$43 -> 0.059896582 | P45: =P44/P$43 -> 0.074230744 | T45: =T44/T$7 -> 0.030052814 | U45: =U44/U$7 -> 0.052307649 | V45: =V44/V$7 -> 0.035579799 | W45: =W44/W$7 -> 0.04352032 | Y45: =Y44/Y$7 -> 0.041301664
B46: D&A | C46: -1841 | D46: =-3827-C46 -> -1986 | E46: =-5893-D46-C46 -> -2066 | F46: =U46-E46-D46-C46 -> -3186 | G46: -2384 | H46: =-4869-G46 -> -2485 | I46: =-7458-H46-G46 -> -2589 | J46: =V46-I46-H46-G46 -> -2716 | K46: -2380 | L46: =-4740-K46 -> -2360 | M46: =-7168-L46-K46 -> -2428 | N46: =W46-M46-L46-K46 -> -2812 | O46: -2231 | P46: =-4475-O46 -> -2244 | T46: -7644 | U46: -9079 | V46: -10174 | W46: -9980 | Y46: -7029
B47: Margin% | C47: =-C46/C$7 -> 0.02048355 | D47: =-D46/D$43 -> 0.016715483 | E47: =-E46/E$7 -> 0.011717664 | F47: =-F46/F$7 -> 0.01572518 | G47: =-G46/G$7 -> 0.014295994 | H47: =-H46/H$43 -> 0.017472684 | I47: =-I46/I$7 -> 0.015689198 | J47: =-J46/J$7 -> 0.01313397 | K47: =-K46/K$43 -> 0.01611931 | L47: =-L46/L$43 -> 0.014388314 | M47: =-M46/M$7 -> 0.011959354 | N47: =-N46/N$7 -> 0.013810174 | O47: =-O46/O$43 -> 0.01309449 | P47: =-P46/P$43 -> 0.012046123 | T47: =-T46/T$7 -> 0.026824347 | U47: =-U46/U$7 -> 0.01426558 | V47: =-V46/V$7 -> 0.014440853 | W47: =-W46/W$7 -> 0.012236105 | Y47: =-Y46/Y$7 -> 0.0079759711
B48: Investments | C48: 1128 | D48: =3101-C48 -> 1973 | E48: =6080-D48-C48 -> 2979 | F48: =U48-E48-D48-C48 -> 2131 | G48: 2227 | H48: =4559-G48 -> 2332 | I48: =4559-H48-G48 -> 0 | J48: =V48-I48-H48-G48 -> 9148 | K48: 3876 | L48: =8735-K48 -> 4859 | M48: =15512-L48-K48 -> 6777 | N48: =W48-M48-L48-K48 -> 12800 | O48: 6278 | P48: =12568-O48 -> 6290 | T48: 6454 | U48: 8211 | V48: 13707 | W48: 28312 | Y48: 22207
B49: Share of % | C49: =C48/C$7 -> 0.012550486 | D49: =D48/D$43 -> 0.016606067 | E49: =E48/E$7 -> 0.016895897 | F49: =F48/F$7 -> 0.010518003 | G49: =G48/G$7 -> 0.013354521 | H49: =H48/H$43 -> 0.016396901 | I49: =I48/I$7 -> 0 | J49: =J48/J$7 -> 0.044237688 | K49: =K48/K$43 -> 0.026251448 | L49: =L48/L$43 -> 0.029624075 | M49: =M48/M$7 -> 0.033380783 | N49: =N48/N$7 -> 0.062862812 | O49: =O48/O$43 -> 0.036847697 | P49: =P48/P$43 -> 0.033765648 | T49: =T48/T$7 -> 0.022648395 | U49: =U48/U$7 -> 0.012901715 | V49: =V48/V$7 -> 0.019455551 | W49: =W48/W$7 -> 0.034712286 | Y49: =Y48/Y$7 -> 0.025198804
B50: Reconciliation
B51: Net Sales | C51: -504 | D51: =-736-C51 -> -232 | E51: =-648-D51-C51 -> 88 | F51: =U51-E51-D51-C51 -> -460 | G51: -595 | H51: =-1005-G51 -> -410 | I51: =4899-H51-G51 -> 5904 | K51: -438 | L51: =-1102-K51 -> -664 | M51: =4899-L51-K51 -> 6001 | O51: 17068 | P51: =34072-O51 -> 17004 | T51: -379 | U51: -1108 | V51: -1462 | W51: 35406
B53: Growth Rates
B54: Aerostructures | D54: 1.199 | E54: =E7/W7-1 -> -0.78382676 | F54: =F7/S7-1 -> #DIV/0! | G54: =G7/C7-1 -> 0.85542464 | H54: =H7/D7-1 -> -0.0099683827 | I54: =I7/E7-1 -> -0.064072824 | J54: =J7/F7-1 -> 0.020665828 | K54: =K7/G7-1 -> 0.24594027 | L54: =L7/H7-1 -> 0.21238981 | M54: =M7/I7-1 -> 0.23029609 | N54: =N7/J7-1 -> -0.015348756 | ... P54: =P7/L7-1 -> 0.036643854 | T54: =T7/Z7-1 -> #DIV/0! | U54: =U7/T7-1 -> 1.2333515 | V54: =V7/U7-1 -> 0.10700677 | W54: =W7/V7-1 -> 0.15767981
B55: Energy | D55: 0.213 | E55: =E43/W43-1 -> -0.81144421 | F55: =F43/S43-1 -> #DIV/0! | G55: =G43/C43-1 -> 0.28670067 | H55: =H43/D43-1 -> 0.19703397 | I55: =I43/E43-1 -> 0.12265731 | J55: =J43/F43-1 -> 0.13949689 | K55: =K43/G43-1 -> 0.056416531 | L55: =L43/H43-1 -> 0.15328149 | M55: =M43/I43-1 -> 0.15959511 | N55: =N43/J43-1 -> 0.16060218 | ... P55: =P43/L43-1 -> 0.1357257 | U55: =U43/T43-1 -> 0.25229521 | V55: =V43/U43-1 -> 0.1828359 | W55: =W43/V43-1 -> 0.13285656
B56: E-mobility | D56: 0.717 | E56: =E31/W31-1 -> #DIV/0! | F56: =F31/S31-1 -> #DIV/0! | G56: =G31/C31-1 -> 0.035822279 | H56: =H31/D31-1 -> -0.12351433 | I56: =I31/E31-1 -> -0.19316859 | J56: =J31/F31-1 -> -0.23063286 | K56: =K31/G31-1 -> -0.13379501 | L56: =L31/H31-1 -> -1 | M56: =M31/I31-1 -> -1 | N56: =N31/J31-1 -> -1 | ... P56: =P31/L31-1 -> #DIV/0! | U56: =U31/T31-1 -> 0.55941972 | V56: =V31/U31-1 -> -0.13078349 | W56: =W31/V31-1 -> -1
B57: Company Revenue | D57: 0.611 | E57: =E69/W69-1 -> -0.7698365 | F57: =F69/S69-1 -> #DIV/0! | G57: =G69/C69-1 -> 0.45130648 | H57: =H69/D69-1 -> -0.082462059 | I57: =I69/E69-1 -> -0.12521634 | J57: =J69/F69-1 -> -0.19520303 | K57: =K69/G69-1 -> 0.0055227651 | L57: =L69/H69-1 -> 0.18404384 | M57: =M69/I69-1 -> -0.30497671 | N57: =N69/J69-1 -> 0.83078204 | ... P57: =P69/L69-1 -> 0.12990686 | T57: =T69/Z69-1 -> #DIV/0! | U57: =U69/T69-1 -> 0.65322536 | V57: =V69/U69-1 -> -0.027398414 | W57: =W69/V69-1 -> 0.17579829
B58: Company OpEx | J58: =J77/F77-1 -> -0.21432054 | K58: =K77/G77-1 -> -0.02470238 | L58: =L77/H77-1 -> 0.21730759 | M58: =M77/I77-1 -> -0.34492148 | N58: =N77/J77-1 -> 0.81920175 | O58: =O77/K77-1 -> 0.11680986 | P58: =P77/L77-1 -> 0.098916025 | U58: =U77/T77-1 -> 0.58939948 | V58: =V77/U77-1 -> -0.081911366 | W58: =W77/V77-1 -> 0.15251375
B59: Share of Total Revenue
B60: Aerostructures | C60: =C7/C$69 -> 0.36942788 | D60: =D7/D$69 -> 0.49960659 | E60: =E7/E$69 -> 0.51285818 | F60: =F7/F$69 -> 0.52825825 | G60: =G7/G$69 -> 0.47229554 | H60: =H7/H$69 -> 0.53907996 | I60: =I7/I$69 -> 0.5487047 | J60: =J7/J$69 -> 0.66995176 | ... P60: =P7/P$69 -> 0.50642439 | T60: =T7/T$69 -> 0.36069145 | U60: =U7/U$69 -> 0.48726011 | V60: =V7/V$69 -> 0.55459528 | W60: =W7/W$69 -> 0.54604924
B61: Energy | C61: =C43/C$69 -> 0.44647679 | D61: =D43/D$69 -> 0.3541088 | E61: =E43/E$69 -> 0.3524691 | F61: =F43/F$69 -> 0.34152122 | G61: =G43/G$69 -> 0.39583782 | H61: =H43/H$69 -> 0.46197573 | I61: =I43/I$69 -> 0.45234271 | J61: =J43/J$69 -> 0.48355347 | ... P61: =P43/P$69 -> 0.45229054 | T61: =T43/T$69 -> 0.48474278 | U61: =U43/U$69 -> 0.36718591 | V61: =V43/V$69 -> 0.44655559 | W61: =W43/W$69 -> 0.43024678
B62: E-mobility | C62: =C33/C$69 -> 0.18657799 | D62: =D33/D$69 -> 0.14667803 | E62: =E33/E$69 -> 0.13441675 | F62: =F33/F$69 -> 0.13142251 | G62: =G33/G$69 -> 0.13354896 | H62: =H33/H$69 -> 0.14017268 | I62: =I33/I$69 -> 0.1250877 | J62: =J33/J$69 -> 0.12617481 | ... P62: =P33/P$69 -> 0 | T62: =T33/T$69 -> 0.15504549 | U62: =U33/U$69 -> 0.14640305 | V62: =V33/V$69 -> 0.13135928 | W62: =W33/W$69 -> 0
B63: Intersegment | C63: =C51/C$69 -> -0.0020716273 | D63: =D51/D$69 -> -0.00069145575 | E63: =E51/E$69 -> 0.00025597096 | F63: =F51/F$69 -> -0.0011993722 | G63: =G51/G$69 -> -0.0016851514 | H63: =H51/H$69 -> -0.0013317915 | I63: =I51/I$69 -> 0.01963151 | J63: =J51/J$69 -> 0 | ... P63: =P51/P$69 -> 0.041285072 | T63: =T51/T$69 -> -0.00047971526 | U63: =U51/U$69 -> -0.000848305 | V63: =V51/V$69 -> -0.0011508657 | W63: =W51/W$69 -> 0.023703983
C64: =C60+C61+C62+C63 -> 1.000411 | D64: =D60+D61+D62+D63 -> 0.99970196 | E64: =E60+E61+E62+E63 -> 1 | F64: =F60+F61+F62+F63 -> 1.0000026 | G64: =G60+G61+G62+G63 -> 0.99999717 | H64: =H60+H61+H62+H63 -> 1.1398966 | I64: =I60+I61+I62+I63 -> 1.1457666 | J64: =J60+J61+J62+J63 -> 1.27968 | ... P64: =P60+P61+P62+P63 -> 1 | T64: =T60+T61+T62+T63 -> 1 | U64: =U60+U61+U62+U63 -> 1.0000008 | V64: =V60+V61+V62+V63 -> 1.1313593 | W64: =W60+W61+W62+W63 -> 1 | Z64: Discount to TEV
B65: Valuation | W65: =W29+W16 -> 0 | Y65: =Y29+Y16 -> 1666652.5 | Z65: =Y65/Main!C10-1 -> -0.077393698
B66: PPS | Y66: =(Y65/Y104)/Main!E3 -> 24.60772
B67: Consolidated IS | M67: Adjusted:
C68: =C43+C33+C7+C51 -> 243387 | D68: =D43+D33+D7+D51 -> 335424 | E68: =E43+E33+E7+E51 -> 343789 | F68: =F43+F33+F7+F51 -> 383535 | G68: =G43+G33+G7+G51 -> 353083 | K68: =K43+K33+K7+K51 -> 395684 | L68: =L43+L33+L7+L51 -> 364565 | O68: =O43+O33+O7+O51 -> 408768 | P68: =P43+P33+P7+P51 -> 411868 | T68: =T43+T33+T7+T51 -> 790052 | U68: =U43+U33+U7+U51 -> 1306135 | V68: =V43+V33+V7+V51 -> 1437220 | W68: =W43+W33+W7+W51 -> 1493673 | Y68: =Y43+Y33+Y7+Y20 -> 1504992 | Z68: =((W68/T68)^(1/(2024-2021)))-1 -> 0.2365166 | AA68: =AA43+AA33+AA7+AA20 -> 1098060 | AB68: =AB43+AB33+AB7+AB20 -> 1198060 | AC68: =AC43+AC33+AC7+AC20 -> 1363060 | AD68: =AD43+AD33+AD7+AD20 -> 1527510 | AE68: =AE43+AE33+AE7+AE20 -> 1670455
B69: Net Sales | C69: 243287 | D69: =578811-C69 -> 335524 | E69: 343789 | F69: =U69-E69-D69-C69 -> 383534 | G69: 353084 | H69: 307856 | I69: 300741 | J69: =V69-I69-H69-G69 -> 308667 | K69: 355034 | L69: 364515 | M69: 209022 | N69: =W69-M69-L69-K69 -> 565102 | O69: 408768 | P69: 411868 | Q69: 248355 | R69: =Q69+P69+O69+N69 -> 1634093 | T69: 790052 | U69: 1306134 | V69: 1270348 | W69: 1493673 | X69: 851025 | Y69: 979331 | AA69: =AA68 -> 1098060 | AB69: =AB68 -> 1198060 | AC69: =AC68 -> 1363060 | AD69: =AD68 -> 1527510 | AE69: =AE68 -> 1670455
B70: Growth Y/Y | J70: =J69/F69-1 -> -0.19520303 | K70: =K69/G69-1 -> 0.0055227651 | L70: =L69/H69-1 -> 0.18404384 | M70: =M69/I69-1 -> -0.30497671 | N70: =N69/J69-1 -> 0.83078204 | O70: =O69/K69-1 -> 0.15134888 | P70: =P69/L69-1 -> 0.12990686 | Q70: =Q69/M69-1 -> 0.18817636 | R70: =R69/W69-1 -> 0.094009867 | U70: =U69/T69-1 -> 0.65322536 | V70: =V69/U69-1 -> -0.027398414 | W70: =W69/V69-1 -> 0.17579829 | X70: NM | Y70: =Y69/X69-1 -> 0.15076643 | AA70: =AA69/Y69-1 -> 0.1212348 | AB70: =AB69/AA69-1 -> 0.091069705 | AC70: =AC69/AB69-1 -> 0.13772265 | AD70: =AD69/AC69-1 -> 0.12064766 | AE70: =AE69/AD69-1 -> 0.093580402
B71: Change in finished/unfinished goods | C71: 17034 | D71: =27170-C71 -> 10136 | E71: 1997 | F71: =U71-E71-D71-C71 -> -16734 | G71: 11082 | H71: -5484 | I71: 6491 | J71: =V71-I71-H71-G71 -> -15781 | K71: 17546 | L71: 13057 | M71: 1159 | N71: =W71-M71-L71-K71 -> -9672 | O71: 10938 | P71: 5779 | Q71: -11360 | R71: =Q71+P71+O71+N71 -> -4315 | T71: 21830 | U71: 12433 | V71: -3692 | W71: 22090 | X71: 17818 | Y71: -9653
B72: Own work capitalized | C72: 6676 | D72: =10806-C72 -> 4130 | E72: 6586 | F72: =U72-E72-D72-C72 -> 12347 | G72: 3450 | H72: 2737 | I72: 2052 | J72: =V72-I72-H72-G72 -> 5535 | K72: 2128 | L72: 2430 | M72: 2740 | N72: =W72-M72-L72-K72 -> 6685 | O72: 2089 | P72: 2621 | Q72: 1753 | R72: =Q72+P72+O72+N72 -> 13148 | T72: 34584 | U72: 29739 | V72: 13774 | W72: 13983 | X72: 13848 | Y72: 8316
B73: Other operating income | C73: 4705 | D73: =12073-C73 -> 7368 | E73: 26667 | F73: =U73-E73-D73-C73 -> 66092 | G73: 5450 | H73: 9434 | I73: 5804 | J73: =V73-I73-H73-G73 -> 13366 | K73: 4993 | L73: 2864 | M73: 11895 | N73: =W73-M73-L73-K73 -> 14250 | O73: 9831 | P73: 11284 | Q73: 6077 | R73: =Q73+P73+O73+N73 -> 41442 | T73: 33999 | U73: 104832 | V73: 34054 | W73: 34002 | X73: 33484 | Y73: 36714
B74: Cost of materials, supplies and services | C74: -173683 | D74: =-393255-C74 -> -219572 | E74: -227588 | F74: =U74-E74-D74-C74 -> -236307 | G74: -234434 | H74: -183964 | I74: -197315 | J74: =V74-I74-H74-G74 -> -187707 | K74: -235753 | L74: -228317 | M74: -101042 | N74: =W74-M74-L74-K74 -> -362785 | O74: -256973 | P74: -253224 | Q74: -108290 | R74: =Q74+P74+O74+N74 -> -981272 | T74: -558334 | U74: -857150 | V74: -803420 | W74: -927897 | X74: -410617 | Y74: -445879
B75: Personnel expenses | C75: -50052 | D75: =-121957-C75 -> -71905 | E75: -73155 | F75: =U75-E75-D75-C75 -> -73153 | G75: -70301 | H75: -61085 | I75: -61564 | J75: =V75-I75-H75-G75 -> -55547 | K75: -68186 | L75: -70973 | M75: -60011 | N75: =W75-M75-L75-K75 -> -95390 | O75: -82925 | P75: -83068 | Q75: -65123 | R75: =Q75+P75+O75+N75 -> -326506 | T75: -173645 | U75: -268265 | V75: -248497 | W75: -294560 | X75: -242556 | Y75: -276864
B76: Other operating expenses | C76: -33563 | D76: =-85015-C76 -> -51452 | E76: -60174 | F76: =U76-E76-D76-C76 -> -55610 | G76: -46972 | H76: -38006 | I76: -37113 | J76: =V76-I76-H76-G76 -> -43574 | K76: -39080 | L76: -45275 | M76: -32845 | N76: =W76-M76-L76-K76 -> -63623 | O76: -43189 | P76: -42356 | Q76: -35368 | R76: =Q76+P76+O76+N76 -> -184536 | T76: -102433 | U76: -200799 | V76: -165665 | W76: -180823 | X76: -138318 | Y76: -131373
B77: Operating Costs | C77: =SUM(C74:C76) -> -257298 | D77: =SUM(D74:D76) -> -342929 | E77: =SUM(E74:E76) -> -360917 | F77: =SUM(F74:F76) -> -365070 | G77: =SUM(G74:G76) -> -351707 | H77: =SUM(H74:H76) -> -283055 | I77: =SUM(I74:I76) -> -295992 | J77: =SUM(J74:J76) -> -286828 | ... R77: =SUM(R74:R76) -> -1492314 | T77: =SUM(T74:T76) -> -834412 | U77: =SUM(U74:U76) -> -1326214 | V77: =SUM(V74:V76) -> -1217582 | W77: =SUM(W74:W76) -> -1403280 | X77: =SUM(X74:X76) -> -791491 | Y77: =SUM(Y74:Y76) -> -854116 | Z77: =((W77/T77)^(1/(2024-2021)))-1 -> 0.18919917
B78: EBITDA | C78: =C69+C71+C72+C73+C74+C75+C76 -> 14404 | D78: =D69+D71+D72+D73+D74+D75+D76 -> 14229 | E78: =E69+E71+E72+E73+E74+E75+E76 -> 18122 | F78: =F69+F71+F72+F73+F74+F75+F76 -> 80169 | G78: =G69+G71+G72+G73+G74+G75+G76 -> 21359 | H78: =H69+H71+H72+H73+H74+H75+H76 -> 31488 | I78: =I69+I71+I72+I73+I74+I75+I76 -> 19096 | J78: =J69+J71+J72+J73+J74+J75+J76 -> 24959 | ... R78: =R69+R71+R72+R73+R74+R75+R76 -> 192054 | T78: =SUM(T69:T76) -> 46053 | U78: =SUM(U69:U76) -> 126924.65 | V78: =SUM(V69:V76) -> 96901.973 | W78: =SUM(W69:W76) -> 160468.18 | X78: =SUM(X69:X76) -> 124684 | Y78: =SUM(Y69:Y76) -> 160592.15 | Z78: =((Y78/T78)^(1/(2025-2021)))-1 -> 0.3665219 | AA78: =AA69*AA80 -> 197650.8 | AB78: =AB69*AB80 -> 179709 | AC78: =AC69*AC80 -> 218089.6 | AD78: =AD69*AD80 -> 259676.7 | AE78: =AE69*AE80 -> 334091
B79: Growth Y/Y | J79: =J78/F78-1 -> -0.68867018 | K79: =K78/G78-1 -> 0.7174025 | L79: =L78/H78-1 -> 0.21636814 | M79: =M78/I78-1 -> 0.61908253 | N79: =N78/J78-1 -> 1.1862655 | O79: =O78/K78-1 -> 0.32323756 | P79: =P78/L78-1 -> 0.38126942 | Q79: =Q78/M78-1 -> 0.16579339 | R79: =R78/W78-1 -> 0.19683544 | U79: =U78/T78-1 -> 1.7560561 | V79: =V78/U78-1 -> -0.23653939 | W79: =W78/V78-1 -> 0.65598462 | X79: NM | Y79: =Y78/X78-1 -> 0.28799325 | AA79: =AA78/Y78-1 -> 0.23076252 | AB79: =AB78/AA78-1 -> -0.090775246 | AC79: =AC78/AB78-1 -> 0.21357083 | AD79: =AD78/AC78-1 -> 0.19068814 | AE79: =AE78/AD78-1 -> 0.28656518
B80: margin% | C80: =C78/C$69 -> 0.059205794 | D80: =D78/D$69 -> 0.042408293 | E80: =E78/E$69 -> 0.052712565 | F80: =F78/F$69 -> 0.2090271 | G80: =G78/G$69 -> 0.060492687 | H80: =H78/H$69 -> 0.10228159 | I80: =I78/I$69 -> 0.063496497 | J80: =J78/J$69 -> 0.080860604 | ... R80: =R78/R$69 -> 0.11752942 | T80: =T78/T$69 -> 0.0582911 | U80: =U78/U$69 -> 0.097175828 | V80: =V78/V$69 -> 0.076279864 | W80: =W78/W$69 -> 0.10743193 | X80: =X78/X$69 -> 0.14651038 | Y80: =Y78/Y$69 -> 0.16398148 | AA80: 0.18 | AB80: 0.15 | AC80: 0.16 | AD80: 0.17 | AE80: 0.2
B81: margin% | I81: =#REF!/I$69 -> #REF! | K81: =#REF!/K$69 -> #REF! | L81: =#REF!/L$69 -> #REF! | M81: =#REF!/M$69 -> #REF! | O81: =#REF!/O$69 -> #REF! | P81: =#REF!/P$69 -> #REF! | T81: =#REF!/T$69 -> #REF! | U81: =#REF!/U$69 -> #REF! | V81: =#REF!/V$69 -> #REF! | W81: =#REF!/W$69 -> #REF!
B82: Depreciation & Amortization | C82: -19220 | D82: =-46599-C82 -> -27379 | E82: -29217 | F82: =U82-E82-D82-C82 -> -33417 | G82: -27856 | H82: -21686 | I82: -25143 | J82: =V82-I82-H82-G82 -> -18201 | K82: -22554 | L82: -23991 | M82: -21102 | N82: =W82-M82-L82-K82 -> -27054 | O82: -24896 | P82: -24418 | Q82: -22854 | R82: =Q82+P82+O82+N82 -> -99222 | T82: -71808 | U82: -109233 | V82: -92886 | W82: -94701 | X82: -84721 | Y82: -91777 | AA82: =-AA69*AA83 -> -98825.4 | AB82: =-AB69*AB83 -> -107825.4 | AC82: =-AC69*AC83 -> -122675.4 | AD82: =-AD69*AD83 -> -137475.9 | AE82: =-AE69*AE83 -> -150340.95
B83: D&A as a % of revenue | T83: =-T82/T69 -> 0.09089022 | U83: =-U82/U69 -> 0.083630776 | V83: =-V82/V69 -> 0.073118547 | W83: =-W82/W69 -> 0.063401427 | X83: =-X82/X69 -> 0.099551717 | Y83: =-Y82/Y69 -> 0.093713974 | AA83: 0.09 | AB83: 0.09 | AC83: 0.09 | AD83: 0.09 | AE83: 0.09
B84: EBIT/Operating result | C84: =C78+C82 -> -4816 | D84: =D78+D82 -> -13150 | E84: =E78+E82 -> -11095 | F84: =F78+F82 -> 46752 | G84: =G78+G82 -> -6497 | H84: =H78+H82 -> 9802 | I84: =I78+I82 -> -6047 | J84: =J78+J82 -> 6758 | ... R84: =R78+R82 -> 92832 | T84: =T78+T82 -> -25755 | U84: =U78+U82 -> 17691.653 | V84: =V78+V82 -> 4015.9726 | W84: =W78+W82 -> 65767.176 | X84: =X78+X82 -> 39963 | Y84: =Y78+Y82 -> 68815.151 | AA84: =AA78+AA82 -> 98825.4 | AB84: =AB78+AB82 -> 71883.6 | AC84: =AC78+AC82 -> 95414.2 | AD84: =AD78+AD82 -> 122200.8 | AE84: =AE78+AE82 -> 183750.05
B85: margin% | C85: =C84/C$69 -> -0.01979555 | D85: =D84/D$69 -> -0.039192427 | E85: =E84/E$69 -> -0.032272702 | F85: =F84/F$69 -> 0.12189793 | G85: =G84/G$69 -> -0.018400721 | H85: =H84/H$69 -> 0.031839561 | I85: =I84/I$69 -> -0.020107002 | J85: =J84/J$69 -> 0.021894145 | ... R85: =R84/R$69 -> 0.056809496 | T85: =T84/T$69 -> -0.03259912 | U85: =U84/U$69 -> 0.013545052 | V85: =V84/V$69 -> 0.0031613169 | W85: =W84/W$69 -> 0.044030505 | X85: =X84/X$69 -> 0.046958667 | Y85: =Y84/Y$69 -> 0.07026751
B86: Interest income | C86: 482 | D86: =1215-C86 -> 733 | E86: 5165 | F86: =U86-E86-D86-C86 -> 1610 | G86: 2057 | H86: 2685 | I86: 2547 | J86: =V86-I86-H86-G86 -> 3154 | K86: 1696 | L86: 2782 | M86: 4107 | N86: =W86-M86-L86-K86 -> -1376 | O86: 1091 | P86: 1407 | Q86: 1400 | R86: =Q86+P86+O86+N86 -> 2522 | T86: 1518 | U86: 7990 | V86: 10443 | W86: 7209 | X86: 8326 | Y86: 5329
B87: Interest expenses | C87: -5008 | D87: =-12304-C87 -> -7296 | E87: -12865 | F87: =U87-E87-D87-C87 -> -7826 | G87: -9744 | H87: -11403 | I87: -11033 | J87: =V87-I87-H87-G87 -> -14866 | K87: -11195 | L87: -11731 | M87: -7314 | N87: =W87-M87-L87-K87 -> -14806 | O87: -9243 | P87: -9594 | Q87: -7252 | R87: =Q87+P87+O87+N87 -> -40895 | T87: -18423 | U87: -32995 | V87: -47046 | W87: -45046 | X87: -31560 | Y87: -21663
B88: Growth Y/Y | J88: =J87/F87-1 -> 0.89956555 | K88: =K87/G87-1 -> 0.14891215 | L88: =L87/H87-1 -> 0.02876436 | M88: =M87/I87-1 -> -0.33707967 | N88: =N87/J87-1 -> -0.0040360554 | O88: =O87/K87-1 -> -0.17436356 | P88: =P87/L87-1 -> -0.18216691 | Q88: =Q87/M87-1 -> -0.0084768936 | U88: =U87/T87-1 -> 0.79096781 | V88: =V87/U87-1 -> 0.4258524 | W88: =W87/V87-1 -> -0.042511584 | Y88: =Y87/X87-1 -> -0.31359316
B89: Other financial income | C89: 3961 | D89: =11031-C89 -> 7070 | E89: 2731 | F89: =U89-E89-D89-C89 -> -8062 | G89: 764 | H89: 405 | I89: -439 | J89: =V89-I89-H89-G89 -> 499 | K89: 2998 | L89: 4238 | M89: -6093 | N89: =W89-M89-L89-K89 -> 20130 | O89: 1687 | P89: 2187 | Q89: 2106 | R89: =Q89+P89+O89+N89 -> 26110 | T89: 5671 | U89: 5700 | V89: 1229 | W89: 21273 | X89: 18106 | Y89: 6596
B90: Other financial expenses | C90: -1001 | D90: =-7451-C90 -> -6450 | E90: -7031 | F90: =U90-E90-D90-C90 -> -12594 | G90: -4965 | H90: -6733 | I90: -2784 | J90: =V90-I90-H90-G90 -> -14038 | K90: -3222 | L90: -2953 | M90: -2165 | N90: =W90-M90-L90-K90 -> -8640 | O90: -11305 | P90: -23646 | Q90: -2439 | R90: =Q90+P90+O90+N90 -> -46030 | T90: -6468 | U90: -27076 | V90: -28520 | W90: -16980 | X90: -4930 | Y90: -40266
B91: Financial expenses | C91: =SUM(C86:C90) -> -1566 | D91: =SUM(D86:D90) -> -5943 | E91: =SUM(E86:E90) -> -12000 | F91: =SUM(F86:F90) -> -26872 | G91: =SUM(G86:G90) -> -11888 | H91: =SUM(H86:H90) -> -15046 | I91: =SUM(I86:I90) -> -11709 | J91: =SUM(J86:J90) -> -25250.1 | ... R91: =SUM(R86:R90) -> -58293 | T91: =T86+T87+T89+T90 -> -17702 | U91: =U86+U87+U89+U90 -> -46381 | V91: =V86+V87+V89+V90 -> -63894 | W91: =W86+W87+W89+W90 -> -33544 | X91: =X86+X87+X89+X90 -> -10058 | Y91: =Y86+Y87+Y89+Y90 -> -50004
B92: Share of result of equity-accounted investees, net of tax | C92: 0 | D92: =0 -> 0 | E92: 0 | F92: =U92-E92-D92-C92 -> 0 | G92: 0 | H92: -83 | I92: -850 | J92: =V92-I92-H92-G92 -> 2353 | K92: -213 | L92: 596 | M92: -3100 | N92: =W92-M92-L92-K92 -> 0 | O92: 0 | P92: 0 | Q92: 0 | R92: 0 | T92: 0 | U92: 0 | V92: 1420 | W92: -2717 | X92: -2717 | Y92: 1125
B93: Result Before Tax | C93: =C84+C91+C92 -> -6382 | D93: =D84+D91+D92 -> -19093 | E93: =E84+E91+E92 -> -23095 | F93: =F84+F91+F92 -> 19880 | G93: =G84+G91+G92 -> -18385 | H93: =H84+H91+H92 -> -5327 | I93: =I84+I91+I92 -> -18606 | J93: =J84+J91+J92 -> -16139.1 | ... R93: =R84+R91+R92 -> 34539 | T93: =T84+T91+T92 -> -43457 | U93: =U84+U91+U92 -> -28689.347 | V93: =V84+V91+V92 -> -58458.027 | W93: =W84+W91+W92 -> 29506.176 | X93: =X84+X91+X92 -> 27188 | Y93: =Y84+Y91+Y92 -> 19936.151
B94: Margin% pre tax | C94: =C93/C69 -> -0.026232392 | D94: =D93/D69 -> -0.05690502 | E94: =E93/E69 -> -0.067177833 | F94: =F93/F69 -> 0.051833736 | G94: =G93/G69 -> -0.052069762 | H94: =H93/H69 -> -0.017303545 | J94: =J93/J69 -> -0.052286446 | K94: =K93/K69 -> 0.011807739 | L94: =L93/L69 -> 0.019867574 | M94: =M93/M69 -> -0.022721709 | N94: =N93/N69 -> 0.040383853 | O94: =O93/O69 -> 0.014367136 | P94: =P93/P69 -> -0.0028168786 | Q94: =Q93/Q69 -> 0.028205559 | R94: =R93/R69 -> 0.021136496 | T94: =T93/T69 -> -0.05500524 | U94: =U93/U69 -> -0.021965087 | V94: =V93/V69 -> -0.046017333 | W94: =W93/W69 -> 0.019754107 | X94: =X93/X69 -> 0.031947358 | Y94: =Y93/Y69 -> 0.020356908
B95: Income tax expense | C95: -805 | D95: =-1010-C95 -> -205 | E95: -5056 | F95: =U95-E95-D95-C95 -> -2019 | G95: 875 | H95: 162 | I95: 1984 | J95: =V95-I95-H95-G95 -> 10471 | K95: -466 | L95: -1773 | M95: -7 | N95: =W95-M95-L95-K95 -> -1091 | O95: -601 | P95: 2306 | Q95: -937 | R95: =Q95+P95+O95+N95 -> -323 | T95: -5923 | U95: -8085 | V95: 13492 | W95: -3337 | X95: -9102 | Y95: -8506
B96: Effective tax rate | C96: =IF(C95<0,C95/C93,"N/A") -> 0.12613601 | D96: =IF(D95<0,D95/D93,"N/A") -> 0.010736919 | E96: =IF(E95<0,E95/E93,"N/A") -> 0.21892184 | F96: =IF(F95<0,F95/F93,"N/A") -> -0.10155936 | G96: =IF(G95<0,G95/G93,"N/A") -> N/A | H96: =IF(H95<0,H95/H93,"N/A") -> N/A | I96: =IF(I95<0,I95/I93,"N/A") -> N/A | J96: =IF(J95<0,J95/J93,"N/A") -> N/A | ... R96: =IF(R95<0,R95/R93,"N/A") -> -0.0093517473 | T96: =T95/T93 -> 0.13629565 | U96: =U95/U93 -> 0.28181192 | V96: =V95/V93 -> -0.23079807 | W96: =W95/W93 -> -0.11309497 | X96: =-X95/X93 -> 0.33478005 | Y96: =-Y95/Y93 -> 0.4266621
B97: Net Income to continuing | C97: =C93+C95 -> -7187 | D97: =D93+D95 -> -19298 | E97: =E93+E95 -> -28151 | F97: =F93+F95 -> 17861 | G97: =G93+G95 -> -17510 | H97: =H93+H95 -> -5165 | I97: =I93+I95 -> -16622 | J97: =J93+J95 -> -5668.1004 | ... R97: =R93+R95 -> 34216 | T97: =T93+T95 -> -49380 | U97: =U93+U95 -> -36774.347 | V97: =V93+V95 -> -44966.027 | W97: =W93+W95 -> 26169.176 | X97: =X93+X95 -> 18086 | Y97: =Y93+Y95 -> 11430.151
B98: margin% | C98: =C97/C69 -> -0.029541241 | D98: =D97/D69 -> -0.057516005 | E98: =E97/E69 -> -0.081884528 | F98: =F97/F69 -> 0.046569535 | G98: =G97/G69 -> -0.049591599 | H98: =H97/H69 -> -0.016777324 | I98: =I97/I69 -> -0.055270149 | J98: =J97/J69 -> -0.018363157 | ... R98: =R97/R69 -> 0.020938833 | T98: =T97/T69 -> -0.062502215 | U98: =U97/U69 -> -0.02815511 | V98: =V97/V69 -> -0.035396622 | W98: =W97/W69 -> 0.017520017 | X98: =X97/X69 -> 0.02125202 | Y98: =Y97/Y69 -> 0.011671387
B99: Result from discotninued operation | C99: 0 | D99: 0 | E99: 0 | F99: =U99-E99-D99-C99 -> 0 | G99: 0 | H99: -419 | I99: 11335 | J99: =V99-I99-H99-G99 -> -4358 | K99: -991 | L99: -25630 | M99: -6234 | N99: =W99-M99-L99-K99 -> 42473 | O99: 0 | P99: 0 | Q99: -23524 | R99: =Q99+P99+O99+N99 -> 18949 | T99: 0 | U99: 0 | V99: 6558 | W99: 9618 | X99: 17701 | Y99: -14463
B100: Net Income | C100: =C97+C99 -> -7187 | D100: =D97+D99 -> -19298 | E100: =E97+E99 -> -28151 | F100: =F97+F99 -> 17861 | G100: =G97+G99 -> -17510 | H100: =H97+H99 -> -5584 | I100: =I97+I99 -> -5287 | J100: =J97+J99 -> -10026.1 | ... R100: =R97+R99 -> 53165 | T100: =T97+T99 -> -49380 | U100: =U97+U99 -> -36774.347 | V100: =V97+V99 -> -38408.027 | W100: =W97+W99 -> 35787.176 | X100: =X97+X99 -> 35787 | Y100: =Y97+Y99 -> -3032.8492 | Z100: =((W100/T100)^(1/(2024-2021)))-1 -> -1.8982394
B101: Result attributable to owners of AG | C101: -7108 | D101: =-26167-C101 -> -19059 | E101: -27866 | F101: 0 | G101: -17418 | H101: -5470 | I101: -5182 | K101: 1116 | L101: -20269 | M101: -10990 | N101: =W101-M101-L101-K101 -> 66232 | O101: 1116 | P101: 1116 | Q101: -17461 | R101: =Q101+P101+O101+N101 -> 51003 | T101: -49009 | U101: -36110 | V101: -37951 | W101: 36089 | X101: 36089 | Y101: -3071
B102: Non-controlling interest | C102: =C100-C101 -> -79 | D102: =D100-D101 -> -239 | E102: =E100-E101 -> -285 | F102: =F100-F101 -> 17861 | G102: =G100-G101 -> -92 | H102: =H100-H101 -> -114 | I102: =I100-I101 -> -105 | K102: =K100-K101 -> 1619.1489 | L102: =L100-L101 -> 108.02876 | M102: =M100-M101 -> -0.33707967 | N102: =N97-N101 -> -44502.004 | O102: =O97-O101 -> 4155.8256 | P102: =P97-P101 -> 29.817833 | Q102: =Q97-Q101 -> 23528.992 | R102: =R97-R101 -> -16787 | T102: =T97-T101 -> -371 | U102: =U97-U101 -> -664.34677 | V102: =V97-V101 -> -7015.0274 | W102: =W97-W101 -> -9919.8242 | X102: -302 | Y102: 38
...

Sheet SubsidiariesAffiliates
B1: Wholly Owned | C1: p.176 of 208 in 2024 annual
B2: Company | C2: Countries | D2: Acquisition Price | E2: Multiple | F2: Description
B3: Alpine Metal Tech | C3: CN|BR|DK|DE|AT|US|UK | F3: Special purpose machinery for steel, auto, aerospace, "lifecycle business." Product line incl. NUMTEC (aluminum wheel industry deburring); GEGA (autogenous touch cutting and scarfing) KNORR (optoelectronic measuring & image processingsystems - rails); MAKRA (clamping devices & testing aluminium wheels. AMAKON (conveyors); MAGNEMAG (paints and inkjets for plate pipe and long products); SIMULATION (fire training); INTERMATO (vertical lathes - machines for machining workpieces with diameters from 100mm to 6m).
B4: Asco Aerospace | C4: CA|US|DE|BE | F4: April 2022 Acquisition. Manufacture high-lift mechanisms and critical structure sub-assemblies. Portfolio: large complex fuselage, wing and landing gear components. Partnership with Lockheed Martin (F-35)
B5: ASTA Group | C5: BA|US|CN|AT|IN
B6: GeGa GmbH
B7: Immobiliere Asco NV
B8: IMT Intermato SRL
B9: Industrie Captial Alpha GmbH
B10: Insulated Conductors and Enameled Wires NV | C10: NL
B11: MAKRA GmbH
B12: MTC Aerosystems | C12: HU| US
B13: PPE Fios Esmaitados S.A
B14: S.R.I.F. NV | C14: BE
B15: Simulation live Fire Training Solution Inc. | C15: US (Pittsburgh)
B16: Universal Alloy Corp | C16: SG|RO|VN|US (Georgia) | F16: <= gloabal manufacturer of structural components and assemblies; 4,300 headcount. Acquired by Montana Tech components
B19: Subsidiary
B20: Cefival S.A. (90% ownership; Persan FR)
B21: PT IMT Intermo Asia | C21: ID
B23: Affiliated
B24: BeLighting
B25: Belairbus NV
B26: Flabel Corporation Nv
