Workbook

Sheet Tabelle1
B1: Date updated: | C1: 46181
B2: #VALUE! | E2: Engine Portfolio | K2: HQ: | L2: Dachauer Str. 665 80995 München Germany | R2: Military Applications
B3: Price: | C3: {=_FV(B2,"Price")} -> 328.6 | E3: Engine | F3: Manufacturer | G3: Application | H3: Thrust category (IBF) | I3: EIS | J3: MTU Service | R3: Eurofighter - EJ200 engines. 160 orders from spain and Germany. Fighter engine - key revenue driver
B4: 52w High: | C4: {=_FV(B2,"52 week high",TRUE)} -> 402.7 | E4: CF6 | F4: GE | G4: A300|747|C-5M | H4: 41,500-69,800 IBF | I4: 1971 | J4: Turbine & compressor parts | L4: Lease engines? | R4: A400- 178 in order. TP400-D6 engines. Good for aftermarket
B5: 52w Low: | C5: {=_FV(B2,"52 week low",TRUE)} -> 99.98 | E5: EJ200 | F5: JV | G5: Eurofighter Typhoon | H5: 20000 | I5: 2003 | J5: Engineering & parts for compressor. | L5: Spare parts | R5: Sikorsky Ch-53K- Germany and French orders appx. 480.
B6: Shares outstanding | C6: {=_FV(B2,"Shares outstanding",TRUE)/1000} -> 53909.16 | E6: GEnx | F6: GE | G6: 787 | H6: 66,500-76,100 | I6: 2012 | J6: Dev. Manu, assembly, repair of turbine center frame. | L6: Good if aircraft are aging? I.e., slower production lines = more business??
B7: P/E | C7: {=_FV(B2,"P/E",TRUE)} -> 17.8007 | D7: Attractive-ish | E7: GE9X | F7: GE | G7: 777X | H7: 100,000 | I7: planned | J7: dev,manu,assembly, repair of turbine center frame | R7: Commercial
B8: Market Cap | C8: {=_FV(B2,"Market cap",TRUE)/1000000} -> 20883.9 | E8: GTF (PW) | F8: PW | G8: A320 neo | A220| Embraer E-jets | I8: 2016 | J8: Manu high-speed, low pressure turbine + forward 4 stages of high pressure compressor | R8: V2500 - engine developed in 1980's. Demand for maintenance, repair, an d overhaul.
B9: (-) Cash | C9: =-Model!Y186 -> -1256 | E9: F110 | F9: GE | G9: F-16|F-15|F-15EX | H9: 29,000 | I9: 1986 | J9: Manu turbine disks for low-pressure compressor | L9: PW GTU engine: | R9: MTU has 38% market share
B10: (+) Debt | C10: =+Model!Y203+Model!Y194 -> 3230 | E10: F414 | F10: GE | G10: F/A-18 Super hornet | H10: 22,000 | I10: 1995 | J10: Parts for high and low pressure turbine | L10: In addition to being responsible for the high-speed low-pressure turbine and the first four stages of the high-pressure compressor, MTU also manufactures brush seals and nickel blisks for high-pressure compressor components that fall outside its design responsibility. Moreover, MTU in Munich is responsible for the final assembly of one-third of the production PW1100G-JM for the A320neo. | R10: Revenues from: spair parts, repairs, durability.
B11: (+) Pension | C11: =+Model!Y192+Model!Y199 -> 671 | E11: GP7000 | F11: GE/PW | G11: A380 | H11: 70,000-81,500 | I11: 2008 | J11: Various components + maintenance of low-pressure turbine | R11: PW 1000G-JM
B12: (+) Minority | C12: =+Model!Y190 -> 61 | E12: JT8D-200 | F12: PW | G12: MD-80 | H12: 18,500-21,700 | I12: 1980 | J12: Various components of various assemblies | R12: MTU has 35% market share for MRO shop visits
B13: Net Debt | C13: =C9+C10+C11+C12 -> 2706 | E13: Lazrac 04 | F13: Safran helicopter engines | G13: Dessault Alpha Jet | H13: 3,000 | I13: 1979 | J13: Hot section of engine | R13: Revenues from: MRO cost management, Repair technologies, maturing aftermarket contracts
B14: Enterprise Value | C14: =C8+C13 -> 23589.9 | E14: MTR390 | F14: MTU/RR | G14: Airbus Tiger heli | H14: 1467 shp (shaft horsepower) | I14: 2013 | J14: Manu high-pressure turbine and combustor | R14: PW LEAP-1A & LEAP-1B
B15: Equity BV | C15: =Model!Y191 -> 4375 | E15: PW300 | F15: PW | G15: Dassault Falcon | H15: 4,000-7,000 | I15: 1992 | R15: GEnx
B16: BVPS | C16: =C15/(C6/1000) -> 81.155039 | E16: PW500 | F16: PW | G16: Cessna citation/Excel/XLS | H16: 3,000-4,500 | I16: 1997 | J16: development of entire low-pressure turbine, incl. exit case and mixer | R16: GE90
B17: P/BV | C17: =C3/C16 -> 4.04904 | E17: PW800 | F17: PW | G17: Gulfstream G400/500/700| Dassault Falcon 6X | H17: 10,000-20,000 | I17: 2018 | J17: high-pressure compressor and low-pressure turbine | L17: Current backlog of Eur. 25B largely driven by PW GTF engine family (PW 1100G-JM) and V2500
E18: PW2000 | F18: PW | G18: 757|C-17 | H18: 37,500-43,000 | I18: 1984 | J18: high-pressure compressor and low-pressure turbine | L18: Received orders of $1.75 B at June 25 Paris Air Show
B19: EBITDA | C19: =Model!Y101 -> 1442 | E19: PW4000 | F19: PW | G19: 777-200(ER) & -300 | H19: 74,000-98,000 | I19: 1995 | J19: high-pressure compressor and low-pressure turbine
B20: TEV/2025 EBITDA | C20: =C14/C19 -> 16.359154 | E20: RB199 | F20: RR/MTU | G20: Panavia Tornado | H20: 16,000-17,000 | I20: 1979 | J20: Manu. Intermediate pressure and high-pressure compressor + intermediate pressure turbine
E21: T408 | F21: MTU/FiatAvio | G21: Sikorsky CH-53K | H21: 7,510 shp | I21: 2019 | J21: The power turbine
B22: OEM Segment | E22: T64 | F22: GE | G22: Sikorsky CH-53G/GS/GA/GE | H22: 4,330 shp | I22: 1972 | J22: Maintenance
B23: 5-yr avg EBITDA AVG | C23: =AVERAGE(Model!U19:Y19) -> 0.38599457 | E23: TP400-D6 | F23: RR/Safran/MTU | G23: A400M | H23: 11,000 shp | I23: 2013 | J23: Joint venture with RR and Safran
B24: TTM EBITDA | C24: =Model!Y18 -> 1141 | E24: V2500 | F24: PW/PAWEI/Japanese aero engines | G24: Airbus A319/320/321|MD-90| Embraer C-390 | H24: 22,000-33,000 | I24: 1989
B25: TEV/EBITDA Valuation multiple | C25: 15
B26: Implied Valuation | C26: =C24*C25 -> 17115 | E26: CEO | F26: Dr. Johannes Bussmann
B27: % of SOTP | C27: =C26/C$35 -> 0.7397882 | E27: CFO | F27: katja Garcia Vila
B29: MRO Segment | E29: No. employees | F29: 2025 | G29: 2024
B30: 5-yr avg EBITDA AVG | C30: =AVERAGE(Model!Y51,Model!X51,Model!W51,Model!V51) -> 0.06338443 | F30: 13345 | G30: 12508
B31: TTM EBITDA | C31: =Model!Y50 -> 301
B32: TEV/EBITDA Valuation multiple | C32: 20
B33: Implied Valuation | C33: =C31*C32 -> 6020
B34: % of SOTP | C34: =C33/C$35 -> 0.2602118
B35: SOTP Valuation | C35: =C26+C33 -> 23135
B36: Difference from actual | C36: =C35/C14 -> 0.98071632

Sheet Model
K1: 6Mo. Figures | P1: BS Restated:
C2: Q1'2024 | D2: Q2'2024 | E2: Q1'2025 | F2: Q2'2025 | G2: Q1'2026 | I2: 1H2022 | J2: 1H2023 | K2: 1H2024 | L2: 2H2024 | M2: 1H2025 | O2: =EOMONTH(P2,-12) -> 42369 | P2: =EOMONTH(Q2,-12) -> 42735 | Q2: =EOMONTH(R2,-12) -> 43100 | R2: =EOMONTH(S2,-12) -> 43465 | S2: =EOMONTH(T2,-12) -> 43830 | T2: =EOMONTH(U2,-12) -> 44196 | U2: =EOMONTH(V2,-12) -> 44561 | V2: 44926 | W2: 45291 | X2: 45657 | Y2: FY2025 | Z2: CAGR
B3: Year end stock price | M3: =Tabelle1!C3 -> 328.6 | O3: 90.1 | P3: 109.8 | Q3: 149.4 | R3: 158.4 | S3: 254.6 | T3: 213.4 | U3: 179.4 | V3: 202.2 | W3: 195.25 | X3: 322 | Y3: 355.3
A4: P.235 | B4: Segment information - OEM
A5: P.228 for cons. | B5: Commercial engine business | C5: 433 | D5: 470 | E5: 507 | F5: =M5-E5 -> 734 | G5: 479 | I5: 596 | J5: 832 | K5: 807 | L5: =X5-K5 -> 917 | M5: 1241 | O5: 2414 | P5: 2401.2 | Q5: 1289.9 | R5: 1602.8 | S5: 1537 | T5: 1052 | U5: 1066 | V5: 1335 | W5: 668 | X5: 1724 | Y5: 2178
B6: Military engine business | C6: 124 | D6: 148 | E6: 113 | F6: =M6-E6 -> 147 | G6: 142 | I6: 213 | J6: 229 | K6: 272 | L6: =X6-K6 -> 340 | M6: 260 | O6: 483.1 | P6: 504 | Q6: 444.9 | R6: 431.1 | S6: 459 | T6: 483 | U6: 482 | V6: 496 | W6: 538 | X6: 612 | Y6: 614
B7: other revenue | C7: 0 | D7: 0 | E7: 0 | F7: =M7-E7 -> -33 | I7: 0 | J7: 0 | K7: 56 | L7: =X7-K7 -> 62 | M7: -33 | O7: 0 | P7: 0 | Q7: 0 | R7: 0 | S7: 0 | T7: 0 | U7: 0 | V7: 0 | W7: 44 | X7: 118 | Y7: 129
A8: X | B8: Commercial & military (OEM segment) | C8: =SUM(C5:C7) -> 557 | D8: =SUM(D5:D7) -> 618 | E8: =SUM(E5:E7) -> 620 | F8: =SUM(F5:F7) -> 848 | G8: =SUM(G5:G7) -> 621 | I8: =SUM(I5:I7) -> 809 | J8: =SUM(J5:J7) -> 1061 | K8: =SUM(K5:K7) -> 1135 | L8: =SUM(L5:L7) -> 1319 | M8: =SUM(M5:M7) -> 1468 | O8: =SUM(O5:O7) -> 2897.1 | P8: =SUM(P5:P7) -> 2905.2 | Q8: =SUM(Q5:Q7) -> 1734.8 | R8: =SUM(R5:R7) -> 2033.9 | S8: =SUM(S5:S7) -> 1996 | T8: =SUM(T5:T7) -> 1535 | U8: =SUM(U5:U7) -> 1548 | V8: =SUM(V5:V7) -> 1831 | ... Y8: =SUM(Y5:Y7) -> 2921 | Z8: =(X8/O8)^(1/(2024-2015))-1 -> -0.018274393
B9: Y/Y growth | P9: =P8/O8-1 -> 0.0027958993 | Q9: =Q8/P8-1 -> -0.40286383 | R9: =R8/Q8-1 -> 0.17241181 | S9: =S8/R8-1 -> -0.018634151 | T9: =T8/S8-1 -> -0.23096192 | U9: =U8/T8-1 -> 0.0084690554 | V9: =V8/U8-1 -> 0.18281654 | W9: =W8/V8-1 -> -0.31731294 | ... Y9: =Y8/X8-1 -> 0.19030155
B10: Adjusted revenue | I10: 809 | J10: 1061 | K10: 1176 | L10: =X10-K10 -> 1355 | M10: 1411 | O10: 2897.1 | P10: 2905.2 | Q10: 1734.8 | R10: 2033.9 | S10: 1996 | T10: 1535 | U10: 1548 | V10: 1831 | W10: 2212 | X10: 2531 | Y10: 2875
B11: Gross profit | I11: 182 | J11: 348 | K11: 358 | L11: =X11-K11 -> 387 | M11: 571 | O11: 378.9 | P11: 422.6 | Q11: 470 | R11: 549.1 | S11: 615 | T11: 286 | U11: 351 | V11: 500 | W11: 266 | X11: 745 | Y11: 1164
B12: margin% | I12: =I11/I$8 -> 0.2249691 | J12: =J11/J$8 -> 0.32799246 | K12: =K11/K$8 -> 0.3154185 | L12: =L11/L$8 -> 0.29340409 | M12: =M11/M$8 -> 0.38896458 | O12: =O11/O$8 -> 0.13078596 | P12: =P11/P$8 -> 0.14546331 | Q12: =Q11/Q$8 -> 0.2709246 | R12: =R11/R$8 -> 0.26997394 | S12: =S11/S$8 -> 0.30811623 | T12: =T11/T$8 -> 0.18631922 | U12: =U11/U$8 -> 0.22674419 | V12: =V11/V$8 -> 0.27307482 | ... Y12: =Y11/Y$8 -> 0.39849367 | Z12: =(X12/O12)^(1/(2024-2015))-1 -> 0.098084147
B13: Amortization of intangibles | I13: -21 | J13: -24 | K13: -26 | L13: =X13-K13 -> -29 | M13: -28 | O13: -59.7 | P13: fina | Q13: -29.1 | R13: -31 | S13: -37 | T13: -39 | U13: -41 | V13: -45 | W13: -50 | X13: -55 | Y13: -58
B14: Depreciation of PPE | C14: -54 | D14: =K14-C14 -> -6 | E14: -58 | F14: =M14-E14 -> -7 | I14: -56 | J14: -56 | K14: -60 | L14: =X14-K14 -> -66 | M14: -65 | O14: -74.5 | P14: -76.2 | Q14: -47.3 | R14: -49 | S14: -53 | T14: -102 | U14: -46 | V14: -47 | W14: -115 | X14: -126 | Y14: -132
B15: Non-cash amortization of program assets | I15: -24 | J15: -23 | K15: -25 | L15: =X15-K15 -> -100 | M15: -25 | O15: 0 | P15: 0 | Q15: -79.7 | R15: -82 | S15: -93 | T15: -51 | U15: -115 | V15: -113 | W15: -50 | X15: -125 | Y15: -49
B16: Impairment losses | I16: -65 | J16: 0 | K16: 0 | L16: =X16-K16 -> -31 | M16: 0 | O16: 0 | P16: 0 | Q16: 0 | R16: 0 | S16: 0 | T16: -71 | U16: -83 | V16: -65 | W16: 0 | X16: -31 | Y16: 0
B17: D&A/adjustments/impairments | I17: =I16+I15+I14+I13 -> -166 | J17: =J16+J15+J14+J13 -> -103 | K17: =K16+K15+K14+K13 -> -111 | L17: =L16+L15+L14+L13 -> -226 | M17: =M16+M15+M14+M13 -> -118 | O17: =O16+O15+O14+O13 -> -134.2 | P17: =P16+P15+P14+P13 -> #VALUE! | Q17: =Q16+Q15+Q14+Q13 -> -156.1 | R17: =R16+R15+R14+R13 -> -162 | S17: =S16+S15+S14+S13 -> -183 | T17: =T16+T15+T14+T13 -> -263 | U17: =U16+U15+U14+U13 -> -285 | V17: =V16+V15+V14+V13 -> -270 | ... Y17: =Y16+Y15+Y14+Y13 -> -239
B18: Segment-level EBITDA | Q18: =Q22-Q17 -> 385.4 | R18: =R22-R17 -> 544.6 | S18: =S22-S17 -> 630 | T18: =T22-T17 -> 400 | U18: =U22-U17 -> 494 | V18: =V22-V17 -> 538 | W18: =W22-W17 -> 723 | X18: =X22-X17 -> 854 | Y18: =Y22-Y17 -> 1141 | Z18: =(Y18/U18)^(1/(2024-2015))-1 -> 0.097476957
B19: margin% | Q19: =Q18/Q$8 -> 0.22215817 | R19: =R18/R$8 -> 0.26776144 | S19: =S18/S$8 -> 0.31563126 | T19: =T18/T$8 -> 0.26058632 | U19: =U18/U$8 -> 0.31912145 | V19: =V18/V$8 -> 0.29382851 | W19: =W18/W$8 -> 0.5784 | X19: =X18/X$8 -> 0.34800326 | Y19: =Y18/Y$8 -> 0.39061965
B20: Valuation multiple | X20: 10 | Y20: 10
Y21: =Y18*Y20 -> 11410
B22: EBIT | C22: 130 | D22: =K22-C22 -> 108 | E22: 176 | F22: =M22-E22 -> 286 | G22: 188 | I22: 67 | J22: 223 | K22: 238 | L22: =X22-K22 -> 279 | M22: 462 | O22: 232.8 | P22: 273.7 | Q22: 229.3 | R22: 382.6 | S22: 447 | T22: 137 | U22: 209 | V22: 268 | W22: 508 | X22: 517 | Y22: 902
B23: margin% | C23: =C22/C$8 -> 0.23339318 | D23: =D22/D$8 -> 0.17475728 | E23: =E22/E$8 -> 0.28387097 | F23: =F22/F$8 -> 0.33726415 | G23: =G22/G$8 -> 0.30273752 | I23: =I22/I$8 -> 0.082818294 | J23: =J22/J$8 -> 0.21017908 | K23: =K22/K$8 -> 0.20969163 | L23: =L22/L$8 -> 0.21152388 | M23: =M22/M$8 -> 0.3147139 | O23: =O22/O$8 -> 0.080356218 | P23: =P22/P$8 -> 0.094210381 | Q23: =Q22/Q$8 -> 0.13217662 | R23: =R22/R$8 -> 0.18811151 | S23: =S22/S$8 -> 0.2239479 | T23: =T22/T$8 -> 0.089250814 | U23: =U22/U$8 -> 0.13501292 | V23: =V22/V$8 -> 0.1463681 | ... Y23: =Y22/Y$8 -> 0.30879836
B24: Special items | I24: =9+12+53+24 -> 98 | J24: =9+11+19 -> 39 | O24: =21.6+30.6 -> 52.2 | P24: =18.7+29.1 -> 47.8 | Q24: =18.6+30.2 -> 48.8 | R24: =18.6+30.2 -> 48.8 | S24: =19+30 -> 49 | T24: =18+27+24+73 -> 142 | U24: =18+23-13+83 -> 111 | V24: =18+23+53+24 -> 118 | W24: =18+23+932+23 -> 996 | X24: =18+25+52 -> 95 | Y24: =18+26-73 -> -29
B25: Adjusted EBIT | C25: 130 | D25: 252 | E25: 176 | F25: 357 | I25: =I22+I24 -> 165 | J25: =J22+J24 -> 262 | K25: 288 | L25: =X25-K25 -> 324 | M25: 415 | O25: =O22+O24 -> 285 | P25: =P22+P24 -> 321.5 | Q25: =Q22+Q24 -> 278.1 | R25: =R22+R24 -> 431.4 | S25: =S22+S24 -> 496 | T25: =T22+T24 -> 279 | U25: =U22+U24 -> 320 | V25: =V22+V24 -> 386 | ... Y25: =Y22+Y24 -> 873
B26: Profit/loss of companies accounted for using equity meth. | I26: 4 | J26: 9 | K26: 12 | L26: =X26-K26 -> 28 | M26: 38 | O26: -2.4 | P26: 1.1 | Q26: 5.3 | R26: 11.4 | S26: 30 | T26: 35 | U26: 44 | V26: 9 | W26: 27 | X26: 40 | Y26: 51
B27: Carrying amount of companeis accounted for using the equity meth | I27: 311 | J27: 307 | K27: 342 | L27: =X27-K27 -> 0 | M27: 311 | O27: 27.6 | P27: 55.8 | Q27: 137.9 | R27: 250.6 | S27: 325 | T27: 323 | U27: 339 | V27: 311 | W27: 305 | X27: 342 | Y27: 292
B28: Assets | I28: 7793 | J28: 7798 | K28: 10684 | L28: =X28-K28 -> 0 | M28: 9846 | O28: 4589.5 | P28: 5115.6 | Q28: 5434.4 | R28: 6034.5 | S28: 6687 | T28: 6996 | U28: 7189 | V28: 7793 | W28: 8802 | X28: 10684 | Y28: 10686
B29: Liabilities | I29: 5242 | J29: 5177 | K29: 7885 | L29: =X29-K29 -> 0 | M29: 6670 | O29: 3429.4 | P29: 3758.8 | Q29: 3795.6 | R29: 4118.2 | S29: 4550 | T29: 4698 | U29: 4729 | V29: 5247 | W29: 6375 | X29: 7885 | Y29: 7021
B30: Material other non-cash items | I30: 16 | J30: -5 | K30: 19 | L30: =X30-K30 -> 15 | M30: -82 | O30: 76.4 | P30: 33.7 | Q30: -35.9 | R30: 41.4 | S30: 34 | T30: -11 | U30: 36 | V30: 8 | W30: 2 | X30: 34 | Y30: -89
B31: CapEx: | L31: =X31-K31 -> 0
B32: Intangible assets | I32: 27 | J32: 28 | K32: 36 | L32: =X32-K32 -> -119 | M32: 38 | O32: -160.9 | P32: -114.3 | Q32: -68.5 | R32: -71.8 | S32: -78 | T32: -42 | U32: -54 | V32: -58 | W32: -78 | X32: -83 | Y32: -85
B33: PPE | I33: 41 | J33: 101 | K33: 122 | L33: =X33-K33 -> -385 | M33: 67 | O33: -102.9 | P33: -112.1 | Q33: -116.4 | R33: -127.5 | S33: -209 | T33: -160 | U33: -148 | V33: -157 | W33: -218 | X33: -263 | Y33: -193
B34: Acquired program assets, dev work, and other assets | I34: 24 | J34: 21 | K34: 47 | L34: =X34-K34 -> -100 | M34: 37 | O34: 0 | P34: 0 | Q34: -45.5 | R34: -59.5 | S34: -16 | T34: -12 | U34: -18 | V34: -26 | W34: -2 | X34: -53 | Y34: -38
B35: Total CAPEX | I35: =I32+I33+I34 -> 92 | J35: =J32+J33+J34 -> 150 | K35: =K32+K33+K34 -> 205 | L35: =L32+L33+L34 -> -604 | M35: =M32+M33+M34 -> 142 | O35: =O32+O33+O34 -> -263.8 | P35: =P32+P33+P34 -> -226.4 | Q35: =Q32+Q33+Q34 -> -230.4 | R35: =R32+R33+R34 -> -258.8 | S35: =S32+S33+S34 -> -303 | T35: =T32+T33+T34 -> -214 | U35: =U32+U33+U34 -> -220 | V35: =V32+V33+V34 -> -241 | ... Y35: =Y32+Y33+Y34 -> -316
B36: Perecent of revenue | I36: =I35/I$8 -> 0.11372064 | J36: =J35/J$8 -> 0.14137606 | K36: =K35/K$8 -> 0.18061674 | L36: =L35/L$8 -> -0.45792267 | M36: =M35/M$8 -> 0.096730245 | O36: =-O35/O$8 -> 0.091056574 | P36: =-P35/P$8 -> 0.07792923 | Q36: =-Q35/Q$8 -> 0.1328107 | R36: =-R35/R$8 -> 0.12724323 | S36: =-S35/S$8 -> 0.15180361 | T36: =-T35/T$8 -> 0.13941368 | U36: =-U35/U$8 -> 0.14211886 | V36: =-V35/V$8 -> 0.13162206 | ... Y36: =-Y35/Y$8 -> 0.10818213
B37: Segment information - MRO
B38: Commercial maintenance business | C38: 1141 | D38: 1163 | E38: 1521 | F38: =M38-E38 -> 1234 | G38: 1640 | I38: 1711 | J38: 2081 | K38: 2214 | L38: =X38-K38 -> 2649 | M38: 2755 | O38: 1580.6 | P38: 1914.4 | Q38: 2285.3 | R38: 2799.8 | S38: 2711 | T38: 2522 | U38: 2741 | V38: 3616 | W38: 4141 | X38: 4863 | Y38: 5783
B39: other revenue | C39: 0 | D39: 0 | E39: 0 | F39: =M39-E39 -> 45 | I39: 0 | J39: 0 | K39: 90 | L39: =X39-K39 -> 113 | M39: 45 | O39: 0 | P39: 0 | Q39: 0 | R39: 0 | S39: 0 | T39: 0 | U39: 0 | V39: 0 | W39: 83 | X39: 203 | Y39: 177
A40: X | B40: Commercial maintenance buisness (MRO) | C40: =SUM(C37:C39) -> 1141 | D40: =SUM(D37:D39) -> 1163 | E40: =SUM(E37:E39) -> 1521 | F40: =SUM(F37:F39) -> 1279 | G40: =SUM(G37:G39) -> 1640 | I40: =I38+I39 -> 1711 | J40: =J38+J39 -> 2081 | K40: =K38+K39 -> 2304 | L40: =L38+L39 -> 2762 | M40: =M38+M39 -> 2800 | O40: =O38+O39 -> 1580.6 | P40: =P38+P39 -> 1914.4 | Q40: =Q38+Q39 -> 2285.3 | R40: =R38+R39 -> 2799.8 | S40: =S38+S39 -> 2711 | T40: =T38+T39 -> 2522 | U40: =U38+U39 -> 2741 | V40: =V38+V39 -> 3616 | ... Y40: =Y38+Y39 -> 5960 | Z40: =(X40/O40)^(1/(2024-2015))-1 -> 0.13816388
B41: Y/Y growth | P41: =P40/O40-1 -> 0.21118563 | Q41: =Q40/P40-1 -> 0.19374216 | R41: =R40/Q40-1 -> 0.22513456 | S41: =S40/R40-1 -> -0.031716551 | T41: =T40/S40-1 -> -0.069715972 | U41: =U40/T40-1 -> 0.086835845 | V41: =V40/U40-1 -> 0.31922656 | W41: =W40/V40-1 -> 0.16814159 | ... Y41: =Y40/X40-1 -> 0.17647059
B42: Adjusted revenue | I42: 1711 | J42: 2081 | K42: 2304 | L42: =X42-K42 -> 2762 | M42: 2799 | O42: 1580.6 | P42: 1914.4 | Q42: 2285.3 | R42: 2799.8 | S42: 2711 | T42: 2522 | U42: 2741 | V42: 3616 | W42: 4225 | X42: 5066 | Y42: 5960
B43: Gross profit | I43: 169 | J43: 171 | K43: 209 | L43: =X43-K43 -> 276 | M43: 257 | O43: 201.1 | P43: 234.8 | Q43: 239.8 | R43: 301.3 | S43: 315 | T43: 205 | U43: 237 | V43: 357 | W43: 383 | X43: 485 | Y43: 1164 | Z43: =(X43/O43)^(1/(2024-2015))-1 -> 0.10276018
B44: margin% | I44: =I43/I$8 -> 0.20889988 | J44: =J43/J$8 -> 0.16116871 | K44: =K43/K$8 -> 0.18414097 | L44: =L43/L$8 -> 0.20924943 | M44: =M43/M$8 -> 0.17506812 | O44: =O43/O$8 -> 0.069414242 | P44: =P43/P$8 -> 0.080820598 | Q44: =Q43/Q$8 -> 0.13822919 | R44: =R43/R$8 -> 0.14813904 | S44: =S43/S$8 -> 0.15781563 | T44: =T43/T$8 -> 0.13355049 | U44: =U43/U$8 -> 0.15310078 | V44: =V43/V$8 -> 0.19497542 | ... Y44: =Y43/Y$8 -> 0.39849367 | Z44: =(X44/O44)^(1/(2024-2015))-1 -> 0.12328758
B45: Amortization of intangibles | I45: -3 | J45: -4 | K45: 4 | L45: =X45-K45 -> 5 | M45: 5 | O45: -10.1 | P45: -10.6 | Q45: -10.4 | R45: -6.7 | S45: -7 | T45: -7 | U45: -7 | V45: -9 | W45: 8 | X45: 9 | Y45: 9
B46: Depreciation of PPE | C46: 32 | D46: =K46-C46 -> 27 | E46: 45 | F46: =M46-E46 -> 34 | I46: -37 | J46: -45 | K46: 59 | L46: =X46-K46 -> 73 | M46: 79 | O46: -23.3 | P46: -25.2 | Q46: 0 | R46: 0 | S46: 0 | T46: 0 | U46: 0 | V46: 0 | W46: 102 | X46: 132 | Y46: 164
B47: Non-cash amortization of program assets | I47: 0 | J47: 0 | L47: =X47-K47 -> 0 | O47: 0 | P47: 0 | Q47: -27 | R47: -25.9 | S47: -66 | T47: -73 | U47: -66 | V47: -77 | W47: 0 | X47: 0
B48: Impairment losses | I48: 0 | J48: -2 | K48: 1 | L48: =X48-K48 -> 0 | M48: 3 | O48: -0.4 | P48: -0.1 | Q48: 0 | R48: -5.9 | S48: -5 | T48: -6 | U48: 0 | V48: -1 | W48: 6 | X48: 1 | Y48: 3
B49: D&A/adjustments/impairments | I49: =I48+I47+I46+I45 -> -40 | J49: =J48+J47+J46+J45 -> -51 | K49: =K48+K47+K46+K45 -> 64 | L49: =L48+L47+L46+L45 -> 78 | M49: =M48+M47+M46+M45 -> 87 | O49: =O48+O47+O46+O45 -> -33.8 | P49: =P48+P47+P46+P45 -> -35.9 | Q49: =Q48+Q47+Q46+Q45 -> -37.4 | R49: =R48+R47+R46+R45 -> -38.5 | S49: =S48+S47+S46+S45 -> -78 | T49: =T48+T47+T46+T45 -> -86 | U49: =U48+U47+U46+U45 -> -73 | V49: =V48+V47+V46+V45 -> -87 | ... Y49: =Y48+Y47+Y46+Y45 -> 176
B50: Segment-level EBITDA | Q50: =Q52-Q49 -> 229.3 | R50: =R52-R49 -> 275.8 | S50: =S52-S49 -> 337 | T50: =T52-T49 -> 211 | U50: =U52-U49 -> 219 | V50: =V52-V49 -> 326 | W50: =W52-W49 -> 230 | X50: =X52-X49 -> 296 | Y50: =Y52-Y49 -> 301 | Z50: =(Y50/U50)^(1/(2024-2015))-1 -> 0.035969409 | AA50: <=5-yr CAGR
B51: margin% | Q51: =Q50/Q$40 -> 0.10033694 | R51: =R50/R$40 -> 0.098507036 | S51: =S50/S$40 -> 0.12430837 | T51: =T50/T$40 -> 0.083663759 | U51: =U50/U$40 -> 0.079897848 | V51: =V50/V$40 -> 0.090154867 | W51: =W50/W$40 -> 0.054450758 | X51: =X50/X$40 -> 0.058428741 | Y51: =Y50/Y$40 -> 0.050503356 | Z51: =AVERAGE(U51:Y51) -> 0.066687114
B52: EBIT | C52: 88 | D52: =K49-C52 -> -24 | E52: 125 | F52: =M49-E52 -> -38 | G52: 132 | I52: 116 | J52: 159 | K52: 183 | L52: =X52-K52 -> 255 | M52: 241 | O52: 152.7 | P52: 179.1 | Q52: 191.9 | R52: 237.3 | S52: 259 | T52: 125 | U52: 146 | V52: 239 | W52: 346 | X52: 438 | Y52: 477
B53: margin% | C53: =C52/C$8 -> 0.15798923 | D53: =D52/D$8 -> -0.038834951 | E53: =E52/E$8 -> 0.2016129 | F53: =F52/F$8 -> -0.044811321 | G53: =G52/G$8 -> 0.21256039 | I53: =I52/I$8 -> 0.1433869 | J53: =J52/J$8 -> 0.14985862 | K53: =K52/K$8 -> 0.16123348 | L53: =L52/L$8 -> 0.19332828 | M53: =M52/M$8 -> 0.16416894 | O53: =O52/O$8 -> 0.05270788 | P53: =P52/P$40 -> 0.093554116 | Q53: =Q52/Q$40 -> 0.08397147 | R53: =R52/R$40 -> 0.084756054 | S53: =S52/S$40 -> 0.095536702 | T53: =T52/T$40 -> 0.049563838 | U53: =U52/U$40 -> 0.053265232 | V53: =V52/V$40 -> 0.066095133 | W53: =W52/W$40 -> 0.081912879 | ... Y53: =Y52/Y$40 -> 0.080033557
B54: Special items | C54: -130 | D54: =K54-C54 -> 130 | E54: -176 | I54: =1+8 -> 9 | J54: =0-21+3 -> -18 | L54: =X54-K54 -> 0 | O54: 2.5 | P54: 2.4 | Q54: 2.5 | R54: 2.4 | S54: 2 | T54: =2+9 -> 11 | U54: =2 -> 2 | V54: =2+27 -> 29 | W54: =-21+3 -> -18 | X54: 0 | Y54: 0
B55: Adjusted EBIT | I55: =I52+I54 -> 125 | J55: =J52+J54 -> 141 | K55: =K52+K54 -> 183 | L55: =X55-K55 -> 255 | M55: =M52+M54 -> 241 | O55: =O52+O54 -> 155.2 | P55: =P52+P54 -> 181.5 | Q55: =Q52+Q54 -> 194.4 | R55: =R52+R54 -> 239.7 | S55: =S52+S54 -> 261 | T55: =T52+T54 -> 136 | U55: =U52+U54 -> 148 | V55: =V52+V54 -> 268 | ... X55: =X52+X54 -> 438 | Y55: 478
B56: Profit/loss of companies accounted for using equity meth. | I56: 24 | J56: 32 | K56: 33 | L56: =X56-K56 -> 49 | M56: 64 | O56: 31.5 | P56: 27.5 | Q56: 37.1 | R56: 32.4 | S56: 50 | T56: 34 | U56: 81 | V56: 60 | W56: 70 | X56: 82 | Y56: 106
B57: Carrying amount of companies accounted for using the equity meth | I57: 317 | J57: 298 | K57: 385 | L57: =X57-K57 -> 0 | M57: 350 | O57: 140.4 | P57: 146.1 | Q57: 153.6 | R57: 176.3 | S57: 213 | T57: 233 | U57: 611 | V57: 628 | W57: 338 | X57: 385 | Y57: 396
B58: Assets | I58: 3056 | J58: 2907 | K58: 3866 | L58: =X58-K58 -> 0 | M58: 3889 | O58: 1273.2 | P58: 1479.6 | Q58: 1565.9 | R58: 1845.9 | S58: 2361 | T58: 2344 | U58: 9704 | V58: 10849 | W58: 3273 | X58: 3866 | Y58: 4429
B59: Liabilities | I59: 2158 | J59: 1933 | K59: 2611 | L59: =X59-K59 -> 0 | M59: 2522 | O59: 791.7 | P59: 994.8 | Q59: 1041.4 | R59: 1277.2 | S59: 1736 | T59: 1667 | U59: 6606 | V59: 7406 | W59: 2267 | X59: 2611 | Y59: 3033
B60: Material other non-cash items | I60: 15 | J60: 18 | K60: 1 | L60: =X60-K60 -> 5 | M60: -23 | O60: -0.5 | P60: 3.6 | Q60: -8 | R60: 25.7 | S60: 15 | T60: 17 | U60: 42 | V60: 43 | W60: 31 | X60: 6 | Y60: -18
B61: CapEx: | L61: =X61-K61 -> 0
B62: Intangible assets | I62: 1 | J62: 0 | K62: 0 | L62: =X62-K62 -> -100 | M62: 112 | O62: -18.9 | P62: -1.1 | Q62: -0.8 | R62: -1.5 | S62: -51 | T62: -2 | U62: -83 | V62: -60 | W62: -4 | X62: -100 | Y62: -161 | Z62: -1
B63: PPE | I63: 61 | J63: 62 | K63: 124 | L63: =X63-K63 -> -464 | M63: 209 | O63: -27 | P63: -47.3 | Q63: -56.9 | R63: -72 | S63: -141 | T63: -123 | U63: -301 | V63: -387 | W63: -211 | X63: -340 | Y63: -426
B64: Acquired program assets, dev work, and other assets | I64: 0 | J64: 0 | K64: 0 | L64: =X64-K64 -> 0 | M64: 0 | O64: 0 | P64: 0 | Q64: 0 | R64: 0 | S64: 0 | T64: 0 | U64: -18 | V64: -26 | W64: -2 | X64: 0 | Y64: 0
B65: Total CAPEX | I65: =I62+I63+I64 -> 62 | J65: =J62+J63+J64 -> 62 | K65: =K62+K63+K64 -> 124 | L65: =L62+L63+L64 -> -564 | M65: =M62+M63+M64 -> 321 | O65: =O62+O63+O64 -> -45.9 | P65: =P62+P63+P64 -> -48.4 | Q65: =Q62+Q63+Q64 -> -57.7 | R65: =R62+R63+R64 -> -73.5 | S65: =S62+S63+S64 -> -192 | T65: =T62+T63+T64 -> -125 | U65: =U62+U63+U64 -> -402 | V65: =V62+V63+V64 -> -473 | ... Y65: =Y62+Y63+Y64 -> -587
B66: Perecent of revenue | I66: =I65/I$8 -> 0.076637824 | J66: =J65/J$8 -> 0.058435438 | K66: =K65/K$8 -> 0.1092511 | L66: =L65/L$8 -> -0.42759666 | M66: =M65/M$8 -> 0.21866485 | O66: =-O65/O$40 -> 0.029039605 | P66: =-P65/P$40 -> 0.025282073 | Q66: =-Q65/Q$40 -> 0.025248326 | R66: =-R65/R$40 -> 0.026251875 | S66: =-S65/S$40 -> 0.070822575 | T66: =-T65/T$40 -> 0.049563838 | U66: =-U65/U$40 -> 0.1466618 | V66: =-V65/V$40 -> 0.13080752 | ... Y66: =-Y65/Y$40 -> 0.098489933
B68: Consolidation | C68: -24 | D68: =K68-C68 -> 24 | E68: -49 | F68: =M68-E68 -> 49 | I68: 0 | J68: 0 | O68: -42.4 | P68: -86.9 | Q68: -122.7 | R68: -266.6 | S68: -79 | T68: -80 | U68: -101 | V68: -117 | W68: -111 | X68: -109 | Y68: -118
B69: Adjusted revenue | C69: -24 | D69: =K69-C69 -> -26 | E69: -49 | F69: =M69-E69 -> -21 | I69: -51 | J69: -49 | K69: -50 | L69: =X69-K69 -> -59 | M69: -70 | O69: -42.4 | P69: -86.9 | Q69: -122.7 | R69: -266.6 | S69: -79 | T69: -80 | U69: -101 | V69: -117 | W69: -111 | X69: -109 | Y69: -118
B70: Gross profit | I70: 0 | J70: 1 | K70: 2 | L70: =X70-K70 -> 0 | M70: 1 | O70: 0.3 | P70: 0.5 | Q70: 1.1 | R70: 0.9 | S70: 1 | T70: 1 | U70: -1 | V70: -2 | W70: 1 | X70: 2 | Y70: 0
B71: Amortization of intangibles | I71: 0 | J71: 0 | L71: =X71-K71 -> 0 | O71: 0 | P71: 0 | Q71: 0 | R71: 0 | S71: 0 | T71: 0 | U71: 0 | V71: 0 | W71: 0 | X71: 0
B72: Depreciation of PPE | I72: 0 | J72: 0 | L72: =X72-K72 -> 0 | O72: 0 | P72: 0 | Q72: 0 | R72: 0 | S72: 0 | T72: 0 | U72: 0 | V72: 0 | W72: 0 | X72: 0
B73: Non-cash amortization of program assets | I73: 0 | J73: 0 | L73: =X73-K73 -> 0 | O73: 0 | P73: 0 | Q73: 0 | R73: 0 | S73: 0 | T73: 0 | U73: 0 | V73: 0 | W73: 0 | X73: 0
B74: Impairment losses | I74: 0 | J74: 0 | L74: =X74-K74 -> 0 | O74: 0 | P74: 0 | Q74: 0 | R74: 0 | S74: 0 | T74: 0 | U74: 0 | V74: 0 | W74: 0 | X74: 0
B75: D&A/adjustments/impairments | I75: =I74+I73+I72+I71 -> 0 | J75: =J74+J73+J72+J71 -> 0 | L75: =X75-K75 -> 0 | O75: =O74+O73+O72+O71 -> 0 | P75: =P74+P73+P72+P71 -> 0 | Q75: =Q74+Q73+Q72+Q71 -> 0 | R75: =R74+R73+R72+R71 -> 0 | S75: =S74+S73+S72+S71 -> 0 | T75: =T74+T73+T72+T71 -> 0 | U75: =U74+U73+U72+U71 -> 0 | V75: =V74+V73+V72+V71 -> 0 | ... X75: =X74+X73+X72+X71 -> 0
B76: EBIT | I76: 0 | J76: 0 | K76: 0 | L76: =X76-K76 -> 0 | M76: 1 | O76: 0.1 | P76: 0 | Q76: 0 | R76: 0.3 | S76: 0 | T76: 0 | U76: 0 | V76: 0 | W76: 1 | X76: 0
B77: Special items | I77: 0 | J77: 0 | L77: =X77-K77 -> 0 | O77: 0 | P77: 0 | Q77: 0 | R77: 0 | S77: 0 | T77: 0 | U77: 0 | V77: 0 | W77: 0 | X77: 0
B78: Adjusted EBIT | I78: =I76+I77 -> 0 | J78: =J76+J77 -> 0 | K78: 0 | L78: =X78-K78 -> 0 | M78: 1 | O78: =O76+O77 -> 0.1 | P78: =P76+P77 -> 0 | Q78: =Q76+Q77 -> 0 | R78: =R76+R77 -> 0.3 | S78: =S76+S77 -> 0 | T78: =T76+T77 -> 0 | U78: =U76+U77 -> 0 | V78: =V76+V77 -> 0 | ... X78: =X76+X77 -> 0
B79: Profit/loss of companies accounted for using equity meth. | I79: 0 | J79: 0 | L79: =X79-K79 -> 0 | O79: 0 | P79: 0 | Q79: 0 | R79: 0 | S79: 0 | T79: 0 | U79: 0 | V79: 0 | W79: 0 | X79: 0
B80: Carrying amount of companeis accounted for using the equity meth | I80: 0 | J80: 0 | L80: =X80-K80 -> 0 | O80: 0 | P80: 0 | Q80: 0 | R80: 0 | S80: 0 | T80: 0 | U80: 0 | V80: 0 | W80: 0 | X80: 0
B81: Assets | I81: -1619 | J81: -1425 | K81: -2066 | L81: =X81-K81 -> 0 | M81: -1953 | O81: -674.4 | P81: -750.6 | Q81: -794.1 | R81: -1029.6 | S81: -1282 | T81: -1237 | U81: -1400 | V81: -1619 | W81: -1871 | X81: -2066 | Y81: -2394
B82: Liabilities | I82: -1282 | J82: -1098 | K82: -1449 | L82: =X82-K82 -> 0 | M82: -1320 | O82: -333.4 | P82: -409.5 | Q82: -453.1 | R82: -688.8 | S82: -896 | T82: -896 | U82: -1063 | V82: -1282 | W82: -1371 | X82: -1449 | Y82: -1708
B83: Material other non-cash items | I83: 0 | J83: 0 | L83: =X83-K83 -> 0 | M83: -1 | O83: 0 | P83: 0 | Q83: 0.1 | R83: -0.1 | S83: 0 | T83: 0 | U83: 0 | V83: 0 | W83: 0 | X83: 0
B84: CapEx: | L84: =X84-K84 -> 0
B85: Intangible assets | I85: 0 | J85: 0 | L85: =X85-K85 -> 0 | O85: 0 | P85: 0 | Q85: 0 | R85: 0 | S85: 0 | T85: 0 | U85: 0 | V85: 0 | W85: 0 | X85: 0
B86: PPE | I86: 0 | J86: 0 | L86: =X86-K86 -> 5 | O86: 0 | P86: 0 | Q86: 0 | R86: 0 | S86: 0 | T86: 0 | U86: 0 | V86: 0 | W86: 0 | X86: 5
B87: Acquired program assets, dev work, and other assets | I87: 0 | J87: 0 | L87: =X87-K87 -> 0 | O87: 0 | P87: 0 | Q87: 0 | R87: 0 | S87: 0 | T87: 0 | U87: 0 | V87: 0 | W87: 0 | X87: 0
B88: Total CAPEX | I88: =I85+I86+I87 -> 0 | J88: =J85+J86+J87 -> 0 | L88: =X88-K88 -> 5 | O88: =O85+O86+O87 -> 0 | P88: =P85+P86+P87 -> 0 | Q88: =Q85+Q86+Q87 -> 0 | R88: =R85+R86+R87 -> 0 | S88: =S85+S86+S87 -> 0 | T88: =T85+T86+T87 -> 0 | U88: =U85+U86+U87 -> 0 | V88: =V85+V86+V87 -> 0 | ... X88: =X85+X86+X87 -> 5
B89: MTU Group Revenue
B90: Group Total Revenue | C90: =C8+C40+C68 -> 1674 | D90: =D8+D40+D69 -> 1755 | E90: =E8+E40+E68 -> 2092 | F90: =F8+F40+F69 -> 2106 | G90: 2231 | I90: =I8+I40+I68 -> 2520 | J90: =J8+J40+J68 -> 3142 | K90: =K8+K40+K68 -> 3439 | L90: =X90-K90 -> 3972 | M90: =M8+M40+M68 -> 4268 | O90: =O8+O40+O68 -> 4435.3 | P90: =P8+P40+P68 -> 4732.7 | Q90: =Q8+Q40+Q68 -> 3897.4 | R90: =R8+R40+R68 -> 4567.1 | S90: =S8+S40+S68 -> 4628 | T90: =T8+T40+T68 -> 3977 | U90: =U8+U40+U68 -> 4188 | V90: =V8+V40+V68 -> 5330 | ... Y90: =Y8+Y40+Y68 -> 8763
B91: Adjusted revenue | C91: =C8+C40+C69 -> 1674 | D91: =K91-C91 -> 1756 | E91: 2212 | F91: =M91-E91 -> 1928 | G91: 2244 | I91: 0 | J91: 0 | K91: =K10+K42+K69 -> 3430 | L91: =X91-K91 -> 4058 | M91: =M10+M42+M69 -> 4140 | O91: 0 | P91: 0 | Q91: 0 | R91: 0 | S91: 0 | T91: 0 | U91: 0 | V91: 0 | W91: 2212 | X91: =X10+X42+X69 -> 7488 | Y91: =Y10+Y42+Y69 -> 8717 | Z91: =(X91/O90)^(1/(2024-2015))-1 -> 0.059915946
B92: Gross profit | E92: 370 | G92: 372 | I92: =I11+I43+I70 -> 351 | J92: =J11+J43+J70 -> 520 | K92: =K11+K43+K70 -> 569 | L92: =X92-K92 -> 663 | M92: =M11+M43+M70 -> 829 | O92: =O11+O43+O70 -> 580.3 | P92: =P11+P43+P70 -> 657.9 | Q92: =Q11+Q43+Q70 -> 710.9 | R92: =R11+R43+R70 -> 851.3 | S92: =S11+S43+S70 -> 931 | T92: =T11+T43+T70 -> 492 | U92: =U11+U43+U70 -> 587 | V92: =V11+V43+V70 -> 855 | ... Y92: =Y11+Y43+Y70 -> 2328
B93: margin% | I93: =I92/I$8 -> 0.43386897 | J93: =J92/J$8 -> 0.49010368 | K93: =K92/K$8 -> 0.50132159 | L93: =X93-K93 -> 0.00071590391 | M93: =M92/M$8 -> 0.5647139 | O93: =O92/O$8 -> 0.20030375 | P93: =P92/P$8 -> 0.22645601 | Q93: =Q92/Q$8 -> 0.40978787 | R93: =R92/R$8 -> 0.41855548 | S93: =S92/S$8 -> 0.46643287 | T93: =T92/T$8 -> 0.32052117 | U93: =U92/U$8 -> 0.37919897 | V93: =V92/V$8 -> 0.46695795 | ... Y93: =Y92/Y$8 -> 0.79698733
B94: Amortization of intangibles | I94: =I13+I45+I71 -> -24 | J94: =J13+J45+J71 -> -28 | K94: =K13+K45+K71 -> -22 | L94: =X94-K94 -> -24 | M94: =M13+M45+M71 -> -23 | O94: =O13+O45+O71 -> -69.8 | P94: =P13+P45+P71 -> #VALUE! | Q94: =Q13+Q45+Q71 -> -39.5 | R94: =R13+R45+R71 -> -37.7 | S94: =S13+S45+S71 -> -44 | T94: =T13+T45+T71 -> -46 | U94: =U13+U45+U71 -> -48 | V94: =V13+V45+V71 -> -54 | ... Y94: =Y13+Y45+Y71 -> -49
B95: Depreciation of PPE | I95: =I14+I46+I72 -> -93 | J95: =J14+J46+J72 -> -101 | K95: =K14+K46+K72 -> -1 | L95: =X95-K95 -> 7 | M95: =M14+M46+M72 -> 14 | O95: =O14+O46+O72 -> -97.8 | P95: =P14+P46+P72 -> -101.4 | Q95: =Q14+Q46+Q72 -> -47.3 | R95: =R14+R46+R72 -> -49 | S95: =S14+S46+S72 -> -53 | T95: =T14+T46+T72 -> -102 | U95: =U14+U46+U72 -> -46 | V95: =V14+V46+V72 -> -47 | ... Y95: =Y14+Y46+Y72 -> 32
B96: Non-cash amortization of program assets | I96: =I15+I47+I73 -> -24 | J96: =J15+J47+J73 -> -23 | K96: =K15+K47+K73 -> -25 | L96: =X96-K96 -> -100 | M96: =M15+M47+M73 -> -25 | O96: =O15+O47+O73 -> 0 | P96: =P15+P47+P73 -> 0 | Q96: =Q15+Q47+Q73 -> -106.7 | R96: =R15+R47+R73 -> -107.9 | S96: =S15+S47+S73 -> -159 | T96: =T15+T47+T73 -> -124 | U96: =U15+U47+U73 -> -181 | V96: =V15+V47+V73 -> -190 | ... Y96: =Y15+Y47+Y73 -> -49
B97: Impairment losses | I97: =I16+I48+I74 -> -65 | J97: =J16+J48+J74 -> -2 | K97: =K16+K48+K74 -> 1 | L97: =X97-K97 -> -31 | M97: =M16+M48+M74 -> 3 | O97: =O16+O48+O74 -> -0.4 | P97: =P16+P48+P74 -> -0.1 | Q97: =Q16+Q48+Q74 -> 0 | R97: =R16+R48+R74 -> -5.9 | S97: =S16+S48+S74 -> -5 | T97: =T16+T48+T74 -> -77 | U97: =U16+U48+U74 -> -83 | V97: =V16+V48+V74 -> -66 | ... Y97: =Y16+Y48+Y74 -> 3
B98: D&A/adjustments/impairments | I98: =I97+I96+I95+I94 -> -206 | J98: =J97+J96+J95+J94 -> -154 | K98: =K97+K96+K95+K94 -> -47 | L98: =L97+L96+L95+L94 -> -148 | M98: =M97+M96+M95+M94 -> -31 | O98: =O97+O96+O95+O94 -> -168 | P98: =P97+P96+P95+P94 -> #VALUE! | Q98: =Q97+Q96+Q95+Q94 -> -193.5 | R98: =R97+R96+R95+R94 -> -200.5 | S98: =S97+S96+S95+S94 -> -261 | T98: =T97+T96+T95+T94 -> -349 | U98: =U97+U96+U95+U94 -> -358 | V98: =V97+V96+V95+V94 -> -357 | ... Y98: =Y97+Y96+Y95+Y94 -> -63
B99: EBIT | I99: =I22+I52+I76 -> 183 | J99: =J22+J52+J76 -> 382 | K99: =K22+K52+K76 -> 421 | L99: =L22+L52+L76 -> 534 | M99: =M22+M52+M76 -> 704 | O99: =O22+O52+O76 -> 385.6 | P99: =P22+P52+P76 -> 452.8 | Q99: =Q22+Q52+Q76 -> 421.2 | R99: =R22+R52+R76 -> 620.2 | S99: =S22+S52+S76 -> 706 | T99: =T22+T52+T76 -> 262 | U99: =U22+U52+U76 -> 355 | V99: =V22+V52+V76 -> 507 | ... Y99: =Y22+Y52+Y76 -> 1379
B100: margin% | I100: =I99/I$8 -> 0.22620519 | J100: =J99/J$8 -> 0.3600377 | K100: =K99/K$8 -> 0.37092511 | L100: =L99/L$8 -> 0.40485216 | M100: =M99/M$8 -> 0.47956403 | O100: =O99/O$8 -> 0.13309862 | P100: =P99/P$8 -> 0.15585846 | Q100: =Q99/Q$8 -> 0.24279456 | R100: =R99/R$8 -> 0.30493141 | S100: =S99/S$8 -> 0.35370741 | T100: =T99/T$8 -> 0.17068404 | U100: =U99/U$8 -> 0.22932817 | V100: =V99/V$8 -> 0.27689787 | ... Y100: =Y99/Y$8 -> 0.4720986 | Z100: =(X100/O100)^(1/(2024-2015))-1 -> 0.12660794
B101: EBITDA (Calculation 1) | O101: =O99-O98 -> 553.6 | P101: =P99-P98 -> #VALUE! | Q101: =Q99-Q98 -> 614.7 | R101: =R99-R98 -> 820.7 | S101: =S99-S98 -> 967 | T101: =T99-T98 -> 611 | U101: =U99-U98 -> 713 | V101: =V99-V98 -> 864 | ... Y101: =Y99-Y98 -> 1442
...

Sheet R&D Capitalization
B2: in € million | C2: 2025 | D2: 2024 | F2: Change against previous year | G2: in € million | H2: in %
B3: Commercial engine business (OEM) | C3: 256 | D3: 249 | F3: 7 | G3: 7 | H3: 2.7
B4: Military engine business (OEM) | C4: 115 | D4: 88 | F4: 27 | G4: 27 | H4: 31
B5: Commercial maintenance business (MRO) | C5: 5 | D5: 5 | F5: 1 | G5: 1 | H5: 10.6
B6: Total research and development expenses | C6: =C3+C4+C5 -> 376 | D6: =D3+D4+D5 -> 342 | F6: 35 | G6: 35 | H6: 10.1
B7: Refund of research and development expenses | C7: -138 | D7: -112 | F7: −26 | G7: −26 | H7: −23.3
B8: Research and development expenses – own contribution | C8: =C6+C7 -> 238 | D8: 231 | F8: 9 | G8: 9 | H8: 3.7
B9: Expenditure meeting recognition criteria for intangible assets
B10: Commercial and military engine business (OEM) | C10: -93 | D10: -93 | F10: 0 | G10: 0 | H10: 0
B11: Amortization of previously capitalized development expenses | C11: 36 | D11: 90 | F11: −54 | G11: −54 | H11: −60.3
B12: Research and development expenses – effect on profit or loss | C12: =C8+C10+C11 -> 181 | D12: =D8+D10+D11 -> 228 | F12: −46 | G12: −46 | H12: −20.1
B13: thereof: in gross profit | C13: 71 | D13: 122 | F13: −51 | G13: −51 | H13: −41.7
B14: thereof: in functional costs – research and development | C14: 111 | D14: 106 | F14: 5 | G14: 5 | H14: 4.8
B16: Joaquin - Useful life of R&D (# years) | C16: 8
B18: Adjustments - Joaquin
B19: (+) expensed R&D | C19: =C12 -> 181
B20: (-) notional R&D amortization | C20: =-C19/C16 -> -22.625

Sheet x

Sheet Alt Presentation
C2: Q3'2021 | D2: Q4'2021 | F2: Q1'2022 | G2: Q2'2022 | H2: Q3'2022 | I2: Q4'2022 | J2: Q1'2023 | K2: Q2'2023 | L2: Q3'2023 | M2: Q4'2023 | N2: Q1'2024 | O2: Q2'2024 | P2: Q3'2024 | Q2: Q4'2024 | R2: Q1'2025 | S2: Q2'2025 | T2: TTM Figures
B3: Revenue | C3: 1349 | D3: 1180 | E3: 0 | F3: 1180 | G3: 1289 | H3: 1004 | I3: 1513 | J3: 1544 | K3: 1549 | L3: 560 | M3: 2125 | N3: 1650 | O3: 1740 | P3: 1897 | Q3: 1711 | R3: 2111 | S3: 2087
B4: Adjusted revenue | C4: 1349 | D4: 1180 | E4: 0 | F4: 1180 | G4: 1289 | H4: 1004 | I4: 1513 | J4: 1544 | K4: 1549 | L4: 1525 | M4: 2195 | N4: 1675 | O4: 1755 | P4: 1864 | Q4: 1678 | R4: 2092 | S4: 2048 | T4: =S4+R4+Q4+P4 -> 7682
B5: Y/Y growth | H5: =H4/C4-1 -> -0.255745 | I5: =I4/D4-1 -> 0.28220339 | J5: =J4/F4-1 -> 0.30847458 | K5: =K4/G4-1 -> 0.20170675 | L5: =L4/H4-1 -> 0.5189243 | M5: =M4/I4-1 -> 0.45076008 | N5: =N4/J4-1 -> 0.08484456 | O5: =O4/K4-1 -> 0.13298903 | P5: =P4/L4-1 -> 0.22229508 | Q5: =Q4/M4-1 -> -0.23553531 | ... S5: =S4/O4-1 -> 0.16695157
B6: Segment-level P&L
B7: Commercial engine business revenue | C7: 350 | D7: 300 | E7: 0 | F7: 278 | G7: 318 | H7: 251 | I7: 388 | J7: 446 | K7: 387 | L7: 393 | M7: 551 | N7: 433 | O7: 470 | P7: 465 | Q7: 419 | R7: 507 | S7: 645 | T7: =S7+R7+Q7+P7 -> 2036
B8: Military engine business | C8: 95 | D8: 172 | E8: 0 | F8: 108 | G8: 106 | H8: 123 | I8: 187 | J8: 103 | K8: 126 | L8: 138 | M8: 186 | N8: 124 | O8: 148 | P8: 153 | Q8: 171 | R8: 113 | S8: 147 | T8: =S8+R8+Q8+P8 -> 584
B9: OEM business | C9: =C7+C8 -> 445 | D9: =D7+D8 -> 472 | E9: =E7+E8 -> 0 | F9: =F7+F8 -> 386 | G9: =G7+G8 -> 424 | H9: =H7+H8 -> 374 | I9: =I7+I8 -> 575 | J9: =J7+J8 -> 549 | ... S9: =S7+S8 -> 792 | T9: =S9+R9+Q9+P9 -> 2620
B10: Commercial Maintenance | C10: 933 | D10: 731 | E10: 0 | F10: 819 | G10: 892 | H10: 658 | I10: 973 | J10: 1021 | K10: 1060 | L10: 1026 | M10: 1489 | N10: 1141 | O10: 1163 | P10: 1274 | Q10: 1117 | R10: 1521 | S10: 1278 | T10: =S10+R10+Q10+P10 -> 5190
B11: Mix
B12: OEM | C12: =C9/C$4 -> 0.32987398 | D12: =D9/D$4 -> 0.4 | E12: =E9/E$4 -> #DIV/0! | F12: =F9/F$4 -> 0.32711864 | G12: =G9/G$4 -> 0.32893716 | H12: =H9/H$4 -> 0.37250996 | I12: =I9/I$4 -> 0.38003966 | J12: =J9/J$4 -> 0.35556995 | ... T12: =T9/T$4 -> 0.34105702
B13: Maintenance | C13: =C10/C$4 -> 0.69162342 | D13: =D10/D$4 -> 0.61949153 | E13: =E10/E$4 -> #DIV/0! | F13: =F10/F$4 -> 0.6940678 | G13: =G10/G$4 -> 0.69200931 | H13: =H10/H$4 -> 0.65537849 | I13: =I10/I$4 -> 0.64309319 | J13: =J10/J$4 -> 0.66126943 | ... T13: =T10/T$4 -> 0.67560531
B14: EBIT (reported) | G14: 159 | K14: 193 | M14: 233 | N14: 188 | O14: 232 | Q14: 249 | R14: 314 | S14: 390 | T14: =S14+R14+Q14+P14 -> 953
B15: OEM business EBIT | C15: 86 | D15: 118 | E15: 0 | F15: 78 | G15: 87 | H15: 89 | I15: 136 | J15: 141 | K15: 121 | L15: 111 | M15: 168 | N15: 130 | O15: 157 | P15: 156 | Q15: 115 | R15: 176 | S15: 239 | T15: =S15+R15+Q15+P15 -> 686
B16: Commercial maintenance business EBIT | C16: 72 | D16: 44 | E16: 0 | F16: 53 | G16: 72 | H16: 28 | I16: 72 | J16: 70 | K16: 72 | L16: 81 | M16: 138 | N16: 88 | O16: 95 | P16: 118 | Q16: 106 | R16: 125 | S16: 116 | T16: =S16+R16+Q16+P16 -> 465
B17: Adjusted EBIT: | C17: =C15+C16 -> 158 | D17: =D15+D16 -> 162 | E17: =E15+E16 -> 0 | F17: =F15+F16 -> 131 | G17: =G15+G16 -> 159 | H17: =H15+H16 -> 117 | I17: =I15+I16 -> 208 | J17: =J15+J16 -> 211 | ... S17: =S15+S16 -> 355 | T17: =S17+R17+Q17+P17 -> 1151
B18: OEM business EBIT mgn | C18: =C15/C9 -> 0.19325843 | D18: =D15/D9 -> 0.25 | E18: =E15/E9 -> #DIV/0! | F18: =F15/F9 -> 0.20207254 | G18: =G15/G9 -> 0.20518868 | H18: =H15/H9 -> 0.23796791 | I18: =I15/I9 -> 0.23652174 | J18: =J15/J9 -> 0.2568306 | ... T18: =T15/T9 -> 0.26183206
B19: Commercial maintenance business EBIT mgn | C19: =C16/C10 -> 0.077170418 | D19: =D16/D10 -> 0.060191518 | E19: =E16/E10 -> #DIV/0! | F19: =F16/F10 -> 0.064713065 | G19: =G16/G10 -> 0.080717489 | H19: =H16/H10 -> 0.042553191 | I19: =I16/I10 -> 0.073997945 | J19: =J16/J10 -> 0.068560235 | ... T19: =T16/T10 -> 0.089595376
B20: EBIT mgn | C20: =C17/C4 -> 0.1171238 | D20: =D17/D4 -> 0.13728814 | E20: =E17/E4 -> #DIV/0! | F20: =F17/F4 -> 0.11101695 | G20: =G17/G4 -> 0.12335144 | H20: =H17/H4 -> 0.11653386 | I20: =I17/I4 -> 0.13747521 | J20: =J17/J4 -> 0.13665803 | ... T20: =T17/T4 -> 0.14983077
B21: Adjusted Net Income | C21: 113 | D21: 122 | E21: 0 | F21: 93 | G21: 114 | H21: 85 | I21: 156 | J21: 157 | K21: 143 | L21: 138 | M21: 223 | N21: 158 | O21: 185 | P21: 199 | Q21: 155 | R21: 221 | S21: 258
B22: Net Income mgn | C22: =C21/C4 -> 0.083765752 | D22: =D21/D4 -> 0.10338983 | E22: =E21/E4 -> #DIV/0! | F22: =F21/F4 -> 0.078813559 | G22: =G21/G4 -> 0.088440652 | H22: =H21/H4 -> 0.084661355 | I22: =I21/I4 -> 0.10310641 | J22: =J21/J4 -> 0.10168394 | ... S22: =S21/S4 -> 0.12597656
B23: Reported Net Income | C23: 92 | D23: 41 | E23: 0 | F23: 53 | G23: 66 | H23: 87 | I23: 121 | J23: 134 | K23: 122 | L23: -568 | M23: 143 | N23: 126 | O23: 162 | P23: 211 | Q23: 215 | R23: 224 | S23: 289
B24: EPS | C24: 1.74 | D24: 0.67 | E24: 0 | F24: 0.99 | G24: 1.24 | H24: 1.62 | I24: 2.23 | J24: 2.47 | K24: 2.28 | L24: -10.61 | M24: 2.56 | N24: 2.35 | O24: 2.96 | P24: 3.9 | Q24: 3.96 | R24: 4.03 | S24: 5.34
B25: Adjusted EPS | C25: 1.74 | D25: 0 | E25: 0 | F25: 0 | G25: 1.24 | H25: 1.62 | I25: 0 | J25: 0 | K25: 2.28 | L25: 2.56 | M25: 4.05 | N25: 2.93 | O25: 3.38 | P25: 3.68 | Q25: 2.8 | R25: 3.99 | S25: 4.77
B26: Non-IFRS:
B27: Reported EBITDA | C27: 220 | D27: 221 | E27: 0 | F27: 278 | G27: 216 | H27: 189 | I27: 255 | J27: 0 | K27: 259 | L27: -711 | M27: 405 | N27: 275 | O27: 321 | P27: 422 | Q27: 344 | R27: 417 | S27: 491 | T27: =S27+R27+Q27+P27 -> 1674
B28: Adjusted EBITDA | C28: 220 | D28: 221 | E28: 0 | F28: 278 | G28: 216 | H28: 189 | I28: 255 | J28: 0 | K28: 259 | L28: 264 | M28: 468 | N28: 294 | O28: 330 | P28: 383 | Q28: 305 | R28: 392 | S28: 446 | T28: =S28+R28+Q28+P28 -> 1526
B29: FCF | C29: 52 | D29: 35 | E29: 0 | F29: 93 | G29: 33 | H29: 18 | I29: 107 | J29: 0 | K29: 42 | L29: 122 | M29: -30 | N29: 16 | O29: 90 | P29: 108 | Q29: 95 | R29: 150 | S29: 61 | T29: =S29+R29+Q29+P29 -> 414
B30: Company-funded R&D | C30: 46 | D30: 44 | E30: 0 | F30: 47 | G30: 54 | H30: 41 | I30: 54 | J30: 0 | K30: 72 | L30: 51 | M30: 58 | N30: 56 | O30: 72 | P30: 45 | Q30: 53 | R30: 78 | S30: 50 | T30: =S30+R30+Q30+P30 -> 226
B31: Customer-funded R&D | C31: 10 | D31: 24 | E31: 0 | F31: 21 | G31: 17 | H31: 19 | I31: 20 | J31: 0 | K31: 18 | L31: 15 | M31: 30 | N31: 24 | O31: 27 | P31: 30 | Q31: 28 | R31: 30 | S31: 33 | T31: =S31+R31+Q31+P31 -> 121
B32: R&D expense | C32: =C31+C30 -> 56 | D32: =D31+D30 -> 68 | E32: =E31+E30 -> 0 | F32: =F31+F30 -> 68 | G32: =G31+G30 -> 71 | H32: =H31+H30 -> 60 | I32: =I31+I30 -> 74 | J32: =J31+J30 -> 0 | ... T32: =T31+T30 -> 347
B33: CapEx on PPE | C33: 78 | D33: 125 | E33: 0 | F33: 62 | G33: 54 | H33: 54 | I33: 136 | J33: 0 | K33: 50 | L33: 78 | M33: 153 | N33: 74 | O33: 97 | P33: 77 | Q33: 112 | R33: 76 | S33: 51
B34: Balance sheet:
B35: Intangibles | C35: 0 | D35: 1128 | E35: 0 | F35: 0 | G35: 0 | H35: 1136 | I35: 1151 | J35: 1151 | K35: 1154 | L35: 0 | M35: 1200 | N35: 0 | O35: 0 | P35: 1213 | Q35: 1313 | R35: 1310 | S35: 1429
B36: Cash & equivalents | C36: 0 | D36: 722 | E36: 0 | F36: 0 | G36: 0 | H36: 775 | I36: 823 | J36: 892 | K36: 771 | L36: 0 | M36: 883 | N36: 0 | O36: 0 | P36: 1910 | Q36: 1747 | R36: 1840 | S36: 1273
B37: Pension provision | C37: 0 | D37: 948 | E37: 0 | F37: 0 | G37: 0 | H37: 746 | I37: 707 | J37: 710 | K37: 721 | L37: 0 | M37: 743 | N37: 0 | O37: 0 | P37: 727 | Q37: 724 | R37: 727 | S37: 713
B38: Equity | C38: 0 | D38: 2760 | E38: 0 | F38: 0 | G38: 0 | H38: 2871 | I38: 3107 | J38: 3273 | K38: 3268 | L38: 0 | M38: 2933 | N38: 0 | O38: 0 | P38: 3350 | Q38: 3438 | R38: 3694 | S38: 3909
B39: Net financial debt | C39: 0 | D39: 673 | E39: 0 | F39: 0 | G39: 0 | H39: 604 | I39: 753 | J39: 646 | K39: 777 | L39: 0 | M39: 631 | N39: 0 | O39: 0 | P39: 631 | Q39: 1061 | R39: 972 | S39: 1147
B40: total assets & liabilities | C40: 0 | D40: 8304 | E40: 0 | F40: 0 | G40: 0 | H40: 9064 | I40: 9230 | J40: 9261 | K40: 9280 | L40: 0 | M40: 10204 | N40: 0 | O40: 0 | P40: 11810 | Q40: 12484 | R40: 12185 | S40: 11781
B41: Order backlog | C41: 0 | D41: 22237 | E41: 0 | F41: 0 | G41: 0 | H41: 25958 | I41: 22273 | J41: 22743 | K41: 21923 | L41: 0 | M41: 24393 | N41: 0 | O41: 0 | P41: 23359 | Q41: 28730 | R41: 27700 | S41: 25037
B42: Y/Y growth | H42: =H41/C41-1 -> #DIV/0! | I42: =I41/D41-1 -> 0.0016189234 | J42: =J41/F41-1 -> #DIV/0! | K42: =K41/G41-1 -> #DIV/0! | L42: =L41/H41-1 -> -1 | M42: =M41/I41-1 -> 0.095182508 | N42: =N41/J41-1 -> -1 | O42: =O41/K41-1 -> -1 | P42: =P41/L41-1 -> #DIV/0! | Q42: =Q41/M41-1 -> 0.17779691 | ... S42: =S41/O41-1 -> #DIV/0!
