Workbook

Sheet Main
B2: #VALUE!
B3: Price | C3: {=_FV(B2,"Price")} -> 326.1 | E3: CEO: | F3: Olivier Andries
B4: 52wh | C4: {=_FV(B2,"52 week high",TRUE)} -> 350.8 | F4: Worked in French Ministry of Industry + Treasury Dept
B5: 52wl | C5: {=_FV(B2,"52 week low",TRUE)} -> 190.7 | F5: Director, Strategy EADS
B6: Shares outstanding (M) | C6: {=_FV(B2,"Shares outstanding",TRUE)/1000000} -> 418.3446 | E6: CEO, Aircraft Engines | F6: Stéphane Cueille
B7: Market Cap | C7: {=_FV(B2,"Market cap",TRUE)/1000000} -> 136296.7 | F7: French Defense Procurement agency
B8: Cash | C8: =Sheet2!AJ105 -> 6707 | F8: Safran Nacelles - 2013
B9: Debt | C9: =Sheet2!AJ117+Sheet2!AJ123 -> 4838 | F9: PhD in Physics + ret. Colonel french armament engineering corps
B10: Convertibles | D10: <= These converted on May 30, 2024 | E10: CEO, Electronics & Defence | F10: Franck Saudo
B11: EV | C11: =C7-C8+C9+C10 -> 134427.7 | F11: head of financial markets, Ministre de l'economie
B12: TTM Revenue | C12: =Sheet2!AJ51+Sheet2!AI51 -> 29039
B13: TTM Earnings | C13: =Sheet2!AJ78+Sheet2!AI78 -> 4431
B14: TTM EPS | C14: =C13/C6 -> 10.591747
B15: PE | C15: {=_FV(B2,"P/E",TRUE)} -> 16.2271
B17: BV | C17: =Sheet2!AJ112 -> 13222
B18: BV/Share | C18: =C17/C6 -> 31.605523
B19: Multiple | C19: =C3/C18 -> 10.317817
B21: Accounting Lesson
B22: IAS38- capitalizing R&D
B25: VIC pitch:
B26: https://www.valueinvestorsclub.com/idea/SAFRAN_SA/5053975887

Sheet Dashboard
C2: =Main!B2 -> #VALUE!
B3: Operating margin | C3: =Sheet2!AU70 -> 0.15124838
B4: Return on Assets | C4: =(Sheet2!AU69*(1-0.3))/AVERAGE(Sheet2!AU108,Sheet2!AT108) -> 0.055638984
B5: Return on Equity | C5: =Sheet2!AU79/AVERAGE(Sheet2!AU114,Sheet2!AT114) -> -0.058475431
B6: Revenue | C6: =Sheet2!AU52 -> 27716
B7: 5-year Revenue CAGR
B8: Gross Profit
B9: Total Debt/Equity | C9: =(Sheet2!AJ123+Sheet2!AJ117)/Sheet2!AJ114 -> 0.3511395
B10: Book Value Per Share
B11: 52 Week Change
B12: Market Cap
B13: Trailing P/E
B14: Price/Sales
B15: Price/Book

Sheet Sheet2
D2: Q1'2022 | E2: Q2'2022 | F2: Q3'2022 | G2: Q4'2022 | H2: Q1'2023 | I2: Q2'2023 | J2: Q3'2023 | K2: Q4'2023 | L2: Q1'2024 | M2: Q2'2024 | N2: Q3'2024 | O2: Q4'2024 | P2: Q1'2025 | Q2: Q2'2025 | R2: Q3'2025 | T2: 1H'2017 | U2: 2H'2017 | V2: 1H'2018 | W2: 2H'2018 | X2: 1H'2019 | Y2: 2H'2019 | Z2: 1H'2020 | AA2: 2H'2020 | AB2: 1H'2021 | AC2: 2H'2021 | AD2: 1H'2022 | AE2: 2H'2022 | AF2: 1H'2023 | AG2: 2H'2023 | AH2: 1H'2024 | AI2: 2H'2024 | AJ2: 1H'2025 | AL2: FY2015 | AM2: FY2016 | AN2: FY2017 | AO2: FY2018 | AP2: FY2019 | AQ2: FY2020 | AR2: FY2021 | AS2: FY2022 | AT2: FY2023 | AU2: FY2024 | AV2: CAGR
C3: No. Units delivered
C4: LEAP engines | D4: 239 | E4: =AB4-D4 -> 160 | F4: 347 | G4: =AE4-F4 -> 324 | H4: 366 | I4: =AF4-H4 -> 419 | J4: 389 | K4: =AG4-J4 -> 396 | L4: 387 | M4: =AH4-L4 -> 277 | N4: 365 | O4: =AU4-N4-M4-L4 -> 378 | P4: 319 | Q4: =AJ4-P4 -> 345 | R4: 511 | T4: 147 | U4: =AN4-T4 -> 312 | V4: 438 | W4: =AO4-V4 -> 680 | X4: 861 | Y4: =AP4-X4 -> 875 | Z4: 450 | AA4: =AQ4-Z4 -> 365 | AB4: 399 | AC4: =AR4-AB4 -> 446 | AD4: 465 | AE4: =AS4-AD4 -> 671 | AF4: 785 | AG4: =AT4-AF4 -> 785 | AH4: 664 | AI4: =AU4-AH4 -> 743 | AJ4: 664 | AL4: 0 | AM4: 77 | AN4: 459 | AO4: 1118 | AP4: 1736 | AQ4: 815 | AR4: 845 | AS4: 1136 | AT4: 1570 | AU4: 1407
C5: CFM56 engines | D5: 15 | E5: =AB5-D5 -> 34 | F5: 17 | G5: =AE5-F5 -> 16 | H5: 15 | I5: =AF5-H5 -> 9 | J5: 14 | K5: =AG5-J5 -> 14 | L5: 12 | M5: =AH5-L5 -> 16 | N5: 13 | O5: =AU5-N5-M5-L5 -> 19 | P5: 12 | Q5: =AJ5-P5 -> 16 | R5: 15 | T5: 710 | U5: =AN5-T5 -> 734 | V5: 591 | W5: =AO5-V5 -> 453 | X5: 258 | Y5: =AP5-X5 -> 133 | Z5: 84 | AA5: =AQ5-Z5 -> 73 | AB5: 49 | AC5: =AR5-AB5 -> 58 | AD5: 27 | AE5: =AS5-AD5 -> 33 | AF5: 24 | AG5: =AT5-AF5 -> 28 | AH5: 28 | AI5: =AU5-AH5 -> 32 | AJ5: 28 | AL5: 1612 | AM5: 1693 | AN5: 1444 | AO5: 1044 | AP5: 391 | AQ5: 157 | AR5: 107 | AS5: 60 | AT5: 52 | AU5: 60
C6: High thrust engines | D6: 48 | E6: =AB6-D6 -> 90 | F6: 40 | G6: =AE6-F6 -> 50 | H6: 37 | I6: =AF6-H6 -> 46 | J6: 58 | K6: =AG6-J6 -> 49 | L6: 56 | M6: =AH6-L6 -> 35 | N6: 51 | O6: =AU6-N6-M6-L6 -> 53 | P6: 48 | Q6: =AJ6-P6 -> 43 | R6: 55 | T6: 256 | U6: =AN6-T6 -> 230 | V6: 201 | W6: =AO6-V6 -> 234 | X6: 234 | Y6: =AP6-X6 -> 255 | Z6: 197 | AA6: =AQ6-Z6 -> 172 | AB6: 138 | AC6: =AR6-AB6 -> 97 | AD6: 91 | AE6: =AS6-AD6 -> 90 | AF6: 83 | AG6: =AT6-AF6 -> 107 | AH6: 91 | AI6: =AU6-AH6 -> 104 | AJ6: 91 | AL6: 695 | AM6: 686 | AN6: 486 | AO6: 435 | AP6: 489 | AQ6: 369 | AR6: 235 | AS6: 181 | AT6: 190 | AU6: 195
C7: Helicopter turbines | D7: 110 | E7: =AB7-D7 -> 174 | F7: 128 | G7: =AE7-F7 -> 153 | H7: 136 | I7: =AF7-H7 -> 138 | J7: 140 | K7: =AG7-J7 -> 174 | L7: 136 | M7: =AH7-L7 -> 169 | N7: 181 | O7: =AU7-N7-M7-L7 -> 196 | P7: 153 | Q7: =AJ7-P7 -> 152 | R7: 192 | T7: 314 | U7: =AN7-T7 -> 358 | V7: 335 | W7: =AO7-V7 -> 438 | X7: 335 | Y7: =AP7-X7 -> 361 | Z7: 275 | AA7: =AQ7-Z7 -> 354 | AB7: 284 | AC7: =AR7-AB7 -> 290 | AD7: 227 | AE7: =AS7-AD7 -> 281 | AF7: 274 | AG7: =AT7-AF7 -> 314 | AH7: 305 | AI7: =AU7-AH7 -> 377 | AJ7: 305 | AL7: 625 | AM7: 714 | AN7: 672 | AO7: 773 | AP7: 696 | AQ7: 629 | AR7: 574 | AS7: 508 | AT7: 588 | AU7: 682
C8: M88 engines | D8: 12 | E8: =AB8-D8 -> 19 | F8: 9 | G8: =AE8-F8 -> 22 | H8: 17 | I8: =AF8-H8 -> 14 | J8: 8 | K8: =AG8-J8 -> 3 | L8: 8 | M8: =AH8-L8 -> 6 | N8: 10 | O8: =AU8-N8-M8-L8 -> 16 | P8: 2 | Q8: =AJ8-P8 -> 12 | R8: 7 | T8: 12 | U8: =AN8-T8 -> 21 | V8: 4 | W8: =AO8-V8 -> 19 | X8: 22 | Y8: =AP8-X8 -> 40 | Z8: 19 | AA8: =AQ8-Z8 -> 14 | AB8: 31 | AC8: =AR8-AB8 -> 33 | AD8: 20 | AE8: =AS8-AD8 -> 31 | AF8: 31 | AG8: =AT8-AF8 -> 11 | AH8: 14 | AI8: =AU8-AH8 -> 26 | AJ8: 14 | AL8: 12 | AM8: 11 | AN8: 33 | AO8: 23 | AP8: 62 | AQ8: 33 | AR8: 64 | AS8: 51 | AT8: 42 | AU8: 40
C9: A320 neo nacelles | D9: 141 | E9: =AB9-D9 -> 123 | F9: 153 | G9: =AE9-F9 -> 151 | H9: 135 | I9: =AF9-H9 -> 140 | J9: 153 | K9: =AG9-J9 -> 151 | L9: 135 | M9: =AH9-L9 -> 162 | N9: 142 | O9: =AU9-N9-M9-L9 -> 183 | P9: 155 | Q9: =AJ9-P9 -> 142 | R9: 166 | T9: 263 | U9: =AN9-T9 -> -28 | V9: 176 | W9: =AO9-V9 -> 262 | X9: 280 | Y9: =AP9-X9 -> 322 | Z9: 248 | AA9: =AQ9-Z9 -> 226 | AB9: 264 | AC9: =AR9-AB9 -> 312 | AD9: 284 | AE9: =AS9-AD9 -> 304 | AF9: 275 | AG9: =AT9-AF9 -> 304 | AH9: 297 | AI9: =AU9-AH9 -> 325 | AJ9: 297 | AL9: 0 | AM9: 0 | AN9: 235 | AO9: 438 | AP9: 602 | AQ9: 474 | AR9: 576 | AS9: 588 | AT9: 579 | AU9: 622
C10: A320 landing gear sets | D10: 346 | E10: =AB10-D10 -> -346 | F10: 8 | G10: =AE10-F10 -> -8 | H10: 126 | I10: =AF10-H10 -> 145 | J10: 126 | K10: =AG10-J10 -> 184 | L10: 167 | M10: =AH10-L10 -> 137 | N10: 159 | O10: =AU10-N10-M10-L10 -> 138 | P10: 171 | Q10: =AJ10-P10 -> 133 | R10: 186 | U10: =AN10-T10 -> 0 | W10: =AO10-V10 -> 0 | X10: 0 | Y10: =AP10-X10 -> 0 | Z10: 0 | AA10: =AQ10-Z10 -> 0 | AB10: 0 | AC10: =AR10-AB10 -> 0 | AD10: 0 | AE10: =AS10-AD10 -> 0 | AF10: 271 | AG10: =AT10-AF10 -> 310 | AH10: 304 | AI10: =AU10-AH10 -> 297 | AJ10: 304 | AL10: 0 | AM10: 0 | AN10: 0 | AO10: 0 | AP10: 0 | AQ10: 0 | AR10: 0 | AS10: 0 | AT10: 581 | AU10: 601
C11: A320 emegency slides | D11: 1106 | E11: =AB11-D11 -> 602 | F11: 1335 | G11: =AE11-F11 -> 1039 | H11: 779 | I11: =AF11-H11 -> 678 | J11: 1165 | K11: =AG11-J11 -> 1328 | L11: 1080 | M11: =AH11-L11 -> 882 | N11: 1256 | O11: =AU11-N11-M11-L11 -> 1223 | P11: 1186 | Q11: =AJ11-P11 -> 776 | R11: 1186 | U11: =AN11-T11 -> 0 | V11: 1296 | W11: =AO11-V11 -> 2330 | X11: 2398 | Y11: =AP11-X11 -> 2523 | Z11: 1524 | AA11: =AQ11-Z11 -> 1425 | AB11: 1708 | AC11: =AR11-AB11 -> 1890 | AD11: 2080 | AE11: =AS11-AD11 -> 2374 | AF11: 1457 | AG11: =AT11-AF11 -> 2493 | AH11: 1962 | AI11: =AU11-AH11 -> 2479 | AJ11: 1962 | AL11: 0 | AM11: 0 | AN11: 0 | AO11: 3626 | AP11: 4921 | AQ11: 2949 | AR11: 3598 | AS11: 4454 | AT11: 3950 | AU11: 4441
C12: A330 neo nacelles | D12: 12 | E12: =AB12-D12 -> -6 | F12: 10 | G12: =AE12-F12 -> 550 | H12: 8 | I12: =AF12-H12 -> 18 | J12: 12 | K12: =AG12-J12 -> 16 | L12: 16 | M12: =AH12-L12 -> 13 | N12: 13 | O12: =AU12-N12-M12-L12 -> 20 | P12: 20 | Q12: =AJ12-P12 -> 9 | R12: 14 | U12: =AN12-T12 -> 0 | W12: =AO12-V12 -> 0 | X12: 51 | Y12: =AP12-X12 -> 41 | Z12: 20 | AA12: =AQ12-Z12 -> 16 | AB12: 6 | AC12: =AR12-AB12 -> 14 | AD12: 28 | AE12: =AS12-AD12 -> 560 | AF12: 26 | AG12: =AT12-AF12 -> 28 | AH12: 29 | AI12: =AU12-AH12 -> 33 | AJ12: 29 | AL12: 0 | AM12: 65 | AN12: 0 | AO12: 0 | AP12: 92 | AQ12: 36 | AR12: 20 | AS12: 588 | AT12: 54 | AU12: 62
C13: A350 landing gear sets | D13: 10 | E13: =AB13-D13 -> 10 | F13: 8 | G13: =AE13-F13 -> 12 | H13: 12 | I13: =AF13-H13 -> 11 | J13: 11 | K13: =AG13-J13 -> 12 | L13: 15 | M13: =AH13-L13 -> 11 | N13: 11 | O13: =AU13-N13-M13-L13 -> 11 | P13: 13 | Q13: =AJ13-P13 -> 13 | R13: 9 | T13: 43 | U13: =AN13-T13 -> 38 | V13: 40 | W13: =AO13-V13 -> 40 | X13: 41 | Y13: =AP13-X13 -> 41 | Z13: 26 | AA13: =AQ13-Z13 -> 26 | AB13: 20 | AC13: =AR13-AB13 -> 19 | AD13: 23 | AE13: =AS13-AD13 -> 20 | AF13: 23 | AG13: =AT13-AF13 -> 23 | AH13: 26 | AI13: =AU13-AH13 -> 22 | AJ13: 26 | AL13: 0 | AM13: 0 | AN13: 81 | AO13: 80 | AP13: 82 | AQ13: 52 | AR13: 39 | AS13: 43 | AT13: 46 | AU13: 48
C14: A350 lavatories | D14: 71 | E14: =AB14-D14 -> 65 | F14: 53 | G14: =AE14-F14 -> 97 | H14: 106 | I14: =AF14-H14 -> 114 | J14: 99 | K14: =AG14-J14 -> 95 | L14: 81 | M14: =AH14-L14 -> 112 | N14: 139 | O14: =AU14-N14-M14-L14 -> 116 | P14: 51 | Q14: =AJ14-P14 -> 142 | R14: 126 | U14: =AN14-T14 -> 0 | V14: 241 | W14: =AO14-V14 -> 310 | X14: 400 | Y14: =AP14-X14 -> 371 | Z14: 199 | AA14: =AQ14-Z14 -> 153 | AB14: 136 | AC14: =AR14-AB14 -> 128 | AD14: 188 | AE14: =AS14-AD14 -> 150 | AF14: 220 | AG14: =AT14-AF14 -> 194 | AH14: 193 | AI14: =AU14-AH14 -> 255 | AJ14: 193 | AL14: 32 | AM14: 56 | AN14: 0 | AO14: 551 | AP14: 771 | AQ14: 352 | AR14: 264 | AS14: 338 | AT14: 414 | AU14: 448
C15: 787 landing gear sets | D15: 0 | E15: =AB15-D15 -> 25 | F15: 6 | G15: =AE15-F15 -> 14 | H15: 6 | I15: =AF15-H15 -> 4 | J15: 6 | K15: =AG15-J15 -> 14 | L15: 11 | M15: =AH15-L15 -> 9 | N15: 14 | O15: =AU15-N15-M15-L15 -> 7 | P15: 16 | Q15: =AJ15-P15 -> 4 | R15: 18 | T15: 66 | U15: =AN15-T15 -> 68 | V15: 74 | W15: =AO15-V15 -> 70 | X15: 84 | Y15: =AP15-X15 -> 81 | Z15: 62 | AA15: =AQ15-Z15 -> 58 | AB15: 25 | AC15: =AR15-AB15 -> 16 | AD15: 1 | AE15: =AS15-AD15 -> 20 | AF15: 10 | AG15: =AT15-AF15 -> 20 | AH15: 20 | AI15: =AU15-AH15 -> 21 | AJ15: 20 | AL15: 0 | AM15: 0 | AN15: 134 | AO15: 144 | AP15: 165 | AQ15: 120 | AR15: 41 | AS15: 21 | AT15: 30 | AU15: 41
C16: 787 primary power distribution systems | D16: 8 | E16: =AB16-D16 -> 126 | F16: 31 | G16: =AE16-F16 -> 52 | H16: 61 | I16: =AF16-H16 -> 66 | J16: 65 | K16: =AG16-J16 -> 90 | L16: 88 | M16: =AH16-L16 -> 81 | N16: 86 | O16: =AU16-N16-M16-L16 -> 89 | P16: 88 | Q16: =AJ16-P16 -> 81 | R16: 97 | U16: =AN16-T16 -> 0 | V16: 296 | W16: =AO16-V16 -> 424 | X16: 561 | Y16: =AP16-X16 -> 493 | Z16: 417 | AA16: =AQ16-Z16 -> 340 | AB16: 134 | AC16: =AR16-AB16 -> 25 | AD16: 29 | AE16: =AS16-AD16 -> 83 | AF16: 127 | AG16: =AT16-AF16 -> 155 | AH16: 169 | AI16: =AU16-AH16 -> 175 | AJ16: 169 | AL16: 127 | AM16: 128 | AN16: 0 | AO16: 720 | AP16: 1054 | AQ16: 757 | AR16: 159 | AS16: 112 | AT16: 282 | AU16: 344
C17: biz & regional jets small nacelles | D17: 117 | E17: =AB17-D17 -> 70 | F17: 113 | G17: =AE17-F17 -> 133 | H17: 134 | I17: =AF17-H17 -> 136 | J17: 137 | K17: =AG17-J17 -> 105 | L17: 121 | M17: =AH17-L17 -> 275 | N17: 169 | O17: =AU17-N17-M17-L17 -> 189 | P17: 181 | Q17: =AJ17-P17 -> 215 | R17: 195 | T17: 234 | U17: =AN17-T17 -> 243 | V17: 309 | W17: =AO17-V17 -> 339 | X17: 304 | Y17: =AP17-X17 -> 331 | Z17: 246 | AA17: =AQ17-Z17 -> 189 | AB17: 187 | AC17: =AR17-AB17 -> 205 | AD17: 270 | AE17: =AS17-AD17 -> 246 | AF17: 270 | AG17: =AT17-AF17 -> 242 | AH17: 396 | AI17: =AU17-AH17 -> 358 | AJ17: 396 | AL17: 711 | AM17: 600 | AN17: 477 | AO17: 648 | AP17: 635 | AQ17: 435 | AR17: 392 | AS17: 516 | AT17: 512 | AU17: 754
C18: Business class seats | D18: 346 | E18: =AB18-D18 -> 341 | F18: 377 | G18: =AE18-F18 -> 509 | H18: 324 | I18: =AF18-H18 -> 112 | J18: 174 | K18: =AG18-J18 -> 373 | L18: 242 | M18: =AH18-L18 -> 508 | N18: 592 | O18: =AU18-N18-M18-L18 -> 1140 | P18: 704 | Q18: =AJ18-P18 -> 46 | R18: 428 | U18: =AN18-T18 -> 0 | V18: 1495 | W18: =AO18-V18 -> 1919 | X18: 2537 | Y18: =AP18-X18 -> 3097 | Z18: 1689 | AA18: =AQ18-Z18 -> 1046 | AB18: 687 | AC18: =AR18-AB18 -> 1410 | AD18: 818 | AE18: =AS18-AD18 -> 886 | AF18: 436 | AG18: =AT18-AF18 -> 547 | AH18: 750 | AI18: =AU18-AH18 -> 1732 | AJ18: 750 | AL18: 0 | AM18: 0 | AN18: 0 | AO18: 3414 | AP18: 5634 | AQ18: 2735 | AR18: 2097 | AS18: 1704 | AT18: 983 | AU18: 2482
C19: A380 nacelles | T19: 21 | U19: =AN19-T19 -> 85 | V19: 20 | W19: =AO19-V19 -> 56 | X19: 12 | Y19: =AP19-X19 -> 12 | Z19: 8 | AA19: =AQ19-Z19 -> 9 | AL19: 104 | AM19: 99 | AN19: 106 | AO19: 76 | AP19: 24 | AQ19: 17
C20: A320 thrust reversers | U20: =AN20-T20 -> 504 | W20: =AO20-V20 -> 310 | X20: 105 | Y20: =AP20-X20 -> 38 | Z20: 29 | AA20: =AQ20-Z20 -> 15 | AL20: 564 | AM20: 548 | AN20: 504 | AO20: 310 | AP20: 143 | AQ20: 44
C21: A330 thrust reversers | T21: 52 | V21: 50 | AL21: 130 | AM21: 91
C22: Spaceflex V2 (A320 lavs and galleys) | U22: =AN22-T22 -> 0 | V22: 178 | W22: =AO22-V22 -> 248 | X22: 197 | Y22: =AP22-X22 -> 172 | Z22: 167 | AA22: =AQ22-Z22 -> 144 | AL22: 0 | AM22: 0 | AN22: 0 | AO22: 426 | AP22: 369 | AQ22: 311
B24: X | C24: Revenue-level information
C25: Propulsion
C26: Revenue | D26: 1942 | E26: 2234 | F26: 2503 | G26: 2827 | H26: 2714 | I26: 2963 | J26: 3083 | K26: 3116 | L26: 3097 | M26: 3364 | N26: 3339 | O26: 3852 | P26: 3684 | Q26: 3857 | R26: 4044 | T26: 4414 | U26: =AN26-T26 -> 4943 | V26: 4744 | W26: =AO26-V26 -> 5708 | X26: 5902 | Y26: =AP26-X26 -> 6143 | Z26: 4047 | AA26: =AQ26-Z26 -> 3616 | AB26: 3249 | AC26: =AR26-AB26 -> 4190 | AD26: 4176 | AE26: =AS26-AD26 -> 5330 | AF26: =H26+I26 -> 5677 | AG26: =AT26-AF26 -> 6199 | AH26: =L26+M26 -> 6461 | AI26: =AU26-AH26 -> 7191 | AJ26: 7541 | AL26: 9319 | AM26: 9391 | AN26: 9357 | AO26: 10452 | AP26: 12045 | AQ26: 7663 | AR26: 7439 | AS26: 9506 | AT26: 11876 | AU26: 13652
C27: Operating Income | T27: 721 | U27: =AN27-T27 -> 795 | V27: 868 | W27: =AO27-V27 -> 1061 | X27: 1227 | Y27: =AP27-X27 -> 1258 | Z27: 699 | AA27: =AQ27-Z27 -> 493 | AB27: 504 | AC27: =AR27-AB27 -> 838 | AD27: 723 | AE27: =AS27-AD27 -> 987 | AF27: 1051 | AG27: =AT27-AF27 -> 1339 | AH27: 1285 | AI27: =AU27-AH27 -> 1534 | AJ27: 1758 | AL27: 1833 | AM27: 1786 | AN27: 1516 | AO27: 1929 | AP27: 2485 | AQ27: 1192 | AR27: 1342 | AS27: 1710 | AT27: 2390 | AU27: 2819
C28: One-off item | T28: 0 | U28: =AN28-T28 -> -40 | V28: -1 | W28: =AO28-V28 -> -30 | X28: 0 | Y28: =AP28-X28 -> -7 | Z28: -20 | AA28: =AQ28-Z28 -> -137 | AB28: -133 | AC28: =AR28-AB28 -> -177 | AD28: -129 | AE28: =AS28-AD28 -> -15 | AF28: -5 | AG28: =AT28-AF28 -> -47 | AH28: 1 | AI28: =AU28-AH28 -> -27 | AJ28: 1 | AL28: -619 | AM28: 3 | AN28: -40 | AO28: -31 | AP28: -7 | AQ28: -157 | AR28: -310 | AS28: -144 | AT28: -52 | AU28: -26
C29: Profit (loss) from operations. | T29: =T27+T28 -> 721 | U29: =U27+U28 -> 755 | V29: =V27+V28 -> 867 | W29: =W27+W28 -> 1031 | X29: =X27+X28 -> 1227 | Y29: =Y27+Y28 -> 1251 | Z29: =Z27+Z28 -> 679 | AA29: =AA27+AA28 -> 356 | ... AJ29: =AJ27+AJ28 -> 1759 | AL29: =AL27+AL28 -> 1214 | AM29: =AM27+AM28 -> 1789 | AN29: =AN27+AN28 -> 1476 | AO29: =AO27+AO28 -> 1898 | AP29: =AP27+AP28 -> 2478 | AQ29: =AQ27+AQ28 -> 1035 | AR29: =AR27+AR28 -> 1032 | AS29: =AS27+AS28 -> 1566 | ... AU29: =AU27+AU28 -> 2793 | AV29: =((AU29/AL29)^(1/(2024-2015)))-1 -> 0.096997923
C30: mgn | T30: =T29/T26 -> 0.16334391 | U30: =U29/U26 -> 0.15274125 | V30: =V29/V26 -> 0.18275717 | W30: =W29/W26 -> 0.18062369 | X30: =X29/X26 -> 0.20789563 | Y30: =Y29/Y26 -> 0.20364643 | Z30: =Z29/Z26 -> 0.1677786 | AA30: =AA29/AA26 -> 0.098451327 | ... AJ30: =AJ29/AJ26 -> 0.23325819 | AK30: =(AI29+AJ29)/(AJ26+AI26) -> 0.22169427 | AL30: =AL29/AL26 -> 0.13027149 | AM30: =AM29/AM26 -> 0.19050154 | AN30: =AN29/AN26 -> 0.15774287 | AO30: =AO29/AO26 -> 0.18159204 | AP30: =AP29/AP26 -> 0.20572852 | AQ30: =AQ29/AQ26 -> 0.1350646 | AR30: =AR29/AR26 -> 0.13872832 | AS30: =AS29/AS26 -> 0.16473806 | ... AU30: =AU29/AU26 -> 0.20458541 | AV30: =((AU30/AL30)^(1/(2024-2015)))-1 -> 0.051430538
C31: Equipment & defense
C32: Revenue | D32: 1716 | E32: 1790 | F32: 1820 | G32: 2209 | H32: 1966 | I32: 2134 | J32: 2134 | K32: 3601 | L32: 2444 | M32: 2726 | N32: 2527 | O32: 1921 | P32: 2783 | Q32: 2826 | R32: 3004 | T32: =2636+612 -> 3248 | U32: =AN32-T32 -> 2012 | V32: =2585+651 -> 3236 | W32: =AO32-V32 -> 2159 | X32: 4553 | Y32: =AP32-X32 -> 4703 | Z32: 3638 | AA32: =AQ32-Z32 -> 3255 | AB32: 2972 | AC32: =AR32-AB32 -> 3353 | AD32: 3506 | AE32: =AS32-AD32 -> 4029 | AF32: =H32+I32 -> 4100 | AG32: =AT32-AF32 -> 4735 | AH32: =L32+M32 -> 5170 | AI32: =AU32-AH32 -> 5448 | AJ32: 5609 | AL32: =4943+1266 -> 6209 | AM32: =5145+1238 -> 6383 | AN32: 5260 | AO32: 5395 | AP32: 9256 | AQ32: 6893 | AR32: 6325 | AS32: 7535 | AT32: 8835 | AU32: 10618
C33: Operating Income | T33: =287+35 -> 322 | U33: =AN33-T33 -> 297 | V33: =347+45 -> 392 | W33: =AO33-V33 -> 378 | X33: 588 | Y33: =AP33-X33 -> 621 | Z33: 343 | AA33: =AQ33-Z33 -> 344 | AB33: 270 | AC33: =AR33-AB33 -> 380 | AD33: 411 | AE33: =AS33-AD33 -> 463 | AF33: 466 | AG33: =AT33-AF33 -> 526 | AH33: 657 | AI33: =AU33-AH33 -> 641 | AJ33: 703 | AL33: =466+64 -> 530 | AM33: =567+76 -> 643 | AN33: 619 | AO33: 770 | AP33: 1209 | AQ33: 687 | AR33: 650 | AS33: 874 | AT33: 992 | AU33: 1298
C34: One-off item | T34: 0 | U34: =AN34-T34 -> -14 | V34: =6+0 -> 6 | W34: =AO34-V34 -> -17 | X34: -1 | Y34: =AP34-X34 -> -20 | Z34: -73 | AA34: =AQ34-Z34 -> -160 | AB34: -59 | AC34: =AR34-AB34 -> -27 | AD34: 42 | AE34: =AS34-AD34 -> -2 | AF34: -7 | AG34: =AT34-AF34 -> -6 | AH34: -12 | AI34: =AU34-AH34 -> 77 | AJ34: -8 | AL34: =-43-10 -> -53 | AM34: =-5-7 -> -12 | AN34: -14 | AO34: -11 | AP34: -21 | AQ34: -233 | AR34: -86 | AS34: 40 | AT34: -13 | AU34: 65
C35: Profit (loss) from operations. | T35: =T33+T34 -> 322 | U35: =U33+U34 -> 283 | V35: =V33+V34 -> 398 | W35: =W33+W34 -> 361 | X35: =X33+X34 -> 587 | Y35: =Y33+Y34 -> 601 | Z35: =Z33+Z34 -> 270 | AA35: =AA33+AA34 -> 184 | ... AJ35: =AJ33+AJ34 -> 695 | AL35: =AL33+AL34 -> 477 | AM35: =AM33+AM34 -> 631 | AN35: =AN33+AN34 -> 605 | AO35: =AO33+AO34 -> 759 | AP35: =AP33+AP34 -> 1188 | AQ35: =AQ33+AQ34 -> 454 | AR35: =AR33+AR34 -> 564 | AS35: =AS33+AS34 -> 914 | ... AU35: =AU33+AU34 -> 1363 | AV35: =((AU35/AL35)^(1/(2024-2015)))-1 -> 0.12373566
C36: mgn | T36: =T35/T32 -> 0.099137931 | U36: =U35/U32 -> 0.14065606 | V36: =V35/V32 -> 0.12299135 | W36: =W35/W32 -> 0.16720704 | X36: =X35/X32 -> 0.12892598 | Y36: =Y35/Y32 -> 0.12779077 | Z36: =Z35/Z32 -> 0.074216603 | AA36: =AA35/AA32 -> 0.056528418 | ... AJ36: =AJ35/AJ32 -> 0.123908 | AL36: =AL35/AL32 -> 0.076823965 | AM36: =AM35/AM32 -> 0.098856337 | AN36: =AN35/AN32 -> 0.11501901 | AO36: =AO35/AO32 -> 0.14068582 | AP36: =AP35/AP32 -> 0.12834918 | AQ36: =AQ35/AQ32 -> 0.06586392 | AR36: =AR35/AR32 -> 0.08916996 | AS36: =AS35/AS32 -> 0.1213006 | ... AU36: =AU35/AU32 -> 0.12836692 | AV36: =((AU36/AL36)^(1/(2024-2015)))-1 -> 0.058700054
C37: Aircraft interiors
C38: Revenue | D38: 409 | E38: 461 | F38: 522 | G38: 586 | H38: 584 | I38: 579 | J38: 605 | K38: 709 | L38: 676 | M38: 735 | N38: 771 | O38: 855 | P38: 788 | Q38: 828 | R38: 802 | T38: 0 | U38: =AN38-T38 -> 1316 | V38: =742+774 -> 1516 | W38: =AO38-V38 -> -130 | X38: 1640 | Y38: =AP38-X38 -> 1681 | Z38: 1072 | AA38: =AQ38-Z38 -> 850 | AB38: 646 | AC38: =AR38-AB38 -> 829 | AD38: 870 | AE38: =AS38-AD38 -> 1108 | AF38: =H38+I38 -> 1163 | AG38: =AT38-AF38 -> 1314 | AH38: =L38+M38 -> 1411 | AI38: =AU38-AH38 -> 1626 | AJ38: 1616 | AN38: 1316 | AO38: 1386 | AP38: 3321 | AQ38: 1922 | AR38: 1475 | AS38: 1978 | AT38: 2477 | AU38: 3037
C39: Operating Income | T39: 0 | U39: =AN39-T39 -> 93 | V39: =129+0 -> 129 | W39: =AO39-V39 -> -11 | X39: 85 | Y39: =AP39-X39 -> 103 | Z39: -101 | AA39: =AQ39-Z39 -> -73 | AB39: -110 | AC39: =AR39-AB39 -> -57 | AD39: -82 | AE39: =AS39-AD39 -> -58 | AF39: -100 | AG39: =AT39-AF39 -> -16 | AH39: 10 | AI39: =AU39-AH39 -> 17 | AJ39: 27 | AN39: 93 | AO39: 118 | AP39: 188 | AQ39: -174 | AR39: -167 | AS39: -140 | AT39: -116 | AU39: 27
C40: One-off item | T40: 0 | U40: =AN40-T40 -> -14 | V40: =-1-2 -> -3 | W40: =AO40-V40 -> 6 | X40: -1 | Y40: =AP40-X40 -> -5 | Z40: -51 | AA40: =AQ40-Z40 -> -21 | AB40: -1 | AC40: =AR40-AB40 -> -16 | AD40: -4 | AE40: =AS40-AD40 -> -342 | AF40: -38 | AG40: =AT40-AF40 -> -390 | AH40: -9 | AI40: =AU40-AH40 -> -36 | AJ40: -29 | AN40: -14 | AO40: 3 | AP40: -6 | AQ40: -72 | AR40: -17 | AS40: -346 | AT40: -428 | AU40: -45
C41: Profit (loss) from operations. | T41: =T39+T40 -> 0 | U41: =U39+U40 -> 79 | V41: =V39+V40 -> 126 | W41: =W39+W40 -> -5 | X41: =X39+X40 -> 84 | Y41: =Y39+Y40 -> 98 | Z41: =Z39+Z40 -> -152 | AA41: =AA39+AA40 -> -94 | ... AJ41: =AJ39+AJ40 -> -2 | AN41: =AN39+AN40 -> 79 | AO41: =AO39+AO40 -> 121 | AP41: =AP39+AP40 -> 182 | AQ41: =AQ39+AQ40 -> -246 | AR41: =AR39+AR40 -> -184 | AS41: =AS39+AS40 -> -486 | AT41: =AT39+AT40 -> -544 | AU41: =AU39+AU40 -> -18
C42: mgn | T42: =T41/T38 -> #DIV/0! | U42: =U41/U38 -> 0.060030395 | V42: =V41/V38 -> 0.083113456 | W42: =W41/W38 -> 0.038461538 | X42: =X41/X38 -> 0.051219512 | Y42: =Y41/Y38 -> 0.058298632 | Z42: =Z41/Z38 -> -0.14179104 | AA42: =AA41/AA38 -> -0.11058824 | ... AJ42: =AJ41/AJ38 -> -0.0012376238 | AK42: =(AI41+AJ41)/(AJ38+AI38) -> -0.006477483 | AN42: =AN41/AN38 -> 0.060030395 | AO42: =AO41/AO38 -> 0.087301587 | AP42: =AP41/AP38 -> 0.05480277 | AQ42: =AQ41/AQ38 -> -0.12799168 | AR42: =AR41/AR38 -> -0.12474576 | AS42: =AS41/AS38 -> -0.24570273 | AT42: =AT41/AT38 -> -0.21962051 | AU42: =AU41/AU38 -> -0.0059269015 | AV42: =((AU42/AN42)^(1/(2024-2017)))-1 -> -1.7183745
C43: Holding Company & others | D43: 4 | E43: 4 | F43: 4 | G43: 4 | H43: 2 | I43: 3 | J43: 3 | K43: 3 | L43: 3 | M43: 2 | N43: 2 | O43: 3 | P43: 2 | Q43: 2 | R43: 2 | T43: 10 | Z43: 7 | AA43: 10 | AF43: =H43+I43 -> 5 | AG43: =AT43-AF43 -> 6 | AH43: =L43+M43 -> 5 | AI43: =AU43-AH43 -> 5 | AJ43: 3 | AL43: 8 | AM43: 7 | AN43: 20 | AO43: 18 | AP43: 18 | AQ43: 20 | AR43: 11 | AS43: 16 | AT43: 11 | AU43: 10
C45: Propulsion share of revenue | T45: =T26/T51 -> 0.57533889 | U45: =U26/U51 -> 0.59690859 | V45: =V26/V51 -> 0.49957877 | W45: =W26/W51 -> 0.73604126 | X45: =X26/X51 -> 0.48797024 | Y45: =Y26/Y51 -> 0.48967716 | Z45: =Z26/Z51 -> 0.46177545 | AA45: =AA26/AA51 -> 0.4675459 | ... AJ45: =AJ26/AJ51 -> 0.51059652 | AL45: =AL26/AL51 -> 0.59983265 | AM45: =AM26/AM51 -> 0.59508269 | AN45: =AN26/AN51 -> 0.58653545 | AO45: =AO26/AO51 -> 0.60587792 | AP45: =AP26/AP51 -> 0.48883929 | AQ45: =AQ26/AQ51 -> 0.46448054 | AR45: =AR26/AR51 -> 0.48780328 | AS45: =AS26/AS51 -> 0.49939585 | ... AU45: =AU26/AU51 -> 0.49976205
C46: Equipment/Defense share of revenue | T46: =T32/T51 -> 0.42335766 | U46: =U32/U51 -> 0.24296583 | V46: =V32/V51 -> 0.34077506 | W46: =W32/W51 -> 0.27840103 | X46: =X32/X51 -> 0.37643654 | Y46: =Y32/Y51 -> 0.37489039 | Z46: =Z32/Z51 -> 0.41510726 | AA46: =AA32/AA51 -> 0.42086889 | ... AJ46: =AJ32/AJ51 -> 0.37978198 | AL46: =AL32/AL51 -> 0.39965242 | AM46: =AM32/AM51 -> 0.40447373 | AN46: =AN32/AN51 -> 0.32971855 | AO46: =AO32/AO51 -> 0.31273549 | AP46: =AP32/AP51 -> 0.37564935 | AQ46: =AQ32/AQ51 -> 0.41780822 | AR46: =AR32/AR51 -> 0.4147541 | AS46: =AS32/AS51 -> 0.39584975 | ... AU46: =AU32/AU51 -> 0.38869568
C47: Interiors share of revenue | T47: =T38/T51 -> 0 | U47: =U38/U51 -> 0.15891801 | V47: =V38/V51 -> 0.15964617 | W47: =W38/W51 -> -0.016763378 | X47: =X38/X51 -> 0.13559322 | Y47: =Y38/Y51 -> 0.13399761 | Z47: =Z38/Z51 -> 0.12231858 | AA47: =AA38/AA51 -> 0.10990432 | ... AJ47: =AJ38/AJ51 -> 0.10941838 | AL47: =AL38/AL51 -> 0 | AM47: =AM38/AM51 -> 0 | AN47: =AN38/AN51 -> 0.082492321 | AO47: =AO38/AO51 -> 0.080343169 | AP47: =AP38/AP51 -> 0.13478084 | AQ47: =AQ38/AQ51 -> 0.11649897 | AR47: =AR38/AR51 -> 0.096721311 | AS47: =AS38/AS51 -> 0.10391384 | ... AU47: =AU38/AU51 -> 0.11117619
C48: Holding share of revenue | T48: =T43/T52 -> 0.0012482836 | U48: =U43/U52 -> 0 | V48: =V43/V52 -> 0 | W48: =W43/W52 -> 0 | X48: =X43/X52 -> 0 | Y48: =Y43/Y52 -> 0 | Z48: =Z43/Z52 -> 0.00078634015 | AA48: =AA43/AA52 -> 0.0012938284 | ... AJ48: =AJ43/AJ52 -> 0.00020181635 | AL48: =AL43/AL52 -> 0.00049315744 | AM48: =AM43/AM52 -> 0.00042470574 | AN48: =AN43/AN52 -> 0.0012212995 | AO48: =AO43/AO52 -> 0.00085612366 | AP48: =AP43/AP52 -> 0.00071718862 | AQ48: =AQ43/AQ52 -> 0.0012025735 | AR48: =AR43/AR52 -> 0.00072688826 | AS48: =AS43/AS52 -> 0.00081954618 | ... AU48: =AU43/AU52 -> 0.00036080242
H49: =SUM(H26:H43) -> 5266 | I49: =SUM(I26:I43) -> 5679 | J49: =SUM(J26:J43) -> 5825 | K49: =SUM(K26:K43) -> 7429 | L49: =SUM(L26:L43) -> 6220 | M49: =SUM(M26:M43) -> 6827 | N49: =SUM(N26:N43) -> 6639 | O49: =SUM(O26:O43) -> 6631 | ... R49: =SUM(R26:R43) -> 7852 | AJ49: =(AJ50/AL51)^(1/(2025-2015))-1 -> 0.064545539
B50: X | C50: Consolidated | AJ50: =+AJ51+AI51 -> 29039
C51: Revenue | D51: =D43+D38+D32+D26 -> 4071 | E51: =E43+E38+E32+E26 -> 4489 | F51: =F43+F38+F32+F26 -> 4849 | G51: =G43+G38+G32+G26 -> 5626 | H51: =H43+H38+H32+H26 -> 5266 | I51: =I43+I38+I32+I26 -> 5679 | J51: =J43+J38+J32+J26 -> 5825 | K51: =K43+K38+K32+K26 -> 7429 | ... R51: =R43+R38+R32+R26 -> 7852 | T51: =T43+T38+T32+T26 -> 7672 | U51: =AN51-T51 -> 8281 | V51: =V43+V38+V32+V26 -> 9496 | W51: =AO51-V51 -> 7755 | X51: =X43+X38+X32+X26 -> 12095 | Y51: =AP51-X51 -> 12545 | Z51: =Z43+Z38+Z32+Z26 -> 8764 | AA51: =AQ51-Z51 -> 7734 | AB51: =AB43+AB38+AB32+AB26 -> 6867 | AC51: =AR51-AB51 -> 8383 | AD51: =AD43+AD38+AD32+AD26 -> 8552 | AE51: =AS51-AD51 -> 10483 | AF51: =AF43+AF38+AF32+AF26 -> 10945 | AG51: =AT51-AF51 -> 12254 | AH51: =AH43+AH38+AH32+AH26 -> 13047 | AI51: =AI43+AI38+AI32+AI26 -> 14270 | AJ51: =AJ43+AJ38+AJ32+AJ26 -> 14769 | AL51: =AL43+AL38+AL32+AL26 -> 15536 | AM51: =AM43+AM38+AM32+AM26 -> 15781 | AN51: =AN43+AN38+AN32+AN26 -> 15953 | AO51: =AO43+AO38+AO32+AO26 -> 17251 | AP51: =AP43+AP38+AP32+AP26 -> 24640 | AQ51: =AQ43+AQ38+AQ32+AQ26 -> 16498 | AR51: =AR43+AR38+AR32+AR26 -> 15250 | AS51: =AS43+AS38+AS32+AS26 -> 19035 | ... AU51: =AU43+AU38+AU32+AU26 -> 27317
C52: Revenue (adjusted) | T52: 8011 | U52: =AN52-T52 -> 8365 | V52: 9393 | W52: =AO52-V52 -> 11632 | X52: 12315 | Y52: =AP52-X52 -> 12783 | Z52: 8902 | AA52: =AQ52-Z52 -> 7729 | AB52: 6769 | AC52: =AR52-AB52 -> 8364 | AD52: 8675 | AE52: =AS52-AD52 -> 10848 | AF52: 11129 | AG52: =AT52-AF52 -> 12522 | AH52: 13204 | AI52: =AU52-AH52 -> 14512 | AJ52: 14865 | AL52: 16222 | AM52: 16482 | AN52: 16376 | AO52: 21025 | AP52: 25098 | AQ52: 16631 | AR52: 15133 | AS52: 19523 | AT52: 23651 | AU52: 27716
C53: Y/Y growth | AM53: =(AM52/AL52)-1 -> 0.016027617 | AN53: =(AN52/AM52)-1 -> -0.0064312583 | AO53: =(AO52/AN52)-1 -> 0.28389106 | AP53: =(AP52/AO52)-1 -> 0.19372176 | AQ53: =(AQ52/AP52)-1 -> -0.33735756 | AR53: =(AR52/AQ52)-1 -> -0.090072756 | AS53: =(AS52/AR52)-1 -> 0.2900945 | AT53: =(AT52/AS52)-1 -> 0.21144291 | AU53: =(AU52/AT52)-1 -> 0.17187434
C54: Other Income | T54: 143 | U54: =AN54-T54 -> 137 | V54: 148 | W54: =AO54-V54 -> 173 | X54: 138 | Y54: =AP54-X54 -> 159 | Z54: 109 | AA54: =AQ54-Z54 -> 158 | AB54: 166 | AC54: =AR54-AB54 -> 207 | AD54: 210 | AE54: =AS54-AD54 -> 230 | AF54: 226 | AG54: =AT54-AF54 -> 248 | AH54: 208 | AI54: =AU54-AH54 -> 230 | AJ54: 210 | AL54: 285 | AM54: 277 | AN54: 280 | AO54: 321 | AP54: 297 | AQ54: 267 | AR54: 373 | AS54: 440 | AT54: 474 | AU54: 438
C55: Income from operations | T55: =T52+T54 -> 8154 | U55: =U52+U54 -> 8502 | V55: =V52+V54 -> 9541 | W55: =W52+W54 -> 11805 | X55: =X52+X54 -> 12453 | Y55: =Y52+Y54 -> 12942 | Z55: =Z52+Z54 -> 9011 | AA55: =AA52+AA54 -> 7887 | ... AJ55: =AJ52+AJ54 -> 15075 | AL55: =AL52+AL54 -> 16507 | AM55: =AM52+AM54 -> 16759 | AN55: =AN52+AN54 -> 16656 | AO55: =AO52+AO54 -> 21346 | AP55: =AP52+AP54 -> 25395 | AQ55: =AQ52+AQ54 -> 16898 | AR55: =AR52+AR54 -> 15506 | AS55: =AS52+AS54 -> 19963 | ... AU55: =AU52+AU54 -> 28154 | AV55: =((AU55/AL55)^(1/(2024-2015)))-1 -> 0.06111768
C56: Y/Y growth | AM56: =(AM55/AL55)-1 -> 0.015266251 | AN56: =(AN55/AM55)-1 -> -0.0061459514 | AO56: =(AO55/AN55)-1 -> 0.28158021 | AP56: =(AP55/AO55)-1 -> 0.18968425 | AQ56: =(AQ55/AP55)-1 -> -0.33459342 | AR56: =(AR55/AQ55)-1 -> -0.082376613 | AS56: =(AS55/AR55)-1 -> 0.28743712 | AT56: =(AT55/AS55)-1 -> 0.2084857 | AU56: =(AU55/AT55)-1 -> 0.16700518
C57: Changes in inventories of finished goods & work-in-progress | T57: 427 | U57: =AN57-T57 -> -232 | V57: 112 | W57: =AO57-V57 -> -109 | X57: 492 | Y57: =AP57-X57 -> -39 | Z57: -39 | AA57: =AQ57-Z57 -> -826 | AB57: 34 | AC57: =AR57-AB57 -> -233 | AD57: 830 | AE57: =AS57-AD57 -> 374 | AF57: 707 | AG57: =AT57-AF57 -> 293 | AH57: 867 | AI57: =AU57-AH57 -> 122 | AJ57: 761 | AL57: 257 | AM57: 308 | AN57: 195 | AO57: 3 | AP57: 453 | AQ57: -865 | AR57: -199 | AS57: 1204 | AT57: 1000 | AU57: 989
C58: Capitalized production | T58: 247 | U58: =AN58-T58 -> 275 | V58: 197 | W58: =AO58-V58 -> 250 | X58: 215 | Y58: =AP58-X58 -> 223 | Z58: 152 | AA58: =AQ58-Z58 -> 177 | AB58: 155 | AC58: =AR58-AB58 -> 217 | AD58: 169 | AE58: =AS58-AD58 -> 213 | AF58: 214 | AG58: =AT58-AF58 -> 266 | AH58: 235 | AI58: =AU58-AH58 -> 291 | AJ58: 245 | AL58: 946 | AM58: 624 | AN58: 522 | AO58: 447 | AP58: 438 | AQ58: 329 | AR58: 372 | AS58: 382 | AT58: 480 | AU58: 526
C59: Raw materials and consumables used | T59: -4784 | U59: =AN59-T59 -> -4665 | V59: -5574 | W59: =AO59-V59 -> -6866 | X59: -7268 | Y59: =AP59-X59 -> -7180 | Z59: -4677 | AA59: =AQ59-Z59 -> -3773 | AB59: -3649 | AC59: =AR59-AB59 -> -4350 | AD59: -5242 | AE59: =AS59-AD59 -> -6482 | AF59: -6706 | AG59: =AT59-AF59 -> -7366 | AH59: -7822 | AI59: =AU59-AH59 -> -8138 | AJ59: -8320 | AL59: -9275 | AM59: -9340 | AN59: -9449 | AO59: -12440 | AP59: -14448 | AQ59: -8450 | AR59: -7999 | AS59: -11724 | AT59: -14072 | AU59: -15960
C60: Personnel costs | T60: -2237 | U60: =AN60-T60 -> -2116 | V60: -2770 | W60: =AO60-V60 -> -2895 | X60: -3185 | Y60: =AP60-X60 -> -3164 | Z60: -2759 | AA60: =AQ60-Z60 -> -2269 | AB60: -2496 | AC60: =AR60-AB60 -> -2423 | AD60: -2871 | AE60: =AS60-AD60 -> -2921 | AF60: -3367 | AG60: =AT60-AF60 -> -3400 | AH60: -3932 | AI60: =AU60-AH60 -> -3869 | AJ60: -4334 | AL60: -4524 | AM60: -4406 | AN60: -4353 | AO60: -5665 | AP60: -6349 | AQ60: -5028 | AR60: -4919 | AS60: -5792 | AT60: -6767 | AU60: -7801
C61: Taxes | T61: -165 | U61: =AN61-T61 -> -119 | V61: -179 | W61: =AO61-V61 -> -116 | X61: -258 | Y61: =AP61-X61 -> -130 | Z61: -203 | AA61: =AQ61-Z61 -> -123 | AB61: -151 | AC61: =AR61-AB61 -> -106 | AD61: -160 | AE61: =AS61-AD61 -> -130 | AF61: -173 | AG61: =AT61-AF61 -> -135 | AH61: -194 | AI61: =AU61-AH61 -> -143 | AJ61: -239 | AL61: -277 | AM61: -286 | AN61: -284 | AO61: -295 | AP61: -388 | AQ61: -326 | AR61: -257 | AS61: -290 | AT61: -308 | AU61: -337
C62: Depreciation, amortization and increased in provisions | T62: -360 | U62: =AN62-T62 -> -652 | V62: -478 | W62: =AO62-V62 -> -698 | X62: -698 | Y62: =AP62-X62 -> -902 | Z62: -639 | AA62: =AQ62-Z62 -> -573 | AB62: -659 | AC62: =AR62-AB62 -> -850 | AD62: -622 | AE62: =AS62-AD62 -> -552 | AF62: -609 | AG62: =AT62-AF62 -> -673 | AH62: -765 | AI62: =AU62-AH62 -> -813 | AJ62: -652 | AL62: -763 | AM62: -634 | AN62: -1012 | AO62: -1176 | AP62: -1600 | AQ62: -1212 | AR62: -1509 | AS62: -1174 | AT62: -1282 | AU62: -1578
C63: Asset impairment | T63: -80 | U63: =AN63-T63 -> 20 | V63: -20 | W63: =AO63-V63 -> 82 | X63: -21 | Y63: =AP63-X63 -> 78 | Z63: -86 | AA63: =AQ63-Z63 -> -63 | AB63: 31 | AC63: =AR63-AB63 -> 47 | AD63: -90 | AE63: =AS63-AD63 -> -162 | AF63: -104 | AG63: =AT63-AF63 -> 54 | AH63: 56 | AI63: =AU63-AH63 -> -38 | AJ63: -145 | AL63: -179 | AM63: -237 | AN63: -60 | AO63: 62 | AP63: 57 | AQ63: -149 | AR63: 78 | AS63: -252 | AT63: -50 | AU63: 18
C64: Other recurring operating income and expenses | T64: 52 | U64: =AN64-T64 -> 107 | V64: 20 | W64: =AO64-V64 -> -211 | X64: 83 | Y64: =AP64-X64 -> 19 | Z64: 70 | AA64: =AQ64-Z64 -> 78 | AB64: 115 | AC64: =AR64-AB64 -> 41 | AD64: 53 | AE64: =AS64-AD64 -> 50 | AF64: 40 | AG64: =AT64-AF64 -> 44 | AH64: 60 | AI64: =AU64-AH64 -> -21 | AJ64: 12 | AL64: 118 | AM64: 115 | AN64: 159 | AO64: -191 | AP64: 102 | AQ64: 148 | AR64: 156 | AS64: 103 | AT64: 84 | AU64: 39
C65: Share in profit from joint ventures | T65: 57 | U65: =AN65-T65 -> 87 | V65: 63 | W65: =AO65-V65 -> 126 | X65: 64 | Y65: =AP65-X65 -> 100 | Z65: 29 | AA65: =AQ65-Z65 -> 19 | AB65: 36 | AC65: =AR65-AB65 -> 4 | AD65: 16 | AE65: =AS65-AD65 -> 57 | AF65: 49 | AG65: =AT65-AF65 -> 50 | AH65: 51 | AI65: =AU65-AH65 -> 85 | AJ65: 65 | AL65: 44 | AM65: 87 | AN65: 144 | AO65: 189 | AP65: 164 | AQ65: 48 | AR65: 40 | AS65: 73 | AT65: 99 | AU65: 136
C66: OpEx | T66: =SUM(T57:T65) -> -6843 | U66: =SUM(U57:U65) -> -7295 | V66: =SUM(V57:V65) -> -8629 | W66: =SUM(W57:W65) -> -10437 | X66: =SUM(X57:X65) -> -10576 | Y66: =SUM(Y57:Y65) -> -10995 | Z66: =SUM(Z57:Z65) -> -8152 | AA66: =SUM(AA57:AA65) -> -7353 | ... AJ66: =SUM(AJ57:AJ65) -> -12607 | AL66: =SUM(AL57:AL65) -> -13653 | AM66: =SUM(AM57:AM65) -> -13769 | AN66: =SUM(AN57:AN65) -> -14138 | AO66: =SUM(AO57:AO65) -> -19066 | AP66: =SUM(AP57:AP65) -> -21571 | AQ66: =SUM(AQ57:AQ65) -> -15505 | AR66: =SUM(AR57:AR65) -> -14237 | AS66: =SUM(AS57:AS65) -> -17470 | ... AU66: =SUM(AU57:AU65) -> -23968
C67: Recurring operating income | T67: =T55+T66 -> 1311 | U67: =U55+U66 -> 1207 | V67: =V55+V66 -> 912 | W67: =W55+W66 -> 1368 | X67: =X55+X66 -> 1877 | Y67: =Y55+Y66 -> 1947 | Z67: =Z55+Z66 -> 859 | AA67: =AA55+AA66 -> 534 | ... AJ67: =AJ55+AJ66 -> 2468 | AL67: =AL55+AL66 -> 2854 | AM67: =AM55+AM66 -> 2990 | AN67: =AN55+AN66 -> 2518 | AO67: =AO55+AO66 -> 2280 | AP67: =AP55+AP66 -> 3824 | AQ67: =AQ55+AQ66 -> 1393 | AR67: =AR55+AR66 -> 1269 | AS67: =AS55+AS66 -> 2493 | ... AU67: =AU55+AU66 -> 4186 | AV67: =((AU67/AL67)^(1/(2024-2015)))-1 -> 0.04347682
C68: Share in profit from joint ventures | T68: -16 | U68: =AN68-T68 -> -74 | V68: -26 | W68: =AO68-V68 -> -89 | X68: 32 | Y68: =AP68-X68 -> -19 | Z68: -144 | AA68: =AQ68-Z68 -> -322 | AB68: -195 | AC68: =AR68-AB68 -> -210 | AD68: -92 | AE68: =AS68-AD68 -> -358 | AF68: -57 | AG68: =AT68-AF68 -> -454 | AH68: -24 | AI68: =AU68-AH68 -> 30 | AJ68: -37 | AL68: -778 | AM68: 349 | AN68: -90 | AO68: -115 | AP68: 13 | AQ68: -466 | AR68: -405 | AS68: -450 | AT68: -511 | AU68: 6
C69: Profit from operations | T69: =T67+T68 -> 1295 | U69: =U67+U68 -> 1133 | V69: =V67+V68 -> 886 | W69: =W67+W68 -> 1279 | X69: =X67+X68 -> 1909 | Y69: =Y67+Y68 -> 1928 | Z69: =Z67+Z68 -> 715 | AA69: =AA67+AA68 -> 212 | ... AJ69: =AJ67+AJ68 -> 2431 | AL69: =AL67+AL68 -> 2076 | AM69: =AM67+AM68 -> 3339 | AN69: =AN67+AN68 -> 2428 | AO69: =AO67+AO68 -> 2165 | AP69: =AP67+AP68 -> 3837 | AQ69: =AQ67+AQ68 -> 927 | AR69: =AR67+AR68 -> 864 | AS69: =AS67+AS68 -> 2043 | ... AU69: =AU67+AU68 -> 4192
C70: Margin | AJ70: =(AJ69+AI69)/(AJ51+AI51) -> 0.16112814 | AL70: =AL69/AL52 -> 0.12797436 | AM70: =AM69/AM52 -> 0.20258464 | AN70: =AN69/AN52 -> 0.14826575 | AO70: =AO69/AO52 -> 0.10297265 | AP70: =AP69/AP52 -> 0.15288071 | AQ70: =AQ69/AQ52 -> 0.055739282 | AR70: =AR69/AR52 -> 0.057093769 | AS70: =AS69/AS52 -> 0.1046458 | ... AU70: =AU69/AU52 -> 0.15124838
C71: Cost of net debt | T71: -28 | U71: =AN71-T71 -> -29 | V71: -34 | W71: =AO71-V71 -> -33 | X71: -21 | Z71: -20 | AA71: =AQ71-Z71 -> -38 | AB71: -51 | AC71: =AR71-AB71 -> -34 | AD71: -38 | AE71: =AS71-AD71 -> -18 | AF71: 42 | AG71: =AT71-AF71 -> 70 | AH71: 84 | AI71: =AU71-AH71 -> 73 | AJ71: 77 | AL71: -29 | AM71: -51 | AN71: -57 | AO71: -67 | AP71: -33 | AQ71: -58 | AR71: -85 | AS71: -56 | AT71: 112 | AU71: 157
C72: ForEx gans (losses) | T72: 2384 | U72: =AN72-T72 -> 687 | V72: -175 | W72: =AO72-V72 -> -176 | X72: 150 | Y72: =AP72-X72 -> -433 | Z72: -1181 | AA72: =AQ72-Z72 -> 924 | AB72: 860 | AC72: =AR72-AB72 -> -1357 | AD72: -5828 | AE72: =AS72-AD72 -> 756 | AF72: 1123 | AG72: =AT72-AF72 -> 727 | AH72: -1961 | AI72: =AU72-AH72 -> -3219 | AJ72: 4628 | AL72: -3270 | AM72: -943 | AN72: 3071 | AO72: -351 | AP72: -283 | AQ72: -257 | AR72: -497 | AS72: -5072 | AT72: 1850 | AU72: -5180
C73: Other financial income/expense | T73: -3 | U73: =AN73-T73 -> 1 | V73: -11 | W73: =AO73-V73 -> -47 | X73: -23 | Y73: =AP73-X73 -> -24 | Z73: -46 | AA73: =AQ73-Z73 -> 4 | AB73: -5 | AC73: =AR73-AB73 -> -9 | AD73: -40 | AE73: =AS73-AD73 -> 5 | AF73: 0 | AG73: =AT73-AF73 -> -4 | AH73: 1 | AI73: =AU73-AH73 -> -29 | AJ73: 35 | AL73: -109 | AM73: -58 | AN73: -2 | AO73: -58 | AP73: -47 | AQ73: -42 | AR73: -14 | AS73: -35 | AT73: -4 | AU73: -28
C74: Income (loss) from financing | T74: =SUM(T71:T73) -> 2353 | U74: =SUM(U71:U73) -> 659 | V74: =SUM(V71:V73) -> -220 | W74: =SUM(W71:W73) -> -256 | X74: =SUM(X71:X73) -> 106 | Y74: =SUM(Y71:Y73) -> -457 | Z74: =SUM(Z71:Z73) -> -1247 | AA74: =SUM(AA71:AA73) -> 890 | ... AJ74: =SUM(AJ71:AJ73) -> 4740 | AL74: =SUM(AL71:AL73) -> -3408 | AM74: =SUM(AM71:AM73) -> -1052 | AN74: =SUM(AN71:AN73) -> 3012 | AO74: =SUM(AO71:AO73) -> -476 | AP74: =SUM(AP71:AP73) -> -363 | AQ74: =SUM(AQ71:AQ73) -> -357 | AR74: =SUM(AR71:AR73) -> -596 | AS74: =SUM(AS71:AS73) -> -5163 | ... AU74: =SUM(AU71:AU73) -> -5051
C75: EBT | T75: =T69+T74 -> 3648 | U75: =U69+U74 -> 1792 | V75: =V69+V74 -> 666 | W75: =W69+W74 -> 1023 | X75: =X69+X74 -> 2015 | Y75: =Y69+Y74 -> 1471 | Z75: =Z69+Z74 -> -532 | AA75: =AA69+AA74 -> 1102 | ... AJ75: =AJ69+AJ74 -> 7171 | AL75: =AL69+AL74 -> -1332 | AM75: =AM69+AM74 -> 2287 | AN75: =AN69+AN74 -> 5440 | AO75: =AO69+AO74 -> 1689 | AP75: =AP69+AP74 -> 3474 | AQ75: =AQ69+AQ74 -> 570 | AR75: =AR69+AR74 -> 268 | AS75: =AS69+AS74 -> -3120 | ... AU75: =AU69+AU74 -> -859
C76: Income tax expense | T76: -1171 | U76: =AN76-T76 -> -489 | V76: -100 | W76: =AO76-V76 -> -248 | X76: -550 | Y76: =AP76-X76 -> -412 | Z76: 207 | AA76: =AQ76-Z76 -> -391 | AB76: -273 | AC76: =AR76-AB76 -> 73 | AD76: 1283 | AE76: =AS76-AD76 -> -589 | AF76: -609 | AG76: =AT76-AF76 -> -627 | AH76: 38 | AI76: =AU76-AH76 -> 246 | AJ76: -2059 | AL76: 505 | AM76: -398 | AN76: -1660 | AO76: -348 | AP76: -962 | AQ76: -184 | AR76: -200 | AS76: 694 | AT76: -1236 | AU76: 284
AL77: =AL76/AL75 -> -0.37912913 | AM77: =AM76/AM75 -> -0.17402711 | AN77: =AN76/AN75 -> -0.30514706 | AO77: =AO76/AO75 -> -0.20603908 | AP77: =AP76/AP75 -> -0.27691422 | AQ77: =AQ76/AQ75 -> -0.32280702 | AR77: =AR76/AR75 -> -0.74626866 | AS77: =AS76/AS75 -> -0.2224359 | ... AU77: =AU76/AU75 -> -0.330617
C78: Net income | T78: =T75+T76+773 -> 3250 | V78: =V75+V76 -> 566 | W78: =W75+W76 -> 775 | X78: =X75+X76 -> 1465 | Y78: =Y75+Y76 -> 1059 | Z78: =Z75+Z76 -> -325 | AA78: =AA75+AA76 -> 711 | AB78: =AB75+AB76 -> 687 | AC78: =AC75+AC76 -> -619 | ... AJ78: =AJ75+AJ76 -> 5112 | AL78: =AL75+AL76+421+21 -> -385 | AM78: =AM75+AM76+74 -> 1963 | AN78: =AN75+AN76+831 -> 4611 | AO78: =AO75+AO76 -> 1341 | AP78: =AP75+AP76 -> 2512 | AQ78: =AQ75+AQ76 -> 386 | AR78: =AR75+AR76 -> 68 | AS78: =AS75+AS76 -> -2426 | AT78: =AT75+AT76 -> 3520 | AU78: =AU75+AU76 -> -575 | AV78: =((AU78/AL78)^(1/(2024-2015)))-1 -> 0.045577782
C79: Attributable to owners | T79: 2449 | V79: 535 | X79: 1432 | Z79: -340 | AB79: 674 | AD79: -3762 | AF79: 1863 | AH79: 57 | AJ79: 5045 | AL79: -424 | AM79: 1283 | AN79: 4550 | AO79: 1283 | AP79: 2447 | AQ79: 352 | AR79: 43 | AS79: -2459 | AT79: 3444 | AU79: -667
C80: Attributable to non-controlling | T80: =T78-T79 -> 801 | V80: =V78-V79 -> 31 | X80: =X78-X79 -> 33 | Z80: =Z78-Z79 -> 15 | AB80: =AB78-AB79 -> 13 | AD80: =AD78-AD79 -> 15 | AF80: =AF78-AF79 -> 42 | AH80: =AH78-AH79 -> 49 | AJ80: =AJ78-AJ79 -> 67 | AL80: =AL78-AL79 -> 39 | AM80: =AM78-AM79 -> 680 | AN80: =AN78-AN79 -> 61 | AO80: =AO78-AO79 -> 58 | AP80: =AP78-AP79 -> 65 | AQ80: =AQ78-AQ79 -> 34 | AR80: =AR78-AR79 -> 25 | AS80: =AS78-AS79 -> 33 | ... AU80: =AU78-AU79 -> 92
C82: Basic shares outstanding | T82: 411.22486 | V82: 428.93557 | X82: 432.21826 | Z82: 425.15518 | AB82: 426.62255 | AD82: 426.83258 | AF82: 420.44786 | AG82: =AT82 -> 417.79549 | AH82: 424.91398 | AI82: 424.91398 | AJ82: 417.93473 | AL82: 416.42814 | AM82: 416.32512 | AN82: 410.24104 | AO82: 430.91181 | AP82: 429.72337 | AQ82: 426.03573 | AR82: 426.65042 | AS82: 426.68066 | AT82: 417.79549 | AU82: 416.14953 | AV82: =((AU82/AL82)^(1/(2024-2015)))-1 -> -7.4361738e-05
C83: Diluted Shares outstanding | T83: 418.50206 | V83: 441.22285 | X83: 437.834 | Z83: 437.74524 | AB83: 440.79065 | AD83: 440.31538 | AF83: 434.53435 | AG83: =AT83 -> 431.37356 | AH83: 437.78017 | AI83: 437.78017 | AJ83: 417.93473 | AL83: 416.42814 | AM83: 423.61895 | AN83: 417.51825 | AO83: 436.33563 | AP83: 434.97673 | AQ83: 440.46049 | AR83: 440.08703 | AS83: 440.15993 | AT83: 431.37356 | AU83: 420.72235 | AV83: =((AU83/AL83)^(1/(2024-2015)))-1 -> 0.0011405609
C84: Basic EPS (from continuing) | T84: =T$79/T82 -> 5.9553793 | V84: =V$79/V82 -> 1.2472736 | X84: =X$79/X82 -> 3.3131409 | Z84: =Z$79/Z82 -> -0.799708 | AB84: =AB$79/AB82 -> 1.5798509 | AD84: =AD$79/AD82 -> -8.8137601 | AF84: =AF$79/AF82 -> 4.4309893 | AH84: =AH$79/AH82 -> 0.1341448 | AJ84: =AJ$79/AJ82 -> 12.071263 | AL84: -1.08 | AM84: 4.41 | AN84: 9.07 | AO84: =AO$79/AO82 -> 2.9774074 | AP84: =AP$79/AP82 -> 5.694361 | AQ84: =AQ$79/AQ82 -> 0.82622178 | AR84: =AR$79/AR82 -> 0.10078509 | AS84: =AS$79/AS82 -> -5.7630923 | AT84: =AT$79/AT82 -> 8.2432675 | AU84: =AU$79/AU82 -> -1.6027893
C85: Diluted EPS (from continuing) | T85: =T$79/T83 -> 5.851823 | V85: =V$79/V83 -> 1.2125392 | X85: =X$79/X83 -> 3.2706459 | Z85: =Z$79/Z83 -> -0.77670747 | AB85: =AB$79/AB83 -> 1.5290705 | AD85: =AD$79/AD83 -> -8.5438759 | AF85: =AF$79/AF83 -> 4.287348 | AH85: =AH$79/AH83 -> 0.13020233 | AJ85: =AJ$79/AJ83 -> 12.071263 | AL85: -1.08 | AM85: 4.33 | AN85: 8.91 | AO85: =AO$79/AO83 -> 2.940397 | AP85: =AP$79/AP83 -> 5.6255883 | AQ85: =AQ$79/AQ83 -> 0.79916361 | AR85: =AR$79/AR83 -> 0.097707947 | AS85: =AS$79/AS83 -> -5.5866058 | AT85: =AT$79/AT83 -> 7.9837995 | AU85: =AU$79/AU83 -> -1.5853686
B87: X | C87: ASSETS
C88: Goodwill | V88: 7346 | X88: 5199 | Z88: 5197 | AB88: 5086 | AD88: 5124 | AF88: 4941 | AH88: 4687 | AJ88: 4864 | AL88: 3590 | AM88: 1864 | AN88: 1831 | AO88: 5173 | AP88: 5199 | AQ88: 5060 | AR88: 5068 | AS88: 4994 | AT88: 4706 | AU88: 4937
C89: Intangible assets | V89: 6285 | X89: 9479 | Z89: 9208 | AB89: 8580 | AD89: 8170 | AF89: 7971 | AH89: 7968 | AJ89: 7820 | AL89: 5321 | AM89: 5178 | AN89: 5596 | AO89: 9757 | AP89: 9479 | AQ89: 8676 | AR89: 8382 | AS89: 8096 | AT89: 7830 | AU89: 7947
C90: PPE | V90: 4116 | X90: 4398 | Z90: 4263 | AB90: 3972 | AD90: 3970 | AF90: 3917 | AH90: 4362 | AJ90: 4780 | AL90: 3272 | AM90: 3169 | AN90: 3518 | AO90: 4454 | AP90: 4398 | AQ90: 4055 | AR90: 3937 | AS90: 3847 | AT90: 4121 | AU90: 4629
C91: Right-of-use assets | V91: 0 | X91: 732 | Z91: 676 | AB91: 609 | AD91: 588 | AF91: 569 | AH91: 659 | AJ91: 728 | AL91: 0 | AM91: 0 | AN91: 0 | AO91: 0 | AP91: 732 | AQ91: 623 | AR91: 606 | AS91: 566 | AT91: 582 | AU91: 653
C92: non-current financial assets | V92: 459 | X92: 429 | Z92: 410 | AB92: 659 | AD92: 746 | AF92: 667 | AH92: 1212 | AJ92: 802 | AL92: 419 | AM92: 382 | AN92: 324 | AO92: 416 | AP92: 429 | AQ92: 431 | AR92: 688 | AS92: 752 | AT92: 997 | AU92: 1073
C93: Investments in equity-accounted companies | V93: 2144 | X93: 2211 | Z93: 2199 | AB93: 2049 | AD93: 1992 | AF93: 1914 | AH93: 1923 | AJ93: 1861 | AL93: 765 | AM93: 2175 | AN93: 2127 | AO93: 2253 | AP93: 2211 | AQ93: 2126 | AR93: 1969 | AS93: 1974 | AT93: 1928 | AU93: 1894
C94: Non-current derivatives | V94: 12 | X94: 33 | Z94: 63 | AB94: 39 | AD94: 6 | AF94: 9 | AH94: 0 | AJ94: 0 | AL94: 35 | AM94: 28 | AN94: 16 | AO94: 13 | AP94: 33 | AQ94: 52 | AR94: 23 | AS94: 18 | AT94: 0 | AU94: 4
C95: Deferred tax assets | V95: 398 | X95: 251 | Z95: 588 | AB95: 177 | AD95: 1887 | AF95: 1297 | AH95: 2024 | AJ95: 263 | AL95: 984 | AM95: 1351 | AN95: 251 | AO95: 391 | AP95: 251 | AQ95: 316 | AR95: 449 | AS95: 1576 | AT95: 1122 | AU95: 2349
C96: Other non-current financial assets | V96: 5 | X96: 4 | Z96: 4 | AB96: 10 | AD96: 9 | AF96: 5 | AH96: 4 | AJ96: 0 | AL96: 0 | AM96: 0 | AN96: 0 | AO96: 4 | AP96: 4 | AQ96: 4 | AR96: 11 | AS96: 8 | AT96: 7 | AU96: 3
C97: Noncurrent assets | V97: =SUM(V88:V96) -> 20765 | X97: =SUM(X88:X96) -> 22736 | Z97: =SUM(Z88:Z96) -> 22608 | AB97: =SUM(AB88:AB96) -> 21181 | AD97: =SUM(AD88:AD96) -> 22492 | AF97: =SUM(AF88:AF96) -> 21290 | AH97: =SUM(AH88:AH96) -> 22839 | AJ97: =SUM(AJ88:AJ96) -> 21118 | AL97: =SUM(AL88:AL96) -> 14386 | AM97: =SUM(AM88:AM96) -> 14147 | AN97: =SUM(AN88:AN96) -> 13663 | AO97: =SUM(AO88:AO96) -> 22461 | AP97: =SUM(AP88:AP96) -> 22736 | AQ97: =SUM(AQ88:AQ96) -> 21343 | AR97: =SUM(AR88:AR96) -> 21133 | AS97: =SUM(AS88:AS96) -> 21831 | ... AU97: =SUM(AU88:AU96) -> 23489
C98: Current financial assets | V98: 127 | X98: 143 | Z98: 129 | AB98: 130 | AD98: 530 | AF98: 635 | AH98: 225 | AJ98: 526 | AL98: 247 | AM98: 147 | AN98: 2113 | AO98: 185 | AP98: 143 | AQ98: 126 | AR98: 104 | AS98: 242 | AT98: 270 | AU98: 243
C99: Current derivatives (positive fair value) | V99: 819 | X99: 674 | Z99: 484 | AB99: 1335 | AD99: 570 | AF99: 1200 | AH99: 1690 | AJ99: 1406 | AL99: 373 | AM99: 592 | AN99: 566 | AO99: 740 | AP99: 674 | AQ99: 694 | AR99: 705 | AS99: 540 | AT99: 1577 | AU99: 952
C100: Inventories/work-in-progress | V100: 5578 | X100: 6312 | Z100: 6340 | AB100: 5270 | AD100: 6050 | AF100: 7381 | AH100: 9344 | AJ100: 10329 | AL100: 4518 | AM100: 4247 | AN100: 3954 | AO100: 5558 | AP100: 6312 | AQ100: 5190 | AR100: 5063 | AS100: 6408 | AT100: 7903 | AU100: 9491
C101: Contract costs | V101: 473 | X101: 471 | Z101: 502 | AB101: 524 | AD101: 616 | AF101: 733 | AH101: 855 | AJ101: 935 | AL101: 0 | AM101: 0 | AN101: 261 | AO101: 470 | AP101: 471 | AQ101: 486 | AR101: 552 | AS101: 664 | AT101: 753 | AU101: 884
C102: Trade and other receivables | V102: 6154 | X102: 7639 | Z102: 6790 | AB102: 5281 | AD102: 6954 | AF102: 8462 | AH102: 9558 | AJ102: 11621 | AL102: 6515 | AM102: 6252 | AN102: 4952 | AO102: 6580 | AP102: 7639 | AQ102: 5769 | AR102: 6504 | AS102: 7904 | AT102: 9417 | AU102: 10572
C103: Contract assets | V103: 1485 | X103: 1743 | Z103: 1741 | AB103: 1768 | AD103: 1896 | AF103: 2057 | AH103: 2290 | AJ103: 2743 | AL103: 0 | AM103: 0 | AN103: 1366 | AO103: 1544 | AP103: 1743 | AQ103: 1695 | AR103: 1853 | AS103: 1982 | AT103: 2157 | AU103: 2503
C104: Tax assets | V104: 589 | X104: 458 | Z104: 390 | AB104: 567 | AD104: 235 | AF104: 357 | AH104: 515 | AJ104: 706 | AL104: 623 | AM104: 513 | AN104: 596 | AO104: 752 | AP104: 458 | AQ104: 481 | AR104: 555 | AS104: 358 | AT104: 422 | AU104: 364
C105: Cash & equivalents | V105: 2380 | X105: 2632 | Z105: 4373 | AB105: 3927 | AD105: 6208 | AF105: 6147 | AH105: 5699 | AJ105: 6707 | AL105: 1845 | AM105: 1926 | AN105: 4914 | AO105: 2330 | AP105: 2632 | AQ105: 3747 | AR105: 5247 | AS105: 6687 | AT105: 6676 | AU105: 6514
...

Sheet Acquisitions
